Workbook
Name AuroraSize: 'Control Panel >>>'!$B$15
Name CallsPerItem: 'Control Panel >>>'!$B$12
Name ContingencyPct: 'Control Panel >>>'!$B$19
Name DatasetCount: 'Control Panel >>>'!$B$7
Name DeliveriesPerMonth: 'Control Panel >>>'!$B$5
Name EnvMultiplier: 'Control Panel >>>'!$B$14
Name GanttCorrGoLive: Gantt!$AE$4
Name HitlPct: 'Control Panel >>>'!$B$16
Name InputTokensPerCallK: 'Control Panel >>>'!$B$10
Name ItemsPerMonth: 'Control Panel >>>'!$B$22
Name LlmItems: 'Control Panel >>>'!$B$23
Name LlmReachablePct: 'Control Panel >>>'!$B$8
Name ModelSKU: 'Control Panel >>>'!$B$9
Name MonthlyTCO: 'Monthly TCO'!$C$23
Name OutputTokensPerCallK: 'Control Panel >>>'!$B$11
Name PointRate: 'Control Panel >>>'!$B$13
Name ProductsPerDelivery: 'Control Panel >>>'!$B$6
Name RampM1: '12mo Run Cost'!$C$4
Name RampM2: '12mo Run Cost'!$D$4
Name RampM3Plus: '12mo Run Cost'!$E$4
Name Run12mo: '12mo Run Cost'!$O$44
Name SlipWeeks: 'Control Panel >>>'!$B$18
Name StoragePerItemKB: 'Control Panel >>>'!$B$17
Name TotalBuildCost: 'Pod Build'!$J$43
Name TotalBuildPoints: 'Pod Build'!$D$43

Sheet Overview
A1: Overview -- headline TCO + cost waterfall
A2: ="Monthly TCO $"&TEXT(MonthlyTCO,"#,##0.00")&" at Control Panel defaults ("&ModelSKU&", "&TEXT(ItemsPerMonth,"#,##0")&" items/mo). 12-mo run cost $"&TEXT(Run12mo,"#,##0")&". Build: "&TEXT(TotalBuildPoints,"#,##0")&" points x $"&TEXT(PointRate,"#,##0.00")&"/point = $"&TEXT(TotalBuildCost,"#,##0")&"." -> Monthly TCO $1,439.33 at Control Panel defaults (Opus-4.8, 9,890 items/mo). 12-mo run cost $14,846. Build: 95 points x $0.00/point = $0.
A3: HEADLINE
B4: Monthly TCO (at Control Panel defaults) | C4: =MonthlyTCO -> 1439.3256
B5: 12-month run cost total | C5: =Run12mo -> 14846.323
B6: Total build points | C6: =TotalBuildPoints -> 95
B7: Total build cost (Points x PointRate) | C7: =TotalBuildCost -> 0
A9: COST WATERFALL -- MONTHLY TCO BY ZONE
A10: Zone / component | B10: Base (invisible) | C10: Block (visible) | D10: Delta
A11: Zone1 Ingestion | B11: =0 -> 0 | C11: =ABS(D11) -> 8.6509692 | D11: ='Monthly TCO'!$C$5 -> 8.6509692 | E11: =B11+D11 -> 8.6509692
A12: Zone2 ETL/Validation | B12: =E11 -> 8.6509692 | C12: =ABS(D12) -> 0 | D12: ='Monthly TCO'!$C$7 -> 0 | E12: =B12+D12 -> 8.6509692
A13: Zone3 Matching | B13: =E12 -> 8.6509692 | C13: =ABS(D13) -> 887.8094 | D13: ='Monthly TCO'!$C$9 -> 887.8094 | E13: =B13+D13 -> 896.46037
A14: Zone4 Orchestrator+Memory | B14: =E13 -> 896.46037 | C14: =ABS(D14) -> 17.793677 | D14: ='Monthly TCO'!$C$11 -> 17.793677 | E14: =B14+D14 -> 914.25405
A15: Zone4 LLM tokens (LIKELY) | B15: =E14 -> 914.25405 | C15: =ABS(D15) -> 202.745 | D15: ='Monthly TCO'!$C$12 -> 202.745 | E15: =B15+D15 -> 1116.999
A16: Zone4 Dense-arm (opt, 0 default) | B16: =E15 -> 1116.999 | C16: =ABS(D16) -> 0 | D16: ='Monthly TCO'!$C$14 -> 0 | E16: =B16+D16 -> 1116.999
A17: Zone4 Evaluations | B17: =E16 -> 1116.999 | C17: =ABS(D17) -> 0 | D17: ='Monthly TCO'!$C$15 -> 0 | E17: =B17+D17 -> 1116.999
A18: Zone5 Persistence/HITL | B18: =E17 -> 1116.999 | C18: =ABS(D18) -> 18.133318 | D18: ='Monthly TCO'!$C$17 -> 18.133318 | E18: =B18+D18 -> 1135.1324
A19: Platform (always-on) | B19: =E18 -> 1135.1324 | C19: =ABS(D19) -> 116.4551 | D19: ='Monthly TCO'!$C$19 -> 116.4551 | E19: =B19+D19 -> 1251.5875
A21: Cumulative total (should equal Subtotal on Monthly TCO) | E21: =E19 -> 1251.5875
A23: TOP COST DRIVERS
A24: Rank | B24: Zone / component | C24: Monthly cost
A25: 1 | B25: =INDEX($A$11:$A$19,MATCH(C25,$D$11:$D$19,0)) -> Zone3 Matching | C25: =LARGE($D$11:$D$19,1) -> 887.8094
A26: 2 | B26: =INDEX($A$11:$A$19,MATCH(C26,$D$11:$D$19,0)) -> Zone4 LLM tokens (LIKELY) | C26: =LARGE($D$11:$D$19,2) -> 202.745
A27: 3 | B27: =INDEX($A$11:$A$19,MATCH(C27,$D$11:$D$19,0)) -> Platform (always-on) | C27: =LARGE($D$11:$D$19,3) -> 116.4551

Sheet Control Panel >>>
A1: JPMC SCUDO POAP TCO -- Control Panel (all scenarios drive live)
A2: Amber cells are editable inputs -- change a value and every tab, total and chart recalculates live. Status labels: VERIFIED (grounded to source) / INDICATIVE (list price, editable) / DERIVED (formula) / ASSUMPTION (stated basis, editable) / RATE_MISSING (no source rate -- $0 until entered). USD, us-east-1 throughout.
A4: SCENARIO SWITCHES & LOADINGS
A5: DeliveriesPerMonth | B5: 10 | C5: ASSUMPTION | D5: Vendor deliveries per month -> volume model
A6: ProductsPerDelivery | B6: 989 | C6: ASSUMPTION | D6: Products per delivery -> ItemsPerMonth = Deliveries x Products
A7: DatasetCount | B7: 5000 | C7: ASSUMPTION | D7: Catalogue size (CDAO datasets) -> storage lines
A8: LlmReachablePct | B8: 1 | C8: DERIVED | D8: Fraction of items reaching the agent loop. CODE-VERIFIED default: the deployed Strands orchestrator invokes specialist+verifier per product UNCONDITIONALLY (not band-gated) -> 1.0, DERIVED. Lower it to model a band-gated future.
A9: ModelSKU | B9: Opus-4.8 | C9: ASSUMPTION | D9: Bedrock model SKU selection via SKU-gate pattern (vendor fixed = Bedrock)
A10: InputTokensPerCallK | B10: 0.8 | C10: ASSUMPTION | D10: Per-call input tokens (thousands). CODE-VERIFIED LIKELY ~0.69-0.94K (specialist), ~0.38-0.52K (verifier). Client sketch said 50K -> carried as the HIGH scenario row, not the default.
A11: OutputTokensPerCallK | B11: 0.25 | C11: ASSUMPTION | D11: Per-call output tokens (thousands). CODE-VERIFIED LIKELY ~0.21-0.27K.
A12: CallsPerItem | B12: 2 | C12: ASSUMPTION | D12: Bedrock calls per item. CODE-VERIFIED: 2 (mapping specialist + verifier). Dense-arm opus_dense_score is OFF by default (DenseBackend=jaro_winkler); if flipped, it fires per taxonomy node scored -> carried as a separate optional line, default 0.
A13: PointRate | B13: 0 | C13: ASSUMPTION | D13: $ per build point. DEFAULT 0 = RATE_MISSING visible zero (un-costed, not free).
A14: EnvMultiplier | B14: 1 | C14: ASSUMPTION | D14: Non-prod environment multiplier on always-on infra
A15: AuroraSize | B15: 2xlarge | C15: ASSUMPTION | D15: Aurora instance class selector (client sketch says 2xLarge; repo-real default is Serverless v2 db.serverless, a material sizing divergence -- see Assumptions)
A16: HitlPct | B16: 0.15 | C16: ASSUMPTION | D16: Fraction of items routed to HITL review (AppSync traffic)
A17: StoragePerItemKB | B17: 50 | C17: ASSUMPTION | D17: Canonical JSON-LD per product (repo estimate: ~2-4KB actual; 50KB is a conservative client-facing ceiling -- see Assumptions)
A18: SlipWeeks | B18: 0 | C18: ASSUMPTION | D18: Gantt stretch (14-week core, spec 5b with 29->14)
A19: ContingencyPct | B19: 0.15 | C19: ASSUMPTION | D19: Uplift on monthly TCO subtotal
A21: DERIVED VOLUME
A22: Items per month (Deliveries x Products) | B22: =DeliveriesPerMonth*ProductsPerDelivery -> 9890 | C22: DERIVED
A23: LLM-reachable items per month | B23: =ItemsPerMonth*LlmReachablePct -> 9890 | C23: DERIVED
A25: SCOPE NOTES
A26: * LlmReachablePct default 1.0 is CODE-VERIFIED (orchestrator.py:113-151): the deployed Strands orchestrator has no dependency on the confidence-band gate for LLM reachability -- it calls mapping+verifier for every non-RESEARCH product. Lower this to model a future band-gated design.
A27: * InputTokensPerCallK/OutputTokensPerCallK defaults are the CODE-VERIFIED LIKELY scenario (measured prompt-template character counts, llm_call_model.md SS3). The client sketch's 50K in / 1K out is carried as a labelled CLIENT-SKETCH HIGH scenario row on Monthly TCO, not the default.
A28: * PointRate defaults to 0 by design (RATE_MISSING convention): Pod Build shows visible $0 build cost until a real $/point rate is supplied -- this is un-costed, not free.
A29: * AuroraSize offers large/xlarge/2xlarge fixed-instance rates from Rates!, matching the client sketch's 'Aurora db 2xLarge' line. The repo-real deployed config is Aurora Serverless v2 (db.serverless, 0.5-2 ACU) -- a material sizing divergence, see Assumptions.
A30: * StoragePerItemKB defaults to 50KB as a conservative client-facing ceiling. The repo-real measured canonical JSON-LD payload is ~2-4KB per fully-published product (arch_infra_persistence.md SSC.5) -- storage cost at 50KB is a deliberate overstatement, not a repo-measured figure.
A31: * All figures are USD, AWS us-east-1 region only -- no other currency or cloud vendor.

Sheet Rates
A1: Rates -- USD list prices, us-east-1, on-demand (July 2026)
A2: Every figure on this tab is an editable input. All rates VERIFIED from AWS Price List Bulk API / aws.amazon.com/*/pricing pages, us-east-1, as cited per row. RATE_MISSING lines are $0 until a real rate is supplied. USD only.
A4: Rate | B4: Unit | C4: Value (USD) | D4: Status | E4: Source URL | F4: Notes / As-of
A5: AMAZON AURORA POSTGRESQL
A6: db.r6g.2xlarge Single-AZ instance (Standard) | B6: USD per hour | C6: 1.038 | D6: VERIFIED | E6: https://pricing.us-east-1.amazonaws.com/offers/v1.0/aws/AmazonRDS/current/us-east-1/index.json | F6: AWS Price List Bulk API (AmazonRDS), sku attrs databaseEngine=Aurora PostgreSQL, instanceType=db.r6g.2xlarge, deploymentOption=Single-AZ, usagetype=InstanceUsage:db.r6g.2xl. As of publicationDate 2026-07-21T17:58:18Z. Matches client sketch's 'Aurora db 2xLarge'.
A7: db.r6g.2xlarge Single-AZ instance (I/O-Optimized) | B7: USD per hour | C7: 1.349 | D7: VERIFIED | E7: https://pricing.us-east-1.amazonaws.com/offers/v1.0/aws/AmazonRDS/current/us-east-1/index.json | F7: Same source/date as above; usagetype=InstanceUsageIOOptimized:db.r6g.2xl. I/O-Optimized carries no per-I/O charge (see storage row) but a higher instance rate.
A8: db.r6g.xlarge Single-AZ instance (Standard) — cheaper alternate | B8: USD per hour | C8: 0.519 | D8: VERIFIED | E8: https://pricing.us-east-1.amazonaws.com/offers/v1.0/aws/AmazonRDS/current/us-east-1/index.json | F8: usagetype=InstanceUsage:db.r6g.xl. As of 2026-07-21.
A9: db.r6g.xlarge Single-AZ instance (I/O-Optimized) | B9: USD per hour | C9: 0.675 | D9: VERIFIED | E9: https://pricing.us-east-1.amazonaws.com/offers/v1.0/aws/AmazonRDS/current/us-east-1/index.json | F9: usagetype=InstanceUsageIOOptimized:db.r6g.xl.
A10: db.r6g.large Single-AZ instance (Standard) — cheaper alternate | B10: USD per hour | C10: 0.26 | D10: VERIFIED | E10: https://pricing.us-east-1.amazonaws.com/offers/v1.0/aws/AmazonRDS/current/us-east-1/index.json | F10: usagetype=InstanceUsage:db.r6g.large.
A11: db.r6g.large Single-AZ instance (I/O-Optimized) | B11: USD per hour | C11: 0.338 | D11: VERIFIED | E11: https://pricing.us-east-1.amazonaws.com/offers/v1.0/aws/AmazonRDS/current/us-east-1/index.json | F11: usagetype=InstanceUsageIOOptimized:db.r6g.large.
A12: AMAZON AURORA SERVERLESS V2 (POSTGRESQL)
A13: Aurora Capacity Unit (Standard config) | B13: USD per ACU-hour | C13: 0.12 | D13: VERIFIED | E13: https://pricing.us-east-1.amazonaws.com/offers/v1.0/aws/AmazonRDS/current/us-east-1/index.json | F13: usagetype=Aurora:ServerlessV2Usage.
A14: Aurora Capacity Unit (I/O-Optimized config) | B14: USD per ACU-hour | C14: 0.16 | D14: VERIFIED | E14: https://pricing.us-east-1.amazonaws.com/offers/v1.0/aws/AmazonRDS/current/us-east-1/index.json | F14: usagetype=Aurora:ServerlessV2IOOptimizedUsage.
A15: AMAZON AURORA POSTGRESQL
A16: Consumed storage (Standard) | B16: USD per GB-month | C16: 0.1 | D16: VERIFIED | E16: https://pricing.us-east-1.amazonaws.com/offers/v1.0/aws/AmazonRDS/current/us-east-1/index.json | F16: usagetype=Aurora:StorageUsage. Standard config also bills I/O separately (next row); I/O-Optimized rolls I/O into a higher $/GB-mo rate with zero per-I/O charge.
A17: Consumed storage (I/O-Optimized) | B17: USD per GB-month | C17: 0.225 | D17: VERIFIED | E17: https://pricing.us-east-1.amazonaws.com/offers/v1.0/aws/AmazonRDS/current/us-east-1/index.json | F17: usagetype=Aurora:IO-OptimizedStorageUsage. I/O-Optimized has $0 per-I/O charge — all read/write I/O cost is folded into this higher storage rate vs. the 0.10 Standard rate.
A18: I/O requests (Standard config only) | B18: USD per 1,000,000 I/Os | C18: 0.2 | D18: VERIFIED | E18: https://pricing.us-east-1.amazonaws.com/offers/v1.0/aws/AmazonRDS/current/us-east-1/index.json | F18: usagetype=Aurora:StorageIOUsage ($0.0000002/IO). Only billed under Standard storage config; I/O-Optimized has no separate I/O charge (folded into the 0.225 GB-mo storage rate above).
A19: AMAZON OPENSEARCH SERVICE
A20: r7g.large.search on-demand instance | B20: USD per hour | C20: 0.178 | D20: VERIFIED | E20: https://pricing.us-east-1.amazonaws.com/offers/v1.0/aws/AmazonES/current/us-east-1/index.json | F20: AWS Price List Bulk API (AmazonES), instanceType=r7g.large.search, usagetype=ESInstance:r7g.large. As of publicationDate 2026-07-09T09:08:58Z.
A21: m7g.large.search on-demand instance | B21: USD per hour | C21: 0.135 | D21: VERIFIED | E21: https://pricing.us-east-1.amazonaws.com/offers/v1.0/aws/AmazonES/current/us-east-1/index.json | F21: instanceType=m7g.large.search, usagetype=ESInstance:m7g.large.
A22: t3.small.search on-demand instance (dev/test) | B22: USD per hour | C22: 0.036 | D22: VERIFIED | E22: https://pricing.us-east-1.amazonaws.com/offers/v1.0/aws/AmazonES/current/us-east-1/index.json | F22: instanceType=t3.small.search, usagetype=ESInstance:t3.small.
A23: EBS gp3 provisioned storage | B23: USD per GB-month | C23: 0.122 | D23: VERIFIED | E23: https://pricing.us-east-1.amazonaws.com/offers/v1.0/aws/AmazonES/current/us-east-1/index.json | F23: usagetype=ES:GP3-Storage. gp3 also has separate optional provisioned-IOPS ($0.008/PIOPS-mo) and provisioned-throughput ($0.064/MiBps-mo) meters not requested in the brief.
A24: AMAZON OPENSEARCH SERVERLESS
A25: Indexing OCU / Search OCU (compute) | B25: USD per OCU-hour | C25: 0.24 | D25: VERIFIED | E25: https://pricing.us-east-1.amazonaws.com/offers/v1.0/aws/AmazonES/current/us-east-1/index.json | F25: usagetype=USE1-IndexingOCU and USE1-SearchOCU, both $0.24/OCU-hr identically. As of 2026-07-09.
A26: Minimum billed OCUs — production (redundancy) vs dev/test | B26: OCU count (not USD) | C26: 0 | D26: VERIFIED | E26: https://docs.aws.amazon.com/opensearch-service/latest/developerguide/serverless-scaling.html | F26: CORRECTION to brief's framing: current AWS docs (fetched 2026-07-22) state the minimum is 2 OCUs total with redundancy ON (1 OCU=[0.5x2] indexing + 1 OCU=[0.5x2] search, for HA) vs 1 OCU total with redundancy OFF/dev-test (0.5 indexing + 0.5 search) — NOT '4-OCU vs 2-OCU' as the brief's note suggested. At $0.24/OCU-hr, production-minimum ~2 OCU x $0.24 x 730hr = ~$350/mo; dev-minimum ~1 OCU x $0.24 x 730hr = ~$175/mo. Flagging this discrepancy rather than fabricating a 4-OCU figure to match the brief's wording.
A27: AMAZON DYNAMODB (ON-DEMAND CAPACITY)
A28: Write request units | B28: USD per 1,000,000 WRU | C28: 0.625 | D28: VERIFIED | E28: https://pricing.us-east-1.amazonaws.com/offers/v1.0/aws/AmazonDynamoDB/current/us-east-1/index.json | F28: usagetype=WriteRequestUnits, group=DDB-WriteUnits, description '$0.625 per million write request units (N. Virginia)'. Standard table class. As of publicationDate 2026-07-22T00:38:27Z.
A29: Read request units | B29: USD per 1,000,000 RRU | C29: 0.125 | D29: VERIFIED | E29: https://pricing.us-east-1.amazonaws.com/offers/v1.0/aws/AmazonDynamoDB/current/us-east-1/index.json | F29: usagetype=ReadRequestUnits, group=DDB-ReadUnits, description '$0.125 per million read request units (N. Virginia)'. Standard table class.
A30: AMAZON DYNAMODB
A31: Storage (Standard table class, beyond 25GB free tier) | B31: USD per GB-month | C31: 0.25 | D31: VERIFIED | E31: https://pricing.us-east-1.amazonaws.com/offers/v1.0/aws/AmazonDynamoDB/current/us-east-1/index.json | F31: usagetype=TimedStorage-ByteHrs, priced tier beyond first 25 free GB-months (first 25 GB-mo is $0/GB). Standard-IA table class is cheaper at $0.10/GB-mo if applicable.
A32: AMAZON NEPTUNE
A33: db.r6g.large instance (Standard) | B33: USD per hour | C33: 0.3287 | D33: VERIFIED | E33: https://pricing.us-east-1.amazonaws.com/offers/v1.0/aws/AmazonNeptune/current/us-east-1/index.json | F33: AWS Price List Bulk API (AmazonNeptune), instanceType=db.r6g.large, usagetype=InstanceUsage:db.r6g.large. Publication date in file is stale (2026-03-13) — cross-check against live console before finalizing budget; no newer bulk-API snapshot was available at fetch time so this is the latest published rate, not a guess.
A34: db.r6g.large instance (I/O-Optimized) | B34: USD per hour | C34: 0.443 | D34: VERIFIED | E34: https://pricing.us-east-1.amazonaws.com/offers/v1.0/aws/AmazonNeptune/current/us-east-1/index.json | F34: usagetype=InstanceUsageIOOptimized:db.r6g.large. Same file caveat as above (publicationDate 2026-03-13T14:07:01Z).
A35: Storage (Standard) | B35: USD per GB-month | C35: 0.1 | D35: VERIFIED | E35: https://pricing.us-east-1.amazonaws.com/offers/v1.0/aws/AmazonNeptune/current/us-east-1/index.json | F35: usagetype=StorageUsage. I/O-Optimized storage is $0.225/GB-mo (usagetype=IO-OptimizedStorageUsage), mirroring the Aurora pattern.
A36: I/O requests (Standard config only) | B36: USD per 1,000,000 I/Os | C36: 0.2 | D36: VERIFIED | E36: https://pricing.us-east-1.amazonaws.com/offers/v1.0/aws/AmazonNeptune/current/us-east-1/index.json | F36: usagetype=StorageIOUsage. Context per brief: repo ships Neptune CFN templates but the live PoC runs FalkorDB on ECS instead — Neptune priced here for comparison, not as the deployed graph store.
A37: AWS FARGATE (X86/LINUX, ON ECS)
A38: vCPU-hour | B38: USD per vCPU-hour | C38: 0.04048 | D38: VERIFIED | E38: https://pricing.us-east-1.amazonaws.com/offers/v1.0/aws/AmazonECS/current/us-east-1/index.json | F38: usagetype=USE1-Fargate-vCPU-Hours:perCPU. As of publicationDate 2026-07-07T16:06:51Z. ARM/Graviton Fargate is cheaper at $0.03238/vCPU-hr (usagetype=USE1-Fargate-ARM-vCPU-Hours:perCPU).
A39: GB-hour (memory) | B39: USD per GB-hour | C39: 0.004445 | D39: VERIFIED | E39: https://pricing.us-east-1.amazonaws.com/offers/v1.0/aws/AmazonECS/current/us-east-1/index.json | F39: usagetype=USE1-Fargate-GB-Hours. ARM/Graviton is cheaper at $0.00356/GB-hr (usagetype=USE1-Fargate-ARM-GB-Hours).
A40: AWS FARGATE
A41: Monthly example: 0.25 vCPU / 0.5 GB, always-on (730 hr/mo) | B41: USD per month | C41: 9.01 | D41: VERIFIED | E41: https://pricing.us-east-1.amazonaws.com/offers/v1.0/aws/AmazonECS/current/us-east-1/index.json | F41: Derived calc: (0.25 vCPU x $0.04048/hr + 0.5 GB x $0.004445/hr) x 730 hr = $9.01/mo. x86/Linux rates; excludes ephemeral storage beyond the free 20GB and any data transfer.
A42: Monthly example: 1 vCPU / 2 GB, always-on (730 hr/mo) | B42: USD per month | C42: 36.04 | D42: VERIFIED | E42: https://pricing.us-east-1.amazonaws.com/offers/v1.0/aws/AmazonECS/current/us-east-1/index.json | F42: Derived calc: (1 vCPU x $0.04048/hr + 2 GB x $0.004445/hr) x 730 hr = $36.04/mo. x86/Linux rates; excludes ephemeral storage beyond the free 20GB and any data transfer.
A43: AMAZON RDS PROXY
A44: Proxy usage (per vCPU of underlying Aurora PostgreSQL instance) | B44: USD per vCPU-hour | C44: 0.015 | D44: VERIFIED | E44: https://pricing.us-east-1.amazonaws.com/offers/v1.0/aws/AmazonRDS/current/us-east-1/index.json | F44: usagetype=USE1-RDS:ProxyUsage, description '$0.015 per hour per vCPU of the Aurora PostgreSQL instances associated with an RDS Proxy'. Same $0.015/vCPU-hr rate applies uniformly across Aurora MySQL/PostgreSQL/RDS engines and to Serverless v2 (ACU-hr) underlying instances. As of publicationDate 2026-07-21T17:58:18Z.
A45: AMAZON AURORA POSTGRESQL
A46: db.r6g.2xlarge (Standard, Single-AZ) | B46: USD per instance-hour | C46: 1.038 | D46: VERIFIED | E46: https://pricing.us-east-1.amazonaws.com/offers/v1.0/aws/AmazonRDS/current/us-east-1/index.json | F46: AWS Price List API bulk offer file for AmazonRDS, us-east-1, publicationDate 2026-07-21. SKU description: '$1.038 per RDS db.r6g.2xlarge Single-AZ instance hour running Aurora PostgreSQL'. IO-Optimized variant for same instance is $1.349/hr (see separate row).
A47: db.r6g.2xlarge (I/O-Optimized, Single-AZ) | B47: USD per instance-hour | C47: 1.349 | D47: VERIFIED | E47: https://pricing.us-east-1.amazonaws.com/offers/v1.0/aws/AmazonRDS/current/us-east-1/index.json | F47: Same source/date as above. I/O-Optimized pricing has no separate per-request I/O charge (bundled into instance rate + storage), trading a higher instance rate for zero I/O billing.
A48: db.r6g.xlarge (Standard, Single-AZ) | B48: USD per instance-hour | C48: 0.519 | D48: VERIFIED | E48: https://pricing.us-east-1.amazonaws.com/offers/v1.0/aws/AmazonRDS/current/us-east-1/index.json | F48: Cheaper alternate to 2xlarge, per brief. I/O-Optimized variant is $0.675/hr.
A49: db.r6g.large (Standard, Single-AZ) | B49: USD per instance-hour | C49: 0.26 | D49: VERIFIED | E49: https://pricing.us-east-1.amazonaws.com/offers/v1.0/aws/AmazonRDS/current/us-east-1/index.json | F49: Cheapest alternate per brief. I/O-Optimized variant is $0.338/hr.
A50: AMAZON AURORA POSTGRESQL SERVERLESS V2
A51: ACU-hour (Standard) | B51: USD per ACU-hour | C51: 0.12 | D51: VERIFIED | E51: https://pricing.us-east-1.amazonaws.com/offers/v1.0/aws/AmazonRDS/current/us-east-1/index.json | F51: Aurora:ServerlessV2Usage SKU, Aurora PostgreSQL, us-east-1. I/O-Optimized Serverless v2 ACU-hour is $0.16.
A52: AMAZON AURORA POSTGRESQL
A53: Database storage (Standard) | B53: USD per GB-month | C53: 0.1 | D53: VERIFIED | E53: https://pricing.us-east-1.amazonaws.com/offers/v1.0/aws/AmazonRDS/current/us-east-1/index.json | F53: Aurora:StorageUsage SKU. I/O-Optimized storage is billed higher at $0.225/GB-month (Aurora:IO-OptimizedStorageUsage) because I/O is free under that tier.
A54: I/O requests (Standard) | B54: USD per 1 million I/O requests | C54: 0.2 | D54: VERIFIED | E54: https://pricing.us-east-1.amazonaws.com/offers/v1.0/aws/AmazonRDS/current/us-east-1/index.json | F54: Aurora:StorageIOUsage SKU. Only applies to Standard configuration — I/O-Optimized configuration has $0 per-I/O charge (cost shifted into higher instance/storage rates above). Choose Standard for I/O-light, low/predictable workloads; I/O-Optimized for I/O-heavy workloads (>~25% of instance cost in I/O).
A55: AMAZON OPENSEARCH SERVICE (MANAGED DOMAIN)
A56: r7g.large.search | B56: USD per instance-hour | C56: 0.178 | D56: VERIFIED | E56: https://pricing.us-east-1.amazonaws.com/offers/v1.0/aws/AmazonES/current/us-east-1/index.json | F56: AWS Price List API bulk offer file for AmazonES, us-east-1, publicationDate 2026-07-09. ESInstance:r7g.large SKU.
A57: m7g.large.search | B57: USD per instance-hour | C57: 0.135 | D57: VERIFIED | E57: https://pricing.us-east-1.amazonaws.com/offers/v1.0/aws/AmazonES/current/us-east-1/index.json | F57: ESInstance:m7g.large SKU, same source as above. General-purpose alternate to r7g (memory-optimized).
A58: t3.small.search (dev/test) | B58: USD per instance-hour | C58: 0.036 | D58: VERIFIED | E58: https://pricing.us-east-1.amazonaws.com/offers/v1.0/aws/AmazonES/current/us-east-1/index.json | F58: ESInstance:t3.small SKU, same source as above. Burstable-credit instance intended for dev/test, not production.
A59: EBS gp3 storage | B59: USD per GB-month | C59: 0.122 | D59: VERIFIED | E59: https://pricing.us-east-1.amazonaws.com/offers/v1.0/aws/AmazonES/current/us-east-1/index.json | F59: ES:GP3-Storage SKU. Baseline 3,000 IOPS / 125 MiB/s included; additional provisioned IOPS billed at $0.008/IOPS-month (ES:GP3-PIOPS) and additional throughput at $0.064/MiBps-month (ES:GP3-Provisioned-ThroughPut) if you exceed baseline.
A60: AMAZON OPENSEARCH SERVERLESS
A61: OCU-hour (Indexing/Search/Semantic/Vector-index-acceleration, all uniform) | B61: USD per OCU-hour | C61: 0.24 | D61: VERIFIED | E61: https://pricing.us-east-1.amazonaws.com/offers/v1.0/aws/AmazonES/current/us-east-1/index.json | F61: USE1-IndexingOCU / USE1-SearchOCU / USE1-SemanticSearchOCU / USE1-VectorIndexAccelerationOCU SKUs, all $0.24/OCU-hr. Minimum OCUs: production (time-series or search/vector collections) bills a minimum of 4 OCUs total (2 indexing incl. primary+replica, 2 search incl. one replica for HA) for the first collection in an account, i.e. 2 OCUs per role x2 for HA; the brief's 'dev/2-OCU' option refers to disabling the standby/HA replica (0.5 OCU indexing + 0.5 OCU search = 1 OCU total per role-pair, described by AWS as halving cost vs the 2-OCU-per-role production minimum) — confirm exact current minimum in AWS OpenSearch Serverless pricing docs before quoting to client, as replica/HA toggle rules have changed across regions/time. Storage is separate: $0.30/GB-month hot (USE1-StorageUsedInHotByteHour), $0.024/GB-month S3-tier (USE1-StorageUsedInS3ByteHour).
A62: AMAZON DYNAMODB (ON-DEMAND MODE)
A63: WriteRequestUnits | B63: USD per million write request units | C63: 0.625 | D63: VERIFIED | E63: https://pricing.us-east-1.amazonaws.com/offers/v1.0/aws/AmazonDynamoDB/current/us-east-1/index.json | F63: AWS Price List API bulk offer file for AmazonDynamoDB, us-east-1, publicationDate 2026-07-22. Standard table class; Standard-IA class is $0.78/million writes.
A64: ReadRequestUnits | B64: USD per million read request units | C64: 0.125 | D64: VERIFIED | E64: https://pricing.us-east-1.amazonaws.com/offers/v1.0/aws/AmazonDynamoDB/current/us-east-1/index.json | F64: Same source/date as above. Standard table class; Standard-IA class is $0.155/million reads.
A65: AMAZON DYNAMODB
A66: Table storage (Standard) | B66: USD per GB-month | C66: 0.25 | D66: VERIFIED | E66: https://pricing.us-east-1.amazonaws.com/offers/v1.0/aws/AmazonDynamoDB/current/us-east-1/index.json | F66: TimedStorage-ByteHrs SKU, beyond the first 25 GB-months which are free tier ($0/GB-month). Standard-IA table class storage is $0.10/GB-month.
A67: AMAZON NEPTUNE
A68: db.r6g.large (Multi-AZ, Standard) | B68: USD per instance-hour | C68: 0.3287 | D68: VERIFIED | E68: https://pricing.us-east-1.amazonaws.com/offers/v1.0/aws/AmazonNeptune/current/us-east-1/index.json | F68: AWS Price List API bulk offer file for AmazonNeptune, us-east-1, publicationDate 2026-03-13 (oldest of the five files fetched — re-verify against live AWS Neptune pricing page before final client quote, as this snapshot is ~4 months old vs the others). Neptune instance pricing is published only as Multi-AZ deployment option in this file (no separate Single-AZ SKU found for db.r6g.large); IO-Optimized variant is $0.443/hr.
A69: Storage | B69: USD per GB-month | C69: 0.1 | D69: VERIFIED | E69: https://pricing.us-east-1.amazonaws.com/offers/v1.0/aws/AmazonNeptune/current/us-east-1/index.json | F69: StorageUsage SKU, same source as above (2026-03-13 snapshot). I/O-Optimized storage tier is $0.225/GB-month (zero per-I/O charge).
A70: I/O requests (Standard) | B70: USD per 1 million I/O requests | C70: 0.2 | D70: VERIFIED | E70: https://pricing.us-east-1.amazonaws.com/offers/v1.0/aws/AmazonNeptune/current/us-east-1/index.json | F70: StorageIOUsage SKU, same source as above. Repo context: PoC currently runs FalkorDB on ECS instead of Neptune — Neptune db.r6g.large ($0.3287/hr Multi-AZ + storage + I/O) vs. FalkorDB-on-Fargate (see ECS Fargate rows: e.g. 1 vCPU/2GB Fargate task ≈ $36.04/month = ~$0.049/hr all-in, far below Neptune's managed-DB rate) — Neptune carries a large premium for managed multi-AZ graph-DB semantics that FalkorDB-on-ECS does not provide out of the box.
A71: AMAZON ECS ON FARGATE
A72: vCPU-hour (Linux/x86) | B72: USD per vCPU-hour | C72: 0.04048 | D72: VERIFIED | E72: https://pricing.us-east-1.amazonaws.com/offers/v1.0/aws/AmazonECS/current/us-east-1/index.json | F72: AWS Price List API bulk offer file for AmazonECS, us-east-1, publicationDate 2026-07-07. USE1-Fargate-vCPU-Hours SKU. ARM/Graviton is cheaper at $0.03238/vCPU-hr (USE1-Fargate-ARM-vCPU-Hours).
A73: GB-hour memory (Linux/x86) | B73: USD per GB-hour | C73: 0.004445 | D73: VERIFIED | E73: https://pricing.us-east-1.amazonaws.com/offers/v1.0/aws/AmazonECS/current/us-east-1/index.json | F73: USE1-Fargate-GB-Hours SKU, same source as above. ARM/Graviton is $0.00356/GB-hr.
A74: Monthly example: 0.25 vCPU / 0.5 GB always-on task | B74: USD per month (730 hrs) | C74: 9.01 | D74: VERIFIED | E74: https://pricing.us-east-1.amazonaws.com/offers/v1.0/aws/AmazonECS/current/us-east-1/index.json | F74: Derived calculation, Linux/x86: 0.25 vCPU x $0.04048/hr x 730 hrs = $7.39, plus 0.5 GB x $0.004445/hr x 730 hrs = $1.62; total $9.01/month. No ephemeral-storage or data-transfer charges included (first 20GB ephemeral storage/task is free).
A75: Monthly example: 1 vCPU / 2 GB always-on task | B75: USD per month (730 hrs) | C75: 36.04 | D75: VERIFIED | E75: https://pricing.us-east-1.amazonaws.com/offers/v1.0/aws/AmazonECS/current/us-east-1/index.json | F75: Derived calculation, Linux/x86: 1 vCPU x $0.04048/hr x 730 hrs = $29.55, plus 2 GB x $0.004445/hr x 730 hrs = $6.49; total $36.04/month. Same caveats as above row.
A76: AMAZON RDS PROXY
A77: vCPU-hour (for Aurora PostgreSQL instances) | B77: USD per vCPU-hour | C77: 0.015 | D77: VERIFIED | E77: https://pricing.us-east-1.amazonaws.com/offers/v1.0/aws/AmazonRDS/current/us-east-1/index.json | F77: USE1-RDS:ProxyUsage SKU, databaseEngine=Aurora PostgreSQL, same offer file as the Aurora rows above (publicationDate 2026-07-21). Priced per vCPU of the underlying Aurora PostgreSQL instance(s) associated with the proxy, uniform across engines (MySQL/PostgreSQL/MariaDB/Aurora all $0.015/vCPU-hr); when fronting Aurora Serverless v2 the equivalent meter is $0.015/ACU-hour (USE1-RDS:Proxy-ASv2-Usage).
A78: AMAZON API GATEWAY
A79: ApiGatewayRequest (REST API request charge, first 333M/month tier) | B79: USD per million requests | C79: 3.5 | D79: VERIFIED | E79: https://pricing.us-east-1.amazonaws.com/offers/v1.0/aws/AmazonApiGateway/current/us-east-1/index.json | F79: As of AWS Price List Bulk API version 20251120010652 (publicationDate 2025-11-20; confirmed still current on 2026-07-22 via the 'current' alias). REST API pricing tiers: $3.50/M (first 333M/mo), $2.80/M (next 667M), $2.38/M (next 19B), $1.51/M (over 20B/mo). Alternate: HTTP API (usagetype ApiGatewayHttpRequest) is $1.00/M requests for the first 300M/mo, $0.90/M thereafter. No perpetual free tier priced gross (the 12-month new-account free tier of 1M REST API calls/month is excluded per brief).
A80: AWS LAMBDA
A81: Lambda-GB-Second (x86, Total Compute, Tier-1) | B81: USD per GB-second | C81: 1.66667e-05 | D81: VERIFIED | E81: https://pricing.us-east-1.amazonaws.com/offers/v1.0/aws/AWSLambda/current/us-east-1/index.json | F81: As of AWS Price List Bulk API version 20260717075216 (publicationDate 2026-07-17). x86 duration Tier-1 (up to 6B GB-s/month): $0.0000166667/GB-s; Tier-2: $0.0000150000; Tier-3: $0.0000133334. Priced gross; excludes the perpetual monthly free tier (400,000 GB-s + 1M requests).
A82: Request (x86, Total Requests) | B82: USD per 1M requests | C82: 0.2 | D82: VERIFIED | E82: https://pricing.us-east-1.amazonaws.com/offers/v1.0/aws/AWSLambda/current/us-east-1/index.json | F82: As of AWS Price List Bulk API version 20260717075216 (publicationDate 2026-07-17). Unit price is $0.0000002/request = $0.20 per 1M requests. Priced gross; excludes the perpetual monthly free tier (1M requests).
A83: AMAZON S3 STANDARD
A84: TimedStorage-ByteHrs (General Purpose, first 50 TB/month) | B84: USD per GB-month | C84: 0.023 | D84: VERIFIED | E84: https://pricing.us-east-1.amazonaws.com/offers/v1.0/aws/AmazonS3/current/us-east-1/index.json | F84: As of AWS Price List Bulk API version 20260720184843 (publicationDate 2026-07-20). First 50TB/mo tier $0.023/GB-mo; next 450TB $0.022; over 500TB $0.021. No free tier for storage beyond the 12-month 5GB new-account allotment; priced gross.
A85: Requests-Tier1 (PUT, COPY, POST, or LIST requests) | B85: USD per 1,000 requests | C85: 0.005 | D85: VERIFIED | E85: https://pricing.us-east-1.amazonaws.com/offers/v1.0/aws/AmazonS3/current/us-east-1/index.json | F85: As of AWS Price List Bulk API version 20260720184843 (publicationDate 2026-07-20). $0.005 per 1,000 PUT/COPY/POST/LIST requests (i.e. $0.005/1000 PUT as requested).
A86: Requests-Tier2 (GET and all other requests) | B86: USD per 1,000 requests | C86: 0.0004 | D86: VERIFIED | E86: https://pricing.us-east-1.amazonaws.com/offers/v1.0/aws/AmazonS3/current/us-east-1/index.json | F86: As of AWS Price List Bulk API version 20260720184843 (publicationDate 2026-07-20). Bulk file lists it as $0.004/10,000 GET requests = $0.0004 per 1,000 GET requests.
A87: AMAZON SQS
A88: Requests-RBP (standard queue, Tier1, first 1B requests/month equivalent) | B88: USD per million requests | C88: 0.4 | D88: VERIFIED | E88: https://pricing.us-east-1.amazonaws.com/offers/v1.0/aws/AWSQueueService/current/us-east-1/index.json | F88: As of AWS Price List Bulk API version 20250828200713 (publicationDate 2025-08-28; re-checked against the 'current' alias on 2026-07-22 and confirmed unchanged/still current). Standard queue request-based pricing: Tier1 $0.40/M, Tier2 $0.30/M, Tier3 $0.24/M requests. Priced gross; excludes the perpetual monthly free tier (1M requests).
A89: AMAZON EVENTBRIDGE
A90: USE1-Event-64K-Chunks (custom events received) | B90: USD per million events | C90: 1 | D90: VERIFIED | E90: https://pricing.us-east-1.amazonaws.com/offers/v1.0/aws/AWSEvents/current/us-east-1/index.json | F90: As of AWS Price List Bulk API version 20260529205301 (publicationDate 2026-05-29). $1.00 per million custom events received (each 64KB chunk billed as one event-equivalent).
A91: AMAZON EVENTBRIDGE SCHEDULER
A92: USE1-ScheduledInvocation | B92: USD per million invocations | C92: 1 | D92: VERIFIED | E92: https://pricing.us-east-1.amazonaws.com/offers/v1.0/aws/AWSEvents/current/us-east-1/index.json | F92: As of AWS Price List Bulk API version 20260529205301 (publicationDate 2026-05-29). $1.00 per million scheduled invocations; priced gross (the first 14M scheduled invocations/month are free-tier priced at $0 in the same file).
A93: AMAZON CLOUDWATCH
A94: USE1-DataProcessing-Bytes (Ingested Logs, Standard log class) | B94: USD per GB | C94: 0.5 | D94: VERIFIED | E94: https://pricing.us-east-1.amazonaws.com/offers/v1.0/aws/AmazonCloudWatch/current/us-east-1/index.json | F94: As of AWS Price List Bulk API version 20260716124606 (publicationDate 2026-07-16). $0.50/GB for custom log data ingested (Standard log class).
A95: USE1-TimedStorage-ByteHrs (log storage, current pricing) | B95: USD per GB-month | C95: 0.03 | D95: VERIFIED | E95: https://pricing.us-east-1.amazonaws.com/offers/v1.0/aws/AmazonCloudWatch/current/us-east-1/index.json | F95: As of AWS Price List Bulk API version 20260716124606 (publicationDate 2026-07-16). $0.03/GB-month of log storage.
A96: CW:MetricMonitorUsage (custom metrics, first 10,000 metrics) | B96: USD per metric-month | C96: 0.3 | D96: VERIFIED | E96: https://pricing.us-east-1.amazonaws.com/offers/v1.0/aws/AmazonCloudWatch/current/us-east-1/index.json | F96: As of AWS Price List Bulk API version 20260716124606 (publicationDate 2026-07-16). $0.30/metric-month for the first 10,000 metrics; $0.10 for the next 240,000; $0.05 for the next 750,000; $0.02 over 1,000,000. Excludes free-tier first 10 metrics.
A97: Dashboard (Basic Dashboard) | B97: USD per dashboard per month | C97: 3 | D97: VERIFIED | E97: https://calculator.aws/pricing/2.0/meteredUnitMaps/cloudwatch/USD/current/cloudwatch.json | F97: Dashboards are absent from the standard Price List Bulk API JSON for AmazonCloudWatch (confirmed by exhaustive text search of that file); sourced instead from AWS's Pricing Calculator metered-unit-map for CloudWatch, esIndex/publicationDate 20260716124606 -- matching the same version/date as the bulk file above, confirming currency. $3.00 per dashboard per month (first 3 dashboards/month free tier excluded, priced gross).
A98: AWS FARGATE
A99: USE1-Fargate-vCPU-Hours:perCPU (Linux/x86) | B99: USD per vCPU-hour | C99: 0.04048 | D99: VERIFIED | E99: https://pricing.us-east-1.amazonaws.com/offers/v1.0/aws/AmazonECS/current/us-east-1/index.json | F99: As of AWS Price List Bulk API version 20260707160651 (publicationDate 2026-07-07). Fargate has no dedicated top-level offer code; billed/listed under AmazonECS. Linux/x86 vCPU rate is $0.040480/vCPU-hour (ARM variant is $0.03238/vCPU-hour, listed separately, not used here).
A100: USE1-Fargate-GB-Hours (Linux/x86 Memory) | B100: USD per GB-hour | C100: 0.004445 | D100: VERIFIED | E100: https://pricing.us-east-1.amazonaws.com/offers/v1.0/aws/AmazonECS/current/us-east-1/index.json | F100: As of AWS Price List Bulk API version 20260707160651 (publicationDate 2026-07-07). Linux/x86 memory rate is $0.004445/GB-hour (ARM variant $0.00356/GB-hour, not used here).
A101: APPLICATION LOAD BALANCER
...

Sheet Pod Build
A1: Pod Build -- client table shape + repo-real extras
A2: ="Points x PointRate (currently $"&TEXT(PointRate,"#,##0.00")&"/point) -- PointRate defaults to 0 (RATE_MISSING convention): visible zero, un-costed not free until a real rate is supplied." -> Points x PointRate (currently $0.00/point) -- PointRate defaults to 0 (RATE_MISSING convention): visible zero, un-costed not free until a real rate is supplied.
A3: Pod | B3: Short Title | C3: AWS Components | D3: Points | E3: Run freq per mo | F3: Est data vol GB | G3: Input tokens K | H3: Output tokens K | I3: Cost estimate $ monthly | J3: Build cost (Points x PointRate) | K3: Status | L3: Basis / source | M3: Dense-arm mult. (0=off)
A4: A | B4: API GW entry + routing | C4: API Gateway (HttpApi) | D4: 2 | E4: =ItemsPerMonth -> 9890 | F4: - | G4: - | H4: - | I4: =ItemsPerMonth*Rates!$C$79/1000000 -> 0.034615 | J4: =D4*PointRate -> 0 | K4: ASSUMPTION | L4: Points: relative sizing, no client estimate supplied. Cost: ItemsPerMonth requests through the /run route, ApiGatewayRequest rate. template.yaml:589-599.
A5: A | B5: Lambda authorizer | C5: Lambda (auth check) | D5: 1 | E5: - | F5: - | G5: - | H5: - | I5: =ItemsPerMonth*0 -> 0 | J5: =D5*PointRate -> 0 | K5: ASSUMPTION | L5: No JWT Lambda authorizer exists in the repo today (auth is an API-key header) -- arch_infra_persistence.md D.1. RATE_MISSING: $0, un-costed, not free, until this component is actually built.
A6: A | B6: Ingestion Coordinator (ETL worker) | C6: Lambda EtlFn, 3008MB, SQS-triggered | D6: 3 | E6: =ItemsPerMonth -> 9890 | F6: - | G6: - | H6: - | I6: =ItemsPerMonth*2.9375*2*Rates!$C$81+ItemsPerMonth*Rates!$C$82/1000000 -> 0.97037577 | J6: =D6*PointRate -> 0 | K6: DERIVED | L6: template.yaml:16-25 EtlFn 3008MB default memory, SQS BatchSize 5. Duration ASSUMPTION (~2s/product, no repo timing evidence); GB-second + per-request Lambda rates.
A7: A | B7: Sanity Check (validate/quarantine) | C7: In-process in EtlFn -- no separate Lambda | D7: 1 | E7: - | F7: - | G7: - | H7: - | I7: =ItemsPerMonth*0 -> 0 | J7: =D7*PointRate -> 0 | K7: DERIVED | L7: etl_handler.py _process_object/_quarantine run inside EtlFn -- no incremental compute cost beyond the Ingestion Coordinator line above.
A8: A | B8: CloudWatch (logs + metrics) | C8: CloudWatch log groups, EMF metrics, dashboard | D8: 1 | E8: =ItemsPerMonth -> 9890 | F8: =ItemsPerMonth*2/1000000 -> 0.01978 | G8: - | H8: - | I8: =(ItemsPerMonth*2/1000000)*(Rates!$C$94+Rates!$C$95)+15*Rates!$C$96+1*Rates!$C$97 -> 7.5104834 | J8: =D8*PointRate -> 0 | K8: ASSUMPTION | L8: ~2KB structured log per product ASSUMPTION; 15 custom EMF metrics per MEMORY note; 1 dashboard. arch_infra_persistence.md A.8.
A9: A | B9: S3 raw landing | C9: S3 RawFeedBucket | D9: 1 | E9: =ItemsPerMonth -> 9890 | F9: =ItemsPerMonth*StoragePerItemKB/1000000 -> 0.4945 | G9: - | H9: - | I9: =ItemsPerMonth*1*Rates!$C$85/1000+ItemsPerMonth*0*Rates!$C$86/1000+ItemsPerMonth*StoragePerItemKB/1000000*Rates!$C$84 -> 0.0608235 | J9: =D9*PointRate -> 0 | K9: DERIVED | L9: template.yaml:176-198 RawFeedBucket, EventBridge-notification-enabled. 1 PUT/vendor object at ingest, storage sized via StoragePerItemKB.
A10: A | B10: EventBridge Scheduler (poller) | C10: EventBridge Scheduler, cron twice-monthly | D10: 1 | E10: 2 | F10: - | G10: - | H10: - | I10: =2*Rates!$C$92/1000000 -> 2e-06 | J10: =D10*PointRate -> 0 | K10: VERIFIED | L10: PollerFn cron(0 6 1,15 * ? *) -- twice-monthly, not per-product. arch_infra_persistence.md A.1/A.3.
A11: A | B11: EventBridge ObjectCreated rule | C11: EventBridge rule, S3->SQS | D11: 1 | E11: =ItemsPerMonth -> 9890 | F11: - | G11: - | H11: - | I11: =ItemsPerMonth*1*Rates!$C$90/1000000 -> 0.00989 | J11: =D11*PointRate -> 0 | K11: VERIFIED | L11: RawFeedIngressRule on default bus, S3 Object Created -> EtlQueue. arch_infra_persistence.md A.3.
A12: A | B12: SQS (EtlQueue + DLQ) | C12: SQS standard queue + DLQ | D12: 1 | E12: =ItemsPerMonth -> 9890 | F12: - | G12: - | H12: - | I12: =ItemsPerMonth*1*Rates!$C$88/1000000 -> 0.003956 | J12: =D12*PointRate -> 0 | K12: VERIFIED | L12: EtlQueue BatchSize 5, DLQ after 3 receives. template.yaml A.2.
A13: A | B13: ETL worker VPC egress (NAT) | C13: NAT Gateway (no-VPC EtlFn needs internet egress) | D13: 1 | E13: - | F13: - | G13: - | H13: - | I13: =ItemsPerMonth*0 -> 0 | J13: =D13*PointRate -> 0 | K13: DERIVED | L13: EtlFn explicitly has NO VPC (template.yaml:488-491); NAT cost is carried once as a shared always-on line under Pod E Platform, not duplicated here -- see Pod E.
A14: A | B14: S3 canonical sink | C14: S3 CleanCanonicalBucket | D14: 1 | E14: =ItemsPerMonth -> 9890 | F14: =ItemsPerMonth*StoragePerItemKB/1000000 -> 0.4945 | G14: - | H14: - | I14: =ItemsPerMonth*1*Rates!$C$85/1000+ItemsPerMonth*0*Rates!$C$86/1000+ItemsPerMonth*StoragePerItemKB/1000000*Rates!$C$84 -> 0.0608235 | J14: =D14*PointRate -> 0 | K14: DERIVED | L14: CleanCanonicalBucket, written by etl_handler.py pass path. 1 PUT/product.
A15: A | B15: S3 quarantine | C15: S3 QuarantineBucket | D15: 1 | E15: =ItemsPerMonth -> 9890 | F15: - | G15: - | H15: - | I15: =ItemsPerMonth*0*Rates!$C$85/1000+ItemsPerMonth*0*Rates!$C$86/1000 -> 0 | J15: =D15*PointRate -> 0 | K15: ASSUMPTION | L15: QuarantineBucket, mutually exclusive with canonical PUT (bad-file path only) -- modelled at $0 incremental (rare-path, no repo-measured quarantine rate).
A16: B | B16: AIA Matching Engine gate A (scope) | C16: In-process, matching.py | D16: 2 | E16: - | F16: - | G16: - | H16: - | I16: =ItemsPerMonth*0 -> 0 | J16: =D16*PointRate -> 0 | K16: DERIVED | L16: Deterministic Python gate, no separate compute -- folded into the matching Lambda compute already priced on the Strands Orchestrator line (Pod C). ZONES.md Zone 3.
A17: B | B17: AIA Matching Engine gate B (precedent) | C17: In-process, aurora_memory.py CONSULT | D17: 2 | E17: - | F17: - | G17: - | H17: - | I17: =ItemsPerMonth*0 -> 0 | J17: =D17*PointRate -> 0 | K17: RATE_MISSING | L17: 1 Aurora RDS Data API ExecuteStatement per item for precedent lookup (arch_infra_persistence.md C.4 roll-up), but rates.json has no per-request RDS Data API meter -- the underlying Aurora instance-hour cost is already priced on the Aurora 2xlarge line below; this row's incremental per-call charge is $0, un-costed not free, until a Data API request rate is sourced.
A18: B | B18: AIA Matching Engine gate C (hybrid retrieval) | C18: FalkorDB on ECS (retrieval store) | D18: 3 | E18: Always-on (shared, see Pod E) | F18: - | G18: - | H18: - | I18: =ItemsPerMonth*0 -> 0 | J18: =D18*PointRate -> 0 | K18: DERIVED | L18: FalkorDB on Fargate is the live retrieval store (both deploy paths) -- always-on ECS task cost carried once under Pod E Platform, not duplicated per-pod. arch_infra_persistence.md A.8.
A19: B | B19: Titan Embeddings (indexing/write path) | C19: Bedrock Titan Text Embeddings V2 | D19: 2 | E19: =LlmItems -> 9890 | F19: - | G19: 0.5 | H19: 0 | I19: =LlmItems*0.5*Rates!$C$139/1000 -> 0.0989 | J19: =D19*PointRate -> 0 | K19: VERIFIED | L19: Titan IS called from projection_handler.py:483 on the write/index path only (not retrieval, which is parked). ~0.5K tokens/item ASSUMPTION for a short product description embed.
A20: B | B20: OpenSearch fuzzy+kNN | C20: OpenSearch Service r7g.large.search + gp3 storage | D20: 4 | E20: Always-on | F20: =DatasetCount*StoragePerItemKB/1000000 -> 0.25 | G20: - | H20: - | I20: =730*EnvMultiplier*Rates!$C$20+DatasetCount*StoragePerItemKB/1000000*Rates!$C$59 -> 129.9705 | J20: =D20*PointRate -> 0 | K20: DERIVED | L20: Template-real domain; write path real (_index_opensearch), matching read path today is a Jaro-Winkler/FalkorDB seam not OpenSearch kNN. Priced at the always-on domain cost the client's list implies. arch_infra_persistence.md A.7/A.8.
A21: B | B21: Aurora 2xlarge (system of record) | C21: Aurora PostgreSQL, AuroraSize selector | D21: 5 | E21: Always-on | F21: - | G21: - | H21: - | I21: =730*EnvMultiplier*IF(AuroraSize="large",Rates!$C$10,IF(AuroraSize="xlarge",Rates!$C$8,Rates!$C$6)) -> 757.74 | J21: =D21*PointRate -> 0 | K21: DERIVED | L21: Client sketch says 'Aurora db 2xLarge'; repo-real deployed shape is Aurora Serverless v2 (db.serverless) -- material divergence, see Assumptions. This line prices the client's fixed-instance-class ask via the AuroraSize selector.
A22: C | B22: Strands Orchestrator Opus 4.8 | C22: Lambda ScudoFn (3008MB) + Bedrock routing | D22: 5 | E22: =ItemsPerMonth -> 9890 | F22: - | G22: - | H22: - | I22: =ItemsPerMonth*2.9375*1*Rates!$C$81+ItemsPerMonth*Rates!$C$82/1000000 -> 0.48617689 | J22: =D22*PointRate -> 0 | K22: VERIFIED | L22: ScudoFn 3008MB default, no LLM call in Orchestrator.route() itself (deterministic Python). orchestrator.py:102-110; llm_call_model.md SS1.
A23: C | B23: AgentCore Memory (short-term events) | C23: Bedrock AgentCore Memory meter (bespoke store) | D23: 3 | E23: =LlmItems -> 9890 | F23: - | G23: - | H23: - | I23: =LlmItems*2*Rates!$C$145/1000 -> 4.945 | J23: =D23*PointRate -> 0 | K23: VERIFIED | L23: Client wants this priced; repo-real substrate is aurora_memory.py (bespoke), not the managed AgentCore Memory service (arch_infra_persistence.md D.1). Rate from Bedrock AgentCore Memory short-term-events meter, applied notionally as the client-facing unit-cost analog.
A24: C | B24: AgentCore Memory (long-term records) | C24: Bedrock AgentCore Memory, built-in strategies | D24: 2 | E24: =LlmItems -> 9890 | F24: - | G24: - | H24: - | I24: =LlmItems*1*Rates!$C$146/1000 -> 7.4175 | J24: =D24*PointRate -> 0 | K24: ASSUMPTION | L24: 1 long-term record/item ASSUMPTION (no repo-measured record count); rate VERIFIED from rates.json.
A25: C | B25: AgentCore Memory (long-term retrieval) | C25: Bedrock AgentCore Memory retrieval meter | D25: 2 | E25: =LlmItems -> 9890 | F25: - | G25: - | H25: - | I25: =LlmItems*1*Rates!$C$148/1000 -> 4.945 | J25: =D25*PointRate -> 0 | K25: ASSUMPTION | L25: 1 retrieval/item ASSUMPTION; rate VERIFIED from rates.json.
A26: C | B26: Specialist agent (mapping) | C26: Bedrock InvokeModel, ModelSKU-gated | D26: 4 | E26: =LlmItems -> 9890 | F26: - | G26: =InputTokensPerCallK -> 0.8 | H26: =OutputTokensPerCallK -> 0.25 | I26: =LlmItems*1*(InputTokensPerCallK/1000*IF(ModelSKU="Opus-4.8",Rates!$C$121,IF(ModelSKU="Sonnet-5",Rates!$C$127,Rates!$C$133))+OutputTokensPerCallK/1000*IF(ModelSKU="Opus-4.8",Rates!$C$122,IF(ModelSKU="Sonnet-5",Rates!$C$128,Rates!$C$134))) -> 101.3725 | J26: =D26*PointRate -> 0 | K26: VERIFIED | L26: 1 InvokeModel call/product via _call_mapping (orchestrator.py:191-203). SKU-gated token cost -- see Monthly TCO for the full CODE-VERIFIED LIKELY / CLIENT-SKETCH HIGH scenario rows.
A27: C | B27: Verifier agent 10-dim | C27: Bedrock InvokeModel, ModelSKU-gated | D27: 4 | E27: =LlmItems -> 9890 | F27: - | G27: =InputTokensPerCallK -> 0.8 | H27: =OutputTokensPerCallK -> 0.25 | I27: =LlmItems*1*(InputTokensPerCallK/1000*IF(ModelSKU="Opus-4.8",Rates!$C$121,IF(ModelSKU="Sonnet-5",Rates!$C$127,Rates!$C$133))+OutputTokensPerCallK/1000*IF(ModelSKU="Opus-4.8",Rates!$C$122,IF(ModelSKU="Sonnet-5",Rates!$C$128,Rates!$C$134))) -> 101.3725 | J27: =D27*PointRate -> 0 | K27: VERIFIED | L27: 1 InvokeModel call/product via _call_verifier (orchestrator.py:237-261), 10-dim rubric, VerifierReport min_length=10/max_length=10. schemas.py:219-247.
A28: C | B28: Dense-arm optional (opus_dense per node) | C28: Bedrock InvokeModel, opt-in, default OFF | D28: 3 | E28: =ItemsPerMonth*$M$28 -> 0 | F28: - | G28: 0.5 | H28: 0.08 | I28: =ItemsPerMonth*$M$28*(0.5/1000*IF(ModelSKU="Opus-4.8",Rates!$C$121,IF(ModelSKU="Sonnet-5",Rates!$C$127,Rates!$C$133))+0.08/1000*IF(ModelSKU="Opus-4.8",Rates!$C$122,IF(ModelSKU="Sonnet-5",Rates!$C$128,Rates!$C$134))) -> 0 | J28: =D28*PointRate -> 0 | K28: DERIVED | L28: Only fires if SCUDO_DENSE_BACKEND=opus (default jaro_winkler, infra/scudo-poc-app.yaml:76-79) -- OFF by default, amber multiplier default 0. When on: N calls/product, N=taxonomy nodes scored (14 in the demo fixture). llm_call_model.md SS1/SS3. | M28: 0
A29: C | B29: Bedrock Evaluations (judge) | C29: LLM-as-judge, billed as judge model's own tokens | D29: 2 | E29: - | F29: - | G29: - | H29: - | I29: =ItemsPerMonth*0 -> 0 | J29: =D29*PointRate -> 0 | K29: ASSUMPTION | L29: No separate meter for LLM-as-judge (rates.json: billed as judge model's standard tokens). Repo has no real Bedrock Evaluations API call anywhere -- bespoke offline harness instead (arch_infra_persistence.md D.1). $0 incremental line, human-eval meter available in Rates if wired later.
A30: D | B30: JAPI Persist outbox writer | C30: Aurora ExecuteStatement (RDS Data API) | D30: 5 | E30: - | F30: - | G30: - | H30: - | I30: =ItemsPerMonth*0 -> 0 | J30: =D30*PointRate -> 0 | K30: RATE_MISSING | L30: ~10 ExecuteStatement calls/fully-published product (outbox insert + projection rows) -- VERIFIED call count, arch_infra_persistence.md SSC, persistence-ops-per-product roll-up. No per-request RDS Data API rate in rates.json, so the incremental per-call charge is $0 (un-costed not free) until sourced; the Aurora instance-hour cost itself is priced separately on the Aurora 2xlarge line.
A31: D | B31: Outbox sweep (EventBridge Schedule) | C31: rate(5 min) Scheduler -> Lambda sweep | D31: 3 | E31: 8928 | F31: - | G31: - | H31: - | I31: =8928*Rates!$C$92/1000000 -> 0.008928 | J31: =D31*PointRate -> 0 | K31: VERIFIED | L31: rate(5 min) = 12/hr * 24 * mean(30.4 days) ~= 8928 invokes/mo, flat regardless of volume. projection_handler.py sweep_outbox; infra/HANDOVER_5zone_alignment.md.
A32: D | B32: HITL AppSync API | C32: AppSync GraphQL ops + notifications | D32: 4 | E32: =ItemsPerMonth*HitlPct -> 1483.5 | F32: - | G32: - | H32: - | I32: =ItemsPerMonth*HitlPct*6*Rates!$C$117/1000000 -> 0.035604 | J32: =D32*PointRate -> 0 | K32: ASSUMPTION | L32: 6 GraphQL ops/HITL item (list+get+mutate+subscribe-notify) is an ASSUMPTION -- no repo-measured op count; HitlPct selector gates volume. rate VERIFIED from rates.json.
A33: D | B33: HITL review ECS task (reviewer console) | C33: Fargate, always-on shared task | D33: 4 | E33: Always-on | F33: - | G33: - | H33: - | I33: =730*EnvMultiplier*(0.5*Rates!$C$38+1*Rates!$C$39) -> 18.02005 | J33: =D33*PointRate -> 0 | K33: DERIVED | L33: Shared with Pod E platform ECS allocation -- this row shows the HITL-attributable slice only, full task priced once under Pod E to avoid double count.
A34: D | B34: S3 projection sink + CloudFront invalidation | C34: S3 PUT/GET + CloudFront requests | D34: 2 | E34: =ItemsPerMonth -> 9890 | F34: =ItemsPerMonth*StoragePerItemKB/1000000 -> 0.4945 | G34: - | H34: - | I34: =ItemsPerMonth*1*Rates!$C$85/1000+ItemsPerMonth*2*Rates!$C$86/1000+ItemsPerMonth*StoragePerItemKB/1000000*Rates!$C$84 -> 0.0687355 | J34: =D34*PointRate -> 0 | K34: ASSUMPTION | L34: 1 PUT (projection write) + 2 GET (dashboard reads)/item ASSUMPTION.
A35: E | B35: FalkorDB on ECS (retrieval store) | C35: Fargate task, always-on, shared | D35: 5 | E35: Always-on | F35: - | G35: - | H35: - | I35: =730*EnvMultiplier*(1*Rates!$C$38+2*Rates!$C$39) -> 36.0401 | J35: =D35*PointRate -> 0 | K35: VERIFIED | L35: Actual live hybrid-retrieval substrate (Neptune/OpenSearch-kNN are dormant seams). 1 vCPU / 2GB always-on Fargate task. ZONES.md Zone3; ua-dogfood-scudo memory.
A36: E | B36: CloudFront distribution | C36: Requests + data transfer out, PoC demo | D36: 4 | E36: 50000 | F36: 10 | G36: - | H36: - | I36: =50000*Rates!$C$115/10000+10*Rates!$C$114 -> 0.9 | J36: =D36*PointRate -> 0 | K36: ASSUMPTION | L36: 50k requests / 10GB out per month is an ASSUMPTION sized for a PoC-scale demo, not production traffic -- see Assumptions sheet.
A37: E | B37: ALB (console + API ingress) | C37: Hourly + LCU-hours, always-on | D37: 3 | E37: Always-on | F37: - | G37: - | H37: - | I37: =730*EnvMultiplier*Rates!$C$102+730*EnvMultiplier*1*Rates!$C$103 -> 22.265 | J37: =D37*PointRate -> 0 | K37: VERIFIED | L37: 1 ALB, always-on hourly charge + nominal LCU-hours. infra/scudo-poc-*.yaml.
A38: E | B38: NAT Gateway (VPC egress) | C38: Hourly + per-GB processed, always-on | D38: 3 | E38: Always-on | F38: 20 | G38: - | H38: - | I38: =730*EnvMultiplier*Rates!$C$105+20*Rates!$C$106 -> 33.75 | J38: =D38*PointRate -> 0 | K38: ASSUMPTION | L38: 20GB/mo egress ASSUMPTION (ETL worker + Lambda-in-VPC egress); this is the priced line that Pod A's nat_share and Pod B's aurora_ops VPC path reference.
A39: E | B39: Secrets Manager (DB + API creds) | C39: Per-secret + API-call meter | D39: 1 | E39: Always-on | F39: - | G39: - | H39: - | I39: =4*Rates!$C$108 -> 1.6 | J39: =D39*PointRate -> 0 | K39: VERIFIED | L39: 4 secrets (CONSOLE_DB_PASSWORD, Bedrock/API keys, MFT gateway cred, JWT signing key).
A40: E | B40: VPC Interface Endpoints | C40: Per-endpoint-hour + per-GB, always-on | D40: 2 | E40: Always-on | F40: - | G40: - | H40: - | I40: =3*730*EnvMultiplier*Rates!$C$111 -> 21.9 | J40: =D40*PointRate -> 0 | K40: ASSUMPTION | L40: 3 endpoints ASSUMPTION (Secrets Manager, Bedrock, S3-gateway-equivalent) -- no repo-measured endpoint count.
A41: E | B41: CodeBuild (console/dashboard build) | C41: Build-minute meter, deploy-time only | D41: 1 | E41: - | F41: - | G41: - | H41: - | I41: =ItemsPerMonth*0 -> 0 | J41: =D41*PointRate -> 0 | K41: RATE_MISSING | L41: No CodeBuild meter in Rates -- research/rates.json has zero CodeBuild entries. $0 visible, un-costed not free, until a real build-minute rate is sourced. scudo-poc-console-build CodeBuild project exists in-repo (deploy-time only, not steady-state run cost).
A42: TOTALS
B43: Total points / monthly cost / build cost | D43: =SUM(D4:D41) -> 95 | I43: =SUM(I4:I41) -> 1251.5875 | J43: =SUM(J4:J41) -> 0

Sheet Monthly TCO
A1: Monthly TCO -- grouped by zone, formula-linked to Pod Build
A2: ="Contingency uplift "&TEXT(ContingencyPct,"0.0%")&" applied to the subtotal below. Three scenario rows show the LLM token cost under different framings -- only the CODE-VERIFIED LIKELY row (Control Panel defaults) feeds the total." -> Contingency uplift 15.0% applied to the subtotal below. Three scenario rows show the LLM token cost under different framings -- only the CODE-VERIFIED LIKELY row (Control Panel defaults) feeds the total.
A3: Zone | B3: Component | C3: Monthly cost formula | D3: Status | E3: Basis / source
A4: ZONE 1 -- INGESTION
A5: Zone1 | B5: API GW + Lambda ETL + S3 + SQS + EventBridge (Pod A total) | C5: ='Pod Build'!$I$4+'Pod Build'!$I$5+'Pod Build'!$I$6+'Pod Build'!$I$7+'Pod Build'!$I$8+'Pod Build'!$I$9+'Pod Build'!$I$10+'Pod Build'!$I$11+'Pod Build'!$I$12+'Pod Build'!$I$13+'Pod Build'!$I$14+'Pod Build'!$I$15 -> 8.6509692 | D5: DERIVED | E5: Cross-links to Pod Build Pod A rows (4-15); avoids re-deriving the same formulas twice.
A6: ZONE 2 -- ETL / VALIDATION
A7: Zone2 | B7: Sanity check + quarantine (folded into Pod A compute) | C7: =0 -> 0 | D7: DERIVED | E7: No incremental Zone2 compute beyond Zone1's Ingestion Coordinator Lambda -- etl_handler.py validate/quarantine run in-process.
A8: ZONE 3 -- MATCHING
A9: Zone3 | B9: Matching Engine + Titan + OpenSearch + Aurora (Pod B total) | C9: ='Pod Build'!$I$16+'Pod Build'!$I$17+'Pod Build'!$I$18+'Pod Build'!$I$19+'Pod Build'!$I$20+'Pod Build'!$I$21 -> 887.8094 | D9: DERIVED | E9: Cross-links to Pod Build Pod B rows (16-21).
A10: ZONE 4 -- AGENTIC
A11: Zone4 | B11: Strands Orchestrator + AgentCore Memory (Pod C infra rows) | C11: ='Pod Build'!$I$22+'Pod Build'!$I$23+'Pod Build'!$I$24+'Pod Build'!$I$25 -> 17.793677 | D11: DERIVED | E11: Cross-links to Pod Build Pod C rows 22-25 (orchestrator Lambda + AgentCore Memory short-term/long-term/retrieval).
A12: Zone4 | B12: LLM tokens -- CODE-VERIFIED LIKELY (default, feeds total) | C12: ='Pod Build'!$I$26+'Pod Build'!$I$27 -> 202.745 | D12: VERIFIED | E12: Sum of Specialist + Verifier lines (Pod Build rows 26-27) at the Control Panel's CODE-VERIFIED defaults (0.8K in / 0.25K out / 2 calls-item). llm_call_model.md SS3: ~$203/mo at Opus 4.8, 9,890 items/mo.
A13: Zone4 | B13: LLM tokens -- CLIENT-SKETCH HIGH (scenario only, NOT in total) | C13: =LlmItems*4*(50/1000*IF(ModelSKU="Opus-4.8",Rates!$C$121,IF(ModelSKU="Sonnet-5",Rates!$C$127,Rates!$C$133))+1/1000*IF(ModelSKU="Opus-4.8",Rates!$C$122,IF(ModelSKU="Sonnet-5",Rates!$C$128,Rates!$C$134))) -> 10879 | D13: ASSUMPTION | E13: Client's original sketch: 4 calls/item, 50K in / 1K out per call. Shown as a labelled scenario for comparison -- excluded from MonthlyTCO total. llm_call_model.md SS3 narrative.
A14: Zone4 | B14: LLM tokens -- DENSE-ARM OPTIONAL (default OFF, scenario only) | C14: ='Pod Build'!$I$28 -> 0 | D14: DERIVED | E14: Cross-links to Pod Build row 28 (opus_dense per taxonomy node); amber multiplier defaults 0 (off), matching deployed SCUDO_DENSE_BACKEND=jaro_winkler. llm_call_model.md SS1/SS3 (14-node demo fixture if enabled).
A15: Zone4 | B15: Bedrock Evaluations (judge -- folded into Specialist/Verifier tokens) | C15: ='Pod Build'!$I$29 -> 0 | D15: ASSUMPTION | E15: No separate meter; $0 incremental (Pod Build row 29).
A16: ZONE 5 -- PERSISTENCE / HITL
A17: Zone5 | B17: Outbox + AppSync + ECS + projection sink (Pod D total) | C17: ='Pod Build'!$I$30+'Pod Build'!$I$31+'Pod Build'!$I$32+'Pod Build'!$I$33+'Pod Build'!$I$34 -> 18.133318 | D17: DERIVED | E17: Cross-links to Pod Build Pod D rows 30-34.
A18: PLATFORM -- ALWAYS-ON (POD E)
A19: Platform | B19: FalkorDB + CloudFront + ALB + NAT + Secrets + VPC endpoints + CodeBuild | C19: ='Pod Build'!$I$35+'Pod Build'!$I$36+'Pod Build'!$I$37+'Pod Build'!$I$38+'Pod Build'!$I$39+'Pod Build'!$I$40+'Pod Build'!$I$41 -> 116.4551 | D19: DERIVED | E19: Cross-links to Pod Build Pod E rows 35-41.
A20: TOTALS
B21: Subtotal (excludes HIGH scenario row) | C21: =C5+C7+C9+C11+C12+C14+C15+C17+C19 -> 1251.5875
B22: Contingency uplift | C22: =C21*ContingencyPct -> 187.73812
B23: MONTHLY TCO (at Control Panel defaults) | C23: =C21+C22 -> 1439.3256

Sheet 12mo Run Cost
A1: 12-mo Run Cost -- ramp profile, Nov 2026 go-live
A2: ="Ramp: M1 "&TEXT(RampM1,"0%")&" / M2 "&TEXT(RampM2,"0%")&" / M3+ "&TEXT(RampM3Plus,"0%")&" of steady-state volume -- applies to volume-driven meters only. Always-on infra (Aurora, OpenSearch, ECS, NAT, ALB, endpoints) does not ramp." -> Ramp: M1 50% / M2 75% / M3+ 100% of steady-state volume -- applies to volume-driven meters only. Always-on infra (Aurora, OpenSearch, ECS, NAT, ALB, endpoints) does not ramp.
A3: Component | B3: Ramp class | C3: Nov 2026 | D3: Dec 2026 | E3: Jan 2027 | F3: Feb 2027 | G3: Mar 2027 | H3: Apr 2027 | I3: May 2027 | J3: Jun 2027 | K3: Jul 2027 | L3: Aug 2027 | M3: Sep 2027 | N3: Oct 2027 | O3: 12-mo Total
A4: Ramp % (of steady-state) -- editable | C4: 0.5 | D4: 0.75 | E4: 1 | F4: =E$4 -> 1 | G4: =E$4 -> 1 | H4: =E$4 -> 1 | I4: =E$4 -> 1 | J4: =E$4 -> 1 | K4: =E$4 -> 1 | L4: =E$4 -> 1 | M4: =E$4 -> 1 | N4: =E$4 -> 1
A5: Pod A: API GW entry + routing | B5: Ramps | C5: ='Pod Build'!$I$4*C$4 -> 0.0173075 | D5: ='Pod Build'!$I$4*D$4 -> 0.02596125 | E5: ='Pod Build'!$I$4*E$4 -> 0.034615 | F5: ='Pod Build'!$I$4*E$4 -> 0.034615 | G5: ='Pod Build'!$I$4*E$4 -> 0.034615 | H5: ='Pod Build'!$I$4*E$4 -> 0.034615 | I5: ='Pod Build'!$I$4*E$4 -> 0.034615 | J5: ='Pod Build'!$I$4*E$4 -> 0.034615 | K5: ='Pod Build'!$I$4*E$4 -> 0.034615 | L5: ='Pod Build'!$I$4*E$4 -> 0.034615 | M5: ='Pod Build'!$I$4*E$4 -> 0.034615 | N5: ='Pod Build'!$I$4*E$4 -> 0.034615 | O5: =SUM(C5:N5) -> 0.38941875
A6: Pod A: Lambda authorizer | B6: Ramps | C6: ='Pod Build'!$I$5*C$4 -> 0 | D6: ='Pod Build'!$I$5*D$4 -> 0 | E6: ='Pod Build'!$I$5*E$4 -> 0 | F6: ='Pod Build'!$I$5*E$4 -> 0 | G6: ='Pod Build'!$I$5*E$4 -> 0 | H6: ='Pod Build'!$I$5*E$4 -> 0 | I6: ='Pod Build'!$I$5*E$4 -> 0 | J6: ='Pod Build'!$I$5*E$4 -> 0 | K6: ='Pod Build'!$I$5*E$4 -> 0 | L6: ='Pod Build'!$I$5*E$4 -> 0 | M6: ='Pod Build'!$I$5*E$4 -> 0 | N6: ='Pod Build'!$I$5*E$4 -> 0 | O6: =SUM(C6:N6) -> 0
A7: Pod A: Ingestion Coordinator (ETL worker) | B7: Ramps | C7: ='Pod Build'!$I$6*C$4 -> 0.48518789 | D7: ='Pod Build'!$I$6*D$4 -> 0.72778183 | E7: ='Pod Build'!$I$6*E$4 -> 0.97037577 | F7: ='Pod Build'!$I$6*E$4 -> 0.97037577 | G7: ='Pod Build'!$I$6*E$4 -> 0.97037577 | H7: ='Pod Build'!$I$6*E$4 -> 0.97037577 | I7: ='Pod Build'!$I$6*E$4 -> 0.97037577 | J7: ='Pod Build'!$I$6*E$4 -> 0.97037577 | K7: ='Pod Build'!$I$6*E$4 -> 0.97037577 | L7: ='Pod Build'!$I$6*E$4 -> 0.97037577 | M7: ='Pod Build'!$I$6*E$4 -> 0.97037577 | N7: ='Pod Build'!$I$6*E$4 -> 0.97037577 | O7: =SUM(C7:N7) -> 10.916727
A8: Pod A: Sanity Check (validate/quarantine) | B8: Ramps | C8: ='Pod Build'!$I$7*C$4 -> 0 | D8: ='Pod Build'!$I$7*D$4 -> 0 | E8: ='Pod Build'!$I$7*E$4 -> 0 | F8: ='Pod Build'!$I$7*E$4 -> 0 | G8: ='Pod Build'!$I$7*E$4 -> 0 | H8: ='Pod Build'!$I$7*E$4 -> 0 | I8: ='Pod Build'!$I$7*E$4 -> 0 | J8: ='Pod Build'!$I$7*E$4 -> 0 | K8: ='Pod Build'!$I$7*E$4 -> 0 | L8: ='Pod Build'!$I$7*E$4 -> 0 | M8: ='Pod Build'!$I$7*E$4 -> 0 | N8: ='Pod Build'!$I$7*E$4 -> 0 | O8: =SUM(C8:N8) -> 0
A9: Pod A: CloudWatch (logs + metrics) | B9: Ramps | C9: ='Pod Build'!$I$8*C$4 -> 3.7552417 | D9: ='Pod Build'!$I$8*D$4 -> 5.6328626 | E9: ='Pod Build'!$I$8*E$4 -> 7.5104834 | F9: ='Pod Build'!$I$8*E$4 -> 7.5104834 | G9: ='Pod Build'!$I$8*E$4 -> 7.5104834 | H9: ='Pod Build'!$I$8*E$4 -> 7.5104834 | I9: ='Pod Build'!$I$8*E$4 -> 7.5104834 | J9: ='Pod Build'!$I$8*E$4 -> 7.5104834 | K9: ='Pod Build'!$I$8*E$4 -> 7.5104834 | L9: ='Pod Build'!$I$8*E$4 -> 7.5104834 | M9: ='Pod Build'!$I$8*E$4 -> 7.5104834 | N9: ='Pod Build'!$I$8*E$4 -> 7.5104834 | O9: =SUM(C9:N9) -> 84.492938
A10: Pod A: S3 raw landing | B10: Ramps | C10: ='Pod Build'!$I$9*C$4 -> 0.03041175 | D10: ='Pod Build'!$I$9*D$4 -> 0.045617625 | E10: ='Pod Build'!$I$9*E$4 -> 0.0608235 | F10: ='Pod Build'!$I$9*E$4 -> 0.0608235 | G10: ='Pod Build'!$I$9*E$4 -> 0.0608235 | H10: ='Pod Build'!$I$9*E$4 -> 0.0608235 | I10: ='Pod Build'!$I$9*E$4 -> 0.0608235 | J10: ='Pod Build'!$I$9*E$4 -> 0.0608235 | K10: ='Pod Build'!$I$9*E$4 -> 0.0608235 | L10: ='Pod Build'!$I$9*E$4 -> 0.0608235 | M10: ='Pod Build'!$I$9*E$4 -> 0.0608235 | N10: ='Pod Build'!$I$9*E$4 -> 0.0608235 | O10: =SUM(C10:N10) -> 0.68426438
A11: Pod A: EventBridge Scheduler (poller) | B11: Ramps | C11: ='Pod Build'!$I$10*C$4 -> 1e-06 | D11: ='Pod Build'!$I$10*D$4 -> 1.5e-06 | E11: ='Pod Build'!$I$10*E$4 -> 2e-06 | F11: ='Pod Build'!$I$10*E$4 -> 2e-06 | G11: ='Pod Build'!$I$10*E$4 -> 2e-06 | H11: ='Pod Build'!$I$10*E$4 -> 2e-06 | I11: ='Pod Build'!$I$10*E$4 -> 2e-06 | J11: ='Pod Build'!$I$10*E$4 -> 2e-06 | K11: ='Pod Build'!$I$10*E$4 -> 2e-06 | L11: ='Pod Build'!$I$10*E$4 -> 2e-06 | M11: ='Pod Build'!$I$10*E$4 -> 2e-06 | N11: ='Pod Build'!$I$10*E$4 -> 2e-06 | O11: =SUM(C11:N11) -> 2.25e-05
A12: Pod A: EventBridge ObjectCreated rule | B12: Ramps | C12: ='Pod Build'!$I$11*C$4 -> 0.004945 | D12: ='Pod Build'!$I$11*D$4 -> 0.0074175 | E12: ='Pod Build'!$I$11*E$4 -> 0.00989 | F12: ='Pod Build'!$I$11*E$4 -> 0.00989 | G12: ='Pod Build'!$I$11*E$4 -> 0.00989 | H12: ='Pod Build'!$I$11*E$4 -> 0.00989 | I12: ='Pod Build'!$I$11*E$4 -> 0.00989 | J12: ='Pod Build'!$I$11*E$4 -> 0.00989 | K12: ='Pod Build'!$I$11*E$4 -> 0.00989 | L12: ='Pod Build'!$I$11*E$4 -> 0.00989 | M12: ='Pod Build'!$I$11*E$4 -> 0.00989 | N12: ='Pod Build'!$I$11*E$4 -> 0.00989 | O12: =SUM(C12:N12) -> 0.1112625
A13: Pod A: SQS (EtlQueue + DLQ) | B13: Ramps | C13: ='Pod Build'!$I$12*C$4 -> 0.001978 | D13: ='Pod Build'!$I$12*D$4 -> 0.002967 | E13: ='Pod Build'!$I$12*E$4 -> 0.003956 | F13: ='Pod Build'!$I$12*E$4 -> 0.003956 | G13: ='Pod Build'!$I$12*E$4 -> 0.003956 | H13: ='Pod Build'!$I$12*E$4 -> 0.003956 | I13: ='Pod Build'!$I$12*E$4 -> 0.003956 | J13: ='Pod Build'!$I$12*E$4 -> 0.003956 | K13: ='Pod Build'!$I$12*E$4 -> 0.003956 | L13: ='Pod Build'!$I$12*E$4 -> 0.003956 | M13: ='Pod Build'!$I$12*E$4 -> 0.003956 | N13: ='Pod Build'!$I$12*E$4 -> 0.003956 | O13: =SUM(C13:N13) -> 0.044505
A14: Pod A: ETL worker VPC egress (NAT) | B14: Ramps | C14: ='Pod Build'!$I$13*C$4 -> 0 | D14: ='Pod Build'!$I$13*D$4 -> 0 | E14: ='Pod Build'!$I$13*E$4 -> 0 | F14: ='Pod Build'!$I$13*E$4 -> 0 | G14: ='Pod Build'!$I$13*E$4 -> 0 | H14: ='Pod Build'!$I$13*E$4 -> 0 | I14: ='Pod Build'!$I$13*E$4 -> 0 | J14: ='Pod Build'!$I$13*E$4 -> 0 | K14: ='Pod Build'!$I$13*E$4 -> 0 | L14: ='Pod Build'!$I$13*E$4 -> 0 | M14: ='Pod Build'!$I$13*E$4 -> 0 | N14: ='Pod Build'!$I$13*E$4 -> 0 | O14: =SUM(C14:N14) -> 0
A15: Pod A: S3 canonical sink | B15: Ramps | C15: ='Pod Build'!$I$14*C$4 -> 0.03041175 | D15: ='Pod Build'!$I$14*D$4 -> 0.045617625 | E15: ='Pod Build'!$I$14*E$4 -> 0.0608235 | F15: ='Pod Build'!$I$14*E$4 -> 0.0608235 | G15: ='Pod Build'!$I$14*E$4 -> 0.0608235 | H15: ='Pod Build'!$I$14*E$4 -> 0.0608235 | I15: ='Pod Build'!$I$14*E$4 -> 0.0608235 | J15: ='Pod Build'!$I$14*E$4 -> 0.0608235 | K15: ='Pod Build'!$I$14*E$4 -> 0.0608235 | L15: ='Pod Build'!$I$14*E$4 -> 0.0608235 | M15: ='Pod Build'!$I$14*E$4 -> 0.0608235 | N15: ='Pod Build'!$I$14*E$4 -> 0.0608235 | O15: =SUM(C15:N15) -> 0.68426438
A16: Pod A: S3 quarantine | B16: Ramps | C16: ='Pod Build'!$I$15*C$4 -> 0 | D16: ='Pod Build'!$I$15*D$4 -> 0 | E16: ='Pod Build'!$I$15*E$4 -> 0 | F16: ='Pod Build'!$I$15*E$4 -> 0 | G16: ='Pod Build'!$I$15*E$4 -> 0 | H16: ='Pod Build'!$I$15*E$4 -> 0 | I16: ='Pod Build'!$I$15*E$4 -> 0 | J16: ='Pod Build'!$I$15*E$4 -> 0 | K16: ='Pod Build'!$I$15*E$4 -> 0 | L16: ='Pod Build'!$I$15*E$4 -> 0 | M16: ='Pod Build'!$I$15*E$4 -> 0 | N16: ='Pod Build'!$I$15*E$4 -> 0 | O16: =SUM(C16:N16) -> 0
A17: Pod B: AIA Matching Engine gate A (scope) | B17: Ramps | C17: ='Pod Build'!$I$16*C$4 -> 0 | D17: ='Pod Build'!$I$16*D$4 -> 0 | E17: ='Pod Build'!$I$16*E$4 -> 0 | F17: ='Pod Build'!$I$16*E$4 -> 0 | G17: ='Pod Build'!$I$16*E$4 -> 0 | H17: ='Pod Build'!$I$16*E$4 -> 0 | I17: ='Pod Build'!$I$16*E$4 -> 0 | J17: ='Pod Build'!$I$16*E$4 -> 0 | K17: ='Pod Build'!$I$16*E$4 -> 0 | L17: ='Pod Build'!$I$16*E$4 -> 0 | M17: ='Pod Build'!$I$16*E$4 -> 0 | N17: ='Pod Build'!$I$16*E$4 -> 0 | O17: =SUM(C17:N17) -> 0
A18: Pod B: AIA Matching Engine gate B (precedent) | B18: Ramps | C18: ='Pod Build'!$I$17*C$4 -> 0 | D18: ='Pod Build'!$I$17*D$4 -> 0 | E18: ='Pod Build'!$I$17*E$4 -> 0 | F18: ='Pod Build'!$I$17*E$4 -> 0 | G18: ='Pod Build'!$I$17*E$4 -> 0 | H18: ='Pod Build'!$I$17*E$4 -> 0 | I18: ='Pod Build'!$I$17*E$4 -> 0 | J18: ='Pod Build'!$I$17*E$4 -> 0 | K18: ='Pod Build'!$I$17*E$4 -> 0 | L18: ='Pod Build'!$I$17*E$4 -> 0 | M18: ='Pod Build'!$I$17*E$4 -> 0 | N18: ='Pod Build'!$I$17*E$4 -> 0 | O18: =SUM(C18:N18) -> 0
A19: Pod B: AIA Matching Engine gate C (hybrid retrieval) | B19: Ramps | C19: ='Pod Build'!$I$18*C$4 -> 0 | D19: ='Pod Build'!$I$18*D$4 -> 0 | E19: ='Pod Build'!$I$18*E$4 -> 0 | F19: ='Pod Build'!$I$18*E$4 -> 0 | G19: ='Pod Build'!$I$18*E$4 -> 0 | H19: ='Pod Build'!$I$18*E$4 -> 0 | I19: ='Pod Build'!$I$18*E$4 -> 0 | J19: ='Pod Build'!$I$18*E$4 -> 0 | K19: ='Pod Build'!$I$18*E$4 -> 0 | L19: ='Pod Build'!$I$18*E$4 -> 0 | M19: ='Pod Build'!$I$18*E$4 -> 0 | N19: ='Pod Build'!$I$18*E$4 -> 0 | O19: =SUM(C19:N19) -> 0
A20: Pod B: Titan Embeddings (indexing/write path) | B20: Ramps | C20: ='Pod Build'!$I$19*C$4 -> 0.04945 | D20: ='Pod Build'!$I$19*D$4 -> 0.074175 | E20: ='Pod Build'!$I$19*E$4 -> 0.0989 | F20: ='Pod Build'!$I$19*E$4 -> 0.0989 | G20: ='Pod Build'!$I$19*E$4 -> 0.0989 | H20: ='Pod Build'!$I$19*E$4 -> 0.0989 | I20: ='Pod Build'!$I$19*E$4 -> 0.0989 | J20: ='Pod Build'!$I$19*E$4 -> 0.0989 | K20: ='Pod Build'!$I$19*E$4 -> 0.0989 | L20: ='Pod Build'!$I$19*E$4 -> 0.0989 | M20: ='Pod Build'!$I$19*E$4 -> 0.0989 | N20: ='Pod Build'!$I$19*E$4 -> 0.0989 | O20: =SUM(C20:N20) -> 1.112625
A21: Pod B: OpenSearch fuzzy+kNN | B21: Always-on | C21: ='Pod Build'!$I$20 -> 129.9705 | D21: ='Pod Build'!$I$20 -> 129.9705 | E21: ='Pod Build'!$I$20 -> 129.9705 | F21: ='Pod Build'!$I$20 -> 129.9705 | G21: ='Pod Build'!$I$20 -> 129.9705 | H21: ='Pod Build'!$I$20 -> 129.9705 | I21: ='Pod Build'!$I$20 -> 129.9705 | J21: ='Pod Build'!$I$20 -> 129.9705 | ... N21: ='Pod Build'!$I$20 -> 129.9705 | O21: =SUM(C21:N21) -> 1559.646
A22: Pod B: Aurora 2xlarge (system of record) | B22: Always-on | C22: ='Pod Build'!$I$21 -> 757.74 | D22: ='Pod Build'!$I$21 -> 757.74 | E22: ='Pod Build'!$I$21 -> 757.74 | F22: ='Pod Build'!$I$21 -> 757.74 | G22: ='Pod Build'!$I$21 -> 757.74 | H22: ='Pod Build'!$I$21 -> 757.74 | I22: ='Pod Build'!$I$21 -> 757.74 | J22: ='Pod Build'!$I$21 -> 757.74 | ... N22: ='Pod Build'!$I$21 -> 757.74 | O22: =SUM(C22:N22) -> 9092.88
A23: Pod C: Strands Orchestrator Opus 4.8 | B23: Ramps | C23: ='Pod Build'!$I$22*C$4 -> 0.24308844 | D23: ='Pod Build'!$I$22*D$4 -> 0.36463266 | E23: ='Pod Build'!$I$22*E$4 -> 0.48617689 | F23: ='Pod Build'!$I$22*E$4 -> 0.48617689 | G23: ='Pod Build'!$I$22*E$4 -> 0.48617689 | H23: ='Pod Build'!$I$22*E$4 -> 0.48617689 | I23: ='Pod Build'!$I$22*E$4 -> 0.48617689 | J23: ='Pod Build'!$I$22*E$4 -> 0.48617689 | K23: ='Pod Build'!$I$22*E$4 -> 0.48617689 | L23: ='Pod Build'!$I$22*E$4 -> 0.48617689 | M23: ='Pod Build'!$I$22*E$4 -> 0.48617689 | N23: ='Pod Build'!$I$22*E$4 -> 0.48617689 | O23: =SUM(C23:N23) -> 5.46949
A24: Pod C: AgentCore Memory (short-term events) | B24: Ramps | C24: ='Pod Build'!$I$23*C$4 -> 2.4725 | D24: ='Pod Build'!$I$23*D$4 -> 3.70875 | E24: ='Pod Build'!$I$23*E$4 -> 4.945 | F24: ='Pod Build'!$I$23*E$4 -> 4.945 | G24: ='Pod Build'!$I$23*E$4 -> 4.945 | H24: ='Pod Build'!$I$23*E$4 -> 4.945 | I24: ='Pod Build'!$I$23*E$4 -> 4.945 | J24: ='Pod Build'!$I$23*E$4 -> 4.945 | K24: ='Pod Build'!$I$23*E$4 -> 4.945 | L24: ='Pod Build'!$I$23*E$4 -> 4.945 | M24: ='Pod Build'!$I$23*E$4 -> 4.945 | N24: ='Pod Build'!$I$23*E$4 -> 4.945 | O24: =SUM(C24:N24) -> 55.63125
A25: Pod C: AgentCore Memory (long-term records) | B25: Ramps | C25: ='Pod Build'!$I$24*C$4 -> 3.70875 | D25: ='Pod Build'!$I$24*D$4 -> 5.563125 | E25: ='Pod Build'!$I$24*E$4 -> 7.4175 | F25: ='Pod Build'!$I$24*E$4 -> 7.4175 | G25: ='Pod Build'!$I$24*E$4 -> 7.4175 | H25: ='Pod Build'!$I$24*E$4 -> 7.4175 | I25: ='Pod Build'!$I$24*E$4 -> 7.4175 | J25: ='Pod Build'!$I$24*E$4 -> 7.4175 | K25: ='Pod Build'!$I$24*E$4 -> 7.4175 | L25: ='Pod Build'!$I$24*E$4 -> 7.4175 | M25: ='Pod Build'!$I$24*E$4 -> 7.4175 | N25: ='Pod Build'!$I$24*E$4 -> 7.4175 | O25: =SUM(C25:N25) -> 83.446875
A26: Pod C: AgentCore Memory (long-term retrieval) | B26: Ramps | C26: ='Pod Build'!$I$25*C$4 -> 2.4725 | D26: ='Pod Build'!$I$25*D$4 -> 3.70875 | E26: ='Pod Build'!$I$25*E$4 -> 4.945 | F26: ='Pod Build'!$I$25*E$4 -> 4.945 | G26: ='Pod Build'!$I$25*E$4 -> 4.945 | H26: ='Pod Build'!$I$25*E$4 -> 4.945 | I26: ='Pod Build'!$I$25*E$4 -> 4.945 | J26: ='Pod Build'!$I$25*E$4 -> 4.945 | K26: ='Pod Build'!$I$25*E$4 -> 4.945 | L26: ='Pod Build'!$I$25*E$4 -> 4.945 | M26: ='Pod Build'!$I$25*E$4 -> 4.945 | N26: ='Pod Build'!$I$25*E$4 -> 4.945 | O26: =SUM(C26:N26) -> 55.63125
A27: Pod C: Specialist agent (mapping) | B27: Ramps | C27: ='Pod Build'!$I$26*C$4 -> 50.68625 | D27: ='Pod Build'!$I$26*D$4 -> 76.029375 | E27: ='Pod Build'!$I$26*E$4 -> 101.3725 | F27: ='Pod Build'!$I$26*E$4 -> 101.3725 | G27: ='Pod Build'!$I$26*E$4 -> 101.3725 | H27: ='Pod Build'!$I$26*E$4 -> 101.3725 | I27: ='Pod Build'!$I$26*E$4 -> 101.3725 | J27: ='Pod Build'!$I$26*E$4 -> 101.3725 | K27: ='Pod Build'!$I$26*E$4 -> 101.3725 | L27: ='Pod Build'!$I$26*E$4 -> 101.3725 | M27: ='Pod Build'!$I$26*E$4 -> 101.3725 | N27: ='Pod Build'!$I$26*E$4 -> 101.3725 | O27: =SUM(C27:N27) -> 1140.4406
A28: Pod C: Verifier agent 10-dim | B28: Ramps | C28: ='Pod Build'!$I$27*C$4 -> 50.68625 | D28: ='Pod Build'!$I$27*D$4 -> 76.029375 | E28: ='Pod Build'!$I$27*E$4 -> 101.3725 | F28: ='Pod Build'!$I$27*E$4 -> 101.3725 | G28: ='Pod Build'!$I$27*E$4 -> 101.3725 | H28: ='Pod Build'!$I$27*E$4 -> 101.3725 | I28: ='Pod Build'!$I$27*E$4 -> 101.3725 | J28: ='Pod Build'!$I$27*E$4 -> 101.3725 | K28: ='Pod Build'!$I$27*E$4 -> 101.3725 | L28: ='Pod Build'!$I$27*E$4 -> 101.3725 | M28: ='Pod Build'!$I$27*E$4 -> 101.3725 | N28: ='Pod Build'!$I$27*E$4 -> 101.3725 | O28: =SUM(C28:N28) -> 1140.4406
A29: Pod C: Dense-arm optional (opus_dense per node) | B29: Ramps | C29: ='Pod Build'!$I$28*C$4 -> 0 | D29: ='Pod Build'!$I$28*D$4 -> 0 | E29: ='Pod Build'!$I$28*E$4 -> 0 | F29: ='Pod Build'!$I$28*E$4 -> 0 | G29: ='Pod Build'!$I$28*E$4 -> 0 | H29: ='Pod Build'!$I$28*E$4 -> 0 | I29: ='Pod Build'!$I$28*E$4 -> 0 | J29: ='Pod Build'!$I$28*E$4 -> 0 | K29: ='Pod Build'!$I$28*E$4 -> 0 | L29: ='Pod Build'!$I$28*E$4 -> 0 | M29: ='Pod Build'!$I$28*E$4 -> 0 | N29: ='Pod Build'!$I$28*E$4 -> 0 | O29: =SUM(C29:N29) -> 0
A30: Pod C: Bedrock Evaluations (judge) | B30: Ramps | C30: ='Pod Build'!$I$29*C$4 -> 0 | D30: ='Pod Build'!$I$29*D$4 -> 0 | E30: ='Pod Build'!$I$29*E$4 -> 0 | F30: ='Pod Build'!$I$29*E$4 -> 0 | G30: ='Pod Build'!$I$29*E$4 -> 0 | H30: ='Pod Build'!$I$29*E$4 -> 0 | I30: ='Pod Build'!$I$29*E$4 -> 0 | J30: ='Pod Build'!$I$29*E$4 -> 0 | K30: ='Pod Build'!$I$29*E$4 -> 0 | L30: ='Pod Build'!$I$29*E$4 -> 0 | M30: ='Pod Build'!$I$29*E$4 -> 0 | N30: ='Pod Build'!$I$29*E$4 -> 0 | O30: =SUM(C30:N30) -> 0
A31: Pod D: JAPI Persist outbox writer | B31: Ramps | C31: ='Pod Build'!$I$30*C$4 -> 0 | D31: ='Pod Build'!$I$30*D$4 -> 0 | E31: ='Pod Build'!$I$30*E$4 -> 0 | F31: ='Pod Build'!$I$30*E$4 -> 0 | G31: ='Pod Build'!$I$30*E$4 -> 0 | H31: ='Pod Build'!$I$30*E$4 -> 0 | I31: ='Pod Build'!$I$30*E$4 -> 0 | J31: ='Pod Build'!$I$30*E$4 -> 0 | K31: ='Pod Build'!$I$30*E$4 -> 0 | L31: ='Pod Build'!$I$30*E$4 -> 0 | M31: ='Pod Build'!$I$30*E$4 -> 0 | N31: ='Pod Build'!$I$30*E$4 -> 0 | O31: =SUM(C31:N31) -> 0
A32: Pod D: Outbox sweep (EventBridge Schedule) | B32: Ramps | C32: ='Pod Build'!$I$31*C$4 -> 0.004464 | D32: ='Pod Build'!$I$31*D$4 -> 0.006696 | E32: ='Pod Build'!$I$31*E$4 -> 0.008928 | F32: ='Pod Build'!$I$31*E$4 -> 0.008928 | G32: ='Pod Build'!$I$31*E$4 -> 0.008928 | H32: ='Pod Build'!$I$31*E$4 -> 0.008928 | I32: ='Pod Build'!$I$31*E$4 -> 0.008928 | J32: ='Pod Build'!$I$31*E$4 -> 0.008928 | K32: ='Pod Build'!$I$31*E$4 -> 0.008928 | L32: ='Pod Build'!$I$31*E$4 -> 0.008928 | M32: ='Pod Build'!$I$31*E$4 -> 0.008928 | N32: ='Pod Build'!$I$31*E$4 -> 0.008928 | O32: =SUM(C32:N32) -> 0.10044
A33: Pod D: HITL AppSync API | B33: Ramps | C33: ='Pod Build'!$I$32*C$4 -> 0.017802 | D33: ='Pod Build'!$I$32*D$4 -> 0.026703 | E33: ='Pod Build'!$I$32*E$4 -> 0.035604 | F33: ='Pod Build'!$I$32*E$4 -> 0.035604 | G33: ='Pod Build'!$I$32*E$4 -> 0.035604 | H33: ='Pod Build'!$I$32*E$4 -> 0.035604 | I33: ='Pod Build'!$I$32*E$4 -> 0.035604 | J33: ='Pod Build'!$I$32*E$4 -> 0.035604 | K33: ='Pod Build'!$I$32*E$4 -> 0.035604 | L33: ='Pod Build'!$I$32*E$4 -> 0.035604 | M33: ='Pod Build'!$I$32*E$4 -> 0.035604 | N33: ='Pod Build'!$I$32*E$4 -> 0.035604 | O33: =SUM(C33:N33) -> 0.400545
A34: Pod D: HITL review ECS task (reviewer console) | B34: Always-on | C34: ='Pod Build'!$I$33 -> 18.02005 | D34: ='Pod Build'!$I$33 -> 18.02005 | E34: ='Pod Build'!$I$33 -> 18.02005 | F34: ='Pod Build'!$I$33 -> 18.02005 | G34: ='Pod Build'!$I$33 -> 18.02005 | H34: ='Pod Build'!$I$33 -> 18.02005 | I34: ='Pod Build'!$I$33 -> 18.02005 | J34: ='Pod Build'!$I$33 -> 18.02005 | ... N34: ='Pod Build'!$I$33 -> 18.02005 | O34: =SUM(C34:N34) -> 216.2406
A35: Pod D: S3 projection sink + CloudFront invalidation | B35: Ramps | C35: ='Pod Build'!$I$34*C$4 -> 0.03436775 | D35: ='Pod Build'!$I$34*D$4 -> 0.051551625 | E35: ='Pod Build'!$I$34*E$4 -> 0.0687355 | F35: ='Pod Build'!$I$34*E$4 -> 0.0687355 | G35: ='Pod Build'!$I$34*E$4 -> 0.0687355 | H35: ='Pod Build'!$I$34*E$4 -> 0.0687355 | I35: ='Pod Build'!$I$34*E$4 -> 0.0687355 | J35: ='Pod Build'!$I$34*E$4 -> 0.0687355 | K35: ='Pod Build'!$I$34*E$4 -> 0.0687355 | L35: ='Pod Build'!$I$34*E$4 -> 0.0687355 | M35: ='Pod Build'!$I$34*E$4 -> 0.0687355 | N35: ='Pod Build'!$I$34*E$4 -> 0.0687355 | O35: =SUM(C35:N35) -> 0.77327438
A36: Pod E: FalkorDB on ECS (retrieval store) | B36: Always-on | C36: ='Pod Build'!$I$35 -> 36.0401 | D36: ='Pod Build'!$I$35 -> 36.0401 | E36: ='Pod Build'!$I$35 -> 36.0401 | F36: ='Pod Build'!$I$35 -> 36.0401 | G36: ='Pod Build'!$I$35 -> 36.0401 | H36: ='Pod Build'!$I$35 -> 36.0401 | I36: ='Pod Build'!$I$35 -> 36.0401 | J36: ='Pod Build'!$I$35 -> 36.0401 | ... N36: ='Pod Build'!$I$35 -> 36.0401 | O36: =SUM(C36:N36) -> 432.4812
A37: Pod E: CloudFront distribution | B37: Ramps | C37: ='Pod Build'!$I$36*C$4 -> 0.45 | D37: ='Pod Build'!$I$36*D$4 -> 0.675 | E37: ='Pod Build'!$I$36*E$4 -> 0.9 | F37: ='Pod Build'!$I$36*E$4 -> 0.9 | G37: ='Pod Build'!$I$36*E$4 -> 0.9 | H37: ='Pod Build'!$I$36*E$4 -> 0.9 | I37: ='Pod Build'!$I$36*E$4 -> 0.9 | J37: ='Pod Build'!$I$36*E$4 -> 0.9 | K37: ='Pod Build'!$I$36*E$4 -> 0.9 | L37: ='Pod Build'!$I$36*E$4 -> 0.9 | M37: ='Pod Build'!$I$36*E$4 -> 0.9 | N37: ='Pod Build'!$I$36*E$4 -> 0.9 | O37: =SUM(C37:N37) -> 10.125
A38: Pod E: ALB (console + API ingress) | B38: Always-on | C38: ='Pod Build'!$I$37 -> 22.265 | D38: ='Pod Build'!$I$37 -> 22.265 | E38: ='Pod Build'!$I$37 -> 22.265 | F38: ='Pod Build'!$I$37 -> 22.265 | G38: ='Pod Build'!$I$37 -> 22.265 | H38: ='Pod Build'!$I$37 -> 22.265 | I38: ='Pod Build'!$I$37 -> 22.265 | J38: ='Pod Build'!$I$37 -> 22.265 | ... N38: ='Pod Build'!$I$37 -> 22.265 | O38: =SUM(C38:N38) -> 267.18
A39: Pod E: NAT Gateway (VPC egress) | B39: Always-on | C39: ='Pod Build'!$I$38 -> 33.75 | D39: ='Pod Build'!$I$38 -> 33.75 | E39: ='Pod Build'!$I$38 -> 33.75 | F39: ='Pod Build'!$I$38 -> 33.75 | G39: ='Pod Build'!$I$38 -> 33.75 | H39: ='Pod Build'!$I$38 -> 33.75 | I39: ='Pod Build'!$I$38 -> 33.75 | J39: ='Pod Build'!$I$38 -> 33.75 | ... N39: ='Pod Build'!$I$38 -> 33.75 | O39: =SUM(C39:N39) -> 405
A40: Pod E: Secrets Manager (DB + API creds) | B40: Always-on | C40: ='Pod Build'!$I$39 -> 1.6 | D40: ='Pod Build'!$I$39 -> 1.6 | E40: ='Pod Build'!$I$39 -> 1.6 | F40: ='Pod Build'!$I$39 -> 1.6 | G40: ='Pod Build'!$I$39 -> 1.6 | H40: ='Pod Build'!$I$39 -> 1.6 | I40: ='Pod Build'!$I$39 -> 1.6 | J40: ='Pod Build'!$I$39 -> 1.6 | ... N40: ='Pod Build'!$I$39 -> 1.6 | O40: =SUM(C40:N40) -> 19.2
A41: Pod E: VPC Interface Endpoints | B41: Always-on | C41: ='Pod Build'!$I$40 -> 21.9 | D41: ='Pod Build'!$I$40 -> 21.9 | E41: ='Pod Build'!$I$40 -> 21.9 | F41: ='Pod Build'!$I$40 -> 21.9 | G41: ='Pod Build'!$I$40 -> 21.9 | H41: ='Pod Build'!$I$40 -> 21.9 | I41: ='Pod Build'!$I$40 -> 21.9 | J41: ='Pod Build'!$I$40 -> 21.9 | ... N41: ='Pod Build'!$I$40 -> 21.9 | O41: =SUM(C41:N41) -> 262.8
A42: Pod E: CodeBuild (console/dashboard build) | B42: Ramps | C42: ='Pod Build'!$I$41*C$4 -> 0 | D42: ='Pod Build'!$I$41*D$4 -> 0 | E42: ='Pod Build'!$I$41*E$4 -> 0 | F42: ='Pod Build'!$I$41*E$4 -> 0 | G42: ='Pod Build'!$I$41*E$4 -> 0 | H42: ='Pod Build'!$I$41*E$4 -> 0 | I42: ='Pod Build'!$I$41*E$4 -> 0 | J42: ='Pod Build'!$I$41*E$4 -> 0 | K42: ='Pod Build'!$I$41*E$4 -> 0 | L42: ='Pod Build'!$I$41*E$4 -> 0 | M42: ='Pod Build'!$I$41*E$4 -> 0 | N42: ='Pod Build'!$I$41*E$4 -> 0 | O42: =SUM(C42:N42) -> 0
A43: TOTALS
A44: Monthly total (all Pod Build lines) | C44: =SUM(C5:C42) -> 1136.4366 | D44: =SUM(D5:D42) -> 1194.012 | E44: =SUM(E5:E42) -> 1251.5875 | F44: =SUM(F5:F42) -> 1251.5875 | G44: =SUM(G5:G42) -> 1251.5875 | H44: =SUM(H5:H42) -> 1251.5875 | I44: =SUM(I5:I42) -> 1251.5875 | J44: =SUM(J5:J42) -> 1251.5875 | ... N44: =SUM(N5:N42) -> 1251.5875 | O44: =SUM(C44:N44) -> 14846.323

Sheet Gantt
A1: Gantt -- 14-week core (Pod lanes, parallel after 2-week foundation)
A2: ="Kickoff w/c 2026-07-27 -> go-live 2026-11-01. SlipWeeks="&TEXT(SlipWeeks,"0")&" applied via proportional stretch inside the core span, additive shift beyond it. Bars = belt-and-braces cell value + conditional formatting (uniform green = proposed/recommended)." -> Kickoff w/c 2026-07-27 -> go-live 2026-11-01. SlipWeeks=0 applied via proportional stretch inside the core span, additive shift beyond it. Bars = belt-and-braces cell value + conditional formatting (uniform green = proposed/recommended).
B3: Task | L3: Jul 26 | M3: Aug 26 | Q3: Sep 26 | U3: Oct 26 | Y3: Nov 26
B4: Week # | L4: 1 | M4: 2 | N4: 3 | O4: 4 | P4: 5 | Q4: 6 | R4: 7 | S4: 8 | T4: 9 | U4: 10 | V4: 11 | W4: 12 | X4: 13 | Y4: 14 | Z4: 15 | AA4: 16 | AB4: 17 | AC4: 18 | AE4: =14+SlipWeeks -> 14 | AF4: =12+SlipWeeks -> 12 | AG4: =16+SlipWeeks -> 16
B5: Go-live range | L5: =IF(L$4=$AE$4,"▲",IF(L$4=$AF$4,"◁",IF(L$4=$AG$4,"▷",IF(AND(L$4>$AF$4,L$4<$AG$4),"·","")))) | M5: =IF(M$4=$AE$4,"▲",IF(M$4=$AF$4,"◁",IF(M$4=$AG$4,"▷",IF(AND(M$4>$AF$4,M$4<$AG$4),"·","")))) | N5: =IF(N$4=$AE$4,"▲",IF(N$4=$AF$4,"◁",IF(N$4=$AG$4,"▷",IF(AND(N$4>$AF$4,N$4<$AG$4),"·","")))) | O5: =IF(O$4=$AE$4,"▲",IF(O$4=$AF$4,"◁",IF(O$4=$AG$4,"▷",IF(AND(O$4>$AF$4,O$4<$AG$4),"·","")))) | P5: =IF(P$4=$AE$4,"▲",IF(P$4=$AF$4,"◁",IF(P$4=$AG$4,"▷",IF(AND(P$4>$AF$4,P$4<$AG$4),"·","")))) | Q5: =IF(Q$4=$AE$4,"▲",IF(Q$4=$AF$4,"◁",IF(Q$4=$AG$4,"▷",IF(AND(Q$4>$AF$4,Q$4<$AG$4),"·","")))) | R5: =IF(R$4=$AE$4,"▲",IF(R$4=$AF$4,"◁",IF(R$4=$AG$4,"▷",IF(AND(R$4>$AF$4,R$4<$AG$4),"·","")))) | S5: =IF(S$4=$AE$4,"▲",IF(S$4=$AF$4,"◁",IF(S$4=$AG$4,"▷",IF(AND(S$4>$AF$4,S$4<$AG$4),"·","")))) | ... AC5: =IF(AC$4=$AE$4,"▲",IF(AC$4=$AF$4,"◁",IF(AC$4=$AG$4,"▷",IF(AND(AC$4>$AF$4,AC$4<$AG$4),"·",""))))
A6: Id | B6: Task | C6: Pod | D6: Start wk | E6: Wks | AI6: Live start | AJ6: Live end | AK6: Basis / source
A7: G-A-1 | B7: Pod A -- Ingestion foundation | C7: A | D7: 1 | E7: 2 | F7: =MIN(18,IF(D7<=14,ROUND((D7-1)*(14+SlipWeeks)/14,0)+1,D7+SlipWeeks)) -> 1 | G7: =MIN(18,IF(D7+E7-1<=14,MAX(ROUND((D7+E7-1)*(14+SlipWeeks)/14,0),F7),D7+E7-1+SlipWeeks)) -> 2 | L7: =IF(AND(L$4>=$F7,L$4<=$G7),1,"") -> 1 | M7: =IF(AND(M$4>=$F7,M$4<=$G7),1,"") -> 1 | N7: =IF(AND(N$4>=$F7,N$4<=$G7),1,"") | O7: =IF(AND(O$4>=$F7,O$4<=$G7),1,"") | P7: =IF(AND(P$4>=$F7,P$4<=$G7),1,"") | Q7: =IF(AND(Q$4>=$F7,Q$4<=$G7),1,"") | R7: =IF(AND(R$4>=$F7,R$4<=$G7),1,"") | S7: =IF(AND(S$4>=$F7,S$4<=$G7),1,"") | ... AC7: =IF(AND(AC$4>=$F7,AC$4<=$G7),1,"") | AK7: API GW, S3 buckets, EventBridge rule/scheduler, SQS provisioned first (shared foundation).
A8: G-A-1a | B8: - IaC: template.yaml Pod A resources | C8: A | D8: 1 | E8: 1 | F8: =MEDIAN($F7,$G7,$F7+ROUND((D8-$D7)/$E7*($G7-$F7+1),0)) -> 1 | G8: =MEDIAN(F8,$G7,$F7+ROUND((D8+E8-$D7)/$E7*($G7-$F7+1),0)-1) -> 1 | L8: =IF(AND(L$4>=$F8,L$4<=$G8),1,"") -> 1 | M8: =IF(AND(M$4>=$F8,M$4<=$G8),1,"") | N8: =IF(AND(N$4>=$F8,N$4<=$G8),1,"") | O8: =IF(AND(O$4>=$F8,O$4<=$G8),1,"") | P8: =IF(AND(P$4>=$F8,P$4<=$G8),1,"") | Q8: =IF(AND(Q$4>=$F8,Q$4<=$G8),1,"") | R8: =IF(AND(R$4>=$F8,R$4<=$G8),1,"") | S8: =IF(AND(S$4>=$F8,S$4<=$G8),1,"") | ... AC8: =IF(AND(AC$4>=$F8,AC$4<=$G8),1,"") | AK8: SAM stack apply.
A9: G-A-1b | B9: - Smoke test: upload -> canonical S3 | C9: A | D9: 2 | E9: 1 | F9: =MEDIAN($F7,$G7,$F7+ROUND((D9-$D7)/$E7*($G7-$F7+1),0)) -> 2 | G9: =MEDIAN(F9,$G7,$F7+ROUND((D9+E9-$D7)/$E7*($G7-$F7+1),0)-1) -> 2 | L9: =IF(AND(L$4>=$F9,L$4<=$G9),1,"") | M9: =IF(AND(M$4>=$F9,M$4<=$G9),1,"") -> 1 | N9: =IF(AND(N$4>=$F9,N$4<=$G9),1,"") | O9: =IF(AND(O$4>=$F9,O$4<=$G9),1,"") | P9: =IF(AND(P$4>=$F9,P$4<=$G9),1,"") | Q9: =IF(AND(Q$4>=$F9,Q$4<=$G9),1,"") | R9: =IF(AND(R$4>=$F9,R$4<=$G9),1,"") | S9: =IF(AND(S$4>=$F9,S$4<=$G9),1,"") | ... AC9: =IF(AND(AC$4>=$F9,AC$4<=$G9),1,"") | AK9: End-to-end ingest smoke.
A10: G-A-2 | B10: Pod A -- ETL worker + validation live | C10: A | D10: 3 | E10: 3 | F10: =MIN(18,IF(D10<=14,ROUND((D10-1)*(14+SlipWeeks)/14,0)+1,D10+SlipWeeks)) -> 3 | G10: =MIN(18,IF(D10+E10-1<=14,MAX(ROUND((D10+E10-1)*(14+SlipWeeks)/14,0),F10),D10+E10-1+SlipWeeks)) -> 5 | L10: =IF(AND(L$4>=$F10,L$4<=$G10),1,"") | M10: =IF(AND(M$4>=$F10,M$4<=$G10),1,"") | N10: =IF(AND(N$4>=$F10,N$4<=$G10),1,"") -> 1 | O10: =IF(AND(O$4>=$F10,O$4<=$G10),1,"") -> 1 | P10: =IF(AND(P$4>=$F10,P$4<=$G10),1,"") -> 1 | Q10: =IF(AND(Q$4>=$F10,Q$4<=$G10),1,"") | R10: =IF(AND(R$4>=$F10,R$4<=$G10),1,"") | S10: =IF(AND(S$4>=$F10,S$4<=$G10),1,"") | ... AC10: =IF(AND(AC$4>=$F10,AC$4<=$G10),1,"") | AK10: Ingestion Coordinator Lambda + sanity-check/quarantine path hardened.
A11: G-A-2a | B11: - Build EtlFn + DLQ wiring | C11: A | D11: 3 | E11: 2 | F11: =MEDIAN($F10,$G10,$F10+ROUND((D11-$D10)/$E10*($G10-$F10+1),0)) -> 3 | G11: =MEDIAN(F11,$G10,$F10+ROUND((D11+E11-$D10)/$E10*($G10-$F10+1),0)-1) -> 4 | L11: =IF(AND(L$4>=$F11,L$4<=$G11),1,"") | M11: =IF(AND(M$4>=$F11,M$4<=$G11),1,"") | N11: =IF(AND(N$4>=$F11,N$4<=$G11),1,"") -> 1 | O11: =IF(AND(O$4>=$F11,O$4<=$G11),1,"") -> 1 | P11: =IF(AND(P$4>=$F11,P$4<=$G11),1,"") | Q11: =IF(AND(Q$4>=$F11,Q$4<=$G11),1,"") | R11: =IF(AND(R$4>=$F11,R$4<=$G11),1,"") | S11: =IF(AND(S$4>=$F11,S$4<=$G11),1,"") | ... AC11: =IF(AND(AC$4>=$F11,AC$4<=$G11),1,"") | AK11: template.yaml EtlFn.
A12: G-A-2b | B12: - Quarantine + CloudWatch dashboards | C12: A | D12: 5 | E12: 1 | F12: =MEDIAN($F10,$G10,$F10+ROUND((D12-$D10)/$E10*($G10-$F10+1),0)) -> 5 | G12: =MEDIAN(F12,$G10,$F10+ROUND((D12+E12-$D10)/$E10*($G10-$F10+1),0)-1) -> 5 | L12: =IF(AND(L$4>=$F12,L$4<=$G12),1,"") | M12: =IF(AND(M$4>=$F12,M$4<=$G12),1,"") | N12: =IF(AND(N$4>=$F12,N$4<=$G12),1,"") | O12: =IF(AND(O$4>=$F12,O$4<=$G12),1,"") | P12: =IF(AND(P$4>=$F12,P$4<=$G12),1,"") -> 1 | Q12: =IF(AND(Q$4>=$F12,Q$4<=$G12),1,"") | R12: =IF(AND(R$4>=$F12,R$4<=$G12),1,"") | S12: =IF(AND(S$4>=$F12,S$4<=$G12),1,"") | ... AC12: =IF(AND(AC$4>=$F12,AC$4<=$G12),1,"") | AK12: arch_infra_persistence.md A.8.
A13: G-B-1 | B13: Pod B -- Matching engine + Titan + OpenSearch | C13: B | D13: 3 | E13: 4 | F13: =MIN(18,IF(D13<=14,ROUND((D13-1)*(14+SlipWeeks)/14,0)+1,D13+SlipWeeks)) -> 3 | G13: =MIN(18,IF(D13+E13-1<=14,MAX(ROUND((D13+E13-1)*(14+SlipWeeks)/14,0),F13),D13+E13-1+SlipWeeks)) -> 6 | L13: =IF(AND(L$4>=$F13,L$4<=$G13),1,"") | M13: =IF(AND(M$4>=$F13,M$4<=$G13),1,"") | N13: =IF(AND(N$4>=$F13,N$4<=$G13),1,"") -> 1 | O13: =IF(AND(O$4>=$F13,O$4<=$G13),1,"") -> 1 | P13: =IF(AND(P$4>=$F13,P$4<=$G13),1,"") -> 1 | Q13: =IF(AND(Q$4>=$F13,Q$4<=$G13),1,"") -> 1 | R13: =IF(AND(R$4>=$F13,R$4<=$G13),1,"") | S13: =IF(AND(S$4>=$F13,S$4<=$G13),1,"") | ... AC13: =IF(AND(AC$4>=$F13,AC$4<=$G13),1,"") | AK13: AIA Matching Engine gates A/B/C, Titan embeddings write path, OpenSearch index.
A14: G-B-1a | B14: - Aurora 2xlarge provisioned | C14: B | D14: 3 | E14: 1 | F14: =MEDIAN($F13,$G13,$F13+ROUND((D14-$D13)/$E13*($G13-$F13+1),0)) -> 3 | G14: =MEDIAN(F14,$G13,$F13+ROUND((D14+E14-$D13)/$E13*($G13-$F13+1),0)-1) -> 3 | L14: =IF(AND(L$4>=$F14,L$4<=$G14),1,"") | M14: =IF(AND(M$4>=$F14,M$4<=$G14),1,"") | N14: =IF(AND(N$4>=$F14,N$4<=$G14),1,"") -> 1 | O14: =IF(AND(O$4>=$F14,O$4<=$G14),1,"") | P14: =IF(AND(P$4>=$F14,P$4<=$G14),1,"") | Q14: =IF(AND(Q$4>=$F14,Q$4<=$G14),1,"") | R14: =IF(AND(R$4>=$F14,R$4<=$G14),1,"") | S14: =IF(AND(S$4>=$F14,S$4<=$G14),1,"") | ... AC14: =IF(AND(AC$4>=$F14,AC$4<=$G14),1,"") | AK14: System-of-record instance.
A15: G-B-1b | B15: - OpenSearch fuzzy+kNN index build | C15: B | D15: 4 | E15: 2 | F15: =MEDIAN($F13,$G13,$F13+ROUND((D15-$D13)/$E13*($G13-$F13+1),0)) -> 4 | G15: =MEDIAN(F15,$G13,$F13+ROUND((D15+E15-$D13)/$E13*($G13-$F13+1),0)-1) -> 5 | L15: =IF(AND(L$4>=$F15,L$4<=$G15),1,"") | M15: =IF(AND(M$4>=$F15,M$4<=$G15),1,"") | N15: =IF(AND(N$4>=$F15,N$4<=$G15),1,"") | O15: =IF(AND(O$4>=$F15,O$4<=$G15),1,"") -> 1 | P15: =IF(AND(P$4>=$F15,P$4<=$G15),1,"") -> 1 | Q15: =IF(AND(Q$4>=$F15,Q$4<=$G15),1,"") | R15: =IF(AND(R$4>=$F15,R$4<=$G15),1,"") | S15: =IF(AND(S$4>=$F15,S$4<=$G15),1,"") | ... AC15: =IF(AND(AC$4>=$F15,AC$4<=$G15),1,"") | AK15: Dense + sparse arms.
A16: G-B-1c | B16: - Matching gate A/B/C integration test | C16: B | D16: 6 | E16: 1 | F16: =MEDIAN($F13,$G13,$F13+ROUND((D16-$D13)/$E13*($G13-$F13+1),0)) -> 6 | G16: =MEDIAN(F16,$G13,$F13+ROUND((D16+E16-$D13)/$E13*($G13-$F13+1),0)-1) -> 6 | L16: =IF(AND(L$4>=$F16,L$4<=$G16),1,"") | M16: =IF(AND(M$4>=$F16,M$4<=$G16),1,"") | N16: =IF(AND(N$4>=$F16,N$4<=$G16),1,"") | O16: =IF(AND(O$4>=$F16,O$4<=$G16),1,"") | P16: =IF(AND(P$4>=$F16,P$4<=$G16),1,"") | Q16: =IF(AND(Q$4>=$F16,Q$4<=$G16),1,"") -> 1 | R16: =IF(AND(R$4>=$F16,R$4<=$G16),1,"") | S16: =IF(AND(S$4>=$F16,S$4<=$G16),1,"") | ... AC16: =IF(AND(AC$4>=$F16,AC$4<=$G16),1,"") | AK16: Confidence-band gate.
A17: G-C-1 | B17: Pod C -- Strands orchestrator + agents | C17: C | D17: 3 | E17: 5 | F17: =MIN(18,IF(D17<=14,ROUND((D17-1)*(14+SlipWeeks)/14,0)+1,D17+SlipWeeks)) -> 3 | G17: =MIN(18,IF(D17+E17-1<=14,MAX(ROUND((D17+E17-1)*(14+SlipWeeks)/14,0),F17),D17+E17-1+SlipWeeks)) -> 7 | L17: =IF(AND(L$4>=$F17,L$4<=$G17),1,"") | M17: =IF(AND(M$4>=$F17,M$4<=$G17),1,"") | N17: =IF(AND(N$4>=$F17,N$4<=$G17),1,"") -> 1 | O17: =IF(AND(O$4>=$F17,O$4<=$G17),1,"") -> 1 | P17: =IF(AND(P$4>=$F17,P$4<=$G17),1,"") -> 1 | Q17: =IF(AND(Q$4>=$F17,Q$4<=$G17),1,"") -> 1 | R17: =IF(AND(R$4>=$F17,R$4<=$G17),1,"") -> 1 | S17: =IF(AND(S$4>=$F17,S$4<=$G17),1,"") | ... AC17: =IF(AND(AC$4>=$F17,AC$4<=$G17),1,"") | AK17: Orchestrator, AgentCore Memory, specialist + verifier agents wired to Bedrock.
A18: G-C-1a | B18: - Strands Orchestrator Opus 4.8 wiring | C18: C | D18: 3 | E18: 2 | F18: =MEDIAN($F17,$G17,$F17+ROUND((D18-$D17)/$E17*($G17-$F17+1),0)) -> 3 | G18: =MEDIAN(F18,$G17,$F17+ROUND((D18+E18-$D17)/$E17*($G17-$F17+1),0)-1) -> 4 | L18: =IF(AND(L$4>=$F18,L$4<=$G18),1,"") | M18: =IF(AND(M$4>=$F18,M$4<=$G18),1,"") | N18: =IF(AND(N$4>=$F18,N$4<=$G18),1,"") -> 1 | O18: =IF(AND(O$4>=$F18,O$4<=$G18),1,"") -> 1 | P18: =IF(AND(P$4>=$F18,P$4<=$G18),1,"") | Q18: =IF(AND(Q$4>=$F18,Q$4<=$G18),1,"") | R18: =IF(AND(R$4>=$F18,R$4<=$G18),1,"") | S18: =IF(AND(S$4>=$F18,S$4<=$G18),1,"") | ... AC18: =IF(AND(AC$4>=$F18,AC$4<=$G18),1,"") | AK18: orchestrator.py.
A19: G-C-1b | B19: - AgentCore Memory short/long-term | C19: C | D19: 5 | E19: 2 | F19: =MEDIAN($F17,$G17,$F17+ROUND((D19-$D17)/$E17*($G17-$F17+1),0)) -> 5 | G19: =MEDIAN(F19,$G17,$F17+ROUND((D19+E19-$D17)/$E17*($G17-$F17+1),0)-1) -> 6 | L19: =IF(AND(L$4>=$F19,L$4<=$G19),1,"") | M19: =IF(AND(M$4>=$F19,M$4<=$G19),1,"") | N19: =IF(AND(N$4>=$F19,N$4<=$G19),1,"") | O19: =IF(AND(O$4>=$F19,O$4<=$G19),1,"") | P19: =IF(AND(P$4>=$F19,P$4<=$G19),1,"") -> 1 | Q19: =IF(AND(Q$4>=$F19,Q$4<=$G19),1,"") -> 1 | R19: =IF(AND(R$4>=$F19,R$4<=$G19),1,"") | S19: =IF(AND(S$4>=$F19,S$4<=$G19),1,"") | ... AC19: =IF(AND(AC$4>=$F19,AC$4<=$G19),1,"") | AK19: Events + records + retrieval.
A20: G-C-1c | B20: - Specialist + Verifier + Evaluations | C20: C | D20: 7 | E20: 1 | F20: =MEDIAN($F17,$G17,$F17+ROUND((D20-$D17)/$E17*($G17-$F17+1),0)) -> 7 | G20: =MEDIAN(F20,$G17,$F17+ROUND((D20+E20-$D17)/$E17*($G17-$F17+1),0)-1) -> 7 | L20: =IF(AND(L$4>=$F20,L$4<=$G20),1,"") | M20: =IF(AND(M$4>=$F20,M$4<=$G20),1,"") | N20: =IF(AND(N$4>=$F20,N$4<=$G20),1,"") | O20: =IF(AND(O$4>=$F20,O$4<=$G20),1,"") | P20: =IF(AND(P$4>=$F20,P$4<=$G20),1,"") | Q20: =IF(AND(Q$4>=$F20,Q$4<=$G20),1,"") | R20: =IF(AND(R$4>=$F20,R$4<=$G20),1,"") -> 1 | S20: =IF(AND(S$4>=$F20,S$4<=$G20),1,"") | ... AC20: =IF(AND(AC$4>=$F20,AC$4<=$G20),1,"") | AK20: 10-dim verifier gate.
A21: G-D-1 | B21: Pod D -- Persistence + HITL | C21: D | D21: 3 | E21: 5 | F21: =MIN(18,IF(D21<=14,ROUND((D21-1)*(14+SlipWeeks)/14,0)+1,D21+SlipWeeks)) -> 3 | G21: =MIN(18,IF(D21+E21-1<=14,MAX(ROUND((D21+E21-1)*(14+SlipWeeks)/14,0),F21),D21+E21-1+SlipWeeks)) -> 7 | L21: =IF(AND(L$4>=$F21,L$4<=$G21),1,"") | M21: =IF(AND(M$4>=$F21,M$4<=$G21),1,"") | N21: =IF(AND(N$4>=$F21,N$4<=$G21),1,"") -> 1 | O21: =IF(AND(O$4>=$F21,O$4<=$G21),1,"") -> 1 | P21: =IF(AND(P$4>=$F21,P$4<=$G21),1,"") -> 1 | Q21: =IF(AND(Q$4>=$F21,Q$4<=$G21),1,"") -> 1 | R21: =IF(AND(R$4>=$F21,R$4<=$G21),1,"") -> 1 | S21: =IF(AND(S$4>=$F21,S$4<=$G21),1,"") | ... AC21: =IF(AND(AC$4>=$F21,AC$4<=$G21),1,"") | AK21: Outbox writer, sweep schedule, AppSync HITL API, ECS reviewer console.
A22: G-D-1a | B22: - JAPI Persist outbox + sweep | C22: D | D22: 3 | E22: 2 | F22: =MEDIAN($F21,$G21,$F21+ROUND((D22-$D21)/$E21*($G21-$F21+1),0)) -> 3 | G22: =MEDIAN(F22,$G21,$F21+ROUND((D22+E22-$D21)/$E21*($G21-$F21+1),0)-1) -> 4 | L22: =IF(AND(L$4>=$F22,L$4<=$G22),1,"") | M22: =IF(AND(M$4>=$F22,M$4<=$G22),1,"") | N22: =IF(AND(N$4>=$F22,N$4<=$G22),1,"") -> 1 | O22: =IF(AND(O$4>=$F22,O$4<=$G22),1,"") -> 1 | P22: =IF(AND(P$4>=$F22,P$4<=$G22),1,"") | Q22: =IF(AND(Q$4>=$F22,Q$4<=$G22),1,"") | R22: =IF(AND(R$4>=$F22,R$4<=$G22),1,"") | S22: =IF(AND(S$4>=$F22,S$4<=$G22),1,"") | ... AC22: =IF(AND(AC$4>=$F22,AC$4<=$G22),1,"") | AK22: Transactional outbox pattern.
A23: G-D-1b | B23: - HITL AppSync + ECS console | C23: D | D23: 5 | E23: 2 | F23: =MEDIAN($F21,$G21,$F21+ROUND((D23-$D21)/$E21*($G21-$F21+1),0)) -> 5 | G23: =MEDIAN(F23,$G21,$F21+ROUND((D23+E23-$D21)/$E21*($G21-$F21+1),0)-1) -> 6 | L23: =IF(AND(L$4>=$F23,L$4<=$G23),1,"") | M23: =IF(AND(M$4>=$F23,M$4<=$G23),1,"") | N23: =IF(AND(N$4>=$F23,N$4<=$G23),1,"") | O23: =IF(AND(O$4>=$F23,O$4<=$G23),1,"") | P23: =IF(AND(P$4>=$F23,P$4<=$G23),1,"") -> 1 | Q23: =IF(AND(Q$4>=$F23,Q$4<=$G23),1,"") -> 1 | R23: =IF(AND(R$4>=$F23,R$4<=$G23),1,"") | S23: =IF(AND(S$4>=$F23,S$4<=$G23),1,"") | ... AC23: =IF(AND(AC$4>=$F23,AC$4<=$G23),1,"") | AK23: Reviewer UI live.
A24: G-D-1c | B24: - Projection sink + CloudFront invalidation | C24: D | D24: 7 | E24: 1 | F24: =MEDIAN($F21,$G21,$F21+ROUND((D24-$D21)/$E21*($G21-$F21+1),0)) -> 7 | G24: =MEDIAN(F24,$G21,$F21+ROUND((D24+E24-$D21)/$E21*($G21-$F21+1),0)-1) -> 7 | L24: =IF(AND(L$4>=$F24,L$4<=$G24),1,"") | M24: =IF(AND(M$4>=$F24,M$4<=$G24),1,"") | N24: =IF(AND(N$4>=$F24,N$4<=$G24),1,"") | O24: =IF(AND(O$4>=$F24,O$4<=$G24),1,"") | P24: =IF(AND(P$4>=$F24,P$4<=$G24),1,"") | Q24: =IF(AND(Q$4>=$F24,Q$4<=$G24),1,"") | R24: =IF(AND(R$4>=$F24,R$4<=$G24),1,"") -> 1 | S24: =IF(AND(S$4>=$F24,S$4<=$G24),1,"") | ... AC24: =IF(AND(AC$4>=$F24,AC$4<=$G24),1,"") | AK24: S3 projection publish.
A25: G-E-1 | B25: Pod E -- Platform (VPC, security, CI/CD) | C25: E | D25: 1 | E25: 3 | F25: =MIN(18,IF(D25<=14,ROUND((D25-1)*(14+SlipWeeks)/14,0)+1,D25+SlipWeeks)) -> 1 | G25: =MIN(18,IF(D25+E25-1<=14,MAX(ROUND((D25+E25-1)*(14+SlipWeeks)/14,0),F25),D25+E25-1+SlipWeeks)) -> 3 | L25: =IF(AND(L$4>=$F25,L$4<=$G25),1,"") -> 1 | M25: =IF(AND(M$4>=$F25,M$4<=$G25),1,"") -> 1 | N25: =IF(AND(N$4>=$F25,N$4<=$G25),1,"") -> 1 | O25: =IF(AND(O$4>=$F25,O$4<=$G25),1,"") | P25: =IF(AND(P$4>=$F25,P$4<=$G25),1,"") | Q25: =IF(AND(Q$4>=$F25,Q$4<=$G25),1,"") | R25: =IF(AND(R$4>=$F25,R$4<=$G25),1,"") | S25: =IF(AND(S$4>=$F25,S$4<=$G25),1,"") | ... AC25: =IF(AND(AC$4>=$F25,AC$4<=$G25),1,"") | AK25: FalkorDB, CloudFront, ALB, NAT, Secrets Manager, VPC endpoints, CodeBuild.
A26: G-E-1a | B26: - VPC endpoints + NAT + Secrets Manager | C26: E | D26: 1 | E26: 2 | F26: =MEDIAN($F25,$G25,$F25+ROUND((D26-$D25)/$E25*($G25-$F25+1),0)) -> 1 | G26: =MEDIAN(F26,$G25,$F25+ROUND((D26+E26-$D25)/$E25*($G25-$F25+1),0)-1) -> 2 | L26: =IF(AND(L$4>=$F26,L$4<=$G26),1,"") -> 1 | M26: =IF(AND(M$4>=$F26,M$4<=$G26),1,"") -> 1 | N26: =IF(AND(N$4>=$F26,N$4<=$G26),1,"") | O26: =IF(AND(O$4>=$F26,O$4<=$G26),1,"") | P26: =IF(AND(P$4>=$F26,P$4<=$G26),1,"") | Q26: =IF(AND(Q$4>=$F26,Q$4<=$G26),1,"") | R26: =IF(AND(R$4>=$F26,R$4<=$G26),1,"") | S26: =IF(AND(S$4>=$F26,S$4<=$G26),1,"") | ... AC26: =IF(AND(AC$4>=$F26,AC$4<=$G26),1,"") | AK26: Network foundation.
A27: G-E-1b | B27: - CodeBuild pipeline + FalkorDB ECS | C27: E | D27: 2 | E27: 2 | F27: =MEDIAN($F25,$G25,$F25+ROUND((D27-$D25)/$E25*($G25-$F25+1),0)) -> 2 | G27: =MEDIAN(F27,$G25,$F25+ROUND((D27+E27-$D25)/$E25*($G25-$F25+1),0)-1) -> 3 | L27: =IF(AND(L$4>=$F27,L$4<=$G27),1,"") | M27: =IF(AND(M$4>=$F27,M$4<=$G27),1,"") -> 1 | N27: =IF(AND(N$4>=$F27,N$4<=$G27),1,"") -> 1 | O27: =IF(AND(O$4>=$F27,O$4<=$G27),1,"") | P27: =IF(AND(P$4>=$F27,P$4<=$G27),1,"") | Q27: =IF(AND(Q$4>=$F27,Q$4<=$G27),1,"") | R27: =IF(AND(R$4>=$F27,R$4<=$G27),1,"") | S27: =IF(AND(S$4>=$F27,S$4<=$G27),1,"") | ... AC27: =IF(AND(AC$4>=$F27,AC$4<=$G27),1,"") | AK27: CI/CD + retrieval store.
A28: G-X-1 | B28: Integration -- first delivery E2E | C28: ALL | D28: 8 | E28: 2 | F28: =MIN(18,IF(D28<=14,ROUND((D28-1)*(14+SlipWeeks)/14,0)+1,D28+SlipWeeks)) -> 8 | G28: =MIN(18,IF(D28+E28-1<=14,MAX(ROUND((D28+E28-1)*(14+SlipWeeks)/14,0),F28),D28+E28-1+SlipWeeks)) -> 9 | L28: =IF(AND(L$4>=$F28,L$4<=$G28),1,"") | M28: =IF(AND(M$4>=$F28,M$4<=$G28),1,"") | N28: =IF(AND(N$4>=$F28,N$4<=$G28),1,"") | O28: =IF(AND(O$4>=$F28,O$4<=$G28),1,"") | P28: =IF(AND(P$4>=$F28,P$4<=$G28),1,"") | Q28: =IF(AND(Q$4>=$F28,Q$4<=$G28),1,"") | R28: =IF(AND(R$4>=$F28,R$4<=$G28),1,"") | S28: =IF(AND(S$4>=$F28,S$4<=$G28),1,"") -> 1 | ... AC28: =IF(AND(AC$4>=$F28,AC$4<=$G28),1,"") | AK28: First vendor delivery run end-to-end through all 5 zones.
A29: G-X-1a | B29: - E2E dry run against fixture delivery | C29: ALL | D29: 8 | E29: 1 | F29: =MEDIAN($F28,$G28,$F28+ROUND((D29-$D28)/$E28*($G28-$F28+1),0)) -> 8 | G29: =MEDIAN(F29,$G28,$F28+ROUND((D29+E29-$D28)/$E28*($G28-$F28+1),0)-1) -> 8 | L29: =IF(AND(L$4>=$F29,L$4<=$G29),1,"") | M29: =IF(AND(M$4>=$F29,M$4<=$G29),1,"") | N29: =IF(AND(N$4>=$F29,N$4<=$G29),1,"") | O29: =IF(AND(O$4>=$F29,O$4<=$G29),1,"") | P29: =IF(AND(P$4>=$F29,P$4<=$G29),1,"") | Q29: =IF(AND(Q$4>=$F29,Q$4<=$G29),1,"") | R29: =IF(AND(R$4>=$F29,R$4<=$G29),1,"") | S29: =IF(AND(S$4>=$F29,S$4<=$G29),1,"") -> 1 | ... AC29: =IF(AND(AC$4>=$F29,AC$4<=$G29),1,"") | AK29: Smoke run.
A30: G-X-1b | B30: - Fix findings from dry run | C30: ALL | D30: 9 | E30: 1 | F30: =MEDIAN($F28,$G28,$F28+ROUND((D30-$D28)/$E28*($G28-$F28+1),0)) -> 9 | G30: =MEDIAN(F30,$G28,$F28+ROUND((D30+E30-$D28)/$E28*($G28-$F28+1),0)-1) -> 9 | L30: =IF(AND(L$4>=$F30,L$4<=$G30),1,"") | M30: =IF(AND(M$4>=$F30,M$4<=$G30),1,"") | N30: =IF(AND(N$4>=$F30,N$4<=$G30),1,"") | O30: =IF(AND(O$4>=$F30,O$4<=$G30),1,"") | P30: =IF(AND(P$4>=$F30,P$4<=$G30),1,"") | Q30: =IF(AND(Q$4>=$F30,Q$4<=$G30),1,"") | R30: =IF(AND(R$4>=$F30,R$4<=$G30),1,"") | S30: =IF(AND(S$4>=$F30,S$4<=$G30),1,"") | ... AC30: =IF(AND(AC$4>=$F30,AC$4<=$G30),1,"") | AK30: Bug-fix buffer.
A31: G-X-2 | B31: Go-live readiness -- HITL live + cutover | C31: ALL | D31: 11 | E31: 4 | F31: =MIN(18,IF(D31<=14,ROUND((D31-1)*(14+SlipWeeks)/14,0)+1,D31+SlipWeeks)) -> 11 | G31: =MIN(18,IF(D31+E31-1<=14,MAX(ROUND((D31+E31-1)*(14+SlipWeeks)/14,0),F31),D31+E31-1+SlipWeeks)) -> 14 | L31: =IF(AND(L$4>=$F31,L$4<=$G31),1,"") | M31: =IF(AND(M$4>=$F31,M$4<=$G31),1,"") | N31: =IF(AND(N$4>=$F31,N$4<=$G31),1,"") | O31: =IF(AND(O$4>=$F31,O$4<=$G31),1,"") | P31: =IF(AND(P$4>=$F31,P$4<=$G31),1,"") | Q31: =IF(AND(Q$4>=$F31,Q$4<=$G31),1,"") | R31: =IF(AND(R$4>=$F31,R$4<=$G31),1,"") | S31: =IF(AND(S$4>=$F31,S$4<=$G31),1,"") | ... AC31: =IF(AND(AC$4>=$F31,AC$4<=$G31),1,"") | AK31: HITL review live for reviewers, production cutover rehearsal, go-live.
A32: G-X-2a | B32: - HITL reviewer UAT | C32: ALL | D32: 11 | E32: 2 | F32: =MEDIAN($F31,$G31,$F31+ROUND((D32-$D31)/$E31*($G31-$F31+1),0)) -> 11 | G32: =MEDIAN(F32,$G31,$F31+ROUND((D32+E32-$D31)/$E31*($G31-$F31+1),0)-1) -> 12 | L32: =IF(AND(L$4>=$F32,L$4<=$G32),1,"") | M32: =IF(AND(M$4>=$F32,M$4<=$G32),1,"") | N32: =IF(AND(N$4>=$F32,N$4<=$G32),1,"") | O32: =IF(AND(O$4>=$F32,O$4<=$G32),1,"") | P32: =IF(AND(P$4>=$F32,P$4<=$G32),1,"") | Q32: =IF(AND(Q$4>=$F32,Q$4<=$G32),1,"") | R32: =IF(AND(R$4>=$F32,R$4<=$G32),1,"") | S32: =IF(AND(S$4>=$F32,S$4<=$G32),1,"") | ... AC32: =IF(AND(AC$4>=$F32,AC$4<=$G32),1,"") | AK32: Reviewer sign-off.
A33: G-X-2b | B33: - Production cutover rehearsal | C33: ALL | D33: 13 | E33: 1 | F33: =MEDIAN($F31,$G31,$F31+ROUND((D33-$D31)/$E31*($G31-$F31+1),0)) -> 13 | G33: =MEDIAN(F33,$G31,$F31+ROUND((D33+E33-$D31)/$E31*($G31-$F31+1),0)-1) -> 13 | L33: =IF(AND(L$4>=$F33,L$4<=$G33),1,"") | M33: =IF(AND(M$4>=$F33,M$4<=$G33),1,"") | N33: =IF(AND(N$4>=$F33,N$4<=$G33),1,"") | O33: =IF(AND(O$4>=$F33,O$4<=$G33),1,"") | P33: =IF(AND(P$4>=$F33,P$4<=$G33),1,"") | Q33: =IF(AND(Q$4>=$F33,Q$4<=$G33),1,"") | R33: =IF(AND(R$4>=$F33,R$4<=$G33),1,"") | S33: =IF(AND(S$4>=$F33,S$4<=$G33),1,"") | ... AC33: =IF(AND(AC$4>=$F33,AC$4<=$G33),1,"") | AK33: Dry-run cutover.
A34: G-X-2c | B34: - Go-live 2026-11-01 | C34: ALL | D34: 14 | E34: 1 | F34: =MEDIAN($F31,$G31,$F31+ROUND((D34-$D31)/$E31*($G31-$F31+1),0)) -> 14 | G34: =MEDIAN(F34,$G31,$F31+ROUND((D34+E34-$D31)/$E31*($G31-$F31+1),0)-1) -> 14 | L34: =IF(AND(L$4>=$F34,L$4<=$G34),1,"") | M34: =IF(AND(M$4>=$F34,M$4<=$G34),1,"") | N34: =IF(AND(N$4>=$F34,N$4<=$G34),1,"") | O34: =IF(AND(O$4>=$F34,O$4<=$G34),1,"") | P34: =IF(AND(P$4>=$F34,P$4<=$G34),1,"") | Q34: =IF(AND(Q$4>=$F34,Q$4<=$G34),1,"") | R34: =IF(AND(R$4>=$F34,R$4<=$G34),1,"") | S34: =IF(AND(S$4>=$F34,S$4<=$G34),1,"") | ... AC34: =IF(AND(AC$4>=$F34,AC$4<=$G34),1,"") | AK34: Live.

Sheet Assumptions
A1: Assumptions -- every ASSUMPTION / RATE_MISSING line, restated
A2: ="This sheet is a static restatement (not formula-linked) of every non-VERIFIED line elsewhere in the workbook, so a reviewer can find every place a number was estimated rather than sourced, and what to do to correct it." -> This sheet is a static restatement (not formula-linked) of every non-VERIFIED line elsewhere in the workbook, so a reviewer can find every place a number was estimated rather than sourced, and what to do to correct it.
A3: Location | B3: Item | C3: What was assumed | D3: Status | E3: Basis / how to correct
A4: Pod Build row 4 | B4: API GW entry + routing | C4: API Gateway (HttpApi) | D4: ASSUMPTION | E4: Points: relative sizing, no client estimate supplied. Cost: ItemsPerMonth requests through the /run route, ApiGatewayRequest rate. template.yaml:589-599.
A5: Pod Build row 5 | B5: Lambda authorizer | C5: Lambda (auth check) | D5: ASSUMPTION | E5: No JWT Lambda authorizer exists in the repo today (auth is an API-key header) -- arch_infra_persistence.md D.1. RATE_MISSING: $0, un-costed, not free, until this component is actually built.
A6: Pod Build row 8 | B6: CloudWatch (logs + metrics) | C6: CloudWatch log groups, EMF metrics, dashboard | D6: ASSUMPTION | E6: ~2KB structured log per product ASSUMPTION; 15 custom EMF metrics per MEMORY note; 1 dashboard. arch_infra_persistence.md A.8.
A7: Pod Build row 15 | B7: S3 quarantine | C7: S3 QuarantineBucket | D7: ASSUMPTION | E7: QuarantineBucket, mutually exclusive with canonical PUT (bad-file path only) -- modelled at $0 incremental (rare-path, no repo-measured quarantine rate).
A8: Pod Build row 17 | B8: AIA Matching Engine gate B (precedent) | C8: In-process, aurora_memory.py CONSULT | D8: RATE_MISSING | E8: 1 Aurora RDS Data API ExecuteStatement per item for precedent lookup (arch_infra_persistence.md C.4 roll-up), but rates.json has no per-request RDS Data API meter -- the underlying Aurora instance-hour cost is already priced on the Aurora 2xlarge line below; this row's incremental per-call charge is $0, un-costed not free, until a Data API request rate is sourced.
A9: Pod Build row 24 | B9: AgentCore Memory (long-term records) | C9: Bedrock AgentCore Memory, built-in strategies | D9: ASSUMPTION | E9: 1 long-term record/item ASSUMPTION (no repo-measured record count); rate VERIFIED from rates.json.
A10: Pod Build row 25 | B10: AgentCore Memory (long-term retrieval) | C10: Bedrock AgentCore Memory retrieval meter | D10: ASSUMPTION | E10: 1 retrieval/item ASSUMPTION; rate VERIFIED from rates.json.
A11: Pod Build row 29 | B11: Bedrock Evaluations (judge) | C11: LLM-as-judge, billed as judge model's own tokens | D11: ASSUMPTION | E11: No separate meter for LLM-as-judge (rates.json: billed as judge model's standard tokens). Repo has no real Bedrock Evaluations API call anywhere -- bespoke offline harness instead (arch_infra_persistence.md D.1). $0 incremental line, human-eval meter available in Rates if wired later.
A12: Pod Build row 30 | B12: JAPI Persist outbox writer | C12: Aurora ExecuteStatement (RDS Data API) | D12: RATE_MISSING | E12: ~10 ExecuteStatement calls/fully-published product (outbox insert + projection rows) -- VERIFIED call count, arch_infra_persistence.md SSC, persistence-ops-per-product roll-up. No per-request RDS Data API rate in rates.json, so the incremental per-call charge is $0 (un-costed not free) until sourced; the Aurora instance-hour cost itself is priced separately on the Aurora 2xlarge line.
A13: Pod Build row 32 | B13: HITL AppSync API | C13: AppSync GraphQL ops + notifications | D13: ASSUMPTION | E13: 6 GraphQL ops/HITL item (list+get+mutate+subscribe-notify) is an ASSUMPTION -- no repo-measured op count; HitlPct selector gates volume. rate VERIFIED from rates.json.
A14: Pod Build row 34 | B14: S3 projection sink + CloudFront invalidation | C14: S3 PUT/GET + CloudFront requests | D14: ASSUMPTION | E14: 1 PUT (projection write) + 2 GET (dashboard reads)/item ASSUMPTION.
... A18: Pod Build row 41 | B18: CodeBuild (console/dashboard build) | C18: Build-minute meter, deploy-time only | D18: RATE_MISSING | E18: No CodeBuild meter in Rates -- research/rates.json has zero CodeBuild entries. $0 visible, un-costed not free, until a real build-minute rate is sourced. scudo-poc-console-build CodeBuild project exists in-repo (deploy-time only, not steady-state run cost).
A20: OTHER NOTES (cross-cutting, not tied to a single Pod Build row)
A21: Control Panel | B21: AuroraSize | C21: AuroraSize=2xlarge vs Serverless v2 | D21: ASSUMPTION | E21: Client sketch specifies a fixed db.r6g.2xlarge Single-AZ instance; the deployed repo stack (infra/scudo-poc-app.yaml) actually provisions Aurora Serverless v2 with an ACU range, not a fixed instance class. The workbook models the client's stated instance class (fixed-price, easier to reason about); to correct, re-price against the Serverless v2 ACU-hour meters in Rates and swap the AuroraSize IF-gate in Pod Build row 21 for an ACU-hour formula.
A22: Control Panel | B22: StoragePerItemKB | C22: StoragePerItemKB=50 (canonical JSON-LD per product) | D22: ASSUMPTION | E22: No repo-measured average canonical-JSON-LD payload size was found; 50KB/item is a round-number placeholder. To correct: sample real canonical objects from the CleanCanonicalBucket and replace the Control Panel default with a measured median.
A23: Pod Build row 5 | B23: Lambda authorizer | C23: No JWT/Lambda authorizer exists in the deployed stack | D23: RATE_MISSING | E23: Auth today is an API-key header (arch_infra_persistence.md D.1), not a Lambda authorizer. Carried at $0 (un-costed, not free) until this component is actually built; if built, price it as a per-request Lambda invocation on the api_gw route.
A24: Pod Build row 17 | B24: AIA Matching Engine gate B (precedent) | C24: No RDS Data API / ExecuteStatement per-request meter in Rates | D24: RATE_MISSING | E24: research/rates.json has zero RDS Data API entries -- only Aurora instance-hour and storage/IO meters exist. The underlying Aurora instance cost IS priced (Pod Build row 21); only the per-call Data API charge itself is un-costed. To correct: source an official RDS Data API ExecuteStatement rate and add it to Rates.
A25: Pod Build row 30 | B25: JAPI Persist outbox writer | C25: Same RDS Data API rate gap as row 17 | D25: RATE_MISSING | E25: ~10 ExecuteStatement calls/product is VERIFIED (arch_infra_persistence.md), but the per-call rate itself is RATE_MISSING for the same reason as row 17 above.
A26: Pod Build row 41 | B26: CodeBuild (console/dashboard build) | C26: No CodeBuild meter in Rates | D26: RATE_MISSING | E26: research/rates.json has zero CodeBuild entries (no build-minute meter sourced). Carried at $0 (un-costed, not free) until a CodeBuild compute-type rate is added to Rates.
A27: Pod Build row 28 / Monthly TCO Zone4 | B27: Dense-arm optional (opus_dense per taxonomy node) | C27: Off by default, matches deployed config | D27: DERIVED | E27: Deployed SCUDO_DENSE_BACKEND=jaro_winkler (infra/scudo-poc-app.yaml:76-79), not opus -- the dense-arm LLM-scoring path is currently disabled in production. The amber multiplier on Pod Build row 28 defaults to 0 for this reason; set >0 only to model a future opus_dense_score rollout.
A28: Monthly TCO Zone4 | B28: LLM tokens -- three scenario framings | C28: LIKELY (feeds total) vs HIGH (scenario only) vs DENSE (off) | D28: VERIFIED / ASSUMPTION | E28: LIKELY is CODE-VERIFIED against llm_call_model.md (~19.8K calls/mo, ~15.8M in + 4.9M out tokens, ~$203/mo at Opus 4.8 defaults). HIGH replays the client's original sketch numbers (4 calls/item, 50K in / 1K out) as a labelled comparison row, NOT fed into the total -- do not confuse the two when quoting a headline figure.
A29: Pod Build (Points column) | B29: Story points -- ASSUMPTION rows | C29: Client-supplied points kept where given; ASSUMPTION points elsewhere | D29: ASSUMPTION | E29: Rows without an explicit client point estimate use relative-sizing placeholders (blue font, hardcoded). PointRate defaults to 0 by design (RATE_MISSING convention) so the Build cost column shows visible zeros, not silent omission, until JPMC supplies a $/point rate.
