Workbook
Name Agent_AGT_CAPEX: Agents!$F$6
Name Agent_AGT_GROWTH: Agents!$F$7
Name Agent_AGT_METER: Agents!$F$8
Name Agent_AGT_OPEX: Agents!$F$5
Name Agent_AGT_ORCH: Agents!$F$11
Name Agent_AGT_R1_CONTENT: Agents!$F$10
Name Agent_AGT_RECON: Agents!$F$9
Name AgentCount: 'Control Panel>>>'!$B$22
Name AgentStack: 'Control Panel>>>'!$B$20
Name AgentStackAgentY1: '5yr Run Cost'!$F$66
Name AgentStackFixedY1: '5yr Run Cost'!$F$67
Name AgentStackMcpY1: '5yr Run Cost'!$F$65
Name AgentStackRunY1: '5yr Run Cost'!$F$64
Name ClusterCount: 'Control Panel>>>'!$B$9
Name ContingencyPct: 'Control Panel>>>'!$B$12
Name DayRate: 'Control Panel>>>'!$B$11
Name EffortBasis: 'Control Panel>>>'!$B$6
Name EnvCount: 'Control Panel>>>'!$B$8
Name GanttCorrGoLive: 'Gantt - Revised'!$BX$4
Name GanttFixedEnd: 'Gantt - POAP As Drawn'!$J$192
Name GanttFoldFixedEnd: 'Gantt - POAP As Drawn'!$J$147
Name GanttGoLive: 'Gantt - POAP As Drawn'!$BW$4
Name GanttParentEnd: 'Gantt - POAP As Drawn'!$J$147
Name GanttParentStart: 'Gantt - POAP As Drawn'!$I$147
Name GanttProbeEnd: 'Gantt - POAP As Drawn'!$J$6
Name GanttStepEnd: 'Gantt - POAP As Drawn'!$J$152
Name GanttStepStart: 'Gantt - POAP As Drawn'!$I$152
Name GoLiveDate: Overview!$B$26
Name GoLiveWeek: Overview!$B$25
Name HCL_Toggle: 'Control Panel>>>'!$B$5
Name Indexation: 'Control Panel>>>'!$B$13
Name McpServerCount: 'Control Panel>>>'!$B$23
Name ModelSKU: 'Control Panel>>>'!$B$19
Name ModelVendor: 'Control Panel>>>'!$B$18
Name NodeSize: 'Control Panel>>>'!$B$10
Name Observability: 'Control Panel>>>'!$B$17
Name OrgSize: 'Control Panel>>>'!$B$16
Name OverlapWeeks: 'Control Panel>>>'!$B$15
Name PilotTotal: 'R1 Pilot'!$I$17
Name Platform: 'Control Panel>>>'!$B$7
Name RagMemoryShape: 'Control Panel>>>'!$B$21
Name RefStackY1_1x2: Overview!$D$41
Name RefStackY1_30x50: Overview!$D$43
Name RefStackY1_5x10: Overview!$D$42
Name RunY1: '5yr Run Cost'!$F$63
Name RunY2: '5yr Run Cost'!$G$63
Name RunY3: '5yr Run Cost'!$H$63
Name RunY4: '5yr Run Cost'!$I$63
Name RunY5: '5yr Run Cost'!$J$63
Name SlipWeeks: 'Control Panel>>>'!$B$14
Name TotalBuild: 'POAP Build Cost'!$I$102
Name TotalRun5yr: '5yr Run Cost'!$K$63
Name WeeklyBurn: 'POAP Build Cost'!$I$99

Sheet Overview
A1: SEGRO POAP Costings — Summary (all figures recalc live from the Control Panel)
A2: ="Active scenario: effort = "&EffortBasis&" · HCL = "&HCL_Toggle&" · platform = "&Platform&" · vendor = "&ModelVendor&" · sku = "&ModelSKU&" · obs = "&Observability&" · agents = "&AgentStack&"/"&AgentCount&" · mcp = "&McpServerCount&" · rag = "&RagMemoryShape&" · envs = "&EnvCount&" · day rate £"&TEXT(DayRate,"#,##0")&" · contingency "&TEXT(ContingencyPct,"0%")&" · slip "&SlipWeeks&" wk · overlap "&OverlapWeeks&" wk" -> Active scenario: effort = Likely · HCL = Include · platform = AKS · vendor = AzureOpenAI · sku = GPT-4o · obs = Azure · agents = Exclude/1 · mcp = 2 · rag = AISearch_Cosmos · envs = 4 · day rate £850 · contingency 15% · slip 0 wk · overlap 0 wk
A4: HEADLINES
A5: Build — POAP phases + loadings (one-off) | B5: =TotalBuild -> 830342.07
A6: Run — 5 years (indexed) | B6: =TotalRun5yr -> 1656842.3
A7: 5-YEAR TCO (build + run) | B7: =TotalBuild+TotalRun5yr -> 2487184.4
A8: TCO per employee (OrgSize input) | B8: =(TotalBuild+TotalRun5yr)/OrgSize -> 3553.1206
A9: Y1 cash (build + run Y1) | B9: =TotalBuild+RunY1 -> 1142415.9
A11: CHART DATA (formula-driven — edit the Control Panel, not these cells)
A12: Waterfall segment | B12: Base (invisible) | C12: Block (visible) | D12: Delta (signed) | E12: Cumulative | F12: Short label | H12: Reverse label | I12: Base (invisible) | J12: Block (visible) | K12: Cumulative (reverse)
A13: Design & Plan | B13: 0 | C13: =D13 -> 66625 | D13: ='POAP Build Cost'!I15 -> 66625 | E13: =D13 -> 66625 | F13: Plan | H13: =F22 -> 5-yr TCO | I13: 0 | J13: =D22 -> 2487184.4 | K13: =I13+J13 -> 2487184.4
A14: Build - SEGRO (Azure foundations, AKS, shared services) | B14: =MIN(E13,E14) -> 66625 | C14: =ABS(D14) -> 221146.58 | D14: ='POAP Build Cost'!I50 -> 221146.58 | E14: =E13+D14 -> 287771.58 | F14: Build | H14: =F13 -> Plan | I14: =K14 -> 2420559.4 | J14: =D13 -> 66625 | K14: =K13-D13 -> 2420559.4
A15: Build - HCL (UnO + TX install, Unica+/CDP deploy) | B15: =MIN(E14,E15) -> 287771.58 | C15: =ABS(D15) -> 158250 | D15: ='POAP Build Cost'!I62 -> 158250 | E15: =E14+D15 -> 446021.58 | F15: Build | H15: =F14 -> Build | I15: =K15 -> 2199412.8 | J15: =D14 -> 221146.58 | K15: =K14-D14 -> 2199412.8
A16: Testing (SIT, pen test, UAT, performance) | B16: =MIN(E15,E16) -> 446021.58 | C16: =ABS(D16) -> 89165 | D16: ='POAP Build Cost'!I75 -> 89165 | E16: =E15+D16 -> 535186.58 | F16: Testing | H16: =F15 -> Build | I16: =K16 -> 2041162.8 | J16: =D15 -> 158250 | K16: =K15-D15 -> 2041162.8
A17: Deploy (prod readiness, migration, go-live) | B17: =MIN(E16,E17) -> 535186.58 | C17: =ABS(D17) -> 66700 | D17: ='POAP Build Cost'!I85 -> 66700 | E17: =E16+D17 -> 601886.58 | F17: Deploy | H17: =F16 -> Testing | I17: =K17 -> 1951997.8 | J17: =D16 -> 89165 | K17: =K16-D16 -> 1951997.8
A18: Hypercare / PGLS + business readiness close-out | B18: =MIN(E17,E18) -> 601886.58 | C18: =ABS(D18) -> 120150 | D18: ='POAP Build Cost'!I94 -> 120150 | E18: =E17+D18 -> 722036.58 | F18: Maintenance | H18: =F17 -> Deploy | I18: =K18 -> 1885297.8 | J18: =D17 -> 66700 | K18: =K17-D17 -> 1885297.8
A19: Contingency | B19: =MIN(E18,E19) -> 722036.58 | C19: =ABS(D19) -> 108305.49 | D19: ='POAP Build Cost'!I98 -> 108305.49 | E19: =E18+D19 -> 830342.07 | F19: Contingency | H19: =F18 -> Maintenance | I19: =K19 -> 1765147.8 | J19: =D18 -> 120150 | K19: =K18-D18 -> 1765147.8
A20: Slip − Overlap | B20: =MIN(E19,E20) -> 830342.07 | C20: =ABS(D20) -> 0 | D20: ='POAP Build Cost'!I100+'POAP Build Cost'!I101 -> 0 | E20: =E19+D20 -> 830342.07 | F20: Slip/Overlap | H20: =F19 -> Contingency | I20: =K20 -> 1656842.3 | J20: =D19 -> 108305.49 | K20: =K19-D19 -> 1656842.3
A21: Run (5yr) | B21: =MIN(E20,E21) -> 830342.07 | C21: =ABS(D21) -> 1656842.3 | D21: =TotalRun5yr -> 1656842.3 | E21: =E20+D21 -> 2487184.4 | F21: Run (5yr) | H21: =F20 -> Slip/Overlap | I21: =K21 -> 1656842.3 | J21: =D20 -> 0 | K21: =K20-D20 -> 1656842.3
A22: 5-yr TCO | B22: 0 | C22: =D22 -> 2487184.4 | D22: =TotalBuild+TotalRun5yr -> 2487184.4 | E22: =D22 -> 2487184.4 | F22: 5-yr TCO | H22: =F21 -> Run (5yr) | I22: =K22 -> 0 | J22: =D21 -> 1656842.3 | K22: =K21-D21 -> 0
A24: GO-LIVE (live — moves with slip)
A25: Live go-live week (29 + slip) | B25: =MAX(1,29+SlipWeeks) -> 29 | D25: Nominal 29 wk (Fri wk29 = 29 Jan 2027); slip extends go-live. Overlap is a cost saving (parallel HCL install), not a critical-path compression — matches the Gantt.
A26: Live go-live date | B26: =DATE(2026,7,13)+((GoLiveWeek-1)*7+4) -> 46416 | D26: Anchored to the Gantt week-1 Monday (13 Jul 2026); Friday of the live go-live week.
A28: GO-LIVE SCENARIOS (Green Book duration band) | B28: Optimistic | C28: Green Book lower | D28: Green Book upper
A29: Slip applied (weeks) | B29: 0 | C29: 3 | D29: 16
A30: Go-live week | B30: =29+0 -> 29 | C30: =29+3 -> 32 | D30: =29+16 -> 45
A31: Go-live date | B31: =DATE(2026,7,13)+((29+0-1)*7+4) -> 46416 | C31: =DATE(2026,7,13)+((29+3-1)*7+4) -> 46437 | D31: =DATE(2026,7,13)+((29+16-1)*7+4) -> 46528
A32: Weeks later than plan | B32: 0 | C32: 3 | D32: 16
A33: ▪ Scenarios hold overlap at 0. +3 wk ≈ Green Book ICT duration optimism-bias lower bound (+10% of the 29-wk pre-go-live span); +16 wk ≈ upper bound (+54%). The live figures above respond to the actual Control Panel slip/overlap.
A35: AGENT / MCP CALCULATOR (live — edit Control Panel)
A36: AgentStack | B36: =AgentStack -> Exclude | C36: RagMemoryShape | D36: =RagMemoryShape -> AISearch_Cosmos
A37: AgentCount (intensity) | B37: =AgentCount -> 1 | C37: McpServerCount (app plugs) | D37: =McpServerCount -> 2
A38: Agent-stack run Y1 (MCP+RAG+memory; £0 when AgentStack=Exclude) | B38: =IFERROR(AgentStackRunY1,0) -> 0
A40: Reference scenarios (proportional from live stack Y1; does not override Control Panel) | B40: Agents | C40: MCP servers | D40: Est. stack Y1 £
A41: Scenario 1 agents × 2 MCP | B41: 1 | C41: 2 | D41: =IF(OR(AgentStack="Exclude",AgentCount=0,McpServerCount=0),0,IFERROR(AgentStackMcpY1*(2/McpServerCount)+AgentStackAgentY1*(1/AgentCount)+AgentStackFixedY1,0)) -> 0
A42: Scenario 5 agents × 10 MCP | B42: 5 | C42: 10 | D42: =IF(OR(AgentStack="Exclude",AgentCount=0,McpServerCount=0),0,IFERROR(AgentStackMcpY1*(10/McpServerCount)+AgentStackAgentY1*(5/AgentCount)+AgentStackFixedY1,0)) -> 0
A43: Scenario 30 agents × 50 MCP | B43: 30 | C43: 50 | D43: =IF(OR(AgentStack="Exclude",AgentCount=0,McpServerCount=0),0,IFERROR(AgentStackMcpY1*(50/McpServerCount)+AgentStackAgentY1*(30/AgentCount)+AgentStackFixedY1,0)) -> 0
A44: ▪ Named agents (which to build) live on the Agents tab and Gantt ASSUMPTION lanes. AgentCount scales intensity; McpServerCount scales application plugs.
A46: Month (from contract) | B46: Cumulative spend £ | C46: Go-live marker
A47: 1 | B47: =MAX(0,MIN(MIN(1*4.33,(GoLiveWeek+6))-0*(GoLiveWeek/29),5*(GoLiveWeek/29)))/(5*(GoLiveWeek/29))*'POAP Build Cost'!I15+MAX(0,MIN(MIN(1*4.33,(GoLiveWeek+6))-5*(GoLiveWeek/29),10*(GoLiveWeek/29)))/(10*(GoLiveWeek/29))*'POAP Build Cost'!I50+MAX(0,MIN(MIN(1*4.33,(GoLiveWeek+6))-15*(GoLiveWeek/29),6*(GoLiveWeek/29)))/(6*(GoLiveWeek/29))*'POAP Build Cost'!I62+MAX(0,MIN(MIN(1*4.33,(GoLiveWeek+6))-21*(GoLiveWeek/29),4*(GoLiveWeek/29)))/(4*(GoLiveWeek/29))*'POAP Build Cost'!I75+MAX(0,MIN(MIN(1*4.33,(GoLiveWeek+6))-25*(GoLiveWeek/29),4*(GoLiveWeek/29)))/(4*(GoLiveWeek/29))*'POAP Build Cost'!I85+MAX(0,MIN(MIN(1*4.33,(GoLiveWeek+6))-GoLiveWeek,6))/6*'POAP Build Cost'!I94+MIN(MIN(1*4.33,(GoLiveWeek+6)),GoLiveWeek)/GoLiveWeek*('POAP Build Cost'!I98+'POAP Build Cost'!I100+'POAP Build Cost'!I101)+MAX(0,1*4.33-GoLiveWeek)/4.33/12*RunY1 -> 73868.38 | C47: =IF(1=ROUNDUP(GoLiveWeek/4.33,0),B47,NA()) -> #N/A
A48: 2 | B48: =MAX(0,MIN(MIN(2*4.33,(GoLiveWeek+6))-0*(GoLiveWeek/29),5*(GoLiveWeek/29)))/(5*(GoLiveWeek/29))*'POAP Build Cost'!I15+MAX(0,MIN(MIN(2*4.33,(GoLiveWeek+6))-5*(GoLiveWeek/29),10*(GoLiveWeek/29)))/(10*(GoLiveWeek/29))*'POAP Build Cost'!I50+MAX(0,MIN(MIN(2*4.33,(GoLiveWeek+6))-15*(GoLiveWeek/29),6*(GoLiveWeek/29)))/(6*(GoLiveWeek/29))*'POAP Build Cost'!I62+MAX(0,MIN(MIN(2*4.33,(GoLiveWeek+6))-21*(GoLiveWeek/29),4*(GoLiveWeek/29)))/(4*(GoLiveWeek/29))*'POAP Build Cost'!I75+MAX(0,MIN(MIN(2*4.33,(GoLiveWeek+6))-25*(GoLiveWeek/29),4*(GoLiveWeek/29)))/(4*(GoLiveWeek/29))*'POAP Build Cost'!I85+MAX(0,MIN(MIN(2*4.33,(GoLiveWeek+6))-GoLiveWeek,6))/6*'POAP Build Cost'!I94+MIN(MIN(2*4.33,(GoLiveWeek+6)),GoLiveWeek)/GoLiveWeek*('POAP Build Cost'!I98+'POAP Build Cost'!I100+'POAP Build Cost'!I101)+MAX(0,2*4.33-GoLiveWeek)/4.33/12*RunY1 -> 179906.91 | C48: =IF(2=ROUNDUP(GoLiveWeek/4.33,0),B48,NA()) -> #N/A
A49: 3 | B49: =MAX(0,MIN(MIN(3*4.33,(GoLiveWeek+6))-0*(GoLiveWeek/29),5*(GoLiveWeek/29)))/(5*(GoLiveWeek/29))*'POAP Build Cost'!I15+MAX(0,MIN(MIN(3*4.33,(GoLiveWeek+6))-5*(GoLiveWeek/29),10*(GoLiveWeek/29)))/(10*(GoLiveWeek/29))*'POAP Build Cost'!I50+MAX(0,MIN(MIN(3*4.33,(GoLiveWeek+6))-15*(GoLiveWeek/29),6*(GoLiveWeek/29)))/(6*(GoLiveWeek/29))*'POAP Build Cost'!I62+MAX(0,MIN(MIN(3*4.33,(GoLiveWeek+6))-21*(GoLiveWeek/29),4*(GoLiveWeek/29)))/(4*(GoLiveWeek/29))*'POAP Build Cost'!I75+MAX(0,MIN(MIN(3*4.33,(GoLiveWeek+6))-25*(GoLiveWeek/29),4*(GoLiveWeek/29)))/(4*(GoLiveWeek/29))*'POAP Build Cost'!I85+MAX(0,MIN(MIN(3*4.33,(GoLiveWeek+6))-GoLiveWeek,6))/6*'POAP Build Cost'!I94+MIN(MIN(3*4.33,(GoLiveWeek+6)),GoLiveWeek)/GoLiveWeek*('POAP Build Cost'!I98+'POAP Build Cost'!I100+'POAP Build Cost'!I101)+MAX(0,3*4.33-GoLiveWeek)/4.33/12*RunY1 -> 291834.51 | C49: =IF(3=ROUNDUP(GoLiveWeek/4.33,0),B49,NA()) -> #N/A
A50: 4 | B50: =MAX(0,MIN(MIN(4*4.33,(GoLiveWeek+6))-0*(GoLiveWeek/29),5*(GoLiveWeek/29)))/(5*(GoLiveWeek/29))*'POAP Build Cost'!I15+MAX(0,MIN(MIN(4*4.33,(GoLiveWeek+6))-5*(GoLiveWeek/29),10*(GoLiveWeek/29)))/(10*(GoLiveWeek/29))*'POAP Build Cost'!I50+MAX(0,MIN(MIN(4*4.33,(GoLiveWeek+6))-15*(GoLiveWeek/29),6*(GoLiveWeek/29)))/(6*(GoLiveWeek/29))*'POAP Build Cost'!I62+MAX(0,MIN(MIN(4*4.33,(GoLiveWeek+6))-21*(GoLiveWeek/29),4*(GoLiveWeek/29)))/(4*(GoLiveWeek/29))*'POAP Build Cost'!I75+MAX(0,MIN(MIN(4*4.33,(GoLiveWeek+6))-25*(GoLiveWeek/29),4*(GoLiveWeek/29)))/(4*(GoLiveWeek/29))*'POAP Build Cost'!I85+MAX(0,MIN(MIN(4*4.33,(GoLiveWeek+6))-GoLiveWeek,6))/6*'POAP Build Cost'!I94+MIN(MIN(4*4.33,(GoLiveWeek+6)),GoLiveWeek)/GoLiveWeek*('POAP Build Cost'!I98+'POAP Build Cost'!I100+'POAP Build Cost'!I101)+MAX(0,4*4.33-GoLiveWeek)/4.33/12*RunY1 -> 413646.1 | C50: =IF(4=ROUNDUP(GoLiveWeek/4.33,0),B50,NA()) -> #N/A
A51: 5 | B51: =MAX(0,MIN(MIN(5*4.33,(GoLiveWeek+6))-0*(GoLiveWeek/29),5*(GoLiveWeek/29)))/(5*(GoLiveWeek/29))*'POAP Build Cost'!I15+MAX(0,MIN(MIN(5*4.33,(GoLiveWeek+6))-5*(GoLiveWeek/29),10*(GoLiveWeek/29)))/(10*(GoLiveWeek/29))*'POAP Build Cost'!I50+MAX(0,MIN(MIN(5*4.33,(GoLiveWeek+6))-15*(GoLiveWeek/29),6*(GoLiveWeek/29)))/(6*(GoLiveWeek/29))*'POAP Build Cost'!I62+MAX(0,MIN(MIN(5*4.33,(GoLiveWeek+6))-21*(GoLiveWeek/29),4*(GoLiveWeek/29)))/(4*(GoLiveWeek/29))*'POAP Build Cost'!I75+MAX(0,MIN(MIN(5*4.33,(GoLiveWeek+6))-25*(GoLiveWeek/29),4*(GoLiveWeek/29)))/(4*(GoLiveWeek/29))*'POAP Build Cost'!I85+MAX(0,MIN(MIN(5*4.33,(GoLiveWeek+6))-GoLiveWeek,6))/6*'POAP Build Cost'!I94+MIN(MIN(5*4.33,(GoLiveWeek+6)),GoLiveWeek)/GoLiveWeek*('POAP Build Cost'!I98+'POAP Build Cost'!I100+'POAP Build Cost'!I101)+MAX(0,5*4.33-GoLiveWeek)/4.33/12*RunY1 -> 541366.54 | C51: =IF(5=ROUNDUP(GoLiveWeek/4.33,0),B51,NA()) -> #N/A
A52: 6 | B52: =MAX(0,MIN(MIN(6*4.33,(GoLiveWeek+6))-0*(GoLiveWeek/29),5*(GoLiveWeek/29)))/(5*(GoLiveWeek/29))*'POAP Build Cost'!I15+MAX(0,MIN(MIN(6*4.33,(GoLiveWeek+6))-5*(GoLiveWeek/29),10*(GoLiveWeek/29)))/(10*(GoLiveWeek/29))*'POAP Build Cost'!I50+MAX(0,MIN(MIN(6*4.33,(GoLiveWeek+6))-15*(GoLiveWeek/29),6*(GoLiveWeek/29)))/(6*(GoLiveWeek/29))*'POAP Build Cost'!I62+MAX(0,MIN(MIN(6*4.33,(GoLiveWeek+6))-21*(GoLiveWeek/29),4*(GoLiveWeek/29)))/(4*(GoLiveWeek/29))*'POAP Build Cost'!I75+MAX(0,MIN(MIN(6*4.33,(GoLiveWeek+6))-25*(GoLiveWeek/29),4*(GoLiveWeek/29)))/(4*(GoLiveWeek/29))*'POAP Build Cost'!I85+MAX(0,MIN(MIN(6*4.33,(GoLiveWeek+6))-GoLiveWeek,6))/6*'POAP Build Cost'!I94+MIN(MIN(6*4.33,(GoLiveWeek+6)),GoLiveWeek)/GoLiveWeek*('POAP Build Cost'!I98+'POAP Build Cost'!I100+'POAP Build Cost'!I101)+MAX(0,6*4.33-GoLiveWeek)/4.33/12*RunY1 -> 648554.86 | C52: =IF(6=ROUNDUP(GoLiveWeek/4.33,0),B52,NA()) -> #N/A
A53: 7 | B53: =MAX(0,MIN(MIN(7*4.33,(GoLiveWeek+6))-0*(GoLiveWeek/29),5*(GoLiveWeek/29)))/(5*(GoLiveWeek/29))*'POAP Build Cost'!I15+MAX(0,MIN(MIN(7*4.33,(GoLiveWeek+6))-5*(GoLiveWeek/29),10*(GoLiveWeek/29)))/(10*(GoLiveWeek/29))*'POAP Build Cost'!I50+MAX(0,MIN(MIN(7*4.33,(GoLiveWeek+6))-15*(GoLiveWeek/29),6*(GoLiveWeek/29)))/(6*(GoLiveWeek/29))*'POAP Build Cost'!I62+MAX(0,MIN(MIN(7*4.33,(GoLiveWeek+6))-21*(GoLiveWeek/29),4*(GoLiveWeek/29)))/(4*(GoLiveWeek/29))*'POAP Build Cost'!I75+MAX(0,MIN(MIN(7*4.33,(GoLiveWeek+6))-25*(GoLiveWeek/29),4*(GoLiveWeek/29)))/(4*(GoLiveWeek/29))*'POAP Build Cost'!I85+MAX(0,MIN(MIN(7*4.33,(GoLiveWeek+6))-GoLiveWeek,6))/6*'POAP Build Cost'!I94+MIN(MIN(7*4.33,(GoLiveWeek+6)),GoLiveWeek)/GoLiveWeek*('POAP Build Cost'!I98+'POAP Build Cost'!I100+'POAP Build Cost'!I101)+MAX(0,7*4.33-GoLiveWeek)/4.33/12*RunY1 -> 744292.73 | C53: =IF(7=ROUNDUP(GoLiveWeek/4.33,0),B53,NA()) -> 744292.73
A54: 8 | B54: =MAX(0,MIN(MIN(8*4.33,(GoLiveWeek+6))-0*(GoLiveWeek/29),5*(GoLiveWeek/29)))/(5*(GoLiveWeek/29))*'POAP Build Cost'!I15+MAX(0,MIN(MIN(8*4.33,(GoLiveWeek+6))-5*(GoLiveWeek/29),10*(GoLiveWeek/29)))/(10*(GoLiveWeek/29))*'POAP Build Cost'!I50+MAX(0,MIN(MIN(8*4.33,(GoLiveWeek+6))-15*(GoLiveWeek/29),6*(GoLiveWeek/29)))/(6*(GoLiveWeek/29))*'POAP Build Cost'!I62+MAX(0,MIN(MIN(8*4.33,(GoLiveWeek+6))-21*(GoLiveWeek/29),4*(GoLiveWeek/29)))/(4*(GoLiveWeek/29))*'POAP Build Cost'!I75+MAX(0,MIN(MIN(8*4.33,(GoLiveWeek+6))-25*(GoLiveWeek/29),4*(GoLiveWeek/29)))/(4*(GoLiveWeek/29))*'POAP Build Cost'!I85+MAX(0,MIN(MIN(8*4.33,(GoLiveWeek+6))-GoLiveWeek,6))/6*'POAP Build Cost'!I94+MIN(MIN(8*4.33,(GoLiveWeek+6)),GoLiveWeek)/GoLiveWeek*('POAP Build Cost'!I98+'POAP Build Cost'!I100+'POAP Build Cost'!I101)+MAX(0,8*4.33-GoLiveWeek)/4.33/12*RunY1 -> 857007.13 | C54: =IF(8=ROUNDUP(GoLiveWeek/4.33,0),B54,NA()) -> #N/A
A55: 9 | B55: =MAX(0,MIN(MIN(9*4.33,(GoLiveWeek+6))-0*(GoLiveWeek/29),5*(GoLiveWeek/29)))/(5*(GoLiveWeek/29))*'POAP Build Cost'!I15+MAX(0,MIN(MIN(9*4.33,(GoLiveWeek+6))-5*(GoLiveWeek/29),10*(GoLiveWeek/29)))/(10*(GoLiveWeek/29))*'POAP Build Cost'!I50+MAX(0,MIN(MIN(9*4.33,(GoLiveWeek+6))-15*(GoLiveWeek/29),6*(GoLiveWeek/29)))/(6*(GoLiveWeek/29))*'POAP Build Cost'!I62+MAX(0,MIN(MIN(9*4.33,(GoLiveWeek+6))-21*(GoLiveWeek/29),4*(GoLiveWeek/29)))/(4*(GoLiveWeek/29))*'POAP Build Cost'!I75+MAX(0,MIN(MIN(9*4.33,(GoLiveWeek+6))-25*(GoLiveWeek/29),4*(GoLiveWeek/29)))/(4*(GoLiveWeek/29))*'POAP Build Cost'!I85+MAX(0,MIN(MIN(9*4.33,(GoLiveWeek+6))-GoLiveWeek,6))/6*'POAP Build Cost'!I94+MIN(MIN(9*4.33,(GoLiveWeek+6)),GoLiveWeek)/GoLiveWeek*('POAP Build Cost'!I98+'POAP Build Cost'!I100+'POAP Build Cost'!I101)+MAX(0,9*4.33-GoLiveWeek)/4.33/12*RunY1 -> 890222.29 | C55: =IF(9=ROUNDUP(GoLiveWeek/4.33,0),B55,NA()) -> #N/A
A56: 10 | B56: =MAX(0,MIN(MIN(10*4.33,(GoLiveWeek+6))-0*(GoLiveWeek/29),5*(GoLiveWeek/29)))/(5*(GoLiveWeek/29))*'POAP Build Cost'!I15+MAX(0,MIN(MIN(10*4.33,(GoLiveWeek+6))-5*(GoLiveWeek/29),10*(GoLiveWeek/29)))/(10*(GoLiveWeek/29))*'POAP Build Cost'!I50+MAX(0,MIN(MIN(10*4.33,(GoLiveWeek+6))-15*(GoLiveWeek/29),6*(GoLiveWeek/29)))/(6*(GoLiveWeek/29))*'POAP Build Cost'!I62+MAX(0,MIN(MIN(10*4.33,(GoLiveWeek+6))-21*(GoLiveWeek/29),4*(GoLiveWeek/29)))/(4*(GoLiveWeek/29))*'POAP Build Cost'!I75+MAX(0,MIN(MIN(10*4.33,(GoLiveWeek+6))-25*(GoLiveWeek/29),4*(GoLiveWeek/29)))/(4*(GoLiveWeek/29))*'POAP Build Cost'!I85+MAX(0,MIN(MIN(10*4.33,(GoLiveWeek+6))-GoLiveWeek,6))/6*'POAP Build Cost'!I94+MIN(MIN(10*4.33,(GoLiveWeek+6)),GoLiveWeek)/GoLiveWeek*('POAP Build Cost'!I98+'POAP Build Cost'!I100+'POAP Build Cost'!I101)+MAX(0,10*4.33-GoLiveWeek)/4.33/12*RunY1 -> 916228.44 | C56: =IF(10=ROUNDUP(GoLiveWeek/4.33,0),B56,NA()) -> #N/A
A57: 11 | B57: =MAX(0,MIN(MIN(11*4.33,(GoLiveWeek+6))-0*(GoLiveWeek/29),5*(GoLiveWeek/29)))/(5*(GoLiveWeek/29))*'POAP Build Cost'!I15+MAX(0,MIN(MIN(11*4.33,(GoLiveWeek+6))-5*(GoLiveWeek/29),10*(GoLiveWeek/29)))/(10*(GoLiveWeek/29))*'POAP Build Cost'!I50+MAX(0,MIN(MIN(11*4.33,(GoLiveWeek+6))-15*(GoLiveWeek/29),6*(GoLiveWeek/29)))/(6*(GoLiveWeek/29))*'POAP Build Cost'!I62+MAX(0,MIN(MIN(11*4.33,(GoLiveWeek+6))-21*(GoLiveWeek/29),4*(GoLiveWeek/29)))/(4*(GoLiveWeek/29))*'POAP Build Cost'!I75+MAX(0,MIN(MIN(11*4.33,(GoLiveWeek+6))-25*(GoLiveWeek/29),4*(GoLiveWeek/29)))/(4*(GoLiveWeek/29))*'POAP Build Cost'!I85+MAX(0,MIN(MIN(11*4.33,(GoLiveWeek+6))-GoLiveWeek,6))/6*'POAP Build Cost'!I94+MIN(MIN(11*4.33,(GoLiveWeek+6)),GoLiveWeek)/GoLiveWeek*('POAP Build Cost'!I98+'POAP Build Cost'!I100+'POAP Build Cost'!I101)+MAX(0,11*4.33-GoLiveWeek)/4.33/12*RunY1 -> 942234.59 | C57: =IF(11=ROUNDUP(GoLiveWeek/4.33,0),B57,NA()) -> #N/A
A58: 12 | B58: =MAX(0,MIN(MIN(12*4.33,(GoLiveWeek+6))-0*(GoLiveWeek/29),5*(GoLiveWeek/29)))/(5*(GoLiveWeek/29))*'POAP Build Cost'!I15+MAX(0,MIN(MIN(12*4.33,(GoLiveWeek+6))-5*(GoLiveWeek/29),10*(GoLiveWeek/29)))/(10*(GoLiveWeek/29))*'POAP Build Cost'!I50+MAX(0,MIN(MIN(12*4.33,(GoLiveWeek+6))-15*(GoLiveWeek/29),6*(GoLiveWeek/29)))/(6*(GoLiveWeek/29))*'POAP Build Cost'!I62+MAX(0,MIN(MIN(12*4.33,(GoLiveWeek+6))-21*(GoLiveWeek/29),4*(GoLiveWeek/29)))/(4*(GoLiveWeek/29))*'POAP Build Cost'!I75+MAX(0,MIN(MIN(12*4.33,(GoLiveWeek+6))-25*(GoLiveWeek/29),4*(GoLiveWeek/29)))/(4*(GoLiveWeek/29))*'POAP Build Cost'!I85+MAX(0,MIN(MIN(12*4.33,(GoLiveWeek+6))-GoLiveWeek,6))/6*'POAP Build Cost'!I94+MIN(MIN(12*4.33,(GoLiveWeek+6)),GoLiveWeek)/GoLiveWeek*('POAP Build Cost'!I98+'POAP Build Cost'!I100+'POAP Build Cost'!I101)+MAX(0,12*4.33-GoLiveWeek)/4.33/12*RunY1 -> 968240.74 | C58: =IF(12=ROUNDUP(GoLiveWeek/4.33,0),B58,NA()) -> #N/A
A59: 13 | B59: =MAX(0,MIN(MIN(13*4.33,(GoLiveWeek+6))-0*(GoLiveWeek/29),5*(GoLiveWeek/29)))/(5*(GoLiveWeek/29))*'POAP Build Cost'!I15+MAX(0,MIN(MIN(13*4.33,(GoLiveWeek+6))-5*(GoLiveWeek/29),10*(GoLiveWeek/29)))/(10*(GoLiveWeek/29))*'POAP Build Cost'!I50+MAX(0,MIN(MIN(13*4.33,(GoLiveWeek+6))-15*(GoLiveWeek/29),6*(GoLiveWeek/29)))/(6*(GoLiveWeek/29))*'POAP Build Cost'!I62+MAX(0,MIN(MIN(13*4.33,(GoLiveWeek+6))-21*(GoLiveWeek/29),4*(GoLiveWeek/29)))/(4*(GoLiveWeek/29))*'POAP Build Cost'!I75+MAX(0,MIN(MIN(13*4.33,(GoLiveWeek+6))-25*(GoLiveWeek/29),4*(GoLiveWeek/29)))/(4*(GoLiveWeek/29))*'POAP Build Cost'!I85+MAX(0,MIN(MIN(13*4.33,(GoLiveWeek+6))-GoLiveWeek,6))/6*'POAP Build Cost'!I94+MIN(MIN(13*4.33,(GoLiveWeek+6)),GoLiveWeek)/GoLiveWeek*('POAP Build Cost'!I98+'POAP Build Cost'!I100+'POAP Build Cost'!I101)+MAX(0,13*4.33-GoLiveWeek)/4.33/12*RunY1 -> 994246.89 | C59: =IF(13=ROUNDUP(GoLiveWeek/4.33,0),B59,NA()) -> #N/A
A60: 14 | B60: =MAX(0,MIN(MIN(14*4.33,(GoLiveWeek+6))-0*(GoLiveWeek/29),5*(GoLiveWeek/29)))/(5*(GoLiveWeek/29))*'POAP Build Cost'!I15+MAX(0,MIN(MIN(14*4.33,(GoLiveWeek+6))-5*(GoLiveWeek/29),10*(GoLiveWeek/29)))/(10*(GoLiveWeek/29))*'POAP Build Cost'!I50+MAX(0,MIN(MIN(14*4.33,(GoLiveWeek+6))-15*(GoLiveWeek/29),6*(GoLiveWeek/29)))/(6*(GoLiveWeek/29))*'POAP Build Cost'!I62+MAX(0,MIN(MIN(14*4.33,(GoLiveWeek+6))-21*(GoLiveWeek/29),4*(GoLiveWeek/29)))/(4*(GoLiveWeek/29))*'POAP Build Cost'!I75+MAX(0,MIN(MIN(14*4.33,(GoLiveWeek+6))-25*(GoLiveWeek/29),4*(GoLiveWeek/29)))/(4*(GoLiveWeek/29))*'POAP Build Cost'!I85+MAX(0,MIN(MIN(14*4.33,(GoLiveWeek+6))-GoLiveWeek,6))/6*'POAP Build Cost'!I94+MIN(MIN(14*4.33,(GoLiveWeek+6)),GoLiveWeek)/GoLiveWeek*('POAP Build Cost'!I98+'POAP Build Cost'!I100+'POAP Build Cost'!I101)+MAX(0,14*4.33-GoLiveWeek)/4.33/12*RunY1 -> 1020253 | C60: =IF(14=ROUNDUP(GoLiveWeek/4.33,0),B60,NA()) -> #N/A
A61: 15 | B61: =MAX(0,MIN(MIN(15*4.33,(GoLiveWeek+6))-0*(GoLiveWeek/29),5*(GoLiveWeek/29)))/(5*(GoLiveWeek/29))*'POAP Build Cost'!I15+MAX(0,MIN(MIN(15*4.33,(GoLiveWeek+6))-5*(GoLiveWeek/29),10*(GoLiveWeek/29)))/(10*(GoLiveWeek/29))*'POAP Build Cost'!I50+MAX(0,MIN(MIN(15*4.33,(GoLiveWeek+6))-15*(GoLiveWeek/29),6*(GoLiveWeek/29)))/(6*(GoLiveWeek/29))*'POAP Build Cost'!I62+MAX(0,MIN(MIN(15*4.33,(GoLiveWeek+6))-21*(GoLiveWeek/29),4*(GoLiveWeek/29)))/(4*(GoLiveWeek/29))*'POAP Build Cost'!I75+MAX(0,MIN(MIN(15*4.33,(GoLiveWeek+6))-25*(GoLiveWeek/29),4*(GoLiveWeek/29)))/(4*(GoLiveWeek/29))*'POAP Build Cost'!I85+MAX(0,MIN(MIN(15*4.33,(GoLiveWeek+6))-GoLiveWeek,6))/6*'POAP Build Cost'!I94+MIN(MIN(15*4.33,(GoLiveWeek+6)),GoLiveWeek)/GoLiveWeek*('POAP Build Cost'!I98+'POAP Build Cost'!I100+'POAP Build Cost'!I101)+MAX(0,15*4.33-GoLiveWeek)/4.33/12*RunY1 -> 1046259.2 | C61: =IF(15=ROUNDUP(GoLiveWeek/4.33,0),B61,NA()) -> #N/A
A62: 16 | B62: =MAX(0,MIN(MIN(16*4.33,(GoLiveWeek+6))-0*(GoLiveWeek/29),5*(GoLiveWeek/29)))/(5*(GoLiveWeek/29))*'POAP Build Cost'!I15+MAX(0,MIN(MIN(16*4.33,(GoLiveWeek+6))-5*(GoLiveWeek/29),10*(GoLiveWeek/29)))/(10*(GoLiveWeek/29))*'POAP Build Cost'!I50+MAX(0,MIN(MIN(16*4.33,(GoLiveWeek+6))-15*(GoLiveWeek/29),6*(GoLiveWeek/29)))/(6*(GoLiveWeek/29))*'POAP Build Cost'!I62+MAX(0,MIN(MIN(16*4.33,(GoLiveWeek+6))-21*(GoLiveWeek/29),4*(GoLiveWeek/29)))/(4*(GoLiveWeek/29))*'POAP Build Cost'!I75+MAX(0,MIN(MIN(16*4.33,(GoLiveWeek+6))-25*(GoLiveWeek/29),4*(GoLiveWeek/29)))/(4*(GoLiveWeek/29))*'POAP Build Cost'!I85+MAX(0,MIN(MIN(16*4.33,(GoLiveWeek+6))-GoLiveWeek,6))/6*'POAP Build Cost'!I94+MIN(MIN(16*4.33,(GoLiveWeek+6)),GoLiveWeek)/GoLiveWeek*('POAP Build Cost'!I98+'POAP Build Cost'!I100+'POAP Build Cost'!I101)+MAX(0,16*4.33-GoLiveWeek)/4.33/12*RunY1 -> 1072265.4 | C62: =IF(16=ROUNDUP(GoLiveWeek/4.33,0),B62,NA()) -> #N/A
A64: Phase | B64: SEGRO | C64: HCL | D64: Azure | E64: ThirdParty
A65: Design & Plan | B65: =SUMIF('POAP Build Cost'!$B$6:$B$14,"SEGRO",'POAP Build Cost'!$I$6:$I$14) -> 52375 | C65: =SUMIF('POAP Build Cost'!$B$6:$B$14,"HCL",'POAP Build Cost'!$I$6:$I$14) -> 14250 | D65: =SUMIF('POAP Build Cost'!$B$6:$B$14,"Azure",'POAP Build Cost'!$I$6:$I$14) -> 0 | E65: =SUMIF('POAP Build Cost'!$B$6:$B$14,"ThirdParty",'POAP Build Cost'!$I$6:$I$14) -> 0
A66: Build - SEGRO (Azure fou | B66: =SUMIF('POAP Build Cost'!$B$19:$B$49,"SEGRO",'POAP Build Cost'!$I$19:$I$49) -> 205445 | C66: =SUMIF('POAP Build Cost'!$B$19:$B$49,"HCL",'POAP Build Cost'!$I$19:$I$49) -> 0 | D66: =SUMIF('POAP Build Cost'!$B$19:$B$49,"Azure",'POAP Build Cost'!$I$19:$I$49) -> 15701.583 | E66: =SUMIF('POAP Build Cost'!$B$19:$B$49,"ThirdParty",'POAP Build Cost'!$I$19:$I$49) -> 0
A67: Build - HCL (UnO + TX in | B67: =SUMIF('POAP Build Cost'!$B$54:$B$61,"SEGRO",'POAP Build Cost'!$I$54:$I$61) -> 15750 | C67: =SUMIF('POAP Build Cost'!$B$54:$B$61,"HCL",'POAP Build Cost'!$I$54:$I$61) -> 142500 | D67: =SUMIF('POAP Build Cost'!$B$54:$B$61,"Azure",'POAP Build Cost'!$I$54:$I$61) -> 0 | E67: =SUMIF('POAP Build Cost'!$B$54:$B$61,"ThirdParty",'POAP Build Cost'!$I$54:$I$61) -> 0
A68: Testing (SIT, pen test, | B68: =SUMIF('POAP Build Cost'!$B$66:$B$74,"SEGRO",'POAP Build Cost'!$I$66:$I$74) -> 55915 | C68: =SUMIF('POAP Build Cost'!$B$66:$B$74,"HCL",'POAP Build Cost'!$I$66:$I$74) -> 19000 | D68: =SUMIF('POAP Build Cost'!$B$66:$B$74,"Azure",'POAP Build Cost'!$I$66:$I$74) -> 0 | E68: =SUMIF('POAP Build Cost'!$B$66:$B$74,"ThirdParty",'POAP Build Cost'!$I$66:$I$74) -> 14250
A69: Deploy (prod readiness, | B69: =SUMIF('POAP Build Cost'!$B$79:$B$84,"SEGRO",'POAP Build Cost'!$I$79:$I$84) -> 47700 | C69: =SUMIF('POAP Build Cost'!$B$79:$B$84,"HCL",'POAP Build Cost'!$I$79:$I$84) -> 19000 | D69: =SUMIF('POAP Build Cost'!$B$79:$B$84,"Azure",'POAP Build Cost'!$I$79:$I$84) -> 0 | E69: =SUMIF('POAP Build Cost'!$B$79:$B$84,"ThirdParty",'POAP Build Cost'!$I$79:$I$84) -> 0
A70: Hypercare / PGLS + busin | B70: =SUMIF('POAP Build Cost'!$B$89:$B$93,"SEGRO",'POAP Build Cost'!$I$89:$I$93) -> 91650 | C70: =SUMIF('POAP Build Cost'!$B$89:$B$93,"HCL",'POAP Build Cost'!$I$89:$I$93) -> 28500 | D70: =SUMIF('POAP Build Cost'!$B$89:$B$93,"Azure",'POAP Build Cost'!$I$89:$I$93) -> 0 | E70: =SUMIF('POAP Build Cost'!$B$89:$B$93,"ThirdParty",'POAP Build Cost'!$I$89:$I$93) -> 0
A72: Run Y1 by side | B72: £/yr
A73: SEGRO | B73: =SUMIF('5yr Run Cost'!$B$5:$B$62,"SEGRO",'5yr Run Cost'!$F$5:$F$62) -> 255064.8
A74: HCL | B74: =SUMIF('5yr Run Cost'!$B$5:$B$62,"HCL",'5yr Run Cost'!$F$5:$F$62) -> 0
A75: Azure | B75: =SUMIF('5yr Run Cost'!$B$5:$B$62,"Azure",'5yr Run Cost'!$F$5:$F$62) -> 52259.024
A76: ThirdParty | B76: =SUMIF('5yr Run Cost'!$B$5:$B$62,"ThirdParty",'5yr Run Cost'!$F$5:$F$62) -> 4750
A79: ▪ Benchmark provenance: all Benchmarks-tab rows are copied from org_it_benchmarks.json and programme_benchmarks.json (both adversarially verified, verdict APPROVE 17 Jul 2026) with their original status labels (VERIFIED / INDICATIVE / ASSUMPTION) carried unchanged; verifier MINORs
A80: ▪ Headcount: SEGRO's actual Group headcount is 463 (ARA 2025 p86; FY2025 average 454, of which 168 indirect/administration) versus the ~700 briefed — anchor OrgSize and all per-user maths to ~450-465, with the 168 'office' population available for knowledge-worker-only SKUs.
A81: ▪ INDICATIVE and list-price rows are vendor list / aggregator figures, not quotes: Microsoft GBP prices are paid-yearly annual-commitment ex-VAT list captured 16 Jul 2026 (a +5% monthly-billing premium applies, and 2026 M365 pricing/packaging updates are announced — re-verify at co
A82: ▪ HCL side is a FLOOR: HCL licence and subscription lines are RATE_MISSING (contract not shared) and are carried as clearly-labelled adjustable input cells defaulting to £0 — never presented as verified figures; totals on the HCL branch therefore understate true cost.
A83: ▪ Contingency framing: the workbook's ContingencyPct should be read against the HM Treasury Green Book optimism-bias band for ICT (10% floor at contract award with evidenced mitigation, 200% upper at outline-business-case stage) — a flat 10-20% default sits at the optimistic end of

Sheet Gantt - POAP As Drawn
A1: Gantt - POAP As Drawn — technical step decomposition per major line of work
A2: The POAP as drawn on slide 3 (16 Jul 2026 deck), decomposed into technical steps per major line of work. Window statuses: POAP-DRAWN = bar drawn on the slide; ASSUMPTION = no bar exists (the work is costed but absent from the plan). Step statuses: DERIVED = step text and position follow from slide sub-items, named documents (slides 5-10) or the verified cost model; ASSUMPTION = position is sequencing judgement, text still sourced. TASK bars dilate with SlipWeeks ONLY on time-driven work (people schedules + Azure commissioning + any people LANE); a pure fixed-fee TASK bar (a RATE_MISSING-licence fold or a third-party pen-test/red-team engagement) SHIFTS under slip but keeps its drawn duration, matching the slip-cost model. STEP bars render RELATIVE to their parent task's live window, so a fixed licence STEP inside a time-driven lane (e.g. the procurement track) rides the lane and may widen with it — the fixed-does-not-stretch rule is a TASK-row property, not a step-row one. Bars recalc live: SlipWeeks dilates TIME-DRIVEN windows (people + Azure commissioning) pro-rata — the same elongation the slip cost prices; FIXED-fee engagements (licences, third-party pen-test/red-team) shift but keep their duration; hypercare shifts whole. A ▶ in the Slip column flags any bar clipped at the grid edge under a large slip. Milestones: ▲ go-live (moves with slip) · ✕ Christmas · ! Bank holiday · ◆ drawn phase gate. Bar colours: SEGRO red · HCL dark blue · Azure mid blue · Third-party purple.
K3: Jul 26 | N3: Aug 26 | S3: Sep 26 | W3: Oct 26 | AA3: Nov 26 | AF3: Dec 26 | AJ3: Jan 27 | AN3: Feb 27 | AR3: Mar 27 | AW3: Apr 27 | BA3: May 27 | BF3: Jun 27 | BJ3: Jul 27 | BN3: Aug 27 | BS3: Sep 27
A4: Id | B4: Major line of work / technical step | C4: Side | D4: Status | E4: Findings | F4: Depends on | G4: Start wk | H4: Wks | I4: Live start | J4: Live end | K4: 1 | L4: 2 | M4: 3 | N4: 4 | O4: 5 | P4: 6 | Q4: 7 | R4: 8 | S4: 9 | T4: 10 | U4: 11 | V4: 12 | W4: 13 | X4: 14 | Y4: 15 | Z4: 16 | AA4: 17 | AB4: 18 | AC4: 19 | AD4: 20 | AE4: 21 | AF4: 22 | AG4: 23 | AH4: 24 | AI4: 25 | AJ4: 26 | AK4: 27 | AL4: 28 | AM4: 29 | AN4: 30 | AO4: 31 | AP4: 32 | AQ4: 33 | AR4: 34 | AS4: 35 | AT4: 36 | AU4: 37 | AV4: 38 | AW4: 39 | AX4: 40 | AY4: 41 | AZ4: 42 | BA4: 43 | BB4: 44 | BC4: 45 | BD4: 46 | BE4: 47 | BF4: 48 | BG4: 49 | BH4: 50 | BI4: 51 | BJ4: 52 | BK4: 53 | BL4: 54 | BM4: 55 | BN4: 56 | BO4: 57 | BP4: 58 | BQ4: 59 | BR4: 60 | BS4: 61 | BT4: Slip | BU4: Basis / source | BW4: =29+SlipWeeks -> 29
B5: Milestones | K5: =IF(K$4=$BW$4,"▲","") | L5: =IF(L$4=$BW$4,"▲","") | M5: =IF(M$4=$BW$4,"▲","") | N5: =IF(N$4=$BW$4,"▲","") | O5: =IF(O$4=$BW$4,"▲","◆") -> ◆ | P5: =IF(P$4=$BW$4,"▲","") | Q5: =IF(Q$4=$BW$4,"▲","") | R5: =IF(R$4=$BW$4,"▲","!") -> ! | S5: =IF(S$4=$BW$4,"▲","") | T5: =IF(T$4=$BW$4,"▲","") | U5: =IF(U$4=$BW$4,"▲","") | V5: =IF(V$4=$BW$4,"▲","") | W5: =IF(W$4=$BW$4,"▲","") | X5: =IF(X$4=$BW$4,"▲","") | Y5: =IF(Y$4=$BW$4,"▲","") | Z5: =IF(Z$4=$BW$4,"▲","") | ... AD5: =IF(AD$4=$BW$4,"▲","") | AE5: =IF(AE$4=$BW$4,"▲","◆") -> ◆ | AF5: =IF(AF$4=$BW$4,"▲","") | AG5: =IF(AG$4=$BW$4,"▲","") | AH5: =IF(AH$4=$BW$4,"▲","✕") -> ✕ | AI5: =IF(AI$4=$BW$4,"▲","◆") -> ◆ | AJ5: =IF(AJ$4=$BW$4,"▲","") | AK5: =IF(AK$4=$BW$4,"▲","") | AL5: =IF(AL$4=$BW$4,"▲","") | AM5: =IF(AM$4=$BW$4,"▲","") -> ▲ | AN5: =IF(AN$4=$BW$4,"▲","") | AO5: =IF(AO$4=$BW$4,"▲","") | AP5: =IF(AP$4=$BW$4,"▲","") | AQ5: =IF(AQ$4=$BW$4,"▲","") | ... BS5: =IF(BS$4=$BW$4,"▲","")
A6: G-P1-L1 | B6: Design & Plan (lane A) [P1-L1] | C6: SEGRO | D6: POAP-DRAWN | E6: F16 | G6: 1 | H6: 5 | I6: =MIN(61,IF(G6<=29,ROUND((G6-1)*(29+SlipWeeks)/29,0)+1,G6+SlipWeeks)) -> 1 | J6: =MIN(61,IF(G6+H6-1<=29,MAX(ROUND((G6+H6-1)*(29+SlipWeeks)/29,0),I6),G6+H6-1+SlipWeeks)) -> 5 | K6: =IF(AND(K$4>=$I6,K$4<=$J6),1,"") -> 1 | L6: =IF(AND(L$4>=$I6,L$4<=$J6),1,"") -> 1 | M6: =IF(AND(M$4>=$I6,M$4<=$J6),1,"") -> 1 | N6: =IF(AND(N$4>=$I6,N$4<=$J6),1,"") -> 1 | O6: =IF(AND(O$4>=$I6,O$4<=$J6),1,"") -> 1 | P6: =IF(AND(P$4>=$I6,P$4<=$J6),1,"") | Q6: =IF(AND(Q$4>=$I6,Q$4<=$J6),1,"") | R6: =IF(AND(R$4>=$I6,R$4<=$J6),1,"") | ... BS6: =IF(AND(BS$4>=$I6,BS$4<=$J6),1,"") | BT6: =IF(IF(G6+H6-1<=29,MAX(ROUND((G6+H6-1)*(29+SlipWeeks)/29,0),$I6),G6+H6-1+SlipWeeks)>61,"▶ clipped","") | BU6: Slide 3 lane A design bar is drawn: '5 weeks' bar x=1.98 w=2.54 = gantt_timeline P1 window weeks 1-5. Role/scope from spec_cost_model P1-L1: 'Solutions architect - workshop lead, HLD/LLD, target arch for EA, KDD papers (AKS v ARO, env count, cluster topology)', 1 FTE x 5 wk.
A7: G-P1-L1-s1 | B7: • Lead Arch Workshop Kick-off | C7: SEGRO | D7: DERIVED | G7: 1 | H7: 1 | I7: =MEDIAN($I$6,$J$6,$I$6+ROUND((G7-$G$6)/$H$6*($J$6-$I$6+1),0)) -> 1 | J7: =MEDIAN(I7,$J$6,$I$6+ROUND((G7+H7-$G$6)/$H$6*($J$6-$I$6+1),0)-1) -> 1 | K7: =IF(AND(K$4>=$I7,K$4<=$J7),1,"") -> 1 | L7: =IF(AND(L$4>=$I7,L$4<=$J7),1,"") | M7: =IF(AND(M$4>=$I7,M$4<=$J7),1,"") | N7: =IF(AND(N$4>=$I7,N$4<=$J7),1,"") | O7: =IF(AND(O$4>=$I7,O$4<=$J7),1,"") | P7: =IF(AND(P$4>=$I7,P$4<=$J7),1,"") | Q7: =IF(AND(Q$4>=$I7,Q$4<=$J7),1,"") | R7: =IF(AND(R$4>=$I7,R$4<=$J7),1,"") | ... BS7: =IF(AND(BS$4>=$I7,BS$4<=$J7),1,"") | BU7: Slide 3 chip 'Arch Workshop Kick-off' (x=1.40) is the first workshop in the drawn left-to-right stagger of the lane-A chain - earliest position, so week 1 at parent start.
A8: G-P1-L1-s2 | B8: • Lead Arch Workshop Sizing | C8: SEGRO | D8: DERIVED | F8: G-P1-L1-s1 | G8: 2 | H8: 1 | I8: =MEDIAN($I$6,$J$6,$I$6+ROUND((G8-$G$6)/$H$6*($J$6-$I$6+1),0)) -> 2 | J8: =MEDIAN(I8,$J$6,$I$6+ROUND((G8+H8-$G$6)/$H$6*($J$6-$I$6+1),0)-1) -> 2 | K8: =IF(AND(K$4>=$I8,K$4<=$J8),1,"") | L8: =IF(AND(L$4>=$I8,L$4<=$J8),1,"") -> 1 | M8: =IF(AND(M$4>=$I8,M$4<=$J8),1,"") | N8: =IF(AND(N$4>=$I8,N$4<=$J8),1,"") | O8: =IF(AND(O$4>=$I8,O$4<=$J8),1,"") | P8: =IF(AND(P$4>=$I8,P$4<=$J8),1,"") | Q8: =IF(AND(Q$4>=$I8,Q$4<=$J8),1,"") | R8: =IF(AND(R$4>=$I8,R$4<=$J8),1,"") | ... BS8: =IF(AND(BS$4>=$I8,BS$4<=$J8),1,"") | BU8: Slide 3 chip 'Arch Workshop Sizing' (x=1.65) is drawn second in the workshop stagger, immediately right of kick-off - next week slot.
A9: G-P1-L1-s3 | B9: • Draft KDD papers (AKS v ARO, env count, cluster topology) feeding the lane-B KDD decisions | C9: SEGRO | D9: ASSUMPTION | F9: G-P1-L1-s1 | G9: 2 | H9: 2 | I9: =MEDIAN($I$6,$J$6,$I$6+ROUND((G9-$G$6)/$H$6*($J$6-$I$6+1),0)) -> 2 | J9: =MEDIAN(I9,$J$6,$I$6+ROUND((G9+H9-$G$6)/$H$6*($J$6-$I$6+1),0)-1) -> 3 | K9: =IF(AND(K$4>=$I9,K$4<=$J9),1,"") | L9: =IF(AND(L$4>=$I9,L$4<=$J9),1,"") -> 1 | M9: =IF(AND(M$4>=$I9,M$4<=$J9),1,"") -> 1 | N9: =IF(AND(N$4>=$I9,N$4<=$J9),1,"") | O9: =IF(AND(O$4>=$I9,O$4<=$J9),1,"") | P9: =IF(AND(P$4>=$I9,P$4<=$J9),1,"") | Q9: =IF(AND(Q$4>=$I9,Q$4<=$J9),1,"") | R9: =IF(AND(R$4>=$I9,R$4<=$J9),1,"") | ... BS9: =IF(AND(BS$4>=$I9,BS$4<=$J9),1,"") | BU9: Text from spec_cost_model P1-L1 desc: 'KDD papers (AKS v ARO, env count, cluster topology)'. Position is judgement: drafting must follow the kick-off/sizing workshops and precede the lane-B 'KDDs documented / agreed' close-out - no drawn bar for the drafting itself.
A10: G-P1-L1-s4 | B10: • Produce High Level Design | C10: SEGRO | D10: ASSUMPTION | F10: G-P1-L1-s2 | G10: 3 | H10: 2 | I10: =MEDIAN($I$6,$J$6,$I$6+ROUND((G10-$G$6)/$H$6*($J$6-$I$6+1),0)) -> 3 | J10: =MEDIAN(I10,$J$6,$I$6+ROUND((G10+H10-$G$6)/$H$6*($J$6-$I$6+1),0)-1) -> 4 | K10: =IF(AND(K$4>=$I10,K$4<=$J10),1,"") | L10: =IF(AND(L$4>=$I10,L$4<=$J10),1,"") | M10: =IF(AND(M$4>=$I10,M$4<=$J10),1,"") -> 1 | N10: =IF(AND(N$4>=$I10,N$4<=$J10),1,"") -> 1 | O10: =IF(AND(O$4>=$I10,O$4<=$J10),1,"") | P10: =IF(AND(P$4>=$I10,P$4<=$J10),1,"") | Q10: =IF(AND(Q$4>=$I10,Q$4<=$J10),1,"") | R10: =IF(AND(R$4>=$I10,R$4<=$J10),1,"") | ... BS10: =IF(AND(BS$4>=$I10,BS$4<=$J10),1,"") | BU10: Slide 5 named doc 'High Level Design'. Position is judgement: mid-phase, after the sizing and cyber workshops provide inputs; slide gives no per-document dates.
A11: G-P1-L1-s5 | B11: • Target Arch for EA (consuming platform engineer's physical infrastructure diagrams) | C11: SEGRO | D11: DERIVED | F11: G-P1-L1-s4 | G11: 4 | H11: 1 | I11: =MEDIAN($I$6,$J$6,$I$6+ROUND((G11-$G$6)/$H$6*($J$6-$I$6+1),0)) -> 4 | J11: =MEDIAN(I11,$J$6,$I$6+ROUND((G11+H11-$G$6)/$H$6*($J$6-$I$6+1),0)-1) -> 4 | K11: =IF(AND(K$4>=$I11,K$4<=$J11),1,"") | L11: =IF(AND(L$4>=$I11,L$4<=$J11),1,"") | M11: =IF(AND(M$4>=$I11,M$4<=$J11),1,"") | N11: =IF(AND(N$4>=$I11,N$4<=$J11),1,"") -> 1 | O11: =IF(AND(O$4>=$I11,O$4<=$J11),1,"") | P11: =IF(AND(P$4>=$I11,P$4<=$J11),1,"") | Q11: =IF(AND(Q$4>=$I11,Q$4<=$J11),1,"") | R11: =IF(AND(R$4>=$I11,R$4<=$J11),1,"") | ... BS11: =IF(AND(BS$4>=$I11,BS$4<=$J11),1,"") | BU11: Slide 3 chip 'Physical infrastructure diagrams and Target Arch for EA' (x=3.07) is drawn last in the lane-A stagger, late in the design bar - week 4 position follows from the drawn order.
A12: G-P1-L1-s6 | B12: • Finalise Low Level Design for Enterprise Arch; KDDs documented / agreed | C12: SEGRO | D12: ASSUMPTION | F12: G-P1-L1-s3, G-P1-L1-s4 | G12: 4 | H12: 2 | I12: =MEDIAN($I$6,$J$6,$I$6+ROUND((G12-$G$6)/$H$6*($J$6-$I$6+1),0)) -> 4 | J12: =MEDIAN(I12,$J$6,$I$6+ROUND((G12+H12-$G$6)/$H$6*($J$6-$I$6+1),0)-1) -> 5 | K12: =IF(AND(K$4>=$I12,K$4<=$J12),1,"") | L12: =IF(AND(L$4>=$I12,L$4<=$J12),1,"") | M12: =IF(AND(M$4>=$I12,M$4<=$J12),1,"") | N12: =IF(AND(N$4>=$I12,N$4<=$J12),1,"") -> 1 | O12: =IF(AND(O$4>=$I12,O$4<=$J12),1,"") -> 1 | P12: =IF(AND(P$4>=$I12,P$4<=$J12),1,"") | Q12: =IF(AND(Q$4>=$I12,Q$4<=$J12),1,"") | R12: =IF(AND(R$4>=$I12,R$4<=$J12),1,"") | ... BS12: =IF(AND(BS$4>=$I12,BS$4<=$J12),1,"") | BU12: Slide 5 named docs 'Low Level Design for Enterprise Arch' and 'KDDs documented / agreed'. Position is judgement: closing deliverables in the final two weeks before the slide-3 'Design phase complete' marker; no per-document dates drawn.
A14: G-P1-L2 | B14: Design & Plan (lane A) [P1-L2] | C14: SEGRO | D14: POAP-DRAWN | E14: F16, F14 | G14: 1 | H14: 5 | I14: =MIN(61,IF(G14<=29,ROUND((G14-1)*(29+SlipWeeks)/29,0)+1,G14+SlipWeeks)) -> 1 | J14: =MIN(61,IF(G14+H14-1<=29,MAX(ROUND((G14+H14-1)*(29+SlipWeeks)/29,0),I14),G14+H14-1+SlipWeeks)) -> 5 | K14: =IF(AND(K$4>=$I14,K$4<=$J14),1,"") -> 1 | L14: =IF(AND(L$4>=$I14,L$4<=$J14),1,"") -> 1 | M14: =IF(AND(M$4>=$I14,M$4<=$J14),1,"") -> 1 | N14: =IF(AND(N$4>=$I14,N$4<=$J14),1,"") -> 1 | O14: =IF(AND(O$4>=$I14,O$4<=$J14),1,"") -> 1 | P14: =IF(AND(P$4>=$I14,P$4<=$J14),1,"") | Q14: =IF(AND(Q$4>=$I14,Q$4<=$J14),1,"") | R14: =IF(AND(R$4>=$I14,R$4<=$J14),1,"") | ... BS14: =IF(AND(BS$4>=$I14,BS$4<=$J14),1,"") | BT14: =IF(IF(G14+H14-1<=29,MAX(ROUND((G14+H14-1)*(29+SlipWeeks)/29,0),$I14),G14+H14-1+SlipWeeks)>61,"▶ clipped","") | BU14: Window = drawn slide 3 '5 weeks' design bar (x=1.98 w=2.54) = weeks 1-5. Role/scope from spec_cost_model P1-L2: 'Platform engineer - sizing workshop, physical infrastructure diagrams, physical sizing of infrastructure', 0.6 FTE.
A15: G-P1-L2-s1 | B15: • Attend Arch Workshop Kick-off; assemble estate sizing inputs | C15: SEGRO | D15: DERIVED | G15: 1 | H15: 1 | I15: =MEDIAN($I$14,$J$14,$I$14+ROUND((G15-$G$14)/$H$14*($J$14-$I$14+1),0)) -> 1 | J15: =MEDIAN(I15,$J$14,$I$14+ROUND((G15+H15-$G$14)/$H$14*($J$14-$I$14+1),0)-1) -> 1 | K15: =IF(AND(K$4>=$I15,K$4<=$J15),1,"") -> 1 | L15: =IF(AND(L$4>=$I15,L$4<=$J15),1,"") | M15: =IF(AND(M$4>=$I15,M$4<=$J15),1,"") | N15: =IF(AND(N$4>=$I15,N$4<=$J15),1,"") | O15: =IF(AND(O$4>=$I15,O$4<=$J15),1,"") | P15: =IF(AND(P$4>=$I15,P$4<=$J15),1,"") | Q15: =IF(AND(Q$4>=$I15,Q$4<=$J15),1,"") | R15: =IF(AND(R$4>=$I15,R$4<=$J15),1,"") | ... BS15: =IF(AND(BS$4>=$I15,BS$4<=$J15),1,"") | BU15: Slide 3 chip 'Arch Workshop Kick-off' (x=1.40), first in the drawn stagger - week 1 at parent start; sizing-input scope from spec_cost_model P1-L2 desc 'sizing workshop'.
A16: G-P1-L2-s2 | B16: • Run Arch Workshop Sizing (the workshop the build phase is 'To be validated' against) | C16: SEGRO | D16: DERIVED | F16: G-P1-L2-s1 | G16: 2 | H16: 1 | I16: =MEDIAN($I$14,$J$14,$I$14+ROUND((G16-$G$14)/$H$14*($J$14-$I$14+1),0)) -> 2 | J16: =MEDIAN(I16,$J$14,$I$14+ROUND((G16+H16-$G$14)/$H$14*($J$14-$I$14+1),0)-1) -> 2 | K16: =IF(AND(K$4>=$I16,K$4<=$J16),1,"") | L16: =IF(AND(L$4>=$I16,L$4<=$J16),1,"") -> 1 | M16: =IF(AND(M$4>=$I16,M$4<=$J16),1,"") | N16: =IF(AND(N$4>=$I16,N$4<=$J16),1,"") | O16: =IF(AND(O$4>=$I16,O$4<=$J16),1,"") | P16: =IF(AND(P$4>=$I16,P$4<=$J16),1,"") | Q16: =IF(AND(Q$4>=$I16,Q$4<=$J16),1,"") | R16: =IF(AND(R$4>=$I16,R$4<=$J16),1,"") | ... BS16: =IF(AND(BS$4>=$I16,BS$4<=$J16),1,"") | BU16: Slide 3 chip 'Arch Workshop Sizing' (x=1.65), second in the drawn stagger. Slide 3 build annotation 'To be validated based on Arch workshop' (x=6.85) hangs on this workshop's output (F14).
A17: G-P1-L2-s3 | B17: • Physical sizing of infrastructure | C17: SEGRO | D17: ASSUMPTION | F17: G-P1-L2-s2 | G17: 3 | H17: 2 | I17: =MEDIAN($I$14,$J$14,$I$14+ROUND((G17-$G$14)/$H$14*($J$14-$I$14+1),0)) -> 3 | J17: =MEDIAN(I17,$J$14,$I$14+ROUND((G17+H17-$G$14)/$H$14*($J$14-$I$14+1),0)-1) -> 4 | K17: =IF(AND(K$4>=$I17,K$4<=$J17),1,"") | L17: =IF(AND(L$4>=$I17,L$4<=$J17),1,"") | M17: =IF(AND(M$4>=$I17,M$4<=$J17),1,"") -> 1 | N17: =IF(AND(N$4>=$I17,N$4<=$J17),1,"") -> 1 | O17: =IF(AND(O$4>=$I17,O$4<=$J17),1,"") | P17: =IF(AND(P$4>=$I17,P$4<=$J17),1,"") | Q17: =IF(AND(Q$4>=$I17,Q$4<=$J17),1,"") | R17: =IF(AND(R$4>=$I17,R$4<=$J17),1,"") | ... BS17: =IF(AND(BS$4>=$I17,BS$4<=$J17),1,"") | BU17: Slide 5 named doc 'Physical sizing of infrastructure'. Position is judgement: follows the sizing workshop; no drawn bar for the document itself.
A18: G-P1-L2-s4 | B18: • Physical Low Level Technical Arch Diagrams / physical infrastructure diagrams | C18: SEGRO | D18: DERIVED | F18: G-P1-L2-s3 | G18: 4 | H18: 2 | I18: =MEDIAN($I$14,$J$14,$I$14+ROUND((G18-$G$14)/$H$14*($J$14-$I$14+1),0)) -> 4 | J18: =MEDIAN(I18,$J$14,$I$14+ROUND((G18+H18-$G$14)/$H$14*($J$14-$I$14+1),0)-1) -> 5 | K18: =IF(AND(K$4>=$I18,K$4<=$J18),1,"") | L18: =IF(AND(L$4>=$I18,L$4<=$J18),1,"") | M18: =IF(AND(M$4>=$I18,M$4<=$J18),1,"") | N18: =IF(AND(N$4>=$I18,N$4<=$J18),1,"") -> 1 | O18: =IF(AND(O$4>=$I18,O$4<=$J18),1,"") -> 1 | P18: =IF(AND(P$4>=$I18,P$4<=$J18),1,"") | Q18: =IF(AND(Q$4>=$I18,Q$4<=$J18),1,"") | R18: =IF(AND(R$4>=$I18,R$4<=$J18),1,"") | ... BS18: =IF(AND(BS$4>=$I18,BS$4<=$J18),1,"") | BU18: Slide 5 named doc 'Physical Low Level Technical Arch Diagrams'; slide 3 chip 'Physical infrastructure diagrams and Target Arch for EA' (x=3.07) is drawn last in the lane-A stagger - late-phase position follows from the drawn order.
A20: G-P1-L3 | B20: Design & Plan (lane A) [P1-L3] | C20: SEGRO | D20: POAP-DRAWN | E20: F16 | G20: 1 | H20: 5 | I20: =MIN(61,IF(G20<=29,ROUND((G20-1)*(29+SlipWeeks)/29,0)+1,G20+SlipWeeks)) -> 1 | J20: =MIN(61,IF(G20+H20-1<=29,MAX(ROUND((G20+H20-1)*(29+SlipWeeks)/29,0),I20),G20+H20-1+SlipWeeks)) -> 5 | K20: =IF(AND(K$4>=$I20,K$4<=$J20),1,"") -> 1 | L20: =IF(AND(L$4>=$I20,L$4<=$J20),1,"") -> 1 | M20: =IF(AND(M$4>=$I20,M$4<=$J20),1,"") -> 1 | N20: =IF(AND(N$4>=$I20,N$4<=$J20),1,"") -> 1 | O20: =IF(AND(O$4>=$I20,O$4<=$J20),1,"") -> 1 | P20: =IF(AND(P$4>=$I20,P$4<=$J20),1,"") | Q20: =IF(AND(Q$4>=$I20,Q$4<=$J20),1,"") | R20: =IF(AND(R$4>=$I20,R$4<=$J20),1,"") | ... BS20: =IF(AND(BS$4>=$I20,BS$4<=$J20),1,"") | BT20: =IF(IF(G20+H20-1<=29,MAX(ROUND((G20+H20-1)*(29+SlipWeeks)/29,0),$I20),G20+H20-1+SlipWeeks)>61,"▶ clipped","") | BU20: Window = drawn slide 3 '5 weeks' design bar = weeks 1-5. Role/scope from spec_cost_model P1-L3: 'Cloud security - Cyber Sec Workshop, cyber security impact analysis + diagrams', 0.4 FTE; IAM workshop/design mapped here as the security-owning role.
A21: G-P1-L3-s1 | B21: • Prepare Cyber Sec Workshop inputs (SEGRO security principles, threat context) | C21: SEGRO | D21: ASSUMPTION | G21: 1 | H21: 1 | I21: =MEDIAN($I$20,$J$20,$I$20+ROUND((G21-$G$20)/$H$20*($J$20-$I$20+1),0)) -> 1 | J21: =MEDIAN(I21,$J$20,$I$20+ROUND((G21+H21-$G$20)/$H$20*($J$20-$I$20+1),0)-1) -> 1 | K21: =IF(AND(K$4>=$I21,K$4<=$J21),1,"") -> 1 | L21: =IF(AND(L$4>=$I21,L$4<=$J21),1,"") | M21: =IF(AND(M$4>=$I21,M$4<=$J21),1,"") | N21: =IF(AND(N$4>=$I21,N$4<=$J21),1,"") | O21: =IF(AND(O$4>=$I21,O$4<=$J21),1,"") | P21: =IF(AND(P$4>=$I21,P$4<=$J21),1,"") | Q21: =IF(AND(Q$4>=$I21,Q$4<=$J21),1,"") | R21: =IF(AND(R$4>=$I21,R$4<=$J21),1,"") | ... BS21: =IF(AND(BS$4>=$I21,BS$4<=$J21),1,"") | BU21: Workshop named on slide 3 ('Cyber Sec Workshop'); preparation step and its week-1 position are judgement - only the workshop chip itself is drawn.
A22: G-P1-L3-s2 | B22: • Run Cyber Sec Workshop | C22: SEGRO | D22: DERIVED | F22: G-P1-L3-s1 | G22: 2 | H22: 1 | I22: =MEDIAN($I$20,$J$20,$I$20+ROUND((G22-$G$20)/$H$20*($J$20-$I$20+1),0)) -> 2 | J22: =MEDIAN(I22,$J$20,$I$20+ROUND((G22+H22-$G$20)/$H$20*($J$20-$I$20+1),0)-1) -> 2 | K22: =IF(AND(K$4>=$I22,K$4<=$J22),1,"") | L22: =IF(AND(L$4>=$I22,L$4<=$J22),1,"") -> 1 | M22: =IF(AND(M$4>=$I22,M$4<=$J22),1,"") | N22: =IF(AND(N$4>=$I22,N$4<=$J22),1,"") | O22: =IF(AND(O$4>=$I22,O$4<=$J22),1,"") | P22: =IF(AND(P$4>=$I22,P$4<=$J22),1,"") | Q22: =IF(AND(Q$4>=$I22,Q$4<=$J22),1,"") | R22: =IF(AND(R$4>=$I22,R$4<=$J22),1,"") | ... BS22: =IF(AND(BS$4>=$I22,BS$4<=$J22),1,"") | BU22: Slide 3 chip 'Cyber Sec Workshop' (x=1.90), third in the drawn left-to-right workshop stagger - early-mid phase position follows from the drawn order.
A23: G-P1-L3-s3 | B23: • Run Identity Access Mgmt Workshop | C23: SEGRO | D23: DERIVED | F23: G-P1-L3-s2 | G23: 3 | H23: 1 | I23: =MEDIAN($I$20,$J$20,$I$20+ROUND((G23-$G$20)/$H$20*($J$20-$I$20+1),0)) -> 3 | J23: =MEDIAN(I23,$J$20,$I$20+ROUND((G23+H23-$G$20)/$H$20*($J$20-$I$20+1),0)-1) -> 3 | K23: =IF(AND(K$4>=$I23,K$4<=$J23),1,"") | L23: =IF(AND(L$4>=$I23,L$4<=$J23),1,"") | M23: =IF(AND(M$4>=$I23,M$4<=$J23),1,"") -> 1 | N23: =IF(AND(N$4>=$I23,N$4<=$J23),1,"") | O23: =IF(AND(O$4>=$I23,O$4<=$J23),1,"") | P23: =IF(AND(P$4>=$I23,P$4<=$J23),1,"") | Q23: =IF(AND(Q$4>=$I23,Q$4<=$J23),1,"") | R23: =IF(AND(R$4>=$I23,R$4<=$J23),1,"") | ... BS23: =IF(AND(BS$4>=$I23,BS$4<=$J23),1,"") | BU23: Slide 3 chip 'Identity Access Mgmt Workshop' (x=2.01), fourth in the drawn stagger, right of the Cyber Sec Workshop chip.
A24: G-P1-L3-s4 | B24: • Cyber security impact analysis | C24: SEGRO | D24: ASSUMPTION | F24: G-P1-L3-s2 | G24: 3 | H24: 2 | I24: =MEDIAN($I$20,$J$20,$I$20+ROUND((G24-$G$20)/$H$20*($J$20-$I$20+1),0)) -> 3 | J24: =MEDIAN(I24,$J$20,$I$20+ROUND((G24+H24-$G$20)/$H$20*($J$20-$I$20+1),0)-1) -> 4 | K24: =IF(AND(K$4>=$I24,K$4<=$J24),1,"") | L24: =IF(AND(L$4>=$I24,L$4<=$J24),1,"") | M24: =IF(AND(M$4>=$I24,M$4<=$J24),1,"") -> 1 | N24: =IF(AND(N$4>=$I24,N$4<=$J24),1,"") -> 1 | O24: =IF(AND(O$4>=$I24,O$4<=$J24),1,"") | P24: =IF(AND(P$4>=$I24,P$4<=$J24),1,"") | Q24: =IF(AND(Q$4>=$I24,Q$4<=$J24),1,"") | R24: =IF(AND(R$4>=$I24,R$4<=$J24),1,"") | ... BS24: =IF(AND(BS$4>=$I24,BS$4<=$J24),1,"") | BU24: Slide 5 named doc 'Cyber security impact analysis'. Position is judgement: follows the Cyber Sec Workshop; no drawn bar for the document.
A25: G-P1-L3-s5 | B25: • Cyber security diagrams | C25: SEGRO | D25: ASSUMPTION | F25: G-P1-L3-s4 | G25: 4 | H25: 2 | I25: =MEDIAN($I$20,$J$20,$I$20+ROUND((G25-$G$20)/$H$20*($J$20-$I$20+1),0)) -> 4 | J25: =MEDIAN(I25,$J$20,$I$20+ROUND((G25+H25-$G$20)/$H$20*($J$20-$I$20+1),0)-1) -> 5 | K25: =IF(AND(K$4>=$I25,K$4<=$J25),1,"") | L25: =IF(AND(L$4>=$I25,L$4<=$J25),1,"") | M25: =IF(AND(M$4>=$I25,M$4<=$J25),1,"") | N25: =IF(AND(N$4>=$I25,N$4<=$J25),1,"") -> 1 | O25: =IF(AND(O$4>=$I25,O$4<=$J25),1,"") -> 1 | P25: =IF(AND(P$4>=$I25,P$4<=$J25),1,"") | Q25: =IF(AND(Q$4>=$I25,Q$4<=$J25),1,"") | R25: =IF(AND(R$4>=$I25,R$4<=$J25),1,"") | ... BS25: =IF(AND(BS$4>=$I25,BS$4<=$J25),1,"") | BU25: Slide 5 named doc 'Cyber security diagrams'. Position is judgement: diagrams follow the impact analysis in the phase tail.
A26: G-P1-L3-s6 | B26: • Identity & access management design | C26: SEGRO | D26: ASSUMPTION | F26: G-P1-L3-s3 | G26: 4 | H26: 2 | I26: =MEDIAN($I$20,$J$20,$I$20+ROUND((G26-$G$20)/$H$20*($J$20-$I$20+1),0)) -> 4 | J26: =MEDIAN(I26,$J$20,$I$20+ROUND((G26+H26-$G$20)/$H$20*($J$20-$I$20+1),0)-1) -> 5 | K26: =IF(AND(K$4>=$I26,K$4<=$J26),1,"") | L26: =IF(AND(L$4>=$I26,L$4<=$J26),1,"") | M26: =IF(AND(M$4>=$I26,M$4<=$J26),1,"") | N26: =IF(AND(N$4>=$I26,N$4<=$J26),1,"") -> 1 | O26: =IF(AND(O$4>=$I26,O$4<=$J26),1,"") -> 1 | P26: =IF(AND(P$4>=$I26,P$4<=$J26),1,"") | Q26: =IF(AND(Q$4>=$I26,Q$4<=$J26),1,"") | R26: =IF(AND(R$4>=$I26,R$4<=$J26),1,"") | ... BS26: =IF(AND(BS$4>=$I26,BS$4<=$J26),1,"") | BU26: Slide 5 named doc 'Identity & access management design'. Position is judgement: follows the IAM workshop; closes with the phase.
A28: G-P1-L4 | B28: Design & Plan (lane A) [P1-L4] | C28: SEGRO | D28: POAP-DRAWN | E28: F16 | G28: 1 | H28: 5 | I28: =MIN(61,IF(G28<=29,ROUND((G28-1)*(29+SlipWeeks)/29,0)+1,G28+SlipWeeks)) -> 1 | J28: =MIN(61,IF(G28+H28-1<=29,MAX(ROUND((G28+H28-1)*(29+SlipWeeks)/29,0),I28),G28+H28-1+SlipWeeks)) -> 5 | K28: =IF(AND(K$4>=$I28,K$4<=$J28),1,"") -> 1 | L28: =IF(AND(L$4>=$I28,L$4<=$J28),1,"") -> 1 | M28: =IF(AND(M$4>=$I28,M$4<=$J28),1,"") -> 1 | N28: =IF(AND(N$4>=$I28,N$4<=$J28),1,"") -> 1 | O28: =IF(AND(O$4>=$I28,O$4<=$J28),1,"") -> 1 | P28: =IF(AND(P$4>=$I28,P$4<=$J28),1,"") | Q28: =IF(AND(Q$4>=$I28,Q$4<=$J28),1,"") | R28: =IF(AND(R$4>=$I28,R$4<=$J28),1,"") | ... BS28: =IF(AND(BS$4>=$I28,BS$4<=$J28),1,"") | BT28: =IF(IF(G28+H28-1<=29,MAX(ROUND((G28+H28-1)*(29+SlipWeeks)/29,0),$I28),G28+H28-1+SlipWeeks)>61,"▶ clipped","") | BU28: Window = drawn slide 3 '5 weeks' design bar = weeks 1-5. Role/scope from spec_cost_model P1-L4: 'Data engineer - Data Mgmt Workshop, data flow design, data governance principles input', 0.4 FTE.
A29: G-P1-L4-s1 | B29: • Prepare Data Mgmt Workshop inputs (data landscape, governance principles) | C29: SEGRO | D29: ASSUMPTION | G29: 1 | H29: 2 | I29: =MEDIAN($I$28,$J$28,$I$28+ROUND((G29-$G$28)/$H$28*($J$28-$I$28+1),0)) -> 1 | J29: =MEDIAN(I29,$J$28,$I$28+ROUND((G29+H29-$G$28)/$H$28*($J$28-$I$28+1),0)-1) -> 2 | K29: =IF(AND(K$4>=$I29,K$4<=$J29),1,"") -> 1 | L29: =IF(AND(L$4>=$I29,L$4<=$J29),1,"") -> 1 | M29: =IF(AND(M$4>=$I29,M$4<=$J29),1,"") | N29: =IF(AND(N$4>=$I29,N$4<=$J29),1,"") | O29: =IF(AND(O$4>=$I29,O$4<=$J29),1,"") | P29: =IF(AND(P$4>=$I29,P$4<=$J29),1,"") | Q29: =IF(AND(Q$4>=$I29,Q$4<=$J29),1,"") | R29: =IF(AND(R$4>=$I29,R$4<=$J29),1,"") | ... BS29: =IF(AND(BS$4>=$I29,BS$4<=$J29),1,"") | BU29: Text from spec_cost_model P1-L4 desc 'data governance principles input' and the slide-3 workshop name; preparation step and its position are judgement - only the workshop chip is drawn.
A30: G-P1-L4-s2 | B30: • Run Data Mgmt Workshop | C30: SEGRO | D30: DERIVED | F30: G-P1-L4-s1 | G30: 3 | H30: 1 | I30: =MEDIAN($I$28,$J$28,$I$28+ROUND((G30-$G$28)/$H$28*($J$28-$I$28+1),0)) -> 3 | J30: =MEDIAN(I30,$J$28,$I$28+ROUND((G30+H30-$G$28)/$H$28*($J$28-$I$28+1),0)-1) -> 3 | K30: =IF(AND(K$4>=$I30,K$4<=$J30),1,"") | L30: =IF(AND(L$4>=$I30,L$4<=$J30),1,"") | M30: =IF(AND(M$4>=$I30,M$4<=$J30),1,"") -> 1 | N30: =IF(AND(N$4>=$I30,N$4<=$J30),1,"") | O30: =IF(AND(O$4>=$I30,O$4<=$J30),1,"") | P30: =IF(AND(P$4>=$I30,P$4<=$J30),1,"") | Q30: =IF(AND(Q$4>=$I30,Q$4<=$J30),1,"") | R30: =IF(AND(R$4>=$I30,R$4<=$J30),1,"") | ... BS30: =IF(AND(BS$4>=$I30,BS$4<=$J30),1,"") | BU30: Slide 3 chip 'Data Mgmt Workshop' (x=2.31), fifth and last workshop in the drawn left-to-right stagger - mid-phase position follows from the drawn order.
A31: G-P1-L4-s3 | B31: • Data flow design | C31: SEGRO | D31: ASSUMPTION | F31: G-P1-L4-s2 | G31: 4 | H31: 2 | I31: =MEDIAN($I$28,$J$28,$I$28+ROUND((G31-$G$28)/$H$28*($J$28-$I$28+1),0)) -> 4 | J31: =MEDIAN(I31,$J$28,$I$28+ROUND((G31+H31-$G$28)/$H$28*($J$28-$I$28+1),0)-1) -> 5 | K31: =IF(AND(K$4>=$I31,K$4<=$J31),1,"") | L31: =IF(AND(L$4>=$I31,L$4<=$J31),1,"") | M31: =IF(AND(M$4>=$I31,M$4<=$J31),1,"") | N31: =IF(AND(N$4>=$I31,N$4<=$J31),1,"") -> 1 | O31: =IF(AND(O$4>=$I31,O$4<=$J31),1,"") -> 1 | P31: =IF(AND(P$4>=$I31,P$4<=$J31),1,"") | Q31: =IF(AND(Q$4>=$I31,Q$4<=$J31),1,"") | R31: =IF(AND(R$4>=$I31,R$4<=$J31),1,"") | ... BS31: =IF(AND(BS$4>=$I31,BS$4<=$J31),1,"") | BU31: Slide 5 named doc 'Data flow design'. Position is judgement: follows the Data Mgmt Workshop; no drawn bar for the document.
A32: G-P1-L4-s4 | B32: • Data governance principles input handed to the build-phase Data Mgmt & Governance workstream | C32: SEGRO | D32: ASSUMPTION | F32: G-P1-L4-s2 | G32: 4 | H32: 2 | I32: =MEDIAN($I$28,$J$28,$I$28+ROUND((G32-$G$28)/$H$28*($J$28-$I$28+1),0)) -> 4 | J32: =MEDIAN(I32,$J$28,$I$28+ROUND((G32+H32-$G$28)/$H$28*($J$28-$I$28+1),0)-1) -> 5 | K32: =IF(AND(K$4>=$I32,K$4<=$J32),1,"") | L32: =IF(AND(L$4>=$I32,L$4<=$J32),1,"") | M32: =IF(AND(M$4>=$I32,M$4<=$J32),1,"") | N32: =IF(AND(N$4>=$I32,N$4<=$J32),1,"") -> 1 | O32: =IF(AND(O$4>=$I32,O$4<=$J32),1,"") -> 1 | P32: =IF(AND(P$4>=$I32,P$4<=$J32),1,"") | Q32: =IF(AND(Q$4>=$I32,Q$4<=$J32),1,"") | R32: =IF(AND(R$4>=$I32,R$4<=$J32),1,"") | ... BS32: =IF(AND(BS$4>=$I32,BS$4<=$J32),1,"") | BU32: Text from spec_cost_model P1-L4 desc 'data governance principles input' (the downstream stream is slide 3 build item 6 'Data Mgmt and Governance Principles'). Handover position at phase tail is judgement.
A34: G-P1-L5 | B34: Design & Plan (lane A) [P1-L5] | C34: SEGRO | D34: POAP-DRAWN | E34: F16 | G34: 1 | H34: 5 | I34: =MIN(61,IF(G34<=29,ROUND((G34-1)*(29+SlipWeeks)/29,0)+1,G34+SlipWeeks)) -> 1 | J34: =MIN(61,IF(G34+H34-1<=29,MAX(ROUND((G34+H34-1)*(29+SlipWeeks)/29,0),I34),G34+H34-1+SlipWeeks)) -> 5 | K34: =IF(AND(K$4>=$I34,K$4<=$J34),1,"") -> 1 | L34: =IF(AND(L$4>=$I34,L$4<=$J34),1,"") -> 1 | M34: =IF(AND(M$4>=$I34,M$4<=$J34),1,"") -> 1 | N34: =IF(AND(N$4>=$I34,N$4<=$J34),1,"") -> 1 | O34: =IF(AND(O$4>=$I34,O$4<=$J34),1,"") -> 1 | P34: =IF(AND(P$4>=$I34,P$4<=$J34),1,"") | Q34: =IF(AND(Q$4>=$I34,Q$4<=$J34),1,"") | R34: =IF(AND(R$4>=$I34,R$4<=$J34),1,"") | ... BS34: =IF(AND(BS$4>=$I34,BS$4<=$J34),1,"") | BT34: =IF(IF(G34+H34-1<=29,MAX(ROUND((G34+H34-1)*(29+SlipWeeks)/29,0),$I34),G34+H34-1+SlipWeeks)>61,"▶ clipped","") | BU34: Window = drawn slide 3 '5 weeks' design bar = weeks 1-5. Role/scope from spec_cost_model P1-L5: 'Business analyst - Use case scope for Release 1 Agreed, KDD documentation, DRG/ARG approval pack', 0.4 FTE.
A35: G-P1-L5-s1 | B35: • Use case scoping for Release 1, closing with 'Use case scope for Release 1 Agreed' | C35: SEGRO | D35: DERIVED | G35: 1 | H35: 2 | I35: =MEDIAN($I$34,$J$34,$I$34+ROUND((G35-$G$34)/$H$34*($J$34-$I$34+1),0)) -> 1 | J35: =MEDIAN(I35,$J$34,$I$34+ROUND((G35+H35-$G$34)/$H$34*($J$34-$I$34+1),0)-1) -> 2 | K35: =IF(AND(K$4>=$I35,K$4<=$J35),1,"") -> 1 | L35: =IF(AND(L$4>=$I35,L$4<=$J35),1,"") -> 1 | M35: =IF(AND(M$4>=$I35,M$4<=$J35),1,"") | N35: =IF(AND(N$4>=$I35,N$4<=$J35),1,"") | O35: =IF(AND(O$4>=$I35,O$4<=$J35),1,"") | P35: =IF(AND(P$4>=$I35,P$4<=$J35),1,"") | Q35: =IF(AND(Q$4>=$I35,Q$4<=$J35),1,"") | R35: =IF(AND(R$4>=$I35,R$4<=$J35),1,"") | ... BS35: =IF(AND(BS$4>=$I35,BS$4<=$J35),1,"") | BU35: Slide 3 chip 'Use case scope for Release 1 Agreed' (x=1.95) is drawn at the very start of the design bar (bar starts x=1.98) - early position follows from the drawing.
A36: G-P1-L5-s2 | B36: • Business context input to the workshop chain (sizing, cyber, IAM, data) | C36: SEGRO | D36: ASSUMPTION | F36: G-P1-L5-s1 | G36: 2 | H36: 2 | I36: =MEDIAN($I$34,$J$34,$I$34+ROUND((G36-$G$34)/$H$34*($J$34-$I$34+1),0)) -> 2 | J36: =MEDIAN(I36,$J$34,$I$34+ROUND((G36+H36-$G$34)/$H$34*($J$34-$I$34+1),0)-1) -> 3 | K36: =IF(AND(K$4>=$I36,K$4<=$J36),1,"") | L36: =IF(AND(L$4>=$I36,L$4<=$J36),1,"") -> 1 | M36: =IF(AND(M$4>=$I36,M$4<=$J36),1,"") -> 1 | N36: =IF(AND(N$4>=$I36,N$4<=$J36),1,"") | O36: =IF(AND(O$4>=$I36,O$4<=$J36),1,"") | P36: =IF(AND(P$4>=$I36,P$4<=$J36),1,"") | Q36: =IF(AND(Q$4>=$I36,Q$4<=$J36),1,"") | R36: =IF(AND(R$4>=$I36,R$4<=$J36),1,"") | ... BS36: =IF(AND(BS$4>=$I36,BS$4<=$J36),1,"") | BU36: Workshops named on slide 3 ('Arch Workshop Sizing', 'Cyber Sec Workshop', 'Identity Access Mgmt Workshop', 'Data Mgmt Workshop'); BA attendance and its weeks-2-3 position are judgement.
A37: G-P1-L5-s3 | B37: • KDD documentation | C37: SEGRO | D37: ASSUMPTION | F37: G-P1-L5-s2 | G37: 3 | H37: 2 | I37: =MEDIAN($I$34,$J$34,$I$34+ROUND((G37-$G$34)/$H$34*($J$34-$I$34+1),0)) -> 3 | J37: =MEDIAN(I37,$J$34,$I$34+ROUND((G37+H37-$G$34)/$H$34*($J$34-$I$34+1),0)-1) -> 4 | K37: =IF(AND(K$4>=$I37,K$4<=$J37),1,"") | L37: =IF(AND(L$4>=$I37,L$4<=$J37),1,"") | M37: =IF(AND(M$4>=$I37,M$4<=$J37),1,"") -> 1 | N37: =IF(AND(N$4>=$I37,N$4<=$J37),1,"") -> 1 | O37: =IF(AND(O$4>=$I37,O$4<=$J37),1,"") | P37: =IF(AND(P$4>=$I37,P$4<=$J37),1,"") | Q37: =IF(AND(Q$4>=$I37,Q$4<=$J37),1,"") | R37: =IF(AND(R$4>=$I37,R$4<=$J37),1,"") | ... BS37: =IF(AND(BS$4>=$I37,BS$4<=$J37),1,"") | BU37: Text from spec_cost_model P1-L5 desc 'KDD documentation' and slide 5 named doc 'KDDs documented / agreed'. Position is judgement: follows the workshop chain, precedes DRG close-out.
A38: G-P1-L5-s4 | B38: • DRG approval doc / DRG-ARG approval pack | C38: SEGRO | D38: ASSUMPTION | F38: G-P1-L5-s3 | G38: 4 | H38: 2 | I38: =MEDIAN($I$34,$J$34,$I$34+ROUND((G38-$G$34)/$H$34*($J$34-$I$34+1),0)) -> 4 | J38: =MEDIAN(I38,$J$34,$I$34+ROUND((G38+H38-$G$34)/$H$34*($J$34-$I$34+1),0)-1) -> 5 | K38: =IF(AND(K$4>=$I38,K$4<=$J38),1,"") | L38: =IF(AND(L$4>=$I38,L$4<=$J38),1,"") | M38: =IF(AND(M$4>=$I38,M$4<=$J38),1,"") | N38: =IF(AND(N$4>=$I38,N$4<=$J38),1,"") -> 1 | O38: =IF(AND(O$4>=$I38,O$4<=$J38),1,"") -> 1 | P38: =IF(AND(P$4>=$I38,P$4<=$J38),1,"") | Q38: =IF(AND(Q$4>=$I38,Q$4<=$J38),1,"") | R38: =IF(AND(R$4>=$I38,R$4<=$J38),1,"") | ... BS38: =IF(AND(BS$4>=$I38,BS$4<=$J38),1,"") | BU38: Slide 5 named doc 'DRG approval doc'; slide 3 lane-B item 'Arch decisions for DRG / ARG'. Position is judgement: approval pack lands at the phase tail; no drawn date for the document.
A40: G-P1-L6 | B40: Design & Plan (lane A) [P1-L6] | C40: SEGRO | D40: POAP-DRAWN | E40: F16 | G40: 1 | H40: 5 | I40: =MIN(61,IF(G40<=29,ROUND((G40-1)*(29+SlipWeeks)/29,0)+1,G40+SlipWeeks)) -> 1 | J40: =MIN(61,IF(G40+H40-1<=29,MAX(ROUND((G40+H40-1)*(29+SlipWeeks)/29,0),I40),G40+H40-1+SlipWeeks)) -> 5 | K40: =IF(AND(K$4>=$I40,K$4<=$J40),1,"") -> 1 | L40: =IF(AND(L$4>=$I40,L$4<=$J40),1,"") -> 1 | M40: =IF(AND(M$4>=$I40,M$4<=$J40),1,"") -> 1 | N40: =IF(AND(N$4>=$I40,N$4<=$J40),1,"") -> 1 | O40: =IF(AND(O$4>=$I40,O$4<=$J40),1,"") -> 1 | P40: =IF(AND(P$4>=$I40,P$4<=$J40),1,"") | Q40: =IF(AND(Q$4>=$I40,Q$4<=$J40),1,"") | R40: =IF(AND(R$4>=$I40,R$4<=$J40),1,"") | ... BS40: =IF(AND(BS$4>=$I40,BS$4<=$J40),1,"") | BT40: =IF(IF(G40+H40-1<=29,MAX(ROUND((G40+H40-1)*(29+SlipWeeks)/29,0),$I40),G40+H40-1+SlipWeeks)>61,"▶ clipped","") | BU40: Window = drawn slide 3 '5 weeks' design bar = weeks 1-5. Role/scope from spec_cost_model P1-L6: 'Project manager - mobilisation, delivery plan, procurement specification and coordination', 1 FTE.
A41: G-P1-L6-s1 | B41: • Architecture Plan & Mobilisations | C41: SEGRO | D41: DERIVED | G41: 1 | H41: 1 | I41: =MEDIAN($I$40,$J$40,$I$40+ROUND((G41-$G$40)/$H$40*($J$40-$I$40+1),0)) -> 1 | J41: =MEDIAN(I41,$J$40,$I$40+ROUND((G41+H41-$G$40)/$H$40*($J$40-$I$40+1),0)-1) -> 1 | K41: =IF(AND(K$4>=$I41,K$4<=$J41),1,"") -> 1 | L41: =IF(AND(L$4>=$I41,L$4<=$J41),1,"") | M41: =IF(AND(M$4>=$I41,M$4<=$J41),1,"") | N41: =IF(AND(N$4>=$I41,N$4<=$J41),1,"") | O41: =IF(AND(O$4>=$I41,O$4<=$J41),1,"") | P41: =IF(AND(P$4>=$I41,P$4<=$J41),1,"") | Q41: =IF(AND(Q$4>=$I41,Q$4<=$J41),1,"") | R41: =IF(AND(R$4>=$I41,R$4<=$J41),1,"") | ... BS41: =IF(AND(BS$4>=$I41,BS$4<=$J41),1,"") | BU41: Slide 3 item 'Architecture Plan & Mobilisations' (x=0.70, numbered 1) is drawn at the head of lane A - week 1 at parent start.
A42: G-P1-L6-s2 | B42: • Coordinate workshop chain and track KDD decisions | C42: SEGRO | D42: ASSUMPTION | F42: G-P1-L6-s1 | G42: 2 | H42: 3 | I42: =MEDIAN($I$40,$J$40,$I$40+ROUND((G42-$G$40)/$H$40*($J$40-$I$40+1),0)) -> 2 | J42: =MEDIAN(I42,$J$40,$I$40+ROUND((G42+H42-$G$40)/$H$40*($J$40-$I$40+1),0)-1) -> 4 | K42: =IF(AND(K$4>=$I42,K$4<=$J42),1,"") | L42: =IF(AND(L$4>=$I42,L$4<=$J42),1,"") -> 1 | M42: =IF(AND(M$4>=$I42,M$4<=$J42),1,"") -> 1 | N42: =IF(AND(N$4>=$I42,N$4<=$J42),1,"") -> 1 | O42: =IF(AND(O$4>=$I42,O$4<=$J42),1,"") | P42: =IF(AND(P$4>=$I42,P$4<=$J42),1,"") | Q42: =IF(AND(Q$4>=$I42,Q$4<=$J42),1,"") | R42: =IF(AND(R$4>=$I42,R$4<=$J42),1,"") | ... BS42: =IF(AND(BS$4>=$I42,BS$4<=$J42),1,"") | BU42: Coordination scope from spec_cost_model P1-L6 desc 'procurement specification and coordination' across the slide-3 workshop chips (drawn weeks 1-3 stagger); the coordinating activity itself has no drawn bar - position is judgement.
A43: G-P1-L6-s3 | B43: • Procurement specification (feeds the lane-B 'Procurement of desired tech stack' bar) | C43: SEGRO | D43: ASSUMPTION | F43: G-P1-L6-s2 | G43: 3 | H43: 3 | I43: =MEDIAN($I$40,$J$40,$I$40+ROUND((G43-$G$40)/$H$40*($J$40-$I$40+1),0)) -> 3 | J43: =MEDIAN(I43,$J$40,$I$40+ROUND((G43+H43-$G$40)/$H$40*($J$40-$I$40+1),0)-1) -> 5 | K43: =IF(AND(K$4>=$I43,K$4<=$J43),1,"") | L43: =IF(AND(L$4>=$I43,L$4<=$J43),1,"") | M43: =IF(AND(M$4>=$I43,M$4<=$J43),1,"") -> 1 | N43: =IF(AND(N$4>=$I43,N$4<=$J43),1,"") -> 1 | O43: =IF(AND(O$4>=$I43,O$4<=$J43),1,"") -> 1 | P43: =IF(AND(P$4>=$I43,P$4<=$J43),1,"") | Q43: =IF(AND(Q$4>=$I43,Q$4<=$J43),1,"") | R43: =IF(AND(R$4>=$I43,R$4<=$J43),1,"") | ... BS43: =IF(AND(BS$4>=$I43,BS$4<=$J43),1,"") | BU43: Slide 5 named doc 'Procurement specification'; the lane-B bar 'Procurement of desired tech stack' is drawn from x=3.10 (~week 3 of the design bar), so the spec is placed alongside it - exact position is judgement.
A44: G-P1-L6-s4 | B44: • Delivery plan | C44: SEGRO | D44: ASSUMPTION | F44: G-P1-L6-s2 | G44: 4 | H44: 2 | I44: =MEDIAN($I$40,$J$40,$I$40+ROUND((G44-$G$40)/$H$40*($J$40-$I$40+1),0)) -> 4 | J44: =MEDIAN(I44,$J$40,$I$40+ROUND((G44+H44-$G$40)/$H$40*($J$40-$I$40+1),0)-1) -> 5 | K44: =IF(AND(K$4>=$I44,K$4<=$J44),1,"") | L44: =IF(AND(L$4>=$I44,L$4<=$J44),1,"") | M44: =IF(AND(M$4>=$I44,M$4<=$J44),1,"") | N44: =IF(AND(N$4>=$I44,N$4<=$J44),1,"") -> 1 | O44: =IF(AND(O$4>=$I44,O$4<=$J44),1,"") -> 1 | P44: =IF(AND(P$4>=$I44,P$4<=$J44),1,"") | Q44: =IF(AND(Q$4>=$I44,Q$4<=$J44),1,"") | R44: =IF(AND(R$4>=$I44,R$4<=$J44),1,"") | ... BS44: =IF(AND(BS$4>=$I44,BS$4<=$J44),1,"") | BU44: Slide 5 named doc 'Delivery plan'. Position is judgement: consolidates workshop/KDD outcomes at the phase tail before 'Design phase complete'.
A46: G-P1-L7 | B46: Design & Plan (lane A) [P1-L7] | C46: HCL | D46: POAP-DRAWN | E46: F14 | G46: 1 | H46: 5 | I46: =MIN(61,IF(G46<=29,ROUND((G46-1)*(29+SlipWeeks)/29,0)+1,G46+SlipWeeks)) -> 1 | J46: =MIN(61,IF(G46+H46-1<=29,MAX(ROUND((G46+H46-1)*(29+SlipWeeks)/29,0),I46),G46+H46-1+SlipWeeks)) -> 5 | K46: =IF(AND(K$4>=$I46,K$4<=$J46),1,"") -> 1 | L46: =IF(AND(L$4>=$I46,L$4<=$J46),1,"") -> 1 | M46: =IF(AND(M$4>=$I46,M$4<=$J46),1,"") -> 1 | N46: =IF(AND(N$4>=$I46,N$4<=$J46),1,"") -> 1 | O46: =IF(AND(O$4>=$I46,O$4<=$J46),1,"") -> 1 | P46: =IF(AND(P$4>=$I46,P$4<=$J46),1,"") | Q46: =IF(AND(Q$4>=$I46,Q$4<=$J46),1,"") | R46: =IF(AND(R$4>=$I46,R$4<=$J46),1,"") | ... BS46: =IF(AND(BS$4>=$I46,BS$4<=$J46),1,"") | BT46: =IF(IF(G46+H46-1<=29,MAX(ROUND((G46+H46-1)*(29+SlipWeeks)/29,0),$I46),G46+H46-1+SlipWeeks)>61,"▶ clipped","") | BU46: Window = drawn slide 3 '5 weeks' design bar = weeks 1-5. Role/scope from spec_cost_model P1-L7: 'HCL architecture/product SME input to design workshops (UnO/TX/Unica/CDP sizing and prerequisites)', 0.6 FTE, side HCL.
A47: G-P1-L7-s1 | B47: • HCL SME attendance at Arch Workshop Kick-off | C47: HCL | D47: DERIVED | G47: 1 | H47: 1 | I47: =MEDIAN($I$46,$J$46,$I$46+ROUND((G47-$G$46)/$H$46*($J$46-$I$46+1),0)) -> 1 | J47: =MEDIAN(I47,$J$46,$I$46+ROUND((G47+H47-$G$46)/$H$46*($J$46-$I$46+1),0)-1) -> 1 | K47: =IF(AND(K$4>=$I47,K$4<=$J47),1,"") -> 1 | L47: =IF(AND(L$4>=$I47,L$4<=$J47),1,"") | M47: =IF(AND(M$4>=$I47,M$4<=$J47),1,"") | N47: =IF(AND(N$4>=$I47,N$4<=$J47),1,"") | O47: =IF(AND(O$4>=$I47,O$4<=$J47),1,"") | P47: =IF(AND(P$4>=$I47,P$4<=$J47),1,"") | Q47: =IF(AND(Q$4>=$I47,Q$4<=$J47),1,"") | R47: =IF(AND(R$4>=$I47,R$4<=$J47),1,"") | ... BS47: =IF(AND(BS$4>=$I47,BS$4<=$J47),1,"") | BU47: Slide 3 chip 'Arch Workshop Kick-off' (x=1.40), first in the drawn stagger; HCL input scope from spec_cost_model P1-L7 desc 'input to design workshops'.
A48: G-P1-L7-s2 | B48: • UnO/TX/Unica/CDP sizing and prerequisites input to Arch Workshop Sizing | C48: HCL | D48: DERIVED | F48: G-P1-L7-s1 | G48: 2 | H48: 1 | I48: =MEDIAN($I$46,$J$46,$I$46+ROUND((G48-$G$46)/$H$46*($J$46-$I$46+1),0)) -> 2 | J48: =MEDIAN(I48,$J$46,$I$46+ROUND((G48+H48-$G$46)/$H$46*($J$46-$I$46+1),0)-1) -> 2 | K48: =IF(AND(K$4>=$I48,K$4<=$J48),1,"") | L48: =IF(AND(L$4>=$I48,L$4<=$J48),1,"") -> 1 | M48: =IF(AND(M$4>=$I48,M$4<=$J48),1,"") | N48: =IF(AND(N$4>=$I48,N$4<=$J48),1,"") | O48: =IF(AND(O$4>=$I48,O$4<=$J48),1,"") | P48: =IF(AND(P$4>=$I48,P$4<=$J48),1,"") | Q48: =IF(AND(Q$4>=$I48,Q$4<=$J48),1,"") | R48: =IF(AND(R$4>=$I48,R$4<=$J48),1,"") | ... BS48: =IF(AND(BS$4>=$I48,BS$4<=$J48),1,"") | BU48: Slide 3 chip 'Arch Workshop Sizing' (x=1.65), second in the drawn stagger; product scope quoted from spec_cost_model P1-L7 desc 'UnO/TX/Unica/CDP sizing and prerequisites'. The build phase is 'To be validated based on Arch workshop' (F14) - this input is what the validation hangs on.
A49: G-P1-L7-s3 | B49: • HCL product input to Cyber Sec / Identity Access Mgmt / Data Mgmt workshops | C49: HCL | D49: DERIVED | F49: G-P1-L7-s2 | G49: 3 | H49: 1 | I49: =MEDIAN($I$46,$J$46,$I$46+ROUND((G49-$G$46)/$H$46*($J$46-$I$46+1),0)) -> 3 | J49: =MEDIAN(I49,$J$46,$I$46+ROUND((G49+H49-$G$46)/$H$46*($J$46-$I$46+1),0)-1) -> 3 | K49: =IF(AND(K$4>=$I49,K$4<=$J49),1,"") | L49: =IF(AND(L$4>=$I49,L$4<=$J49),1,"") | M49: =IF(AND(M$4>=$I49,M$4<=$J49),1,"") -> 1 | N49: =IF(AND(N$4>=$I49,N$4<=$J49),1,"") | O49: =IF(AND(O$4>=$I49,O$4<=$J49),1,"") | P49: =IF(AND(P$4>=$I49,P$4<=$J49),1,"") | Q49: =IF(AND(Q$4>=$I49,Q$4<=$J49),1,"") | R49: =IF(AND(R$4>=$I49,R$4<=$J49),1,"") | ... BS49: =IF(AND(BS$4>=$I49,BS$4<=$J49),1,"") | BU49: Slide 3 chips 'Cyber Sec Workshop' (x=1.90), 'Identity Access Mgmt Workshop' (x=2.01), 'Data Mgmt Workshop' (x=2.31) - drawn mid-stagger after the sizing workshop.
A50: G-P1-L7-s4 | B50: • Product prerequisite validation input to physical sizing and KDD papers | C50: HCL | D50: ASSUMPTION | F50: G-P1-L7-s2 | G50: 4 | H50: 2 | I50: =MEDIAN($I$46,$J$46,$I$46+ROUND((G50-$G$46)/$H$46*($J$46-$I$46+1),0)) -> 4 | J50: =MEDIAN(I50,$J$46,$I$46+ROUND((G50+H50-$G$46)/$H$46*($J$46-$I$46+1),0)-1) -> 5 | K50: =IF(AND(K$4>=$I50,K$4<=$J50),1,"") | L50: =IF(AND(L$4>=$I50,L$4<=$J50),1,"") | M50: =IF(AND(M$4>=$I50,M$4<=$J50),1,"") | N50: =IF(AND(N$4>=$I50,N$4<=$J50),1,"") -> 1 | O50: =IF(AND(O$4>=$I50,O$4<=$J50),1,"") -> 1 | P50: =IF(AND(P$4>=$I50,P$4<=$J50),1,"") | Q50: =IF(AND(Q$4>=$I50,Q$4<=$J50),1,"") | R50: =IF(AND(R$4>=$I50,R$4<=$J50),1,"") | ... BS50: =IF(AND(BS$4>=$I50,BS$4<=$J50),1,"") | BU50: Scope from spec_cost_model P1-L7 desc ('sizing and prerequisites') supporting the slide-5 docs 'Physical sizing of infrastructure' and 'KDDs documented / agreed'; tail-of-phase position is judgement - no drawn bar for HCL input.
A52: G-P1-PROC | B52: Decisions & procurement (lane B) | C52: SEGRO | D52: POAP-DRAWN | E52: F10 | G52: 1 | H52: 5 | I52: =MIN(61,IF(G52<=29,ROUND((G52-1)*(29+SlipWeeks)/29,0)+1,G52+SlipWeeks)) -> 1 | J52: =MIN(61,IF(G52+H52-1<=29,MAX(ROUND((G52+H52-1)*(29+SlipWeeks)/29,0),I52),G52+H52-1+SlipWeeks)) -> 5 | K52: =IF(AND(K$4>=$I52,K$4<=$J52),1,"") -> 1 | L52: =IF(AND(L$4>=$I52,L$4<=$J52),1,"") -> 1 | M52: =IF(AND(M$4>=$I52,M$4<=$J52),1,"") -> 1 | N52: =IF(AND(N$4>=$I52,N$4<=$J52),1,"") -> 1 | O52: =IF(AND(O$4>=$I52,O$4<=$J52),1,"") -> 1 | P52: =IF(AND(P$4>=$I52,P$4<=$J52),1,"") | Q52: =IF(AND(Q$4>=$I52,Q$4<=$J52),1,"") | R52: =IF(AND(R$4>=$I52,R$4<=$J52),1,"") | ... BS52: =IF(AND(BS$4>=$I52,BS$4<=$J52),1,"") | BT52: =IF(IF(G52+H52-1<=29,MAX(ROUND((G52+H52-1)*(29+SlipWeeks)/29,0),$I52),G52+H52-1+SlipWeeks)>61,"▶ clipped","") | BU52: Slide 3 lane B 'Decisions & procurement' (label x=0.67) is drawn inside the P1 window: four KDD chips stacked at the lane start (x=1.37-1.40) plus 'Arch decisions for DRG / ARG' (x=0.53), then the 'Procurement of desired tech stack' bar drawn x=3.10 w=1.31 - per F10 geometry 'roughly a 2.5-2.7 week allowance', ending at the phase boundary. Window = weeks 1-5 in gantt_timeline week numbers; the drawn procurement portion is the final ~2.5 wk. F10 (MAJOR): architect 18 Jul 2026 - 'Procurrent of commercial components would take longer than 2 weeks' - and the licence items P1-L8/P1-L9 are absent from the drawn lane.
A53: G-P1-PROC-s1 | B53: • Agree KDD: TCO AKS v ARO | C53: SEGRO | D53: DERIVED | G53: 1 | H53: 3 | I53: =MEDIAN($I$52,$J$52,$I$52+ROUND((G53-$G$52)/$H$52*($J$52-$I$52+1),0)) -> 1 | J53: =MEDIAN(I53,$J$52,$I$52+ROUND((G53+H53-$G$52)/$H$52*($J$52-$I$52+1),0)-1) -> 3 | K53: =IF(AND(K$4>=$I53,K$4<=$J53),1,"") -> 1 | L53: =IF(AND(L$4>=$I53,L$4<=$J53),1,"") -> 1 | M53: =IF(AND(M$4>=$I53,M$4<=$J53),1,"") -> 1 | N53: =IF(AND(N$4>=$I53,N$4<=$J53),1,"") | O53: =IF(AND(O$4>=$I53,O$4<=$J53),1,"") | P53: =IF(AND(P$4>=$I53,P$4<=$J53),1,"") | Q53: =IF(AND(Q$4>=$I53,Q$4<=$J53),1,"") | R53: =IF(AND(R$4>=$I53,R$4<=$J53),1,"") | ... BS53: =IF(AND(BS$4>=$I53,BS$4<=$J53),1,"") | BU53: Slide 3 lane-B chip 'KDD: TCO AKS v ARO' (x=1.40, numbered 1) drawn at the lane start - decision window runs from week 1 ahead of the procurement bar (drawn from x=3.10).
A54: G-P1-PROC-s2 | B54: • Agree KDD: Vol of Environments | C54: SEGRO | D54: DERIVED | G54: 1 | H54: 3 | I54: =MEDIAN($I$52,$J$52,$I$52+ROUND((G54-$G$52)/$H$52*($J$52-$I$52+1),0)) -> 1 | J54: =MEDIAN(I54,$J$52,$I$52+ROUND((G54+H54-$G$52)/$H$52*($J$52-$I$52+1),0)-1) -> 3 | K54: =IF(AND(K$4>=$I54,K$4<=$J54),1,"") -> 1 | L54: =IF(AND(L$4>=$I54,L$4<=$J54),1,"") -> 1 | M54: =IF(AND(M$4>=$I54,M$4<=$J54),1,"") -> 1 | N54: =IF(AND(N$4>=$I54,N$4<=$J54),1,"") | O54: =IF(AND(O$4>=$I54,O$4<=$J54),1,"") | P54: =IF(AND(P$4>=$I54,P$4<=$J54),1,"") | Q54: =IF(AND(Q$4>=$I54,Q$4<=$J54),1,"") | R54: =IF(AND(R$4>=$I54,R$4<=$J54),1,"") | ... BS54: =IF(AND(BS$4>=$I54,BS$4<=$J54),1,"") | BU54: Slide 3 lane-B chip 'KDD: Vol of Environments' (x=1.39, numbered 2) drawn stacked at the lane start alongside the other KDD chips - same drawn decision window.
A55: G-P1-PROC-s3 | B55: • Agree KDD: Hybrid Tech Stack | C55: SEGRO | D55: DERIVED | G55: 1 | H55: 3 | I55: =MEDIAN($I$52,$J$52,$I$52+ROUND((G55-$G$52)/$H$52*($J$52-$I$52+1),0)) -> 1 | J55: =MEDIAN(I55,$J$52,$I$52+ROUND((G55+H55-$G$52)/$H$52*($J$52-$I$52+1),0)-1) -> 3 | K55: =IF(AND(K$4>=$I55,K$4<=$J55),1,"") -> 1 | L55: =IF(AND(L$4>=$I55,L$4<=$J55),1,"") -> 1 | M55: =IF(AND(M$4>=$I55,M$4<=$J55),1,"") -> 1 | N55: =IF(AND(N$4>=$I55,N$4<=$J55),1,"") | O55: =IF(AND(O$4>=$I55,O$4<=$J55),1,"") | P55: =IF(AND(P$4>=$I55,P$4<=$J55),1,"") | Q55: =IF(AND(Q$4>=$I55,Q$4<=$J55),1,"") | R55: =IF(AND(R$4>=$I55,R$4<=$J55),1,"") | ... BS55: =IF(AND(BS$4>=$I55,BS$4<=$J55),1,"") | BU55: Slide 3 lane-B chip 'KDD: Hybrid Tech Stack' (x=1.39, numbered 3) drawn stacked at the lane start - same drawn decision window.
A56: G-P1-PROC-s4 | B56: • Agree Single Cluster vs Multi Cluster deployment | C56: SEGRO | D56: DERIVED | G56: 1 | H56: 3 | I56: =MEDIAN($I$52,$J$52,$I$52+ROUND((G56-$G$52)/$H$52*($J$52-$I$52+1),0)) -> 1 | J56: =MEDIAN(I56,$J$52,$I$52+ROUND((G56+H56-$G$52)/$H$52*($J$52-$I$52+1),0)-1) -> 3 | K56: =IF(AND(K$4>=$I56,K$4<=$J56),1,"") -> 1 | L56: =IF(AND(L$4>=$I56,L$4<=$J56),1,"") -> 1 | M56: =IF(AND(M$4>=$I56,M$4<=$J56),1,"") -> 1 | N56: =IF(AND(N$4>=$I56,N$4<=$J56),1,"") | O56: =IF(AND(O$4>=$I56,O$4<=$J56),1,"") | P56: =IF(AND(P$4>=$I56,P$4<=$J56),1,"") | Q56: =IF(AND(Q$4>=$I56,Q$4<=$J56),1,"") | R56: =IF(AND(R$4>=$I56,R$4<=$J56),1,"") | ... BS56: =IF(AND(BS$4>=$I56,BS$4<=$J56),1,"") | BU56: Slide 3 lane-B chip 'Single Cluster Vs Multi Cluster deployment' (x=1.37, numbered 4) drawn stacked at the lane start - same drawn decision window.
A57: G-P1-PROC-s5 | B57: • Take architecture decisions through DRG / ARG | C57: SEGRO | D57: DERIVED | G57: 1 | H57: 3 | I57: =MEDIAN($I$52,$J$52,$I$52+ROUND((G57-$G$52)/$H$52*($J$52-$I$52+1),0)) -> 1 | J57: =MEDIAN(I57,$J$52,$I$52+ROUND((G57+H57-$G$52)/$H$52*($J$52-$I$52+1),0)-1) -> 3 | K57: =IF(AND(K$4>=$I57,K$4<=$J57),1,"") -> 1 | L57: =IF(AND(L$4>=$I57,L$4<=$J57),1,"") -> 1 | M57: =IF(AND(M$4>=$I57,M$4<=$J57),1,"") -> 1 | N57: =IF(AND(N$4>=$I57,N$4<=$J57),1,"") | O57: =IF(AND(O$4>=$I57,O$4<=$J57),1,"") | P57: =IF(AND(P$4>=$I57,P$4<=$J57),1,"") | Q57: =IF(AND(Q$4>=$I57,Q$4<=$J57),1,"") | R57: =IF(AND(R$4>=$I57,R$4<=$J57),1,"") | ... BS57: =IF(AND(BS$4>=$I57,BS$4<=$J57),1,"") | BU57: Slide 3 lane-B item 'Arch decisions for DRG / ARG' (x=0.53) drawn at the head of the lane spanning the KDD chain; governance runs with the KDD decisions ahead of procurement.
A58: G-P1-PROC-s6 | B58: • Procurement of desired tech stack | C58: SEGRO | D58: DERIVED | F58: G-P1-PROC-s1, G-P1-PROC-s3, G-P1-PROC-s4 | G58: 3 | H58: 3 | I58: =MEDIAN($I$52,$J$52,$I$52+ROUND((G58-$G$52)/$H$52*($J$52-$I$52+1),0)) -> 3 | J58: =MEDIAN(I58,$J$52,$I$52+ROUND((G58+H58-$G$52)/$H$52*($J$52-$I$52+1),0)-1) -> 5 | K58: =IF(AND(K$4>=$I58,K$4<=$J58),1,"") | L58: =IF(AND(L$4>=$I58,L$4<=$J58),1,"") | M58: =IF(AND(M$4>=$I58,M$4<=$J58),1,"") -> 1 | N58: =IF(AND(N$4>=$I58,N$4<=$J58),1,"") -> 1 | O58: =IF(AND(O$4>=$I58,O$4<=$J58),1,"") -> 1 | P58: =IF(AND(P$4>=$I58,P$4<=$J58),1,"") | Q58: =IF(AND(Q$4>=$I58,Q$4<=$J58),1,"") | R58: =IF(AND(R$4>=$I58,R$4<=$J58),1,"") | ... BS58: =IF(AND(BS$4>=$I58,BS$4<=$J58),1,"") | BU58: Slide 3 lane-B bar 'Procurement of desired tech stack' drawn x=3.10 w=1.31 - per F10 'roughly a 2.5-2.7 week allowance', starting ~week 3 of the design bar and running to the phase boundary (clamped to the parent weeks 1-5 window). F10: architect says procurement of commercial components 'would take longer than 2 weeks'.
A59: G-P1-PROC-s7 | B59: • P1-L8: procure Oracle 19 licence (mandatory for Unica+ MaxAI CDM) - folded into the drawn procurement window | C59: SEGRO | D59: ASSUMPTION | F59: G-P1-PROC-s6 | G59: 3 | H59: 3 | I59: =MEDIAN($I$52,$J$52,$I$52+ROUND((G59-$G$52)/$H$52*($J$52-$I$52+1),0)) -> 3 | J59: =MEDIAN(I59,$J$52,$I$52+ROUND((G59+H59-$G$52)/$H$52*($J$52-$I$52+1),0)-1) -> 5 | K59: =IF(AND(K$4>=$I59,K$4<=$J59),1,"") | L59: =IF(AND(L$4>=$I59,L$4<=$J59),1,"") | M59: =IF(AND(M$4>=$I59,M$4<=$J59),1,"") -> 1 | N59: =IF(AND(N$4>=$I59,N$4<=$J59),1,"") -> 1 | O59: =IF(AND(O$4>=$I59,O$4<=$J59),1,"") -> 1 | P59: =IF(AND(P$4>=$I59,P$4<=$J59),1,"") | Q59: =IF(AND(Q$4>=$I59,Q$4<=$J59),1,"") | R59: =IF(AND(R$4>=$I59,R$4<=$J59),1,"") | ... BS59: =IF(AND(BS$4>=$I59,BS$4<=$J59),1,"") | BU59: P1-L8 in spec_cost_model: 'Oracle 19 licence (mandatory for Unica+ MaxAI CDM) - procurement item, price not shared', RATE_MISSING at GBP 0; its basis notes it is 'absent from POAP Decisions & procurement lane (F10)'. Not drawn anywhere on slide 3, so its position inside the ~2.5 wk drawn procurement window is judgement.
A60: G-P1-PROC-s8 | B60: • P1-L9: procure Aerospike edition/licence (CDP caching, V6.3.0.35 disclosed, edition/licence unstated) - folded into the drawn procurement window | C60: SEGRO | D60: ASSUMPTION | F60: G-P1-PROC-s6 | G60: 3 | H60: 3 | I60: =MEDIAN($I$52,$J$52,$I$52+ROUND((G60-$G$52)/$H$52*($J$52-$I$52+1),0)) -> 3 | J60: =MEDIAN(I60,$J$52,$I$52+ROUND((G60+H60-$G$52)/$H$52*($J$52-$I$52+1),0)-1) -> 5 | K60: =IF(AND(K$4>=$I60,K$4<=$J60),1,"") | L60: =IF(AND(L$4>=$I60,L$4<=$J60),1,"") | M60: =IF(AND(M$4>=$I60,M$4<=$J60),1,"") -> 1 | N60: =IF(AND(N$4>=$I60,N$4<=$J60),1,"") -> 1 | O60: =IF(AND(O$4>=$I60,O$4<=$J60),1,"") -> 1 | P60: =IF(AND(P$4>=$I60,P$4<=$J60),1,"") | Q60: =IF(AND(Q$4>=$I60,Q$4<=$J60),1,"") | R60: =IF(AND(R$4>=$I60,R$4<=$J60),1,"") | ... BS60: =IF(AND(BS$4>=$I60,BS$4<=$J60),1,"") | BU60: P1-L9 in spec_cost_model: 'Aerospike edition/licence (CDP caching, V6.3.0.35 disclosed, edition/licence unstated) - procurement item', RATE_MISSING at GBP 0; its basis notes 'absent from POAP procurement lane (F10)'. Not drawn on slide 3, so its position inside the drawn procurement window is judgement.
A62: G-P2-L1 | B62: Azure foundations [P2-L1] | C62: SEGRO | D62: POAP-DRAWN | G62: 6 | H62: 5 | I62: =MIN(61,IF(G62<=29,ROUND((G62-1)*(29+SlipWeeks)/29,0)+1,G62+SlipWeeks)) -> 6 | J62: =MIN(61,IF(G62+H62-1<=29,MAX(ROUND((G62+H62-1)*(29+SlipWeeks)/29,0),I62),G62+H62-1+SlipWeeks)) -> 10 | K62: =IF(AND(K$4>=$I62,K$4<=$J62),1,"") | L62: =IF(AND(L$4>=$I62,L$4<=$J62),1,"") | M62: =IF(AND(M$4>=$I62,M$4<=$J62),1,"") | N62: =IF(AND(N$4>=$I62,N$4<=$J62),1,"") | O62: =IF(AND(O$4>=$I62,O$4<=$J62),1,"") | P62: =IF(AND(P$4>=$I62,P$4<=$J62),1,"") -> 1 | Q62: =IF(AND(Q$4>=$I62,Q$4<=$J62),1,"") -> 1 | R62: =IF(AND(R$4>=$I62,R$4<=$J62),1,"") -> 1 | ... BS62: =IF(AND(BS$4>=$I62,BS$4<=$J62),1,"") | BT62: =IF(IF(G62+H62-1<=29,MAX(ROUND((G62+H62-1)*(29+SlipWeeks)/29,0),$I62),G62+H62-1+SlipWeeks)>61,"▶ clipped","") | BU62: Slide 3 build item 1 bar x=4.55 w=2.22: 'Provision Azure Foundations | Env Segregation | Networking | Subscriptions | Private DNS | VPN Tunnel Connectivity & workspaces'. Drawn from phase start; width 2.22 of the 4.31 full-phase bar = ~5.2 wk -> weeks 6-10 (F17 evidence corroborates: item 1 'drawn completing in roughly the first half of the build'). Cost line P2-L1 (2 FTE squad-shape ASSUMPTION).
A63: G-P2-L1-s1 | B63: • Stand up subscriptions and environment segregation (landing zones per env) | C63: SEGRO | D63: DERIVED | G63: 6 | H63: 1 | I63: =MEDIAN($I$62,$J$62,$I$62+ROUND((G63-$G$62)/$H$62*($J$62-$I$62+1),0)) -> 6 | J63: =MEDIAN(I63,$J$62,$I$62+ROUND((G63+H63-$G$62)/$H$62*($J$62-$I$62+1),0)-1) -> 6 | K63: =IF(AND(K$4>=$I63,K$4<=$J63),1,"") | L63: =IF(AND(L$4>=$I63,L$4<=$J63),1,"") | M63: =IF(AND(M$4>=$I63,M$4<=$J63),1,"") | N63: =IF(AND(N$4>=$I63,N$4<=$J63),1,"") | O63: =IF(AND(O$4>=$I63,O$4<=$J63),1,"") | P63: =IF(AND(P$4>=$I63,P$4<=$J63),1,"") -> 1 | Q63: =IF(AND(Q$4>=$I63,Q$4<=$J63),1,"") | R63: =IF(AND(R$4>=$I63,R$4<=$J63),1,"") | ... BS63: =IF(AND(BS$4>=$I63,BS$4<=$J63),1,"") | BU63: P2-L1 desc sub-items 'env segregation' + 'subscriptions' (slide 3 item 1: 'Env Segregation ... Subscriptions'); slide 7 'Environment Configuration Document | Defines core Azure foundation'. First step: every other P2 resource deploys into these subscriptions.
A64: G-P2-L1-s2 | B64: • Networking build - VNets, subnets, peering across the segregated environments | C64: SEGRO | D64: DERIVED | F64: G-P2-L1-s1 | G64: 7 | H64: 2 | I64: =MEDIAN($I$62,$J$62,$I$62+ROUND((G64-$G$62)/$H$62*($J$62-$I$62+1),0)) -> 7 | J64: =MEDIAN(I64,$J$62,$I$62+ROUND((G64+H64-$G$62)/$H$62*($J$62-$I$62+1),0)-1) -> 8 | K64: =IF(AND(K$4>=$I64,K$4<=$J64),1,"") | L64: =IF(AND(L$4>=$I64,L$4<=$J64),1,"") | M64: =IF(AND(M$4>=$I64,M$4<=$J64),1,"") | N64: =IF(AND(N$4>=$I64,N$4<=$J64),1,"") | O64: =IF(AND(O$4>=$I64,O$4<=$J64),1,"") | P64: =IF(AND(P$4>=$I64,P$4<=$J64),1,"") | Q64: =IF(AND(Q$4>=$I64,Q$4<=$J64),1,"") -> 1 | R64: =IF(AND(R$4>=$I64,R$4<=$J64),1,"") -> 1 | ... BS64: =IF(AND(BS$4>=$I64,BS$4<=$J64),1,"") | BU64: P2-L1 desc sub-item 'networking' (slide 3 item 1 'Networking'). Positioned after subscriptions exist; note F17 tension - network segmentation decisions sit in the cyber design (item 4) drawn in parallel, so layout rework risk is live.
A65: G-P2-L1-s3 | B65: • Private DNS zones and workspaces provisioning | C65: SEGRO | D65: DERIVED | F65: G-P2-L1-s2 | G65: 9 | H65: 1 | I65: =MEDIAN($I$62,$J$62,$I$62+ROUND((G65-$G$62)/$H$62*($J$62-$I$62+1),0)) -> 9 | J65: =MEDIAN(I65,$J$62,$I$62+ROUND((G65+H65-$G$62)/$H$62*($J$62-$I$62+1),0)-1) -> 9 | K65: =IF(AND(K$4>=$I65,K$4<=$J65),1,"") | L65: =IF(AND(L$4>=$I65,L$4<=$J65),1,"") | M65: =IF(AND(M$4>=$I65,M$4<=$J65),1,"") | N65: =IF(AND(N$4>=$I65,N$4<=$J65),1,"") | O65: =IF(AND(O$4>=$I65,O$4<=$J65),1,"") | P65: =IF(AND(P$4>=$I65,P$4<=$J65),1,"") | Q65: =IF(AND(Q$4>=$I65,Q$4<=$J65),1,"") | R65: =IF(AND(R$4>=$I65,R$4<=$J65),1,"") | ... BS65: =IF(AND(BS$4>=$I65,BS$4<=$J65),1,"") | BU65: P2-L1 desc sub-items 'Private DNS' + 'workspaces' (slide 3 item 1 'Private DNS ... & workspaces'). Positioned after core networking - privatelink DNS zones bind to the VNet layout.
A66: G-P2-L1-s4 | B66: • VPN tunnel connectivity established; write up Environment build specification | C66: SEGRO | D66: DERIVED | F66: G-P2-L1-s3 | G66: 10 | H66: 1 | I66: =MEDIAN($I$62,$J$62,$I$62+ROUND((G66-$G$62)/$H$62*($J$62-$I$62+1),0)) -> 10 | J66: =MEDIAN(I66,$J$62,$I$62+ROUND((G66+H66-$G$62)/$H$62*($J$62-$I$62+1),0)-1) -> 10 | K66: =IF(AND(K$4>=$I66,K$4<=$J66),1,"") | L66: =IF(AND(L$4>=$I66,L$4<=$J66),1,"") | M66: =IF(AND(M$4>=$I66,M$4<=$J66),1,"") | N66: =IF(AND(N$4>=$I66,N$4<=$J66),1,"") | O66: =IF(AND(O$4>=$I66,O$4<=$J66),1,"") | P66: =IF(AND(P$4>=$I66,P$4<=$J66),1,"") | Q66: =IF(AND(Q$4>=$I66,Q$4<=$J66),1,"") | R66: =IF(AND(R$4>=$I66,R$4<=$J66),1,"") | ... BS66: =IF(AND(BS$4>=$I66,BS$4<=$J66),1,"") | BU66: P2-L1 desc sub-item 'VPN tunnel connectivity' (slide 3 item 1 'VPN Tunnel Connectivity'); slide 6 build doc 'Environment build specification' closes out the foundations bar (drawn ending ~week 10).
A68: G-P2-L2 | B68: AKS platform build & harden [P2-L2] | C68: SEGRO | D68: POAP-DRAWN | F68: G-P2-L1 | G68: 8 | H68: 5 | I68: =MIN(61,IF(G68<=29,ROUND((G68-1)*(29+SlipWeeks)/29,0)+1,G68+SlipWeeks)) -> 8 | J68: =MIN(61,IF(G68+H68-1<=29,MAX(ROUND((G68+H68-1)*(29+SlipWeeks)/29,0),I68),G68+H68-1+SlipWeeks)) -> 12 | K68: =IF(AND(K$4>=$I68,K$4<=$J68),1,"") | L68: =IF(AND(L$4>=$I68,L$4<=$J68),1,"") | M68: =IF(AND(M$4>=$I68,M$4<=$J68),1,"") | N68: =IF(AND(N$4>=$I68,N$4<=$J68),1,"") | O68: =IF(AND(O$4>=$I68,O$4<=$J68),1,"") | P68: =IF(AND(P$4>=$I68,P$4<=$J68),1,"") | Q68: =IF(AND(Q$4>=$I68,Q$4<=$J68),1,"") | R68: =IF(AND(R$4>=$I68,R$4<=$J68),1,"") -> 1 | ... BS68: =IF(AND(BS$4>=$I68,BS$4<=$J68),1,"") | BT68: =IF(IF(G68+H68-1<=29,MAX(ROUND((G68+H68-1)*(29+SlipWeeks)/29,0),$I68),G68+H68-1+SlipWeeks)>61,"▶ clipped","") | BU68: Slide 3 build item 2 bar x=5.52 w=2.33: 'Build and harden AKS platform | AKS cluster operational processes | node pools | RBAC | Entra ID integration | backup strategy'. Offset (5.52-4.55)=0.97 in = ~2.25 wk after phase start -> starts week 8; width 2.33 = ~5.4 wk -> weeks 8-12. Cost line P2-L2 (1 FTE ASSUMPTION). Sequencing: foundations (P2-L1) before AKS.
A69: G-P2-L2-s1 | B69: • Provision AKS cluster and node pools into the foundations networking | C69: SEGRO | D69: DERIVED | G69: 8 | H69: 1 | I69: =MEDIAN($I$68,$J$68,$I$68+ROUND((G69-$G$68)/$H$68*($J$68-$I$68+1),0)) -> 8 | J69: =MEDIAN(I69,$J$68,$I$68+ROUND((G69+H69-$G$68)/$H$68*($J$68-$I$68+1),0)-1) -> 8 | K69: =IF(AND(K$4>=$I69,K$4<=$J69),1,"") | L69: =IF(AND(L$4>=$I69,L$4<=$J69),1,"") | M69: =IF(AND(M$4>=$I69,M$4<=$J69),1,"") | N69: =IF(AND(N$4>=$I69,N$4<=$J69),1,"") | O69: =IF(AND(O$4>=$I69,O$4<=$J69),1,"") | P69: =IF(AND(P$4>=$I69,P$4<=$J69),1,"") | Q69: =IF(AND(Q$4>=$I69,Q$4<=$J69),1,"") | R69: =IF(AND(R$4>=$I69,R$4<=$J69),1,"") -> 1 | ... BS69: =IF(AND(BS$4>=$I69,BS$4<=$J69),1,"") | BU69: P2-L2 desc sub-item 'node pools' (slide 3 item 2 'node pools'); slide 7 'Kubernetes Cluster Configuration Document | Define platform hosting setup'. Starts at the drawn item-2 bar start (x=5.52), once subscriptions/networking exist.
A70: G-P2-L2-s2 | B70: • RBAC and Entra ID integration onto the cluster | C70: SEGRO | D70: DERIVED | F70: G-P2-L2-s1 | G70: 9 | H70: 1 | I70: =MEDIAN($I$68,$J$68,$I$68+ROUND((G70-$G$68)/$H$68*($J$68-$I$68+1),0)) -> 9 | J70: =MEDIAN(I70,$J$68,$I$68+ROUND((G70+H70-$G$68)/$H$68*($J$68-$I$68+1),0)-1) -> 9 | K70: =IF(AND(K$4>=$I70,K$4<=$J70),1,"") | L70: =IF(AND(L$4>=$I70,L$4<=$J70),1,"") | M70: =IF(AND(M$4>=$I70,M$4<=$J70),1,"") | N70: =IF(AND(N$4>=$I70,N$4<=$J70),1,"") | O70: =IF(AND(O$4>=$I70,O$4<=$J70),1,"") | P70: =IF(AND(P$4>=$I70,P$4<=$J70),1,"") | Q70: =IF(AND(Q$4>=$I70,Q$4<=$J70),1,"") | R70: =IF(AND(R$4>=$I70,R$4<=$J70),1,"") | ... BS70: =IF(AND(BS$4>=$I70,BS$4<=$J70),1,"") | BU70: P2-L2 desc sub-items 'RBAC | Entra ID integration' (slide 3 item 2 same phrases); slide 7 'Identity & Authentication Configuration Document | Secures user & system access'. Identity wiring follows cluster existence.
A71: G-P2-L2-s3 | B71: • Harden cluster and stand up AKS cluster operational processes | C71: SEGRO | D71: DERIVED | F71: G-P2-L2-s2 | G71: 10 | H71: 2 | I71: =MEDIAN($I$68,$J$68,$I$68+ROUND((G71-$G$68)/$H$68*($J$68-$I$68+1),0)) -> 10 | J71: =MEDIAN(I71,$J$68,$I$68+ROUND((G71+H71-$G$68)/$H$68*($J$68-$I$68+1),0)-1) -> 11 | K71: =IF(AND(K$4>=$I71,K$4<=$J71),1,"") | L71: =IF(AND(L$4>=$I71,L$4<=$J71),1,"") | M71: =IF(AND(M$4>=$I71,M$4<=$J71),1,"") | N71: =IF(AND(N$4>=$I71,N$4<=$J71),1,"") | O71: =IF(AND(O$4>=$I71,O$4<=$J71),1,"") | P71: =IF(AND(P$4>=$I71,P$4<=$J71),1,"") | Q71: =IF(AND(Q$4>=$I71,Q$4<=$J71),1,"") | R71: =IF(AND(R$4>=$I71,R$4<=$J71),1,"") | ... BS71: =IF(AND(BS$4>=$I71,BS$4<=$J71),1,"") | BU71: P2-L2 desc sub-item 'AKS cluster operational processes' + bar title 'Build and harden AKS platform' (slide 3 item 2); slide 6 build doc 'Operational Runbook'. Hardening/ops maturity is the bulk of the bar after provisioning.
A72: G-P2-L2-s4 | B72: • Implement and document cluster backup strategy | C72: SEGRO | D72: DERIVED | F72: G-P2-L2-s3 | G72: 12 | H72: 1 | I72: =MEDIAN($I$68,$J$68,$I$68+ROUND((G72-$G$68)/$H$68*($J$68-$I$68+1),0)) -> 12 | J72: =MEDIAN(I72,$J$68,$I$68+ROUND((G72+H72-$G$68)/$H$68*($J$68-$I$68+1),0)-1) -> 12 | K72: =IF(AND(K$4>=$I72,K$4<=$J72),1,"") | L72: =IF(AND(L$4>=$I72,L$4<=$J72),1,"") | M72: =IF(AND(M$4>=$I72,M$4<=$J72),1,"") | N72: =IF(AND(N$4>=$I72,N$4<=$J72),1,"") | O72: =IF(AND(O$4>=$I72,O$4<=$J72),1,"") | P72: =IF(AND(P$4>=$I72,P$4<=$J72),1,"") | Q72: =IF(AND(Q$4>=$I72,Q$4<=$J72),1,"") | R72: =IF(AND(R$4>=$I72,R$4<=$J72),1,"") | ... BS72: =IF(AND(BS$4>=$I72,BS$4<=$J72),1,"") | BU72: P2-L2 desc sub-item 'backup strategy' (slide 3 item 2 'backup strategy'); slide 6 build doc 'Backup & Disaster Recovery Design'. Closes the drawn item-2 bar (~week 12).
A74: G-P2-L3 | B74: Shared platform services [P2-L3] | C74: SEGRO | D74: POAP-DRAWN | F74: G-P2-L2 | G74: 10 | H74: 6 | I74: =MIN(61,IF(G74<=29,ROUND((G74-1)*(29+SlipWeeks)/29,0)+1,G74+SlipWeeks)) -> 10 | J74: =MIN(61,IF(G74+H74-1<=29,MAX(ROUND((G74+H74-1)*(29+SlipWeeks)/29,0),I74),G74+H74-1+SlipWeeks)) -> 15 | K74: =IF(AND(K$4>=$I74,K$4<=$J74),1,"") | L74: =IF(AND(L$4>=$I74,L$4<=$J74),1,"") | M74: =IF(AND(M$4>=$I74,M$4<=$J74),1,"") | N74: =IF(AND(N$4>=$I74,N$4<=$J74),1,"") | O74: =IF(AND(O$4>=$I74,O$4<=$J74),1,"") | P74: =IF(AND(P$4>=$I74,P$4<=$J74),1,"") | Q74: =IF(AND(Q$4>=$I74,Q$4<=$J74),1,"") | R74: =IF(AND(R$4>=$I74,R$4<=$J74),1,"") | ... BS74: =IF(AND(BS$4>=$I74,BS$4<=$J74),1,"") | BT74: =IF(IF(G74+H74-1<=29,MAX(ROUND((G74+H74-1)*(29+SlipWeeks)/29,0),$I74),G74+H74-1+SlipWeeks)>61,"▶ clipped","") | BU74: Slide 3 build item 3 bar x=6.48 w=2.39: 'Deploy shared platform services | PostgreSQL | SQL Server | MongoDB/Cosmos | Kafka | Redis | monitoring stack | ingress controllers and cert management'. Offset (6.48-4.55)=1.93 in = ~4.5 wk -> starts week 10; width 2.39 = ~5.5 wk -> weeks 10-15 (clipped at phase end). Cost line P2-L3 (1.5 FTE ASSUMPTION, 8 named services). Sequencing: AKS (P2-L2) before shared services.
A75: G-P2-L3-s1 | B75: • Deploy database services - PostgreSQL, SQL Server, MongoDB/Cosmos | C75: SEGRO | D75: DERIVED | G75: 10 | H75: 2 | I75: =MEDIAN($I$74,$J$74,$I$74+ROUND((G75-$G$74)/$H$74*($J$74-$I$74+1),0)) -> 10 | J75: =MEDIAN(I75,$J$74,$I$74+ROUND((G75+H75-$G$74)/$H$74*($J$74-$I$74+1),0)-1) -> 11 | K75: =IF(AND(K$4>=$I75,K$4<=$J75),1,"") | L75: =IF(AND(L$4>=$I75,L$4<=$J75),1,"") | M75: =IF(AND(M$4>=$I75,M$4<=$J75),1,"") | N75: =IF(AND(N$4>=$I75,N$4<=$J75),1,"") | O75: =IF(AND(O$4>=$I75,O$4<=$J75),1,"") | P75: =IF(AND(P$4>=$I75,P$4<=$J75),1,"") | Q75: =IF(AND(Q$4>=$I75,Q$4<=$J75),1,"") | R75: =IF(AND(R$4>=$I75,R$4<=$J75),1,"") | ... BS75: =IF(AND(BS$4>=$I75,BS$4<=$J75),1,"") | BU75: P2-L3 desc sub-items 'PostgreSQL | SQL Server | MongoDB/Cosmos' (slide 3 item 3 same phrases). Data stores first - downstream services and the HCL install both consume them.
A76: G-P2-L3-s2 | B76: • Deploy messaging and cache - Kafka, Redis | C76: SEGRO | D76: DERIVED | F76: G-P2-L3-s1 | G76: 12 | H76: 1 | I76: =MEDIAN($I$74,$J$74,$I$74+ROUND((G76-$G$74)/$H$74*($J$74-$I$74+1),0)) -> 12 | J76: =MEDIAN(I76,$J$74,$I$74+ROUND((G76+H76-$G$74)/$H$74*($J$74-$I$74+1),0)-1) -> 12 | K76: =IF(AND(K$4>=$I76,K$4<=$J76),1,"") | L76: =IF(AND(L$4>=$I76,L$4<=$J76),1,"") | M76: =IF(AND(M$4>=$I76,M$4<=$J76),1,"") | N76: =IF(AND(N$4>=$I76,N$4<=$J76),1,"") | O76: =IF(AND(O$4>=$I76,O$4<=$J76),1,"") | P76: =IF(AND(P$4>=$I76,P$4<=$J76),1,"") | Q76: =IF(AND(Q$4>=$I76,Q$4<=$J76),1,"") | R76: =IF(AND(R$4>=$I76,R$4<=$J76),1,"") | ... BS76: =IF(AND(BS$4>=$I76,BS$4<=$J76),1,"") | BU76: P2-L3 desc sub-items 'Kafka | Redis' (slide 3 item 3 same phrases). Note P2-L17 basis: HCL's own matrix marks Event Hubs = N for UnO/CDP/Unica+ - the Kafka endpoint may be forced self-hosted on the cluster.
A77: G-P2-L3-s3 | B77: • Ingress controllers and certificate management | C77: SEGRO | D77: DERIVED | F77: G-P2-L3-s2 | G77: 13 | H77: 1 | I77: =MEDIAN($I$74,$J$74,$I$74+ROUND((G77-$G$74)/$H$74*($J$74-$I$74+1),0)) -> 13 | J77: =MEDIAN(I77,$J$74,$I$74+ROUND((G77+H77-$G$74)/$H$74*($J$74-$I$74+1),0)-1) -> 13 | K77: =IF(AND(K$4>=$I77,K$4<=$J77),1,"") | L77: =IF(AND(L$4>=$I77,L$4<=$J77),1,"") | M77: =IF(AND(M$4>=$I77,M$4<=$J77),1,"") | N77: =IF(AND(N$4>=$I77,N$4<=$J77),1,"") | O77: =IF(AND(O$4>=$I77,O$4<=$J77),1,"") | P77: =IF(AND(P$4>=$I77,P$4<=$J77),1,"") | Q77: =IF(AND(Q$4>=$I77,Q$4<=$J77),1,"") | R77: =IF(AND(R$4>=$I77,R$4<=$J77),1,"") | ... BS77: =IF(AND(BS$4>=$I77,BS$4<=$J77),1,"") | BU77: P2-L3 desc sub-item 'ingress controllers and cert management' (slide 3 item 3 same phrase); slide 6 build doc 'Secrets & certificate register'.
A78: G-P2-L3-s4 | B78: • Deploy monitoring stack across the shared services | C78: SEGRO | D78: DERIVED | F78: G-P2-L3-s3 | G78: 14 | H78: 1 | I78: =MEDIAN($I$74,$J$74,$I$74+ROUND((G78-$G$74)/$H$74*($J$74-$I$74+1),0)) -> 14 | J78: =MEDIAN(I78,$J$74,$I$74+ROUND((G78+H78-$G$74)/$H$74*($J$74-$I$74+1),0)-1) -> 14 | K78: =IF(AND(K$4>=$I78,K$4<=$J78),1,"") | L78: =IF(AND(L$4>=$I78,L$4<=$J78),1,"") | M78: =IF(AND(M$4>=$I78,M$4<=$J78),1,"") | N78: =IF(AND(N$4>=$I78,N$4<=$J78),1,"") | O78: =IF(AND(O$4>=$I78,O$4<=$J78),1,"") | P78: =IF(AND(P$4>=$I78,P$4<=$J78),1,"") | Q78: =IF(AND(Q$4>=$I78,Q$4<=$J78),1,"") | R78: =IF(AND(R$4>=$I78,R$4<=$J78),1,"") | ... BS78: =IF(AND(BS$4>=$I78,BS$4<=$J78),1,"") | BU78: P2-L3 desc sub-item 'monitoring stack' (slide 3 item 3 'monitoring stack'); slide 6 build doc 'Monitoring & Logging Design'. Late-bar position: monitoring wraps the services already deployed.
A79: G-P2-L3-s5 | B79: • Service integration wiring and configuration documentation | C79: SEGRO | D79: DERIVED | F79: G-P2-L3-s4 | G79: 15 | H79: 1 | I79: =MEDIAN($I$74,$J$74,$I$74+ROUND((G79-$G$74)/$H$74*($J$74-$I$74+1),0)) -> 15 | J79: =MEDIAN(I79,$J$74,$I$74+ROUND((G79+H79-$G$74)/$H$74*($J$74-$I$74+1),0)-1) -> 15 | K79: =IF(AND(K$4>=$I79,K$4<=$J79),1,"") | L79: =IF(AND(L$4>=$I79,L$4<=$J79),1,"") | M79: =IF(AND(M$4>=$I79,M$4<=$J79),1,"") | N79: =IF(AND(N$4>=$I79,N$4<=$J79),1,"") | O79: =IF(AND(O$4>=$I79,O$4<=$J79),1,"") | P79: =IF(AND(P$4>=$I79,P$4<=$J79),1,"") | Q79: =IF(AND(Q$4>=$I79,Q$4<=$J79),1,"") | R79: =IF(AND(R$4>=$I79,R$4<=$J79),1,"") | ... BS79: =IF(AND(BS$4>=$I79,BS$4<=$J79),1,"") | BU79: Slide 6 build docs 'Integration specification' + 'Configuration document*'; slide 7 'Integration Configuration Document | Enables connectivity'. Closes the item-3 bar at phase end, ready for the HCL install (which follows sequentially, F2).
A81: G-P2-L4 | B81: Cyber security design [P2-L4] | C81: SEGRO | D81: POAP-DRAWN | E81: F17 | G81: 6 | H81: 10 | I81: =MIN(61,IF(G81<=29,ROUND((G81-1)*(29+SlipWeeks)/29,0)+1,G81+SlipWeeks)) -> 6 | J81: =MIN(61,IF(G81+H81-1<=29,MAX(ROUND((G81+H81-1)*(29+SlipWeeks)/29,0),I81),G81+H81-1+SlipWeeks)) -> 15 | K81: =IF(AND(K$4>=$I81,K$4<=$J81),1,"") | L81: =IF(AND(L$4>=$I81,L$4<=$J81),1,"") | M81: =IF(AND(M$4>=$I81,M$4<=$J81),1,"") | N81: =IF(AND(N$4>=$I81,N$4<=$J81),1,"") | O81: =IF(AND(O$4>=$I81,O$4<=$J81),1,"") | P81: =IF(AND(P$4>=$I81,P$4<=$J81),1,"") -> 1 | Q81: =IF(AND(Q$4>=$I81,Q$4<=$J81),1,"") -> 1 | R81: =IF(AND(R$4>=$I81,R$4<=$J81),1,"") -> 1 | ... BS81: =IF(AND(BS$4>=$I81,BS$4<=$J81),1,"") | BT81: =IF(IF(G81+H81-1<=29,MAX(ROUND((G81+H81-1)*(29+SlipWeeks)/29,0),$I81),G81+H81-1+SlipWeeks)>61,"▶ clipped","") | BU81: Slide 3 build item 4 bar x=4.55 w=4.32: 'Complete Cyber Security design | Managed identities | Key Vault integration | secrets management | network segmentation | WAF | API security | privileged access controls' - drawn across the FULL 10-week build (same extent as the 'SEGRO 10 weeks' bar w=4.31) -> weeks 6-15. F17: architect view is this design should substantially PRECEDE foundations/networking ('c4 needs doing before ... c1,2,3, to avoid rework on the network layout'); the drawn geometry does the opposite. Cost line P2-L4 (0.5 FTE ASSUMPTION).
A82: G-P2-L4-s1 | B82: • Network segmentation design | C82: SEGRO | D82: DERIVED | G82: 6 | H82: 2 | I82: =MEDIAN($I$81,$J$81,$I$81+ROUND((G82-$G$81)/$H$81*($J$81-$I$81+1),0)) -> 6 | J82: =MEDIAN(I82,$J$81,$I$81+ROUND((G82+H82-$G$81)/$H$81*($J$81-$I$81+1),0)-1) -> 7 | K82: =IF(AND(K$4>=$I82,K$4<=$J82),1,"") | L82: =IF(AND(L$4>=$I82,L$4<=$J82),1,"") | M82: =IF(AND(M$4>=$I82,M$4<=$J82),1,"") | N82: =IF(AND(N$4>=$I82,N$4<=$J82),1,"") | O82: =IF(AND(O$4>=$I82,O$4<=$J82),1,"") | P82: =IF(AND(P$4>=$I82,P$4<=$J82),1,"") -> 1 | Q82: =IF(AND(Q$4>=$I82,Q$4<=$J82),1,"") -> 1 | R82: =IF(AND(R$4>=$I82,R$4<=$J82),1,"") | ... BS82: =IF(AND(BS$4>=$I82,BS$4<=$J82),1,"") | BU82: P2-L4 desc sub-item 'network segmentation' (slide 3 item 4 'network segmentation'). Placed first within the drawn full-span bar because it feeds the foundations networking build (weeks 7-8) - the F17 rework risk is smallest if this lands earliest.
A83: G-P2-L4-s2 | B83: • Managed identities and privileged access controls design | C83: SEGRO | D83: DERIVED | F83: G-P2-L4-s1 | G83: 8 | H83: 2 | I83: =MEDIAN($I$81,$J$81,$I$81+ROUND((G83-$G$81)/$H$81*($J$81-$I$81+1),0)) -> 8 | J83: =MEDIAN(I83,$J$81,$I$81+ROUND((G83+H83-$G$81)/$H$81*($J$81-$I$81+1),0)-1) -> 9 | K83: =IF(AND(K$4>=$I83,K$4<=$J83),1,"") | L83: =IF(AND(L$4>=$I83,L$4<=$J83),1,"") | M83: =IF(AND(M$4>=$I83,M$4<=$J83),1,"") | N83: =IF(AND(N$4>=$I83,N$4<=$J83),1,"") | O83: =IF(AND(O$4>=$I83,O$4<=$J83),1,"") | P83: =IF(AND(P$4>=$I83,P$4<=$J83),1,"") | Q83: =IF(AND(Q$4>=$I83,Q$4<=$J83),1,"") | R83: =IF(AND(R$4>=$I83,R$4<=$J83),1,"") -> 1 | ... BS83: =IF(AND(BS$4>=$I83,BS$4<=$J83),1,"") | BU83: P2-L4 desc sub-items 'managed identities' + 'privileged access controls' (slide 3 item 4 'Managed identities ... privileged access controls'); slide 7 'Identity & Authentication Configuration Document | Secures user & system access'. Aligned with the AKS RBAC/Entra ID step (week 9).
A84: G-P2-L4-s3 | B84: • Key Vault integration and secrets management design | C84: SEGRO | D84: DERIVED | F84: G-P2-L4-s2 | G84: 10 | H84: 2 | I84: =MEDIAN($I$81,$J$81,$I$81+ROUND((G84-$G$81)/$H$81*($J$81-$I$81+1),0)) -> 10 | J84: =MEDIAN(I84,$J$81,$I$81+ROUND((G84+H84-$G$81)/$H$81*($J$81-$I$81+1),0)-1) -> 11 | K84: =IF(AND(K$4>=$I84,K$4<=$J84),1,"") | L84: =IF(AND(L$4>=$I84,L$4<=$J84),1,"") | M84: =IF(AND(M$4>=$I84,M$4<=$J84),1,"") | N84: =IF(AND(N$4>=$I84,N$4<=$J84),1,"") | O84: =IF(AND(O$4>=$I84,O$4<=$J84),1,"") | P84: =IF(AND(P$4>=$I84,P$4<=$J84),1,"") | Q84: =IF(AND(Q$4>=$I84,Q$4<=$J84),1,"") | R84: =IF(AND(R$4>=$I84,R$4<=$J84),1,"") | ... BS84: =IF(AND(BS$4>=$I84,BS$4<=$J84),1,"") | BU84: P2-L4 desc sub-items 'Key Vault integration' + 'secrets management' (slide 3 item 4 same phrases); slide 7 'Secrets Management Configuration Document | Enables connectivity to systems' and 'Operational Support Configuration Document | Protects credentials & certificates'; slide 6 'Secrets & certificate register'.
A85: G-P2-L4-s4 | B85: • WAF and API security design | C85: SEGRO | D85: DERIVED | F85: G-P2-L4-s3 | G85: 12 | H85: 2 | I85: =MEDIAN($I$81,$J$81,$I$81+ROUND((G85-$G$81)/$H$81*($J$81-$I$81+1),0)) -> 12 | J85: =MEDIAN(I85,$J$81,$I$81+ROUND((G85+H85-$G$81)/$H$81*($J$81-$I$81+1),0)-1) -> 13 | K85: =IF(AND(K$4>=$I85,K$4<=$J85),1,"") | L85: =IF(AND(L$4>=$I85,L$4<=$J85),1,"") | M85: =IF(AND(M$4>=$I85,M$4<=$J85),1,"") | N85: =IF(AND(N$4>=$I85,N$4<=$J85),1,"") | O85: =IF(AND(O$4>=$I85,O$4<=$J85),1,"") | P85: =IF(AND(P$4>=$I85,P$4<=$J85),1,"") | Q85: =IF(AND(Q$4>=$I85,Q$4<=$J85),1,"") | R85: =IF(AND(R$4>=$I85,R$4<=$J85),1,"") | ... BS85: =IF(AND(BS$4>=$I85,BS$4<=$J85),1,"") | BU85: P2-L4 desc sub-items 'WAF' + 'API security' (slide 3 item 4 'WAF | API security'). Aligned with gateway commissioning; SEGRO principle - all integration via APIM with OAuth (P2-L21 basis).
A86: G-P2-L4-s5 | B86: • Consolidate and sign off the Security & access design document | C86: SEGRO | D86: DERIVED | F86: G-P2-L4-s4 | G86: 14 | H86: 2 | I86: =MEDIAN($I$81,$J$81,$I$81+ROUND((G86-$G$81)/$H$81*($J$81-$I$81+1),0)) -> 14 | J86: =MEDIAN(I86,$J$81,$I$81+ROUND((G86+H86-$G$81)/$H$81*($J$81-$I$81+1),0)-1) -> 15 | K86: =IF(AND(K$4>=$I86,K$4<=$J86),1,"") | L86: =IF(AND(L$4>=$I86,L$4<=$J86),1,"") | M86: =IF(AND(M$4>=$I86,M$4<=$J86),1,"") | N86: =IF(AND(N$4>=$I86,N$4<=$J86),1,"") | O86: =IF(AND(O$4>=$I86,O$4<=$J86),1,"") | P86: =IF(AND(P$4>=$I86,P$4<=$J86),1,"") | Q86: =IF(AND(Q$4>=$I86,Q$4<=$J86),1,"") | R86: =IF(AND(R$4>=$I86,R$4<=$J86),1,"") | ... BS86: =IF(AND(BS$4>=$I86,BS$4<=$J86),1,"") | BU86: Slide 6 build doc 'Security & access design'; bar title 'Complete Cyber Security design' (slide 3 item 4) - completion lands at the drawn bar end (week 15).
A88: G-P2-L5 | B88: Data mgmt & governance principles [P2-L5] | C88: SEGRO | D88: POAP-DRAWN | G88: 6 | H88: 10 | I88: =MIN(61,IF(G88<=29,ROUND((G88-1)*(29+SlipWeeks)/29,0)+1,G88+SlipWeeks)) -> 6 | J88: =MIN(61,IF(G88+H88-1<=29,MAX(ROUND((G88+H88-1)*(29+SlipWeeks)/29,0),I88),G88+H88-1+SlipWeeks)) -> 15 | K88: =IF(AND(K$4>=$I88,K$4<=$J88),1,"") | L88: =IF(AND(L$4>=$I88,L$4<=$J88),1,"") | M88: =IF(AND(M$4>=$I88,M$4<=$J88),1,"") | N88: =IF(AND(N$4>=$I88,N$4<=$J88),1,"") | O88: =IF(AND(O$4>=$I88,O$4<=$J88),1,"") | P88: =IF(AND(P$4>=$I88,P$4<=$J88),1,"") -> 1 | Q88: =IF(AND(Q$4>=$I88,Q$4<=$J88),1,"") -> 1 | R88: =IF(AND(R$4>=$I88,R$4<=$J88),1,"") -> 1 | ... BS88: =IF(AND(BS$4>=$I88,BS$4<=$J88),1,"") | BT88: =IF(IF(G88+H88-1<=29,MAX(ROUND((G88+H88-1)*(29+SlipWeeks)/29,0),$I88),G88+H88-1+SlipWeeks)>61,"▶ clipped","") | BU88: Slide 3 build item 6 bar x=4.55 w=6.23: 'Data Mgmt and Governance Principles: Data classification | Data ownership | Data retention policies | Data lineage | Master data requirements | Information architecture'. Drawn from phase start and OVERHANGING the SEGRO 10-wk bar (w=6.23 vs 4.31 - it extends ~4.5 wk into the HCL build window); clipped here to the P2 window weeks 6-15 owned by cost line P2-L5 (0.5 FTE ASSUMPTION). The overhang belongs to the P3 fragment if carried.
A89: G-P2-L5-s1 | B89: • Data classification scheme | C89: SEGRO | D89: DERIVED | G89: 6 | H89: 2 | I89: =MEDIAN($I$88,$J$88,$I$88+ROUND((G89-$G$88)/$H$88*($J$88-$I$88+1),0)) -> 6 | J89: =MEDIAN(I89,$J$88,$I$88+ROUND((G89+H89-$G$88)/$H$88*($J$88-$I$88+1),0)-1) -> 7 | K89: =IF(AND(K$4>=$I89,K$4<=$J89),1,"") | L89: =IF(AND(L$4>=$I89,L$4<=$J89),1,"") | M89: =IF(AND(M$4>=$I89,M$4<=$J89),1,"") | N89: =IF(AND(N$4>=$I89,N$4<=$J89),1,"") | O89: =IF(AND(O$4>=$I89,O$4<=$J89),1,"") | P89: =IF(AND(P$4>=$I89,P$4<=$J89),1,"") -> 1 | Q89: =IF(AND(Q$4>=$I89,Q$4<=$J89),1,"") -> 1 | R89: =IF(AND(R$4>=$I89,R$4<=$J89),1,"") | ... BS89: =IF(AND(BS$4>=$I89,BS$4<=$J89),1,"") | BU89: P2-L5 desc sub-item 'classification' (slide 3 item 6 'Data classification'). First in the governance chain - classification drives retention and ownership decisions.
A90: G-P2-L5-s2 | B90: • Data ownership model | C90: SEGRO | D90: DERIVED | F90: G-P2-L5-s1 | G90: 8 | H90: 2 | I90: =MEDIAN($I$88,$J$88,$I$88+ROUND((G90-$G$88)/$H$88*($J$88-$I$88+1),0)) -> 8 | J90: =MEDIAN(I90,$J$88,$I$88+ROUND((G90+H90-$G$88)/$H$88*($J$88-$I$88+1),0)-1) -> 9 | K90: =IF(AND(K$4>=$I90,K$4<=$J90),1,"") | L90: =IF(AND(L$4>=$I90,L$4<=$J90),1,"") | M90: =IF(AND(M$4>=$I90,M$4<=$J90),1,"") | N90: =IF(AND(N$4>=$I90,N$4<=$J90),1,"") | O90: =IF(AND(O$4>=$I90,O$4<=$J90),1,"") | P90: =IF(AND(P$4>=$I90,P$4<=$J90),1,"") | Q90: =IF(AND(Q$4>=$I90,Q$4<=$J90),1,"") | R90: =IF(AND(R$4>=$I90,R$4<=$J90),1,"") -> 1 | ... BS90: =IF(AND(BS$4>=$I90,BS$4<=$J90),1,"") | BU90: P2-L5 desc sub-item 'ownership' (slide 3 item 6 'Data ownership').
A91: G-P2-L5-s3 | B91: • Data retention policies | C91: SEGRO | D91: DERIVED | F91: G-P2-L5-s2 | G91: 10 | H91: 2 | I91: =MEDIAN($I$88,$J$88,$I$88+ROUND((G91-$G$88)/$H$88*($J$88-$I$88+1),0)) -> 10 | J91: =MEDIAN(I91,$J$88,$I$88+ROUND((G91+H91-$G$88)/$H$88*($J$88-$I$88+1),0)-1) -> 11 | K91: =IF(AND(K$4>=$I91,K$4<=$J91),1,"") | L91: =IF(AND(L$4>=$I91,L$4<=$J91),1,"") | M91: =IF(AND(M$4>=$I91,M$4<=$J91),1,"") | N91: =IF(AND(N$4>=$I91,N$4<=$J91),1,"") | O91: =IF(AND(O$4>=$I91,O$4<=$J91),1,"") | P91: =IF(AND(P$4>=$I91,P$4<=$J91),1,"") | Q91: =IF(AND(Q$4>=$I91,Q$4<=$J91),1,"") | R91: =IF(AND(R$4>=$I91,R$4<=$J91),1,"") | ... BS91: =IF(AND(BS$4>=$I91,BS$4<=$J91),1,"") | BU91: P2-L5 desc sub-item 'retention' (slide 3 item 6 'Data retention policies'). Follows classification/ownership; informs the database services being deployed weeks 10-11 (G-P2-L3-s1).
A92: G-P2-L5-s4 | B92: • Data lineage and master data requirements | C92: SEGRO | D92: DERIVED | F92: G-P2-L5-s3 | G92: 12 | H92: 2 | I92: =MEDIAN($I$88,$J$88,$I$88+ROUND((G92-$G$88)/$H$88*($J$88-$I$88+1),0)) -> 12 | J92: =MEDIAN(I92,$J$88,$I$88+ROUND((G92+H92-$G$88)/$H$88*($J$88-$I$88+1),0)-1) -> 13 | K92: =IF(AND(K$4>=$I92,K$4<=$J92),1,"") | L92: =IF(AND(L$4>=$I92,L$4<=$J92),1,"") | M92: =IF(AND(M$4>=$I92,M$4<=$J92),1,"") | N92: =IF(AND(N$4>=$I92,N$4<=$J92),1,"") | O92: =IF(AND(O$4>=$I92,O$4<=$J92),1,"") | P92: =IF(AND(P$4>=$I92,P$4<=$J92),1,"") | Q92: =IF(AND(Q$4>=$I92,Q$4<=$J92),1,"") | R92: =IF(AND(R$4>=$I92,R$4<=$J92),1,"") | ... BS92: =IF(AND(BS$4>=$I92,BS$4<=$J92),1,"") | BU92: P2-L5 desc sub-items 'lineage' + 'master data' (slide 3 item 6 'Data lineage | Master data requirements').
A93: G-P2-L5-s5 | B93: • Information architecture consolidation; feed the Updated Systems matrix | C93: SEGRO | D93: DERIVED | F93: G-P2-L5-s4 | G93: 14 | H93: 2 | I93: =MEDIAN($I$88,$J$88,$I$88+ROUND((G93-$G$88)/$H$88*($J$88-$I$88+1),0)) -> 14 | J93: =MEDIAN(I93,$J$88,$I$88+ROUND((G93+H93-$G$88)/$H$88*($J$88-$I$88+1),0)-1) -> 15 | K93: =IF(AND(K$4>=$I93,K$4<=$J93),1,"") | L93: =IF(AND(L$4>=$I93,L$4<=$J93),1,"") | M93: =IF(AND(M$4>=$I93,M$4<=$J93),1,"") | N93: =IF(AND(N$4>=$I93,N$4<=$J93),1,"") | O93: =IF(AND(O$4>=$I93,O$4<=$J93),1,"") | P93: =IF(AND(P$4>=$I93,P$4<=$J93),1,"") | Q93: =IF(AND(Q$4>=$I93,Q$4<=$J93),1,"") | R93: =IF(AND(R$4>=$I93,R$4<=$J93),1,"") | ... BS93: =IF(AND(BS$4>=$I93,BS$4<=$J93),1,"") | BU93: P2-L5 desc sub-item 'information architecture' (slide 3 item 6 'Information architecture'); slide 6 build docs 'Updated Systems matrix' + 'Updated app landscape' are the natural landing artifacts. Closes the P2-owned portion of the drawn bar.
A95: G-P2-L6 | B95: Agent eval harness & observability (FND-4) [P2-L6] | C95: SEGRO | D95: ASSUMPTION | E95: F13 | G95: 7 | H95: 9 | I95: =MIN(61,IF(G95<=29,ROUND((G95-1)*(29+SlipWeeks)/29,0)+1,G95+SlipWeeks)) -> 7 | J95: =MIN(61,IF(G95+H95-1<=29,MAX(ROUND((G95+H95-1)*(29+SlipWeeks)/29,0),I95),G95+H95-1+SlipWeeks)) -> 15 | K95: =IF(AND(K$4>=$I95,K$4<=$J95),1,"") | L95: =IF(AND(L$4>=$I95,L$4<=$J95),1,"") | M95: =IF(AND(M$4>=$I95,M$4<=$J95),1,"") | N95: =IF(AND(N$4>=$I95,N$4<=$J95),1,"") | O95: =IF(AND(O$4>=$I95,O$4<=$J95),1,"") | P95: =IF(AND(P$4>=$I95,P$4<=$J95),1,"") | Q95: =IF(AND(Q$4>=$I95,Q$4<=$J95),1,"") -> 1 | R95: =IF(AND(R$4>=$I95,R$4<=$J95),1,"") -> 1 | ... BS95: =IF(AND(BS$4>=$I95,BS$4<=$J95),1,"") | BT95: =IF(IF(G95+H95-1<=29,MAX(ROUND((G95+H95-1)*(29+SlipWeeks)/29,0),$I95),G95+H95-1+SlipWeeks)>61,"▶ clipped","") | BU95: NOT drawn anywhere on the POAP - F13: 'No agent evaluation harness / AI observability workstream anywhere in the POAP' (the HCL bar's generic 'observability integration' is the only adjacent text). Window is the cost model's implied shape: platform.json FND-4 = 20 pd over 9 wk (0.44 FTE), placed weeks 7-15 so the harness completes with the build and gates the first pilots. Quantity source itself labels the task ASSUMPTION.
A96: G-P2-L6-s1 | B96: • Define golden sets for agent output evaluation | C96: SEGRO | D96: ASSUMPTION | G96: 7 | H96: 2 | I96: =MEDIAN($I$95,$J$95,$I$95+ROUND((G96-$G$95)/$H$95*($J$95-$I$95+1),0)) -> 7 | J96: =MEDIAN(I96,$J$95,$I$95+ROUND((G96+H96-$G$95)/$H$95*($J$95-$I$95+1),0)-1) -> 8 | K96: =IF(AND(K$4>=$I96,K$4<=$J96),1,"") | L96: =IF(AND(L$4>=$I96,L$4<=$J96),1,"") | M96: =IF(AND(M$4>=$I96,M$4<=$J96),1,"") | N96: =IF(AND(N$4>=$I96,N$4<=$J96),1,"") | O96: =IF(AND(O$4>=$I96,O$4<=$J96),1,"") | P96: =IF(AND(P$4>=$I96,P$4<=$J96),1,"") | Q96: =IF(AND(Q$4>=$I96,Q$4<=$J96),1,"") -> 1 | R96: =IF(AND(R$4>=$I96,R$4<=$J96),1,"") -> 1 | ... BS96: =IF(AND(BS$4>=$I96,BS$4<=$J96),1,"") | BU96: P2-L6 desc sub-item 'golden sets' (spec_cost_model: 'golden sets, scored promotion gates, run-trace logging, eval dashboard (absent from POAP, F13)'). Design-first step, no infra dependency.
A97: G-P2-L6-s2 | B97: • Build scored promotion gates | C97: SEGRO | D97: ASSUMPTION | F97: G-P2-L6-s1 | G97: 9 | H97: 2 | I97: =MEDIAN($I$95,$J$95,$I$95+ROUND((G97-$G$95)/$H$95*($J$95-$I$95+1),0)) -> 9 | J97: =MEDIAN(I97,$J$95,$I$95+ROUND((G97+H97-$G$95)/$H$95*($J$95-$I$95+1),0)-1) -> 10 | K97: =IF(AND(K$4>=$I97,K$4<=$J97),1,"") | L97: =IF(AND(L$4>=$I97,L$4<=$J97),1,"") | M97: =IF(AND(M$4>=$I97,M$4<=$J97),1,"") | N97: =IF(AND(N$4>=$I97,N$4<=$J97),1,"") | O97: =IF(AND(O$4>=$I97,O$4<=$J97),1,"") | P97: =IF(AND(P$4>=$I97,P$4<=$J97),1,"") | Q97: =IF(AND(Q$4>=$I97,Q$4<=$J97),1,"") | R97: =IF(AND(R$4>=$I97,R$4<=$J97),1,"") | ... BS97: =IF(AND(BS$4>=$I97,BS$4<=$J97),1,"") | BU97: P2-L6 desc sub-item 'scored promotion gates' (spec_cost_model P2-L6). F13: SEGRO's counter-proposal makes the eval-harness baseline 'a promotion gate for the first pilot'.
A98: G-P2-L6-s3 | B98: • Integrate run-trace logging into the platform observability stack | C98: SEGRO | D98: ASSUMPTION | F98: G-P2-L6-s2 | G98: 11 | H98: 2 | I98: =MEDIAN($I$95,$J$95,$I$95+ROUND((G98-$G$95)/$H$95*($J$95-$I$95+1),0)) -> 11 | J98: =MEDIAN(I98,$J$95,$I$95+ROUND((G98+H98-$G$95)/$H$95*($J$95-$I$95+1),0)-1) -> 12 | K98: =IF(AND(K$4>=$I98,K$4<=$J98),1,"") | L98: =IF(AND(L$4>=$I98,L$4<=$J98),1,"") | M98: =IF(AND(M$4>=$I98,M$4<=$J98),1,"") | N98: =IF(AND(N$4>=$I98,N$4<=$J98),1,"") | O98: =IF(AND(O$4>=$I98,O$4<=$J98),1,"") | P98: =IF(AND(P$4>=$I98,P$4<=$J98),1,"") | Q98: =IF(AND(Q$4>=$I98,Q$4<=$J98),1,"") | R98: =IF(AND(R$4>=$I98,R$4<=$J98),1,"") | ... BS98: =IF(AND(BS$4>=$I98,BS$4<=$J98),1,"") | BU98: P2-L6 desc sub-item 'run-trace logging' (spec_cost_model P2-L6); positioned after the monitoring stack starts landing (G-P2-L3) - the only drawn adjacency is the HCL bar's 'observability integration' (F13 evidence).
A99: G-P2-L6-s4 | B99: • Stand up eval dashboard and run baseline evaluations | C99: SEGRO | D99: ASSUMPTION | F99: G-P2-L6-s3 | G99: 13 | H99: 3 | I99: =MEDIAN($I$95,$J$95,$I$95+ROUND((G99-$G$95)/$H$95*($J$95-$I$95+1),0)) -> 13 | J99: =MEDIAN(I99,$J$95,$I$95+ROUND((G99+H99-$G$95)/$H$95*($J$95-$I$95+1),0)-1) -> 15 | K99: =IF(AND(K$4>=$I99,K$4<=$J99),1,"") | L99: =IF(AND(L$4>=$I99,L$4<=$J99),1,"") | M99: =IF(AND(M$4>=$I99,M$4<=$J99),1,"") | N99: =IF(AND(N$4>=$I99,N$4<=$J99),1,"") | O99: =IF(AND(O$4>=$I99,O$4<=$J99),1,"") | P99: =IF(AND(P$4>=$I99,P$4<=$J99),1,"") | Q99: =IF(AND(Q$4>=$I99,Q$4<=$J99),1,"") | R99: =IF(AND(R$4>=$I99,R$4<=$J99),1,"") | ... BS99: =IF(AND(BS$4>=$I99,BS$4<=$J99),1,"") | BU99: P2-L6 desc sub-item 'eval dashboard' (spec_cost_model P2-L6). Completes at week 15 so the baseline exists before the HCL install/test phases consume it.
A101: G-P2-L7 | B101: Project/delivery management [P2-L7] | C101: SEGRO | D101: POAP-DRAWN | G101: 6 | H101: 10 | I101: =MIN(61,IF(G101<=29,ROUND((G101-1)*(29+SlipWeeks)/29,0)+1,G101+SlipWeeks)) -> 6 | J101: =MIN(61,IF(G101+H101-1<=29,MAX(ROUND((G101+H101-1)*(29+SlipWeeks)/29,0),I101),G101+H101-1+SlipWeeks)) -> 15 | K101: =IF(AND(K$4>=$I101,K$4<=$J101),1,"") | L101: =IF(AND(L$4>=$I101,L$4<=$J101),1,"") | M101: =IF(AND(M$4>=$I101,M$4<=$J101),1,"") | N101: =IF(AND(N$4>=$I101,N$4<=$J101),1,"") | O101: =IF(AND(O$4>=$I101,O$4<=$J101),1,"") | P101: =IF(AND(P$4>=$I101,P$4<=$J101),1,"") -> 1 | Q101: =IF(AND(Q$4>=$I101,Q$4<=$J101),1,"") -> 1 | R101: =IF(AND(R$4>=$I101,R$4<=$J101),1,"") -> 1 | ... BS101: =IF(AND(BS$4>=$I101,BS$4<=$J101),1,"") | BT101: =IF(IF(G101+H101-1<=29,MAX(ROUND((G101+H101-1)*(29+SlipWeeks)/29,0),$I101),G101+H101-1+SlipWeeks)>61,"▶ clipped","") | BU101: Spans the drawn 'SEGRO 10 weeks' bar (slide 3, x=4.55 w=4.31) end-to-end - the PM allocation itself is the cost model's ASSUMPTION ('1 PM on a 6-workstream build phase', P2-L7); the window is the drawn phase bar. The bar carries the annotation 'To be validated based on Arch workshop' (F14 context).
A102: G-P2-L7-s1 | B102: • Mobilise the build squad and baseline the 10-week plan | C102: SEGRO | D102: DERIVED | G102: 6 | H102: 1 | I102: =MEDIAN($I$101,$J$101,$I$101+ROUND((G102-$G$101)/$H$101*($J$101-$I$101+1),0)) -> 6 | J102: =MEDIAN(I102,$J$101,$I$101+ROUND((G102+H102-$G$101)/$H$101*($J$101-$I$101+1),0)-1) -> 6 | K102: =IF(AND(K$4>=$I102,K$4<=$J102),1,"") | L102: =IF(AND(L$4>=$I102,L$4<=$J102),1,"") | M102: =IF(AND(M$4>=$I102,M$4<=$J102),1,"") | N102: =IF(AND(N$4>=$I102,N$4<=$J102),1,"") | O102: =IF(AND(O$4>=$I102,O$4<=$J102),1,"") | P102: =IF(AND(P$4>=$I102,P$4<=$J102),1,"") -> 1 | Q102: =IF(AND(Q$4>=$I102,Q$4<=$J102),1,"") | R102: =IF(AND(R$4>=$I102,R$4<=$J102),1,"") | ... BS102: =IF(AND(BS$4>=$I102,BS$4<=$J102),1,"") | BU102: Slide 3 'SEGRO 10 weeks' bar start + annotation 'To be validated based on Arch workshop' (x=6.85) - the plan enters the build unvalidated, so baselining is the first PM act.
A103: G-P2-L7-s2 | B103: • Coordinate build workstreams 1-6 and track build-document production | C103: SEGRO | D103: DERIVED | F103: G-P2-L7-s1 | G103: 7 | H103: 4 | I103: =MEDIAN($I$101,$J$101,$I$101+ROUND((G103-$G$101)/$H$101*($J$101-$I$101+1),0)) -> 7 | J103: =MEDIAN(I103,$J$101,$I$101+ROUND((G103+H103-$G$101)/$H$101*($J$101-$I$101+1),0)-1) -> 10 | K103: =IF(AND(K$4>=$I103,K$4<=$J103),1,"") | L103: =IF(AND(L$4>=$I103,L$4<=$J103),1,"") | M103: =IF(AND(M$4>=$I103,M$4<=$J103),1,"") | N103: =IF(AND(N$4>=$I103,N$4<=$J103),1,"") | O103: =IF(AND(O$4>=$I103,O$4<=$J103),1,"") | P103: =IF(AND(P$4>=$I103,P$4<=$J103),1,"") | Q103: =IF(AND(Q$4>=$I103,Q$4<=$J103),1,"") -> 1 | R103: =IF(AND(R$4>=$I103,R$4<=$J103),1,"") -> 1 | ... BS103: =IF(AND(BS$4>=$I103,BS$4<=$J103),1,"") | BU103: Slide 3 numbered build items 1-6 within lane C; slide 6 build docs list ('Environment build specification ... Operational Runbook') is the deliverable register the PM tracks.
A104: G-P2-L7-s3 | B104: • Progress/RAID management through the back half of the build; prepare HCL install handover | C104: SEGRO | D104: DERIVED | F104: G-P2-L7-s2 | G104: 11 | H104: 4 | I104: =MEDIAN($I$101,$J$101,$I$101+ROUND((G104-$G$101)/$H$101*($J$101-$I$101+1),0)) -> 11 | J104: =MEDIAN(I104,$J$101,$I$101+ROUND((G104+H104-$G$101)/$H$101*($J$101-$I$101+1),0)-1) -> 14 | K104: =IF(AND(K$4>=$I104,K$4<=$J104),1,"") | L104: =IF(AND(L$4>=$I104,L$4<=$J104),1,"") | M104: =IF(AND(M$4>=$I104,M$4<=$J104),1,"") | N104: =IF(AND(N$4>=$I104,N$4<=$J104),1,"") | O104: =IF(AND(O$4>=$I104,O$4<=$J104),1,"") | P104: =IF(AND(P$4>=$I104,P$4<=$J104),1,"") | Q104: =IF(AND(Q$4>=$I104,Q$4<=$J104),1,"") | R104: =IF(AND(R$4>=$I104,R$4<=$J104),1,"") | ... BS104: =IF(AND(BS$4>=$I104,BS$4<=$J104),1,"") | BU104: Slide 3: 'HCL 6 weeks' bar (x=8.91) starts immediately after the SEGRO bar ends (x=8.86) - drawn strictly sequential (F2 evidence), so handover readiness is the PM focus in the closing weeks.
A105: G-P2-L7-s4 | B105: • Close the SEGRO build phase and hand over to the HCL install | C105: SEGRO | D105: DERIVED | F105: G-P2-L7-s3 | G105: 15 | H105: 1 | I105: =MEDIAN($I$101,$J$101,$I$101+ROUND((G105-$G$101)/$H$101*($J$101-$I$101+1),0)) -> 15 | J105: =MEDIAN(I105,$J$101,$I$101+ROUND((G105+H105-$G$101)/$H$101*($J$101-$I$101+1),0)-1) -> 15 | K105: =IF(AND(K$4>=$I105,K$4<=$J105),1,"") | L105: =IF(AND(L$4>=$I105,L$4<=$J105),1,"") | M105: =IF(AND(M$4>=$I105,M$4<=$J105),1,"") | N105: =IF(AND(N$4>=$I105,N$4<=$J105),1,"") | O105: =IF(AND(O$4>=$I105,O$4<=$J105),1,"") | P105: =IF(AND(P$4>=$I105,P$4<=$J105),1,"") | Q105: =IF(AND(Q$4>=$I105,Q$4<=$J105),1,"") | R105: =IF(AND(R$4>=$I105,R$4<=$J105),1,"") | ... BS105: =IF(AND(BS$4>=$I105,BS$4<=$J105),1,"") | BU105: End of the drawn 'SEGRO 10 weeks' bar; slide 6 build doc 'Service transition pack' (listed twice on slide 6) is the closing handover artifact.
A107: G-P2-L8 | B107: Pen-test booking & remediation window [P2-L8] | C107: SEGRO | D107: ASSUMPTION | E107: F7 | G107: 13 | H107: 3 | I107: =MIN(61,IF(G107<=29,ROUND((G107-1)*(29+SlipWeeks)/29,0)+1,G107+SlipWeeks)) -> 13 | J107: =MIN(61,IF(G107+H107-1<=29,MAX(ROUND((G107+H107-1)*(29+SlipWeeks)/29,0),I107),G107+H107-1+SlipWeeks)) -> 15 | K107: =IF(AND(K$4>=$I107,K$4<=$J107),1,"") | L107: =IF(AND(L$4>=$I107,L$4<=$J107),1,"") | M107: =IF(AND(M$4>=$I107,M$4<=$J107),1,"") | N107: =IF(AND(N$4>=$I107,N$4<=$J107),1,"") | O107: =IF(AND(O$4>=$I107,O$4<=$J107),1,"") | P107: =IF(AND(P$4>=$I107,P$4<=$J107),1,"") | Q107: =IF(AND(Q$4>=$I107,Q$4<=$J107),1,"") | R107: =IF(AND(R$4>=$I107,R$4<=$J107),1,"") | ... BS107: =IF(AND(BS$4>=$I107,BS$4<=$J107),1,"") | BT107: =IF(IF(G107+H107-1<=29,MAX(ROUND((G107+H107-1)*(29+SlipWeeks)/29,0),$I107),G107+H107-1+SlipWeeks)>61,"▶ clipped","") | BU107: NOT drawn on the POAP - F7: booking 'is not shown'; P2-L8 basis: "F7 recommendation: add a 'book pen test' task in October; POAP shows none". Window ASSUMPTION per F7 recommendation ('Add a book pen test task in October'): October 2026 = weeks 13-16 (gantt_timeline month_headers), placed weeks 13-15 inside P2. 2 days procurement admin (cost model); F7: CREST firms quote 4-8 wk booking lead times and the drawn 'Pen Testing' sits early Dec (x=11.30).
A108: G-P2-L8-s1 | B108: • Scope the CREST pen test (cloud platform scope) and issue RFQ | C108: SEGRO | D108: ASSUMPTION | G108: 13 | H108: 1 | I108: =MEDIAN($I$107,$J$107,$I$107+ROUND((G108-$G$107)/$H$107*($J$107-$I$107+1),0)) -> 13 | J108: =MEDIAN(I108,$J$107,$I$107+ROUND((G108+H108-$G$107)/$H$107*($J$107-$I$107+1),0)-1) -> 13 | K108: =IF(AND(K$4>=$I108,K$4<=$J108),1,"") | L108: =IF(AND(L$4>=$I108,L$4<=$J108),1,"") | M108: =IF(AND(M$4>=$I108,M$4<=$J108),1,"") | N108: =IF(AND(N$4>=$I108,N$4<=$J108),1,"") | O108: =IF(AND(O$4>=$I108,O$4<=$J108),1,"") | P108: =IF(AND(P$4>=$I108,P$4<=$J108),1,"") | Q108: =IF(AND(Q$4>=$I108,Q$4<=$J108),1,"") | R108: =IF(AND(R$4>=$I108,R$4<=$J108),1,"") | ... BS108: =IF(AND(BS$4>=$I108,BS$4<=$J108),1,"") | BU108: F7: 'Pen testing is inside the 4-week December window' and slide 9 requires a 'Penetration Test Report' - scope must be fixed before booking. Early-October start per F7 'bookable only if procurement of the pen test starts by ~October'.
A109: G-P2-L8-s2 | B109: • Confirm the booking for the December test window | C109: SEGRO | D109: ASSUMPTION | F109: G-P2-L8-s1 | G109: 14 | H109: 1 | I109: =MEDIAN($I$107,$J$107,$I$107+ROUND((G109-$G$107)/$H$107*($J$107-$I$107+1),0)) -> 14 | J109: =MEDIAN(I109,$J$107,$I$107+ROUND((G109+H109-$G$107)/$H$107*($J$107-$I$107+1),0)-1) -> 14 | K109: =IF(AND(K$4>=$I109,K$4<=$J109),1,"") | L109: =IF(AND(L$4>=$I109,L$4<=$J109),1,"") | M109: =IF(AND(M$4>=$I109,M$4<=$J109),1,"") | N109: =IF(AND(N$4>=$I109,N$4<=$J109),1,"") | O109: =IF(AND(O$4>=$I109,O$4<=$J109),1,"") | P109: =IF(AND(P$4>=$I109,P$4<=$J109),1,"") | Q109: =IF(AND(Q$4>=$I109,Q$4<=$J109),1,"") | R109: =IF(AND(R$4>=$I109,R$4<=$J109),1,"") | ... BS109: =IF(AND(BS$4>=$I109,BS$4<=$J109),1,"") | BU109: F7: 'CREST-accredited test firms commonly quote multi-week booking lead times (4-8 weeks as a planning assumption)' - booking mid-October + 4-8 wk lead lands the engagement in the drawn early-Dec 'Pen Testing' slot (x=11.30, P4 weeks 22-25).
A110: G-P2-L8-s3 | B110: • Reserve a named remediation + retest window in early January before go/no-go | C110: SEGRO | D110: ASSUMPTION | F110: G-P2-L8-s2 | G110: 15 | H110: 1 | I110: =MEDIAN($I$107,$J$107,$I$107+ROUND((G110-$G$107)/$H$107*($J$107-$I$107+1),0)) -> 15 | J110: =MEDIAN(I110,$J$107,$I$107+ROUND((G110+H110-$G$107)/$H$107*($J$107-$I$107+1),0)-1) -> 15 | K110: =IF(AND(K$4>=$I110,K$4<=$J110),1,"") | L110: =IF(AND(L$4>=$I110,L$4<=$J110),1,"") | M110: =IF(AND(M$4>=$I110,M$4<=$J110),1,"") | N110: =IF(AND(N$4>=$I110,N$4<=$J110),1,"") | O110: =IF(AND(O$4>=$I110,O$4<=$J110),1,"") | P110: =IF(AND(P$4>=$I110,P$4<=$J110),1,"") | Q110: =IF(AND(Q$4>=$I110,Q$4<=$J110),1,"") | R110: =IF(AND(R$4>=$I110,R$4<=$J110),1,"") | ... BS110: =IF(AND(BS$4>=$I110,BS$4<=$J110),1,"") | BU110: F7 recommendation: 'hold a named remediation window in early Jan before go/no-go' ('Go / No Go decision' drawn x=13.99, mid-Jan). Scheduling only - execution is P5-L4 in the deploy fragment.
A112: G-P2-L27 | B112: DevSecOps automation [P2-L27] | C112: SEGRO | D112: ASSUMPTION | E112: F19 | G112: 6 | H112: 10 | I112: =MIN(61,IF(G112<=29,ROUND((G112-1)*(29+SlipWeeks)/29,0)+1,G112+SlipWeeks)) -> 6 | J112: =MIN(61,IF(G112+H112-1<=29,MAX(ROUND((G112+H112-1)*(29+SlipWeeks)/29,0),I112),G112+H112-1+SlipWeeks)) -> 15 | K112: =IF(AND(K$4>=$I112,K$4<=$J112),1,"") | L112: =IF(AND(L$4>=$I112,L$4<=$J112),1,"") | M112: =IF(AND(M$4>=$I112,M$4<=$J112),1,"") | N112: =IF(AND(N$4>=$I112,N$4<=$J112),1,"") | O112: =IF(AND(O$4>=$I112,O$4<=$J112),1,"") | P112: =IF(AND(P$4>=$I112,P$4<=$J112),1,"") -> 1 | Q112: =IF(AND(Q$4>=$I112,Q$4<=$J112),1,"") -> 1 | R112: =IF(AND(R$4>=$I112,R$4<=$J112),1,"") -> 1 | ... BS112: =IF(AND(BS$4>=$I112,BS$4<=$J112),1,"") | BT112: =IF(IF(G112+H112-1<=29,MAX(ROUND((G112+H112-1)*(29+SlipWeeks)/29,0),$I112),G112+H112-1+SlipWeeks)>61,"▶ clipped","") | BU112: NO drawn bar - that absence IS F19: 'No DevSecOps automation workstream exists anywhere in the POAP'; slide 7 names a 'CI/CD Configuration Document | Automates build & deploy' but 'no build task produces the pipeline that document would describe'. Window is the cost model's implied shape (judgement): P2-L27 = 0.6 FTE x 10 wk = 30 pd across the full build -> weeks 6-15, starting with foundations so IaC codifies them from day one. Trigger: senior architect review 18 Jul 2026.
A113: G-P2-L27-s1 | B113: • IaC pipelines for the Azure foundations | C113: SEGRO | D113: ASSUMPTION | G113: 6 | H113: 2 | I113: =MEDIAN($I$112,$J$112,$I$112+ROUND((G113-$G$112)/$H$112*($J$112-$I$112+1),0)) -> 6 | J113: =MEDIAN(I113,$J$112,$I$112+ROUND((G113+H113-$G$112)/$H$112*($J$112-$I$112+1),0)-1) -> 7 | K113: =IF(AND(K$4>=$I113,K$4<=$J113),1,"") | L113: =IF(AND(L$4>=$I113,L$4<=$J113),1,"") | M113: =IF(AND(M$4>=$I113,M$4<=$J113),1,"") | N113: =IF(AND(N$4>=$I113,N$4<=$J113),1,"") | O113: =IF(AND(O$4>=$I113,O$4<=$J113),1,"") | P113: =IF(AND(P$4>=$I113,P$4<=$J113),1,"") -> 1 | Q113: =IF(AND(Q$4>=$I113,Q$4<=$J113),1,"") -> 1 | R113: =IF(AND(R$4>=$I113,R$4<=$J113),1,"") | ... BS113: =IF(AND(BS$4>=$I113,BS$4<=$J113),1,"") | BU113: P2-L27 desc sub-item 'IaC pipelines' (spec_cost_model: 'IaC pipelines, policy-as-code, image scanning, CI/CD for infra + agent deployment'). Placed alongside G-P2-L1 so foundations are provisioned as code rather than hand-built (F19: 'hand-built environments and manual deploys plausibly move cost, quality and go-live risk materially').
A114: G-P2-L27-s2 | B114: • Policy-as-code guardrails across subscriptions and the cluster | C114: SEGRO | D114: ASSUMPTION | F114: G-P2-L27-s1 | G114: 8 | H114: 2 | I114: =MEDIAN($I$112,$J$112,$I$112+ROUND((G114-$G$112)/$H$112*($J$112-$I$112+1),0)) -> 8 | J114: =MEDIAN(I114,$J$112,$I$112+ROUND((G114+H114-$G$112)/$H$112*($J$112-$I$112+1),0)-1) -> 9 | K114: =IF(AND(K$4>=$I114,K$4<=$J114),1,"") | L114: =IF(AND(L$4>=$I114,L$4<=$J114),1,"") | M114: =IF(AND(M$4>=$I114,M$4<=$J114),1,"") | N114: =IF(AND(N$4>=$I114,N$4<=$J114),1,"") | O114: =IF(AND(O$4>=$I114,O$4<=$J114),1,"") | P114: =IF(AND(P$4>=$I114,P$4<=$J114),1,"") | Q114: =IF(AND(Q$4>=$I114,Q$4<=$J114),1,"") | R114: =IF(AND(R$4>=$I114,R$4<=$J114),1,"") -> 1 | ... BS114: =IF(AND(BS$4>=$I114,BS$4<=$J114),1,"") | BU114: P2-L27 desc sub-item 'policy-as-code' (spec_cost_model P2-L27). Follows the IaC baseline; aligned with the AKS build start (week 8).
A115: G-P2-L27-s3 | B115: • Image scanning and container registry hygiene | C115: SEGRO | D115: ASSUMPTION | F115: G-P2-L27-s2 | G115: 10 | H115: 2 | I115: =MEDIAN($I$112,$J$112,$I$112+ROUND((G115-$G$112)/$H$112*($J$112-$I$112+1),0)) -> 10 | J115: =MEDIAN(I115,$J$112,$I$112+ROUND((G115+H115-$G$112)/$H$112*($J$112-$I$112+1),0)-1) -> 11 | K115: =IF(AND(K$4>=$I115,K$4<=$J115),1,"") | L115: =IF(AND(L$4>=$I115,L$4<=$J115),1,"") | M115: =IF(AND(M$4>=$I115,M$4<=$J115),1,"") | N115: =IF(AND(N$4>=$I115,N$4<=$J115),1,"") | O115: =IF(AND(O$4>=$I115,O$4<=$J115),1,"") | P115: =IF(AND(P$4>=$I115,P$4<=$J115),1,"") | Q115: =IF(AND(Q$4>=$I115,Q$4<=$J115),1,"") | R115: =IF(AND(R$4>=$I115,R$4<=$J115),1,"") | ... BS115: =IF(AND(BS$4>=$I115,BS$4<=$J115),1,"") | BU115: P2-L27 desc sub-item 'image scanning' (spec_cost_model P2-L27). Positioned as workloads start landing on the cluster (shared services deploy from week 10).
A116: G-P2-L27-s4 | B116: • CI/CD pipelines for infra and agent deployment | C116: SEGRO | D116: ASSUMPTION | F116: G-P2-L27-s3 | G116: 12 | H116: 2 | I116: =MEDIAN($I$112,$J$112,$I$112+ROUND((G116-$G$112)/$H$112*($J$112-$I$112+1),0)) -> 12 | J116: =MEDIAN(I116,$J$112,$I$112+ROUND((G116+H116-$G$112)/$H$112*($J$112-$I$112+1),0)-1) -> 13 | K116: =IF(AND(K$4>=$I116,K$4<=$J116),1,"") | L116: =IF(AND(L$4>=$I116,L$4<=$J116),1,"") | M116: =IF(AND(M$4>=$I116,M$4<=$J116),1,"") | N116: =IF(AND(N$4>=$I116,N$4<=$J116),1,"") | O116: =IF(AND(O$4>=$I116,O$4<=$J116),1,"") | P116: =IF(AND(P$4>=$I116,P$4<=$J116),1,"") | Q116: =IF(AND(Q$4>=$I116,Q$4<=$J116),1,"") | R116: =IF(AND(R$4>=$I116,R$4<=$J116),1,"") | ... BS116: =IF(AND(BS$4>=$I116,BS$4<=$J116),1,"") | BU116: P2-L27 desc sub-item 'CI/CD for infra + agent deployment' (spec_cost_model P2-L27); slide 7 'CI/CD Configuration Document | Automates build & deploy' is the deliverable this pipeline work substantiates. Boundary note per P2-L27 basis: this BUILDS the pipelines; P5-L2 executes the deploy-phase cutover.
...

Sheet Gantt - Revised
A1: Gantt - Corrected — technical step decomposition per major line of work
A2: The corrected sequence implementing review findings (F1/F2/F10/F16/F17/F19/F23/F26). Every window is RECOMMENDED — a proposed re-draw, not a committed plan. Cost totals are unchanged: windows move, quantities do not. The F1 re-anchor moves nominal go-live to week 31 (range weeks 29-33); the sheet renders BOTH the nominal marker and the range band, not a single committed date. Bars recalc live: SlipWeeks dilates TIME-DRIVEN windows (people + Azure commissioning) pro-rata — the same elongation the slip cost prices; FIXED-fee engagements (licences, third-party pen-test/red-team) shift but keep their duration; hypercare shifts whole. A ▶ in the Slip column flags any bar clipped at the grid edge under a large slip. Milestones: ▲ nominal go-live · ◁▷ F1 range band · ✕ Christmas · ! Bank holiday · ◆ drawn phase gate. Bar colours: SEGRO red · HCL dark blue · Azure mid blue · Third-party purple · corrected bars green (proposed, not committed).
L3: Jul 26 | O3: Aug 26 | T3: Sep 26 | X3: Oct 26 | AB3: Nov 26 | AG3: Dec 26 | AK3: Jan 27 | AO3: Feb 27 | AS3: Mar 27 | AX3: Apr 27 | BB3: May 27 | BG3: Jun 27 | BK3: Jul 27 | BO3: Aug 27 | BT3: Sep 27
A4: Id | B4: Major line of work / technical step | C4: Side | D4: Status | E4: Findings | F4: Depends on | G4: Start wk | H4: Wks | I4: Live start | J4: Live end | K4: Change vs as-drawn (per finding) | L4: 1 | M4: 2 | N4: 3 | O4: 4 | P4: 5 | Q4: 6 | R4: 7 | S4: 8 | T4: 9 | U4: 10 | V4: 11 | W4: 12 | X4: 13 | Y4: 14 | Z4: 15 | AA4: 16 | AB4: 17 | AC4: 18 | AD4: 19 | AE4: 20 | AF4: 21 | AG4: 22 | AH4: 23 | AI4: 24 | AJ4: 25 | AK4: 26 | AL4: 27 | AM4: 28 | AN4: 29 | AO4: 30 | AP4: 31 | AQ4: 32 | AR4: 33 | AS4: 34 | AT4: 35 | AU4: 36 | AV4: 37 | AW4: 38 | AX4: 39 | AY4: 40 | AZ4: 41 | BA4: 42 | BB4: 43 | BC4: 44 | BD4: 45 | BE4: 46 | BF4: 47 | BG4: 48 | BH4: 49 | BI4: 50 | BJ4: 51 | BK4: 52 | BL4: 53 | BM4: 54 | BN4: 55 | BO4: 56 | BP4: 57 | BQ4: 58 | BR4: 59 | BS4: 60 | BT4: 61 | BU4: Slip | BV4: Basis / source | BX4: =31+SlipWeeks -> 31 | BY4: =29+SlipWeeks -> 29 | BZ4: =33+SlipWeeks -> 33
B5: Go-live range (F1) | L5: =IF(L$4=$BX$4,"▲",IF(L$4=$BY$4,"◁",IF(L$4=$BZ$4,"▷",IF(AND(L$4>$BY$4,L$4<$BZ$4),"·","")))) | M5: =IF(M$4=$BX$4,"▲",IF(M$4=$BY$4,"◁",IF(M$4=$BZ$4,"▷",IF(AND(M$4>$BY$4,M$4<$BZ$4),"·","")))) | N5: =IF(N$4=$BX$4,"▲",IF(N$4=$BY$4,"◁",IF(N$4=$BZ$4,"▷",IF(AND(N$4>$BY$4,N$4<$BZ$4),"·","")))) | O5: =IF(O$4=$BX$4,"▲",IF(O$4=$BY$4,"◁",IF(O$4=$BZ$4,"▷",IF(AND(O$4>$BY$4,O$4<$BZ$4),"·","")))) | P5: =IF(P$4=$BX$4,"▲",IF(P$4=$BY$4,"◁",IF(P$4=$BZ$4,"▷",IF(AND(P$4>$BY$4,P$4<$BZ$4),"·","◆")))) -> ◆ | Q5: =IF(Q$4=$BX$4,"▲",IF(Q$4=$BY$4,"◁",IF(Q$4=$BZ$4,"▷",IF(AND(Q$4>$BY$4,Q$4<$BZ$4),"·","")))) | R5: =IF(R$4=$BX$4,"▲",IF(R$4=$BY$4,"◁",IF(R$4=$BZ$4,"▷",IF(AND(R$4>$BY$4,R$4<$BZ$4),"·","")))) | S5: =IF(S$4=$BX$4,"▲",IF(S$4=$BY$4,"◁",IF(S$4=$BZ$4,"▷",IF(AND(S$4>$BY$4,S$4<$BZ$4),"·","!")))) -> ! | T5: =IF(T$4=$BX$4,"▲",IF(T$4=$BY$4,"◁",IF(T$4=$BZ$4,"▷",IF(AND(T$4>$BY$4,T$4<$BZ$4),"·","")))) | U5: =IF(U$4=$BX$4,"▲",IF(U$4=$BY$4,"◁",IF(U$4=$BZ$4,"▷",IF(AND(U$4>$BY$4,U$4<$BZ$4),"·","")))) | V5: =IF(V$4=$BX$4,"▲",IF(V$4=$BY$4,"◁",IF(V$4=$BZ$4,"▷",IF(AND(V$4>$BY$4,V$4<$BZ$4),"·","")))) | W5: =IF(W$4=$BX$4,"▲",IF(W$4=$BY$4,"◁",IF(W$4=$BZ$4,"▷",IF(AND(W$4>$BY$4,W$4<$BZ$4),"·","")))) | X5: =IF(X$4=$BX$4,"▲",IF(X$4=$BY$4,"◁",IF(X$4=$BZ$4,"▷",IF(AND(X$4>$BY$4,X$4<$BZ$4),"·","")))) | Y5: =IF(Y$4=$BX$4,"▲",IF(Y$4=$BY$4,"◁",IF(Y$4=$BZ$4,"▷",IF(AND(Y$4>$BY$4,Y$4<$BZ$4),"·","")))) | Z5: =IF(Z$4=$BX$4,"▲",IF(Z$4=$BY$4,"◁",IF(Z$4=$BZ$4,"▷",IF(AND(Z$4>$BY$4,Z$4<$BZ$4),"·","")))) | AA5: =IF(AA$4=$BX$4,"▲",IF(AA$4=$BY$4,"◁",IF(AA$4=$BZ$4,"▷",IF(AND(AA$4>$BY$4,AA$4<$BZ$4),"·","")))) | ... AE5: =IF(AE$4=$BX$4,"▲",IF(AE$4=$BY$4,"◁",IF(AE$4=$BZ$4,"▷",IF(AND(AE$4>$BY$4,AE$4<$BZ$4),"·","")))) | AF5: =IF(AF$4=$BX$4,"▲",IF(AF$4=$BY$4,"◁",IF(AF$4=$BZ$4,"▷",IF(AND(AF$4>$BY$4,AF$4<$BZ$4),"·","◆")))) -> ◆ | AG5: =IF(AG$4=$BX$4,"▲",IF(AG$4=$BY$4,"◁",IF(AG$4=$BZ$4,"▷",IF(AND(AG$4>$BY$4,AG$4<$BZ$4),"·","")))) | AH5: =IF(AH$4=$BX$4,"▲",IF(AH$4=$BY$4,"◁",IF(AH$4=$BZ$4,"▷",IF(AND(AH$4>$BY$4,AH$4<$BZ$4),"·","")))) | AI5: =IF(AI$4=$BX$4,"▲",IF(AI$4=$BY$4,"◁",IF(AI$4=$BZ$4,"▷",IF(AND(AI$4>$BY$4,AI$4<$BZ$4),"·","✕")))) -> ✕ | AJ5: =IF(AJ$4=$BX$4,"▲",IF(AJ$4=$BY$4,"◁",IF(AJ$4=$BZ$4,"▷",IF(AND(AJ$4>$BY$4,AJ$4<$BZ$4),"·","◆")))) -> ◆ | AK5: =IF(AK$4=$BX$4,"▲",IF(AK$4=$BY$4,"◁",IF(AK$4=$BZ$4,"▷",IF(AND(AK$4>$BY$4,AK$4<$BZ$4),"·","")))) | AL5: =IF(AL$4=$BX$4,"▲",IF(AL$4=$BY$4,"◁",IF(AL$4=$BZ$4,"▷",IF(AND(AL$4>$BY$4,AL$4<$BZ$4),"·","")))) | AM5: =IF(AM$4=$BX$4,"▲",IF(AM$4=$BY$4,"◁",IF(AM$4=$BZ$4,"▷",IF(AND(AM$4>$BY$4,AM$4<$BZ$4),"·","")))) | AN5: =IF(AN$4=$BX$4,"▲",IF(AN$4=$BY$4,"◁",IF(AN$4=$BZ$4,"▷",IF(AND(AN$4>$BY$4,AN$4<$BZ$4),"·","")))) -> ◁ | AO5: =IF(AO$4=$BX$4,"▲",IF(AO$4=$BY$4,"◁",IF(AO$4=$BZ$4,"▷",IF(AND(AO$4>$BY$4,AO$4<$BZ$4),"·","")))) -> · | AP5: =IF(AP$4=$BX$4,"▲",IF(AP$4=$BY$4,"◁",IF(AP$4=$BZ$4,"▷",IF(AND(AP$4>$BY$4,AP$4<$BZ$4),"·","")))) -> ▲ | AQ5: =IF(AQ$4=$BX$4,"▲",IF(AQ$4=$BY$4,"◁",IF(AQ$4=$BZ$4,"▷",IF(AND(AQ$4>$BY$4,AQ$4<$BZ$4),"·","")))) -> · | AR5: =IF(AR$4=$BX$4,"▲",IF(AR$4=$BY$4,"◁",IF(AR$4=$BZ$4,"▷",IF(AND(AR$4>$BY$4,AR$4<$BZ$4),"·","")))) -> ▷ | ... BT5: =IF(BT$4=$BX$4,"▲",IF(BT$4=$BY$4,"◁",IF(BT$4=$BZ$4,"▷",IF(AND(BT$4>$BY$4,BT$4<$BZ$4),"·",""))))
A6: G-P2-L4-R | B6: Build - SEGRO (pulled forward into Design) [P2-L4] | C6: SEGRO | D6: RECOMMENDED | E6: F17 | G6: 3 | H6: 6 | I6: =MIN(61,IF(G6<=29,ROUND((G6-1)*(29+SlipWeeks)/29,0)+1,G6+SlipWeeks)) -> 3 | J6: =MIN(61,IF(G6+H6-1<=29,MAX(ROUND((G6+H6-1)*(29+SlipWeeks)/29,0),I6),G6+H6-1+SlipWeeks)) -> 8 | K6: Pulled forward from the full P2 span (weeks 6-15) to weeks 3-8 so security design completes before network build-out completes, not weeks after it. | L6: =IF(AND(L$4>=$I6,L$4<=$J6),1,"") | M6: =IF(AND(M$4>=$I6,M$4<=$J6),1,"") | N6: =IF(AND(N$4>=$I6,N$4<=$J6),1,"") -> 1 | O6: =IF(AND(O$4>=$I6,O$4<=$J6),1,"") -> 1 | P6: =IF(AND(P$4>=$I6,P$4<=$J6),1,"") -> 1 | Q6: =IF(AND(Q$4>=$I6,Q$4<=$J6),1,"") -> 1 | R6: =IF(AND(R$4>=$I6,R$4<=$J6),1,"") -> 1 | S6: =IF(AND(S$4>=$I6,S$4<=$J6),1,"") -> 1 | ... BT6: =IF(AND(BT$4>=$I6,BT$4<=$J6),1,"") | BU6: =IF(IF(G6+H6-1<=29,MAX(ROUND((G6+H6-1)*(29+SlipWeeks)/29,0),$I6),G6+H6-1+SlipWeeks)>61,"▶ clipped","") | BV6: F17: 'Front-load the security-design decisions that constrain network layout (segmentation model, WAF placement, private endpoints, API security) into the design phase or build weeks 1-2; keep only implementation hardening in the parallel bar' - the corrected bar starts week 3 in P1, alongside the Cyber Sec Workshop in the P1 workshop chain, and completes end of week 8 (first 3 weeks of P2), BEFORE the as-drawn network build-out (item 1, first ~half of the 10-week build) completes - avoiding rework of an already-provisioned network layout. Implementation hardening only remains in the parallel build bar per the recommendation. Quantity unchanged (25 pd likely, P2-L4).
A7: G-P2-L4-R-s1 | B7: • Security-design decisions that constrain network layout - segmentation model, WAF placement, private endpoints, API security - taken in the design phase alongside the Cyber Sec Workshop | C7: SEGRO | D7: RECOMMENDED | G7: 3 | H7: 3 | I7: =MEDIAN($I$6,$J$6,$I$6+ROUND((G7-$G$6)/$H$6*($J$6-$I$6+1),0)) -> 3 | J7: =MEDIAN(I7,$J$6,$I$6+ROUND((G7+H7-$G$6)/$H$6*($J$6-$I$6+1),0)-1) -> 5 | L7: =IF(AND(L$4>=$I7,L$4<=$J7),1,"") | M7: =IF(AND(M$4>=$I7,M$4<=$J7),1,"") | N7: =IF(AND(N$4>=$I7,N$4<=$J7),1,"") -> 1 | O7: =IF(AND(O$4>=$I7,O$4<=$J7),1,"") -> 1 | P7: =IF(AND(P$4>=$I7,P$4<=$J7),1,"") -> 1 | Q7: =IF(AND(Q$4>=$I7,Q$4<=$J7),1,"") | R7: =IF(AND(R$4>=$I7,R$4<=$J7),1,"") | S7: =IF(AND(S$4>=$I7,S$4<=$J7),1,"") | ... BT7: =IF(AND(BT$4>=$I7,BT$4<=$J7),1,"") | BV7: F17: 'Front-load the security-design decisions that constrain network layout (segmentation model, WAF placement, private endpoints, API security) into the design phase or build weeks 1-2' - taken in P1 weeks 3-5 so they are settled before any network provisioning starts in P2.
A8: G-P2-L4-R-s2 | B8: • Complete remaining cyber security design - managed identities, Key Vault, secrets management, PAM - in build weeks 1-3, before network build-out completes | C8: SEGRO | D8: RECOMMENDED | F8: G-P2-L4-R-s1 | G8: 6 | H8: 3 | I8: =MEDIAN($I$6,$J$6,$I$6+ROUND((G8-$G$6)/$H$6*($J$6-$I$6+1),0)) -> 6 | J8: =MEDIAN(I8,$J$6,$I$6+ROUND((G8+H8-$G$6)/$H$6*($J$6-$I$6+1),0)-1) -> 8 | L8: =IF(AND(L$4>=$I8,L$4<=$J8),1,"") | M8: =IF(AND(M$4>=$I8,M$4<=$J8),1,"") | N8: =IF(AND(N$4>=$I8,N$4<=$J8),1,"") | O8: =IF(AND(O$4>=$I8,O$4<=$J8),1,"") | P8: =IF(AND(P$4>=$I8,P$4<=$J8),1,"") | Q8: =IF(AND(Q$4>=$I8,Q$4<=$J8),1,"") -> 1 | R8: =IF(AND(R$4>=$I8,R$4<=$J8),1,"") -> 1 | S8: =IF(AND(S$4>=$I8,S$4<=$J8),1,"") -> 1 | ... BT8: =IF(AND(BT$4>=$I8,BT$4<=$J8),1,"") | BV8: F17: 'keep only implementation hardening in the parallel bar' - the design content completes by week 8, ahead of the network build-out finishing; only implementation hardening continues alongside the rest of the build.
A10: G-P1-REV-R | B10: Design & Plan | C10: SEGRO | D10: RECOMMENDED | E10: F16 | G10: 2 | H10: 6 | I10: =MIN(61,IF(G10<=29,ROUND((G10-1)*(29+SlipWeeks)/29,0)+1,G10+SlipWeeks)) -> 2 | J10: =MIN(61,IF(G10+H10-1<=29,MAX(ROUND((G10+H10-1)*(29+SlipWeeks)/29,0),I10),G10+H10-1+SlipWeeks)) -> 7 | K10: New TAD/HLD/LLD review-and-revision track inside P1 extending 2 weeks into early P2; no as-drawn counterpart exists - the as-drawn plan has no review or revision cycle at all. | L10: =IF(AND(L$4>=$I10,L$4<=$J10),1,"") | M10: =IF(AND(M$4>=$I10,M$4<=$J10),1,"") -> 1 | N10: =IF(AND(N$4>=$I10,N$4<=$J10),1,"") -> 1 | O10: =IF(AND(O$4>=$I10,O$4<=$J10),1,"") -> 1 | P10: =IF(AND(P$4>=$I10,P$4<=$J10),1,"") -> 1 | Q10: =IF(AND(Q$4>=$I10,Q$4<=$J10),1,"") -> 1 | R10: =IF(AND(R$4>=$I10,R$4<=$J10),1,"") -> 1 | S10: =IF(AND(S$4>=$I10,S$4<=$J10),1,"") | ... BT10: =IF(AND(BT$4>=$I10,BT$4<=$J10),1,"") | BU10: =IF(IF(G10+H10-1<=29,MAX(ROUND((G10+H10-1)*(29+SlipWeeks)/29,0),$I10),G10+H10-1+SlipWeeks)>61,"▶ clipped","") | BV10: F16: 'Publish a review/approval schedule per gating document (owner, turnaround SLA, revision allowance) and hold at least one built-in revision cycle before the build-start gate' - NEW explicit TAD/HLD/LLD review + revision track covering the 14 slide-5 design documents. One full revision loop for 14 documents does not fit inside the 5-week P1 window on top of authoring, so the track runs weeks 2-7, extending 2 weeks into early P2. Build-start impact, stated honestly: SEGRO build tasks gated on an approved TAD/HLD/LLD/DRG pack carry up to a 2-week start risk against the week-6 build start; this risk is absorbed in the go-live range shown in G-TEST-REANCHOR-R. No cost change - review effort sits inside the existing P1 role lines (P1-L1 to P1-L7), which is why no single cost_line is cited.
A11: G-P1-REV-R-s1 | B11: • Publish the review/approval schedule per gating document - owner, turnaround SLA, revision allowance - for all 14 slide-5 design documents (TAD, HLD, LLD, DRG pack and the rest) | C11: SEGRO | D11: RECOMMENDED | G11: 2 | H11: 1 | I11: =MEDIAN($I$10,$J$10,$I$10+ROUND((G11-$G$10)/$H$10*($J$10-$I$10+1),0)) -> 2 | J11: =MEDIAN(I11,$J$10,$I$10+ROUND((G11+H11-$G$10)/$H$10*($J$10-$I$10+1),0)-1) -> 2 | L11: =IF(AND(L$4>=$I11,L$4<=$J11),1,"") | M11: =IF(AND(M$4>=$I11,M$4<=$J11),1,"") -> 1 | N11: =IF(AND(N$4>=$I11,N$4<=$J11),1,"") | O11: =IF(AND(O$4>=$I11,O$4<=$J11),1,"") | P11: =IF(AND(P$4>=$I11,P$4<=$J11),1,"") | Q11: =IF(AND(Q$4>=$I11,Q$4<=$J11),1,"") | R11: =IF(AND(R$4>=$I11,R$4<=$J11),1,"") | S11: =IF(AND(S$4>=$I11,S$4<=$J11),1,"") | ... BT11: =IF(AND(BT$4>=$I11,BT$4<=$J11),1,"") | BV11: F16: 'Publish a review/approval schedule per gating document (owner, turnaround SLA, revision allowance)' - schedule issued in week 2 so reviews can start as documents land.
A12: G-P1-REV-R-s2 | B12: • First-pass reviews of the 14 slide-5 design documents as they land through the P1 workshop chain | C12: SEGRO | D12: RECOMMENDED | F12: G-P1-REV-R-s1 | G12: 3 | H12: 3 | I12: =MEDIAN($I$10,$J$10,$I$10+ROUND((G12-$G$10)/$H$10*($J$10-$I$10+1),0)) -> 3 | J12: =MEDIAN(I12,$J$10,$I$10+ROUND((G12+H12-$G$10)/$H$10*($J$10-$I$10+1),0)-1) -> 5 | L12: =IF(AND(L$4>=$I12,L$4<=$J12),1,"") | M12: =IF(AND(M$4>=$I12,M$4<=$J12),1,"") | N12: =IF(AND(N$4>=$I12,N$4<=$J12),1,"") -> 1 | O12: =IF(AND(O$4>=$I12,O$4<=$J12),1,"") -> 1 | P12: =IF(AND(P$4>=$I12,P$4<=$J12),1,"") -> 1 | Q12: =IF(AND(Q$4>=$I12,Q$4<=$J12),1,"") | R12: =IF(AND(R$4>=$I12,R$4<=$J12),1,"") | S12: =IF(AND(S$4>=$I12,S$4<=$J12),1,"") | ... BT12: =IF(AND(BT$4>=$I12,BT$4<=$J12),1,"") | BV12: F16: reviews executed against the published schedule's 'turnaround SLA' during weeks 3-5, while the documents are being authored - not deferred past 'Design phase complete'.
A13: G-P1-REV-R-s3 | B13: • Built-in revision cycle: revise, re-review and approve the gating documents (TAD, HLD, LLD, DRG approval) before the build-start gate | C13: SEGRO | D13: RECOMMENDED | F13: G-P1-REV-R-s2 | G13: 6 | H13: 2 | I13: =MEDIAN($I$10,$J$10,$I$10+ROUND((G13-$G$10)/$H$10*($J$10-$I$10+1),0)) -> 6 | J13: =MEDIAN(I13,$J$10,$I$10+ROUND((G13+H13-$G$10)/$H$10*($J$10-$I$10+1),0)-1) -> 7 | L13: =IF(AND(L$4>=$I13,L$4<=$J13),1,"") | M13: =IF(AND(M$4>=$I13,M$4<=$J13),1,"") | N13: =IF(AND(N$4>=$I13,N$4<=$J13),1,"") | O13: =IF(AND(O$4>=$I13,O$4<=$J13),1,"") | P13: =IF(AND(P$4>=$I13,P$4<=$J13),1,"") | Q13: =IF(AND(Q$4>=$I13,Q$4<=$J13),1,"") -> 1 | R13: =IF(AND(R$4>=$I13,R$4<=$J13),1,"") -> 1 | S13: =IF(AND(S$4>=$I13,S$4<=$J13),1,"") | ... BT13: =IF(AND(BT$4>=$I13,BT$4<=$J13),1,"") | BV13: F16: 'hold at least one built-in revision cycle before the build-start gate' - the revision loop runs weeks 6-7 (early P2); build tasks gated on approved designs carry up to a 2-week start risk, noted in the parent basis.
A15: G-P1-PROC-R | B15: Decisions & procurement | C15: SEGRO | D15: RECOMMENDED | E15: F10 | G15: 1 | H15: 5 | I15: =MIN(61,IF(G15<=29,ROUND((G15-1)*(29+SlipWeeks)/29,0)+1,G15+SlipWeeks)) -> 1 | J15: =MIN(61,IF(G15+H15-1<=29,MAX(ROUND((G15+H15-1)*(29+SlipWeeks)/29,0),I15),G15+H15-1+SlipWeeks)) -> 5 | K15: Procurement starts week 1 and runs 5 weeks with named owners and latest-order dates, replacing the drawn ~2.5-week allowance that starts mid-P1. | L15: =IF(AND(L$4>=$I15,L$4<=$J15),1,"") -> 1 | M15: =IF(AND(M$4>=$I15,M$4<=$J15),1,"") -> 1 | N15: =IF(AND(N$4>=$I15,N$4<=$J15),1,"") -> 1 | O15: =IF(AND(O$4>=$I15,O$4<=$J15),1,"") -> 1 | P15: =IF(AND(P$4>=$I15,P$4<=$J15),1,"") -> 1 | Q15: =IF(AND(Q$4>=$I15,Q$4<=$J15),1,"") | R15: =IF(AND(R$4>=$I15,R$4<=$J15),1,"") | S15: =IF(AND(S$4>=$I15,S$4<=$J15),1,"") | ... BT15: =IF(AND(BT$4>=$I15,BT$4<=$J15),1,"") | BU15: =IF(IF(G15+H15-1<=29,MAX(ROUND((G15+H15-1)*(29+SlipWeeks)/29,0),$I15),G15+H15-1+SlipWeeks)>61,"▶ clipped","") | BV15: F10: 'Add named procurement tasks with owners and latest-order dates back-planned from the HCL install start' - the corrected procurement track starts week 1 and runs the full 5-week P1 window (>=4 weeks), covering the Oracle 19 and Aerospike licence lead times (P1-L8, P1-L9) plus the MinIO EOL remediation scoping (P3-L8) and the ARO subscription branch if KDD-1 selects ARO. F10's evidence: the drawn bar is roughly a 2.5-2.7 week allowance starting mid-P1, which the senior architect independently challenged ('Procurrent of commercial components would take longer than 2 weeks'). Quantities unchanged - the licence lines remain RATE_MISSING at GBP 0 until quoted. cost_line is null (this track spans P1-L8/P1-L9 plus the P3-L8 MinIO remediation scoping and the conditional ARO subscription - no single cost-model id represents it); the covered lines are listed in 'covers'.
A16: G-P1-PROC-R-s1 | B16: • Name the procurement tasks with owners; back-plan latest-order dates from the corrected HCL install start (week 13) for Oracle 19, Aerospike, MinIO successor and the conditional ARO subscription | C16: SEGRO | D16: RECOMMENDED | G16: 1 | H16: 1 | I16: =MEDIAN($I$15,$J$15,$I$15+ROUND((G16-$G$15)/$H$15*($J$15-$I$15+1),0)) -> 1 | J16: =MEDIAN(I16,$J$15,$I$15+ROUND((G16+H16-$G$15)/$H$15*($J$15-$I$15+1),0)-1) -> 1 | L16: =IF(AND(L$4>=$I16,L$4<=$J16),1,"") -> 1 | M16: =IF(AND(M$4>=$I16,M$4<=$J16),1,"") | N16: =IF(AND(N$4>=$I16,N$4<=$J16),1,"") | O16: =IF(AND(O$4>=$I16,O$4<=$J16),1,"") | P16: =IF(AND(P$4>=$I16,P$4<=$J16),1,"") | Q16: =IF(AND(Q$4>=$I16,Q$4<=$J16),1,"") | R16: =IF(AND(R$4>=$I16,R$4<=$J16),1,"") | S16: =IF(AND(S$4>=$I16,S$4<=$J16),1,"") | ... BT16: =IF(AND(BT$4>=$I16,BT$4<=$J16),1,"") | BV16: F10: 'Add named procurement tasks with owners and latest-order dates back-planned from the HCL install start' - done in week 1 so lead times run from the earliest possible date.
A17: G-P1-PROC-R-s2 | B17: • Issue quotes/orders for the long-lead commercial components: Oracle 19 (mandatory for Unica+ MaxAI CDM, P1-L8) and Aerospike edition/licence (P1-L9) | C17: SEGRO | D17: RECOMMENDED | F17: G-P1-PROC-R-s1 | G17: 2 | H17: 2 | I17: =MEDIAN($I$15,$J$15,$I$15+ROUND((G17-$G$15)/$H$15*($J$15-$I$15+1),0)) -> 2 | J17: =MEDIAN(I17,$J$15,$I$15+ROUND((G17+H17-$G$15)/$H$15*($J$15-$I$15+1),0)-1) -> 3 | L17: =IF(AND(L$4>=$I17,L$4<=$J17),1,"") | M17: =IF(AND(M$4>=$I17,M$4<=$J17),1,"") -> 1 | N17: =IF(AND(N$4>=$I17,N$4<=$J17),1,"") -> 1 | O17: =IF(AND(O$4>=$I17,O$4<=$J17),1,"") | P17: =IF(AND(P$4>=$I17,P$4<=$J17),1,"") | Q17: =IF(AND(Q$4>=$I17,Q$4<=$J17),1,"") | R17: =IF(AND(R$4>=$I17,R$4<=$J17),1,"") | S17: =IF(AND(S$4>=$I17,S$4<=$J17),1,"") | ... BT17: =IF(AND(BT$4>=$I17,BT$4<=$J17),1,"") | BV17: F10: these items 'can gate the HCL install bar' per the finding - orders issued weeks 2-3 against the week-1 latest-order dates.
A18: G-P1-PROC-R-s3 | B18: • Track lead times and confirm delivery/entitlement against the latest-order dates before the Design phase complete gate | C18: SEGRO | D18: RECOMMENDED | F18: G-P1-PROC-R-s2 | G18: 4 | H18: 2 | I18: =MEDIAN($I$15,$J$15,$I$15+ROUND((G18-$G$15)/$H$15*($J$15-$I$15+1),0)) -> 4 | J18: =MEDIAN(I18,$J$15,$I$15+ROUND((G18+H18-$G$15)/$H$15*($J$15-$I$15+1),0)-1) -> 5 | L18: =IF(AND(L$4>=$I18,L$4<=$J18),1,"") | M18: =IF(AND(M$4>=$I18,M$4<=$J18),1,"") | N18: =IF(AND(N$4>=$I18,N$4<=$J18),1,"") | O18: =IF(AND(O$4>=$I18,O$4<=$J18),1,"") -> 1 | P18: =IF(AND(P$4>=$I18,P$4<=$J18),1,"") -> 1 | Q18: =IF(AND(Q$4>=$I18,Q$4<=$J18),1,"") | R18: =IF(AND(R$4>=$I18,R$4<=$J18),1,"") | S18: =IF(AND(S$4>=$I18,S$4<=$J18),1,"") | ... BT18: =IF(AND(BT$4>=$I18,BT$4<=$J18),1,"") | BV18: F10: confirmation weeks 4-5 keeps the 'latest-order dates back-planned from the HCL install start' honest - any slip is visible ~8 weeks before the corrected HCL install start (week 13).
A20: G-P2-L27-R | B20: Build - SEGRO [P2-L27] | C20: SEGRO | D20: RECOMMENDED | E20: F19 | G20: 6 | H20: 3 | I20: =MIN(61,IF(G20<=29,ROUND((G20-1)*(29+SlipWeeks)/29,0)+1,G20+SlipWeeks)) -> 6 | J20: =MIN(61,IF(G20+H20-1<=29,MAX(ROUND((G20+H20-1)*(29+SlipWeeks)/29,0),I20),G20+H20-1+SlipWeeks)) -> 8 | K20: Concentrated into the first 3 weeks of P2 (weeks 6-8) so pipelines and policy gates exist before workloads deploy, instead of running across the full 10-week build. | L20: =IF(AND(L$4>=$I20,L$4<=$J20),1,"") | M20: =IF(AND(M$4>=$I20,M$4<=$J20),1,"") | N20: =IF(AND(N$4>=$I20,N$4<=$J20),1,"") | O20: =IF(AND(O$4>=$I20,O$4<=$J20),1,"") | P20: =IF(AND(P$4>=$I20,P$4<=$J20),1,"") | Q20: =IF(AND(Q$4>=$I20,Q$4<=$J20),1,"") -> 1 | R20: =IF(AND(R$4>=$I20,R$4<=$J20),1,"") -> 1 | S20: =IF(AND(S$4>=$I20,S$4<=$J20),1,"") -> 1 | ... BT20: =IF(AND(BT$4>=$I20,BT$4<=$J20),1,"") | BU20: =IF(IF(G20+H20-1<=29,MAX(ROUND((G20+H20-1)*(29+SlipWeeks)/29,0),$I20),G20+H20-1+SlipWeeks)>61,"▶ clipped","") | BV20: F19: 'Add a named DevSecOps workstream (IaC for foundations, policy-as-code, image scanning, CI/CD for platform and agent deployment) to the build phase; the workbook carries it as P2-L27' - placed in the FIRST 3 weeks of P2 (weeks 6-8) so pipelines and policy gates exist before workloads deploy onto the platform, rather than being spread across the full 10-week build where later workstreams would deploy without gates. Quantity unchanged (30 pd likely, P2-L27) - the same effort concentrated into a shorter elapsed window. PLANNING NOTE: 30 pd across 3 weeks implies ~2.0 DevSecOps FTE vs the P2-L27 profile of 0.6 FTE over 10 weeks - a resourcing assumption, not a cost change (pd constant); if 2.0 FTE is infeasible in the first 3 build weeks, spread to weeks 6-10 while still landing the pipelines before the bulk of workloads deploy, which is all F19 requires.
A21: G-P2-L27-R-s1 | B21: • IaC pipelines for foundations stood up first - before foundations provisioning scales | C21: SEGRO | D21: RECOMMENDED | G21: 6 | H21: 1 | I21: =MEDIAN($I$20,$J$20,$I$20+ROUND((G21-$G$20)/$H$20*($J$20-$I$20+1),0)) -> 6 | J21: =MEDIAN(I21,$J$20,$I$20+ROUND((G21+H21-$G$20)/$H$20*($J$20-$I$20+1),0)-1) -> 6 | L21: =IF(AND(L$4>=$I21,L$4<=$J21),1,"") | M21: =IF(AND(M$4>=$I21,M$4<=$J21),1,"") | N21: =IF(AND(N$4>=$I21,N$4<=$J21),1,"") | O21: =IF(AND(O$4>=$I21,O$4<=$J21),1,"") | P21: =IF(AND(P$4>=$I21,P$4<=$J21),1,"") | Q21: =IF(AND(Q$4>=$I21,Q$4<=$J21),1,"") -> 1 | R21: =IF(AND(R$4>=$I21,R$4<=$J21),1,"") | S21: =IF(AND(S$4>=$I21,S$4<=$J21),1,"") | ... BT21: =IF(AND(BT$4>=$I21,BT$4<=$J21),1,"") | BV21: F19: 'IaC for foundations' is the first named element of the recommended workstream - it must exist in week 6 so build item 1 provisions through pipelines, not by hand.
A22: G-P2-L27-R-s2 | B22: • Policy-as-code gates and image scanning wired into the pipelines | C22: SEGRO | D22: RECOMMENDED | F22: G-P2-L27-R-s1 | G22: 7 | H22: 1 | I22: =MEDIAN($I$20,$J$20,$I$20+ROUND((G22-$G$20)/$H$20*($J$20-$I$20+1),0)) -> 7 | J22: =MEDIAN(I22,$J$20,$I$20+ROUND((G22+H22-$G$20)/$H$20*($J$20-$I$20+1),0)-1) -> 7 | L22: =IF(AND(L$4>=$I22,L$4<=$J22),1,"") | M22: =IF(AND(M$4>=$I22,M$4<=$J22),1,"") | N22: =IF(AND(N$4>=$I22,N$4<=$J22),1,"") | O22: =IF(AND(O$4>=$I22,O$4<=$J22),1,"") | P22: =IF(AND(P$4>=$I22,P$4<=$J22),1,"") | Q22: =IF(AND(Q$4>=$I22,Q$4<=$J22),1,"") | R22: =IF(AND(R$4>=$I22,R$4<=$J22),1,"") -> 1 | S22: =IF(AND(S$4>=$I22,S$4<=$J22),1,"") | ... BT22: =IF(AND(BT$4>=$I22,BT$4<=$J22),1,"") | BV22: F19: 'policy-as-code, image scanning' - gates live in week 7, ahead of shared-services and AKS workload deployments.
A23: G-P2-L27-R-s3 | B23: • CI/CD for platform and agent deployment operational; all subsequent P2/P3 deployments flow through the gated pipelines | C23: SEGRO | D23: RECOMMENDED | F23: G-P2-L27-R-s2 | G23: 8 | H23: 1 | I23: =MEDIAN($I$20,$J$20,$I$20+ROUND((G23-$G$20)/$H$20*($J$20-$I$20+1),0)) -> 8 | J23: =MEDIAN(I23,$J$20,$I$20+ROUND((G23+H23-$G$20)/$H$20*($J$20-$I$20+1),0)-1) -> 8 | L23: =IF(AND(L$4>=$I23,L$4<=$J23),1,"") | M23: =IF(AND(M$4>=$I23,M$4<=$J23),1,"") | N23: =IF(AND(N$4>=$I23,N$4<=$J23),1,"") | O23: =IF(AND(O$4>=$I23,O$4<=$J23),1,"") | P23: =IF(AND(P$4>=$I23,P$4<=$J23),1,"") | Q23: =IF(AND(Q$4>=$I23,Q$4<=$J23),1,"") | R23: =IF(AND(R$4>=$I23,R$4<=$J23),1,"") | S23: =IF(AND(S$4>=$I23,S$4<=$J23),1,"") -> 1 | ... BT23: =IF(AND(BT$4>=$I23,BT$4<=$J23),1,"") | BV23: F19: 'CI/CD for platform and agent deployment' complete by end week 8 - the pipelines the slide-7 'CI/CD Configuration Document' describes now exist before the workloads they deploy.
A25: G-P3-L1-R | B25: Build - HCL [P3-L1] | C25: HCL | D25: RECOMMENDED | E25: F2 | F25: G-P1-PROC-R, G-P2-L27-R | G25: 13 | H25: 6 | I25: =MIN(61,IF(G25<=29,ROUND((G25-1)*(29+SlipWeeks)/29,0)+1,G25+SlipWeeks)) -> 13 | J25: =MIN(61,IF(G25+H25-1<=29,MAX(ROUND((G25+H25-1)*(29+SlipWeeks)/29,0),I25),G25+H25-1+SlipWeeks)) -> 18 | K25: Starts week 13 (once AKS hardening completes at end of SEGRO build week 7), overlapping the SEGRO build tail by 3 weeks instead of running strictly sequential from week 16. | L25: =IF(AND(L$4>=$I25,L$4<=$J25),1,"") | M25: =IF(AND(M$4>=$I25,M$4<=$J25),1,"") | N25: =IF(AND(N$4>=$I25,N$4<=$J25),1,"") | O25: =IF(AND(O$4>=$I25,O$4<=$J25),1,"") | P25: =IF(AND(P$4>=$I25,P$4<=$J25),1,"") | Q25: =IF(AND(Q$4>=$I25,Q$4<=$J25),1,"") | R25: =IF(AND(R$4>=$I25,R$4<=$J25),1,"") | S25: =IF(AND(S$4>=$I25,S$4<=$J25),1,"") | ... BT25: =IF(AND(BT$4>=$I25,BT$4<=$J25),1,"") | BU25: =IF(IF(G25+H25-1<=29,MAX(ROUND((G25+H25-1)*(29+SlipWeeks)/29,0),$I25),G25+H25-1+SlipWeeks)>61,"▶ clipped","") | BV25: F2: 'Re-plan the HCL install to start once the AKS platform is hardened (end of SEGRO week 6-7) rather than after the full SEGRO bar; validate the overlap window with HCL' - corrected start week 13 = end of SEGRO build week 7 (grid week 12), giving a 3-week overlap with the SEGRO build tail (weeks 13-15), inside F2's 2-4 week planning assumption. Later HCL scope (connectivity, routing, observability integration) is sequenced after the wider SEGRO stack completes at week 15. Priced via the model's OverlapWeeks lever: 'Priced via the OverlapWeeks input (Azure double-running saving only - person-days are not reduced by parallel working)' - the 90 pd likely quantity is unchanged; only elapsed double-running shortens. The install remains gated on KDD-1 closure per F3.
A26: G-P3-L1-R-s1 | B26: • HCL install base UnO platform onto the hardened AKS platform, overlapping the SEGRO build tail | C26: HCL | D26: RECOMMENDED | G26: 13 | H26: 2 | I26: =MEDIAN($I$25,$J$25,$I$25+ROUND((G26-$G$25)/$H$25*($J$25-$I$25+1),0)) -> 13 | J26: =MEDIAN(I26,$J$25,$I$25+ROUND((G26+H26-$G$25)/$H$25*($J$25-$I$25+1),0)-1) -> 14 | L26: =IF(AND(L$4>=$I26,L$4<=$J26),1,"") | M26: =IF(AND(M$4>=$I26,M$4<=$J26),1,"") | N26: =IF(AND(N$4>=$I26,N$4<=$J26),1,"") | O26: =IF(AND(O$4>=$I26,O$4<=$J26),1,"") | P26: =IF(AND(P$4>=$I26,P$4<=$J26),1,"") | Q26: =IF(AND(Q$4>=$I26,Q$4<=$J26),1,"") | R26: =IF(AND(R$4>=$I26,R$4<=$J26),1,"") | S26: =IF(AND(S$4>=$I26,S$4<=$J26),1,"") | ... BT26: =IF(AND(BT$4>=$I26,BT$4<=$J26),1,"") | BV26: F2: 'start once the AKS platform is hardened (end of SEGRO week 6-7)' - the base install needs only the hardened AKS platform (SEGRO item 2), not the full stack, so it starts week 13 in parallel with the remaining SEGRO build.
A27: G-P3-L1-R-s2 | B27: • Install TX components (DX, Foundry) and run platform validation | C27: HCL | D27: RECOMMENDED | F27: G-P3-L1-R-s1 | G27: 15 | H27: 2 | I27: =MEDIAN($I$25,$J$25,$I$25+ROUND((G27-$G$25)/$H$25*($J$25-$I$25+1),0)) -> 15 | J27: =MEDIAN(I27,$J$25,$I$25+ROUND((G27+H27-$G$25)/$H$25*($J$25-$I$25+1),0)-1) -> 16 | L27: =IF(AND(L$4>=$I27,L$4<=$J27),1,"") | M27: =IF(AND(M$4>=$I27,M$4<=$J27),1,"") | N27: =IF(AND(N$4>=$I27,N$4<=$J27),1,"") | O27: =IF(AND(O$4>=$I27,O$4<=$J27),1,"") | P27: =IF(AND(P$4>=$I27,P$4<=$J27),1,"") | Q27: =IF(AND(Q$4>=$I27,Q$4<=$J27),1,"") | R27: =IF(AND(R$4>=$I27,R$4<=$J27),1,"") | S27: =IF(AND(S$4>=$I27,S$4<=$J27),1,"") | ... BT27: =IF(AND(BT$4>=$I27,BT$4<=$J27),1,"") | BV27: F2: overlap sequencing - component installs proceed while the SEGRO build completes (week 15); 'validate the overlap window with HCL' applies to this boundary.
A28: G-P3-L1-R-s3 | B28: • Connectivity, routing and observability integration against the completed SEGRO stack | C28: HCL | D28: RECOMMENDED | F28: G-P3-L1-R-s2 | G28: 17 | H28: 2 | I28: =MEDIAN($I$25,$J$25,$I$25+ROUND((G28-$G$25)/$H$25*($J$25-$I$25+1),0)) -> 17 | J28: =MEDIAN(I28,$J$25,$I$25+ROUND((G28+H28-$G$25)/$H$25*($J$25-$I$25+1),0)-1) -> 18 | L28: =IF(AND(L$4>=$I28,L$4<=$J28),1,"") | M28: =IF(AND(M$4>=$I28,M$4<=$J28),1,"") | N28: =IF(AND(N$4>=$I28,N$4<=$J28),1,"") | O28: =IF(AND(O$4>=$I28,O$4<=$J28),1,"") | P28: =IF(AND(P$4>=$I28,P$4<=$J28),1,"") | Q28: =IF(AND(Q$4>=$I28,Q$4<=$J28),1,"") | R28: =IF(AND(R$4>=$I28,R$4<=$J28),1,"") | S28: =IF(AND(S$4>=$I28,S$4<=$J28),1,"") | ... BT28: =IF(AND(BT$4>=$I28,BT$4<=$J28),1,"") | BV28: F2: the finding notes 'later HCL scope (connectivity, routing, gateways, certificates) depends on the wider stack' - so this step runs weeks 17-18, after the SEGRO build ends (week 15).
A30: G-TEST-REANCHOR-R | B30: Testing & Deploy (re-anchored) | C30: SEGRO | D30: RECOMMENDED | E30: F1, F14, F23 | F30: G-P3-L1-R | G30: 19 | H30: 13 | I30: =MIN(61,IF(G30<=29,ROUND((G30-1)*(29+SlipWeeks)/29,0)+1,G30+SlipWeeks)) -> 19 | J30: =MIN(61,IF(G30+H30-1<=29,MAX(ROUND((G30+H30-1)*(29+SlipWeeks)/29,0),I30),G30+H30-1+SlipWeeks)) -> 31 | K30: New re-anchoring task: SIT pulled left to mid-Nov (week 19), explicit Christmas freeze gap weeks 24-25, UAT in January weeks 26-27; go-live moves from end of week 29 to an honest week 29-33 range (ASSUMPTION-within-RECOMMENDED). | L30: =IF(AND(L$4>=$I30,L$4<=$J30),1,"") | M30: =IF(AND(M$4>=$I30,M$4<=$J30),1,"") | N30: =IF(AND(N$4>=$I30,N$4<=$J30),1,"") | O30: =IF(AND(O$4>=$I30,O$4<=$J30),1,"") | P30: =IF(AND(P$4>=$I30,P$4<=$J30),1,"") | Q30: =IF(AND(Q$4>=$I30,Q$4<=$J30),1,"") | R30: =IF(AND(R$4>=$I30,R$4<=$J30),1,"") | S30: =IF(AND(S$4>=$I30,S$4<=$J30),1,"") | ... BT30: =IF(AND(BT$4>=$I30,BT$4<=$J30),1,"") | BU30: =IF(IF(G30+H30-1<=29,MAX(ROUND((G30+H30-1)*(29+SlipWeeks)/29,0),$I30),G30+H30-1+SlipWeeks)>61,"▶ clipped","") | BV30: F1: 'Pull testing left (start mid-Nov) or extend to 6 weeks crossing Christmas with an explicit freeze gap; do not book UAT sign-off or go/no-go inputs in the week of 21 Dec' - the corrected sequence does both: SIT/pen test start week 19 (w/c 16 Nov 2026 = mid-Nov, enabled by the F2 overlap ending the HCL install at week 18), an explicit freeze gap holds weeks 24-25 (Christmas), and UAT sign-off runs weeks 26-27, clear of w/c 21 Dec. Resulting go-live movement, stated HONESTLY as a range and labelled ASSUMPTION-within-RECOMMENDED: nominal go-live end of week 31 vs the as-drawn end of week 29, presented as a week 29-33 range (late Jan to late Feb 2027) - NOT a new committed date - because F14 says 'Present go-live as a range' until the Arch workshop confirms durations, and the range must absorb the F16 review-cycle build-start risk (up to 2 weeks). The week 29-33 band shown here is the mechanical Christmas-freeze + F16 floor; F14's own recommendation cites the wider Green Book ICT optimism-bias band (+3 to +16 wk, i.e. potentially into Q2 2027), which the SlipWeeks lever on the As-Drawn sheet prices beyond this floor - so the true upper bound is SlipWeeks-driven, not capped at week 33. No cost change: the P4/P5 quantities are unchanged; this task only re-anchors their windows (spans cost lines P4-L1 to P5-L5, so no single cost_line is cited).
A31: G-TEST-REANCHOR-R-s1 | B31: • SIT + pen test execution, pulled left to start mid-November | C31: SEGRO | D31: RECOMMENDED | G31: 19 | H31: 3 | I31: =MEDIAN($I$30,$J$30,$I$30+ROUND((G31-$G$30)/$H$30*($J$30-$I$30+1),0)) -> 19 | J31: =MEDIAN(I31,$J$30,$I$30+ROUND((G31+H31-$G$30)/$H$30*($J$30-$I$30+1),0)-1) -> 21 | L31: =IF(AND(L$4>=$I31,L$4<=$J31),1,"") | M31: =IF(AND(M$4>=$I31,M$4<=$J31),1,"") | N31: =IF(AND(N$4>=$I31,N$4<=$J31),1,"") | O31: =IF(AND(O$4>=$I31,O$4<=$J31),1,"") | P31: =IF(AND(P$4>=$I31,P$4<=$J31),1,"") | Q31: =IF(AND(Q$4>=$I31,Q$4<=$J31),1,"") | R31: =IF(AND(R$4>=$I31,R$4<=$J31),1,"") | S31: =IF(AND(S$4>=$I31,S$4<=$J31),1,"") | ... BT31: =IF(AND(BT$4>=$I31,BT$4<=$J31),1,"") | BV31: F1: 'Pull testing left (start mid-Nov)' - week 19 is w/c 16 Nov 2026; possible because the overlapped HCL install (G-P3-L1-R) completes at week 18. The F7-booked pen test lands here, well clear of December.
A32: G-TEST-REANCHOR-R-s2 | B32: • HCL fix-and-retest window between the SIT defect surge and UAT (detail carried in G-P4-FIX-R - same window, not double-counted) | C32: SEGRO | D32: RECOMMENDED | F32: G-TEST-REANCHOR-R-s1 | G32: 22 | H32: 2 | I32: =MEDIAN($I$30,$J$30,$I$30+ROUND((G32-$G$30)/$H$30*($J$30-$I$30+1),0)) -> 22 | J32: =MEDIAN(I32,$J$30,$I$30+ROUND((G32+H32-$G$30)/$H$30*($J$30-$I$30+1),0)-1) -> 23 | L32: =IF(AND(L$4>=$I32,L$4<=$J32),1,"") | M32: =IF(AND(M$4>=$I32,M$4<=$J32),1,"") | N32: =IF(AND(N$4>=$I32,N$4<=$J32),1,"") | O32: =IF(AND(O$4>=$I32,O$4<=$J32),1,"") | P32: =IF(AND(P$4>=$I32,P$4<=$J32),1,"") | Q32: =IF(AND(Q$4>=$I32,Q$4<=$J32),1,"") | R32: =IF(AND(R$4>=$I32,R$4<=$J32),1,"") | S32: =IF(AND(S$4>=$I32,S$4<=$J32),1,"") | ... BT32: =IF(AND(BT$4>=$I32,BT$4<=$J32),1,"") | BV32: F23: 'Add an explicit fix-and-retest loop with an HCL turnaround SLA inside (or immediately after) the test window' - this step reserves the elapsed weeks in the re-anchored sequence; the task-level detail is G-P4-FIX-R.
A33: G-TEST-REANCHOR-R-s3 | B33: • Explicit Christmas freeze gap - no UAT sign-off, no go/no-go inputs, no cutover activity booked | C33: SEGRO | D33: RECOMMENDED | F33: G-TEST-REANCHOR-R-s2 | G33: 24 | H33: 2 | I33: =MEDIAN($I$30,$J$30,$I$30+ROUND((G33-$G$30)/$H$30*($J$30-$I$30+1),0)) -> 24 | J33: =MEDIAN(I33,$J$30,$I$30+ROUND((G33+H33-$G$30)/$H$30*($J$30-$I$30+1),0)-1) -> 25 | L33: =IF(AND(L$4>=$I33,L$4<=$J33),1,"") | M33: =IF(AND(M$4>=$I33,M$4<=$J33),1,"") | N33: =IF(AND(N$4>=$I33,N$4<=$J33),1,"") | O33: =IF(AND(O$4>=$I33,O$4<=$J33),1,"") | P33: =IF(AND(P$4>=$I33,P$4<=$J33),1,"") | Q33: =IF(AND(Q$4>=$I33,Q$4<=$J33),1,"") | R33: =IF(AND(R$4>=$I33,R$4<=$J33),1,"") | S33: =IF(AND(S$4>=$I33,S$4<=$J33),1,"") | ... BT33: =IF(AND(BT$4>=$I33,BT$4<=$J33),1,"") | BV33: F1: 'extend to 6 weeks crossing Christmas with an explicit freeze gap; do not book UAT sign-off or go/no-go inputs in the week of 21 Dec' - weeks 24-25 (w/c 21 Dec and 28 Dec) are held as a named freeze, not silently worked through.
A34: G-TEST-REANCHOR-R-s4 | B34: • UAT execution and sign-off, clear of the freeze | C34: SEGRO | D34: RECOMMENDED | F34: G-TEST-REANCHOR-R-s3 | G34: 26 | H34: 2 | I34: =MEDIAN($I$30,$J$30,$I$30+ROUND((G34-$G$30)/$H$30*($J$30-$I$30+1),0)) -> 26 | J34: =MEDIAN(I34,$J$30,$I$30+ROUND((G34+H34-$G$30)/$H$30*($J$30-$I$30+1),0)-1) -> 27 | L34: =IF(AND(L$4>=$I34,L$4<=$J34),1,"") | M34: =IF(AND(M$4>=$I34,M$4<=$J34),1,"") | N34: =IF(AND(N$4>=$I34,N$4<=$J34),1,"") | O34: =IF(AND(O$4>=$I34,O$4<=$J34),1,"") | P34: =IF(AND(P$4>=$I34,P$4<=$J34),1,"") | Q34: =IF(AND(Q$4>=$I34,Q$4<=$J34),1,"") | R34: =IF(AND(R$4>=$I34,R$4<=$J34),1,"") | S34: =IF(AND(S$4>=$I34,S$4<=$J34),1,"") | ... BT34: =IF(AND(BT$4>=$I34,BT$4<=$J34),1,"") | BV34: F1: 'do not book UAT sign-off or go/no-go inputs in the week of 21 Dec' - UAT runs weeks 26-27 (w/c 4 and 11 Jan 2027), after the freeze, with the fix-and-retest loop already complete.
A35: G-TEST-REANCHOR-R-s5 | B35: • Deploy: production readiness, go/no-go, migration execution, go-live within the stated range | C35: SEGRO | D35: RECOMMENDED | F35: G-TEST-REANCHOR-R-s4 | G35: 28 | H35: 4 | I35: =MEDIAN($I$30,$J$30,$I$30+ROUND((G35-$G$30)/$H$30*($J$30-$I$30+1),0)) -> 28 | J35: =MEDIAN(I35,$J$30,$I$30+ROUND((G35+H35-$G$30)/$H$30*($J$30-$I$30+1),0)-1) -> 31 | L35: =IF(AND(L$4>=$I35,L$4<=$J35),1,"") | M35: =IF(AND(M$4>=$I35,M$4<=$J35),1,"") | N35: =IF(AND(N$4>=$I35,N$4<=$J35),1,"") | O35: =IF(AND(O$4>=$I35,O$4<=$J35),1,"") | P35: =IF(AND(P$4>=$I35,P$4<=$J35),1,"") | Q35: =IF(AND(Q$4>=$I35,Q$4<=$J35),1,"") | R35: =IF(AND(R$4>=$I35,R$4<=$J35),1,"") | S35: =IF(AND(S$4>=$I35,S$4<=$J35),1,"") | ... BT35: =IF(AND(BT$4>=$I35,BT$4<=$J35),1,"") | BV35: F14: 'Present go-live as a range' - deploy runs weeks 28-31 with nominal go-live end of week 31; the movement vs the as-drawn week-29 go-live is labelled ASSUMPTION-within-RECOMMENDED and shown as a week 29-33 range, not a new committed date. The go/no-go gate (~week 30) takes the G-P4-L8-R red-team/audit outputs as named inputs.
A37: G-P4-FIX-R | B37: Testing [P4-L6] | C37: HCL | D37: RECOMMENDED | E37: F23 | F37: G-P3-L1-R | G37: 22 | H37: 2 | I37: =MIN(61,IF(G37<=29,ROUND((G37-1)*(29+SlipWeeks)/29,0)+1,G37+SlipWeeks)) -> 22 | J37: =MIN(61,IF(G37+H37-1<=29,MAX(ROUND((G37+H37-1)*(29+SlipWeeks)/29,0),I37),G37+H37-1+SlipWeeks)) -> 23 | K37: New 2-week explicit HCL fix-and-retest window inserted between SIT and UAT, with greenfield and brownfield retest coverage; no as-drawn counterpart exists. | L37: =IF(AND(L$4>=$I37,L$4<=$J37),1,"") | M37: =IF(AND(M$4>=$I37,M$4<=$J37),1,"") | N37: =IF(AND(N$4>=$I37,N$4<=$J37),1,"") | O37: =IF(AND(O$4>=$I37,O$4<=$J37),1,"") | P37: =IF(AND(P$4>=$I37,P$4<=$J37),1,"") | Q37: =IF(AND(Q$4>=$I37,Q$4<=$J37),1,"") | R37: =IF(AND(R$4>=$I37,R$4<=$J37),1,"") | S37: =IF(AND(S$4>=$I37,S$4<=$J37),1,"") | ... BT37: =IF(AND(BT$4>=$I37,BT$4<=$J37),1,"") | BU37: =IF(IF(G37+H37-1<=29,MAX(ROUND((G37+H37-1)*(29+SlipWeeks)/29,0),$I37),G37+H37-1+SlipWeeks)>61,"▶ clipped","") | BV37: F23: 'Add an explicit fix-and-retest loop with an HCL turnaround SLA inside (or immediately after) the test window, and state greenfield/brownfield coverage in the test scope; P4-L6 carries the HCL-side cost but the elapsed time must be planned' - NEW ~2-week window at weeks 22-23, between the SIT defect surge (weeks 19-21) and UAT (weeks 26-27) in the re-anchored sequence, so material HCL defects no longer slip the go/no-go directly. Cost unchanged: P4-L6 (20 pd likely) already carries the HCL-side effort; this task plans the elapsed time the as-drawn plan omitted.
A38: G-P4-FIX-R-s1 | B38: • HCL defect triage and fix under a stated turnaround SLA, on defects raised by SIT against HCL-installed components | C38: HCL | D38: RECOMMENDED | G38: 22 | H38: 1 | I38: =MEDIAN($I$37,$J$37,$I$37+ROUND((G38-$G$37)/$H$37*($J$37-$I$37+1),0)) -> 22 | J38: =MEDIAN(I38,$J$37,$I$37+ROUND((G38+H38-$G$37)/$H$37*($J$37-$I$37+1),0)-1) -> 22 | L38: =IF(AND(L$4>=$I38,L$4<=$J38),1,"") | M38: =IF(AND(M$4>=$I38,M$4<=$J38),1,"") | N38: =IF(AND(N$4>=$I38,N$4<=$J38),1,"") | O38: =IF(AND(O$4>=$I38,O$4<=$J38),1,"") | P38: =IF(AND(P$4>=$I38,P$4<=$J38),1,"") | Q38: =IF(AND(Q$4>=$I38,Q$4<=$J38),1,"") | R38: =IF(AND(R$4>=$I38,R$4<=$J38),1,"") | S38: =IF(AND(S$4>=$I38,S$4<=$J38),1,"") | ... BT38: =IF(AND(BT$4>=$I38,BT$4<=$J38),1,"") | BV38: F23: 'an explicit fix-and-retest loop with an HCL turnaround SLA' - week 22 is the fix half of the loop; the SLA makes HCL turnaround a managed commitment rather than untimed goodwill.
A39: G-P4-FIX-R-s2 | B39: • Retest with explicit greenfield coverage (clean-install paths) AND brownfield coverage (integration with the existing estate) before UAT entry | C39: HCL | D39: RECOMMENDED | F39: G-P4-FIX-R-s1 | G39: 23 | H39: 1 | I39: =MEDIAN($I$37,$J$37,$I$37+ROUND((G39-$G$37)/$H$37*($J$37-$I$37+1),0)) -> 23 | J39: =MEDIAN(I39,$J$37,$I$37+ROUND((G39+H39-$G$37)/$H$37*($J$37-$I$37+1),0)-1) -> 23 | L39: =IF(AND(L$4>=$I39,L$4<=$J39),1,"") | M39: =IF(AND(M$4>=$I39,M$4<=$J39),1,"") | N39: =IF(AND(N$4>=$I39,N$4<=$J39),1,"") | O39: =IF(AND(O$4>=$I39,O$4<=$J39),1,"") | P39: =IF(AND(P$4>=$I39,P$4<=$J39),1,"") | Q39: =IF(AND(Q$4>=$I39,Q$4<=$J39),1,"") | R39: =IF(AND(R$4>=$I39,R$4<=$J39),1,"") | S39: =IF(AND(S$4>=$I39,S$4<=$J39),1,"") | ... BT39: =IF(AND(BT$4>=$I39,BT$4<=$J39),1,"") | BV39: F23: 'state greenfield/brownfield coverage in the test scope' - the architect flagged both scenarios need testing; the retest week exercises fixed components on both paths so UAT starts on a known-good baseline.
A41: G-P4-L8-R | B41: Testing [P4-L8] | C41: ThirdParty | D41: RECOMMENDED | E41: F26 | G41: 26 | H41: 3 | I41: =MIN(61,IF(G41<=29,ROUND((G41-1)*(29+SlipWeeks)/29,0)+1,G41+SlipWeeks)) -> 26 | J41: =MIN(61,I41+H41-1) -> 28 | K41: Moved from inside the December test window to weeks 26-28 as a named go/no-go input completing immediately before the gate, clear of the Christmas freeze. | L41: =IF(AND(L$4>=$I41,L$4<=$J41),1,"") | M41: =IF(AND(M$4>=$I41,M$4<=$J41),1,"") | N41: =IF(AND(N$4>=$I41,N$4<=$J41),1,"") | O41: =IF(AND(O$4>=$I41,O$4<=$J41),1,"") | P41: =IF(AND(P$4>=$I41,P$4<=$J41),1,"") | Q41: =IF(AND(Q$4>=$I41,Q$4<=$J41),1,"") | R41: =IF(AND(R$4>=$I41,R$4<=$J41),1,"") | S41: =IF(AND(S$4>=$I41,S$4<=$J41),1,"") | ... BT41: =IF(AND(BT$4>=$I41,BT$4<=$J41),1,"") | BU41: =IF($I41+H41-1>61,"▶ clipped","") | BV41: F26: 'Add a pre-go-live AI red-team exercise and audit dry-run as named go/no-go inputs (carried as P4-L8), plus a recurring cadence as agent surfaces and edge cases grow (R-L31)' - placed at weeks 26-28, late in the re-anchored test window running into the deploy start, completing BEFORE the go/no-go gate (~week 30 in G-TEST-REANCHOR-R-s5) so its findings are genuine gate inputs. It cannot sit earlier without landing in the Christmas freeze (weeks 24-25), which F1 rules out for go/no-go inputs. Cost unchanged: fixed engagement of 3-8 tester-days (P4-L8); the recurring cadence is already carried as R-L31 in the run model.
A42: G-P4-L8-R-s1 | B42: • AI red-team exercise on agent surfaces - prompt injection, tool-abuse/data-exfiltration, jailbreak testing | C42: ThirdParty | D42: RECOMMENDED | G42: 26 | H42: 1 | I42: =MEDIAN($I$41,$J$41,$I$41+ROUND((G42-$G$41)/$H$41*($J$41-$I$41+1),0)) -> 26 | J42: =MEDIAN(I42,$J$41,$I$41+ROUND((G42+H42-$G$41)/$H$41*($J$41-$I$41+1),0)-1) -> 26 | L42: =IF(AND(L$4>=$I42,L$4<=$J42),1,"") | M42: =IF(AND(M$4>=$I42,M$4<=$J42),1,"") | N42: =IF(AND(N$4>=$I42,N$4<=$J42),1,"") | O42: =IF(AND(O$4>=$I42,O$4<=$J42),1,"") | P42: =IF(AND(P$4>=$I42,P$4<=$J42),1,"") | Q42: =IF(AND(Q$4>=$I42,Q$4<=$J42),1,"") | R42: =IF(AND(R$4>=$I42,R$4<=$J42),1,"") | S42: =IF(AND(S$4>=$I42,S$4<=$J42),1,"") | ... BT42: =IF(AND(BT$4>=$I42,BT$4<=$J42),1,"") | BV42: F26: 'Add a pre-go-live AI red-team exercise' - scope drawn from the finding's own list (prompt injection, data exfiltration via tools, jailbreaks); runs week 26 in parallel with UAT on the same environments.
A43: G-P4-L8-R-s2 | B43: • Audit dry-run against the platform's operational and governance evidence | C43: ThirdParty | D43: RECOMMENDED | F43: G-P4-L8-R-s1 | G43: 27 | H43: 1 | I43: =MEDIAN($I$41,$J$41,$I$41+ROUND((G43-$G$41)/$H$41*($J$41-$I$41+1),0)) -> 27 | J43: =MEDIAN(I43,$J$41,$I$41+ROUND((G43+H43-$G$41)/$H$41*($J$41-$I$41+1),0)-1) -> 27 | L43: =IF(AND(L$4>=$I43,L$4<=$J43),1,"") | M43: =IF(AND(M$4>=$I43,M$4<=$J43),1,"") | N43: =IF(AND(N$4>=$I43,N$4<=$J43),1,"") | O43: =IF(AND(O$4>=$I43,O$4<=$J43),1,"") | P43: =IF(AND(P$4>=$I43,P$4<=$J43),1,"") | Q43: =IF(AND(Q$4>=$I43,Q$4<=$J43),1,"") | R43: =IF(AND(R$4>=$I43,R$4<=$J43),1,"") | S43: =IF(AND(S$4>=$I43,S$4<=$J43),1,"") | ... BT43: =IF(AND(BT$4>=$I43,BT$4<=$J43),1,"") | BV43: F26: 'and audit dry-run' - the finding notes 'no audit dry-run precedes go-live on a platform whose product is agent behaviour'; week 27 closes that gap before the gate.
A44: G-P4-L8-R-s3 | B44: • Findings triage and red-team/audit report issued as named go/no-go inputs | C44: ThirdParty | D44: RECOMMENDED | F44: G-P4-L8-R-s2 | G44: 28 | H44: 1 | I44: =MEDIAN($I$41,$J$41,$I$41+ROUND((G44-$G$41)/$H$41*($J$41-$I$41+1),0)) -> 28 | J44: =MEDIAN(I44,$J$41,$I$41+ROUND((G44+H44-$G$41)/$H$41*($J$41-$I$41+1),0)-1) -> 28 | L44: =IF(AND(L$4>=$I44,L$4<=$J44),1,"") | M44: =IF(AND(M$4>=$I44,M$4<=$J44),1,"") | N44: =IF(AND(N$4>=$I44,N$4<=$J44),1,"") | O44: =IF(AND(O$4>=$I44,O$4<=$J44),1,"") | P44: =IF(AND(P$4>=$I44,P$4<=$J44),1,"") | Q44: =IF(AND(Q$4>=$I44,Q$4<=$J44),1,"") | R44: =IF(AND(R$4>=$I44,R$4<=$J44),1,"") | S44: =IF(AND(S$4>=$I44,S$4<=$J44),1,"") | ... BT44: =IF(AND(BT$4>=$I44,BT$4<=$J44),1,"") | BV44: F26: 'as named go/no-go inputs (carried as P4-L8)' - the report lands week 28, ahead of the go/no-go gate in the re-anchored deploy step (G-TEST-REANCHOR-R-s5).

Sheet Control Panel>>>
A1: SEGRO POAP Costings — Control Panel (all scenarios drive live)
A2: Amber cells are editable inputs — change a toggle and every tab, total and chart recalculates live. Status labels: VERIFIED (grounded to source) / VERIFIED-ESTIMATE / INDICATIVE (list price, editable) / DERIVED (formula) / ASSUMPTION (stated basis, editable) / RATE_MISSING (no source rate — £0 until entered).
A4: SCENARIO SWITCHES & LOADINGS
A5: Include HCL delivery & licence lines | B5: Include | C5: ASSUMPTION | D5: Includes/excludes all people_hcl rate lines and HCL RATE_MISSING licence/AMS input cells from build and run totals
A6: Effort estimate basis | B6: Likely | C6: ASSUMPTION | D6: Selects the effort column (low/likely/high person-days) used for all people cost lines
A7: Container platform | B7: AKS | C7: ASSUMPTION | D7: AKS: aks_standard_mgmt_hr flat per cluster. ARO: adds aro_openshift_licence_vcpu_hr per worker vCPU plus 3 control-plane node VMs. Note HCL's own matrix marks AKS x CDP = N
A8: Number of environments | B8: 4 | C8: ASSUMPTION | D8: Multiplies per-environment infrastructure lines (dev/test/preprod/prod)
A9: Cluster topology | B9: Single | C9: ASSUMPTION | D9: Open KDD (F3; CDP AKS incompatibility may force a split). Dual doubles cluster-level fees only (AKS mgmt fee, ARO control planes) - total worker-node count is workload-driven and does not double when the same workload is split across two clusters.
A10: Node pool sizing | B10: M | C10: ASSUMPTION | D10: Maps node pool SKU: S/M -> vm_d4s_v5_node_hr, L -> vm_d8s_v5_node_hr (S = fewer nodes of D4s_v5)
A11: Blended day rate (GBP) - adjustable placeholder, RATE_MISSING in sources | B11: 850 | C11: ASSUMPTION | D11: Overrides blended_day_rate for lines costed on the blended basis (role-specific lines keep their own VERIFIED medians)
A12: Contingency % on build (HM Treasury ICT optimism-bias band is 10-200% on capex - 15% sits at the optimistic end) | B12: 0.15 | C12: ASSUMPTION | D12: Uplift applied to build-phase totals
A13: Annual indexation % on run costs | B13: 0.03 | C13: ASSUMPTION | D13: Annual uplift applied to run-cost years 2-5
A14: Schedule slip (weeks) | B14: 0 | C14: ASSUMPTION | D14: Extends build-phase duration (and people cost) by N weeks; HM Treasury ICT duration optimism-bias is +10% to +54% (programme_benchmarks.json) as sensitivity anchors
A15: Phase overlap (weeks) | B15: 0 | C15: ASSUMPTION | D15: Weeks the HCL install runs PARALLEL to the SEGRO build. Models a COST saving only — nets off Azure environment double-running on the time-driven P1–P5 lines. It does NOT move the modelled go-live (the as-drawn Gantt draws HCL sequential — that is finding F2; the schedule benefit is shown on the Corr
A16: Organisation headcount for per-user licences (brief assumed ~700; SEGRO ARA25 VERIFIED headcount is 463, average 454 - set to ~463 for ARA-anchored runs) | B16: 700 | C16: ASSUMPTION | D16: Multiplies all per-user licence lines
A17: Observability stack (Azure-native vs Datadog) | B17: Azure | C17: ASSUMPTION | D17: Azure (default): Log Analytics + Azure Monitor (Azure-native). Datadog: APM + Infrastructure + LLM Observability metered SKUs (LLM spans) — a separate metered line Azure Monitor does not charge for. List prices are INDICATIVE ceilings; negotiated discount tier is RATE_MISSING.
A18: Model vendor (Azure-served) | B18: AzureOpenAI | C18: ASSUMPTION | D18: Azure-only serving plane family. Pair with ModelSKU.
A19: Model SKU (GPT→5.6 / Claude→Fable / Grok→4.5 / Llama) | B19: GPT-4o | C19: ASSUMPTION | D19: Foundation-model SKU. Default GPT-4o = headline continuity. Wrong-vendor SKUs evaluate to £0 via vendor_gate+model_gate. Llama uses GPU lines (not token mirrors).
A20: Agent stack (MCP + RAG + memory) | B20: Exclude | C20: ASSUMPTION | D20: Exclude (default): no MCP/RAG/memory/agent-intensity cost — headline-neutral. Include: ACA MCP × McpServerCount, APIM, embeddings, RAG shape, Cosmos memory × AgentCount.
A21: RAG + memory store shape | B21: AISearch_Cosmos | C21: ASSUMPTION | D21: AISearch_Cosmos: Azure AI Search + Cosmos Mongo memory. CosmosOnly: Cosmos for memory and vectors (AI Search £0).
A22: Agent count (intensity calculator) | B22: 1 | C22: ASSUMPTION | D22: Scales per-agent tokens/memory/embeddings when AgentStack=Include (1–100 guidance).
A23: MCP server count (application plugs) | B23: 2 | C23: ASSUMPTION | D23: Scales MCP Container Apps + APIM when AgentStack=Include (1–50 application plugs).
A25: SCOPE NOTES
A26: ▪ HCL FLOOR caveat: all HCL licence/subscription/AMS lines (UnO, Unica+, CDP, DX, AMS) are RATE_MISSING at GBP 0 because HCL has not shared contract pricing. Any total that includes them is therefore a FLOOR, not an estimate - never present it as the expected HCL cost.
A27: ▪ INDICATIVE and VERIFIED prices are vendor LIST prices with no EA/MACC discount applied. Azure PAYG list is the ceiling: SEGRO's EA discount, 1-yr/3-yr reservations (typically 30-60% off VMs and databases) and savings plans would all reduce the infra figures. Microsoft GBP licence prices are paid-yea
A28: ▪ Headcount: SEGRO ARA25 (VERIFIED) reports 463 employees (average 454, of which 168 indirect/administration). The brief's ~700 figure is retained as the OrgSize toggle default per instruction, but per-user licence maths should be sanity-checked at ~463; the delta overstates per-user costs by ~50%.
A29: ▪ Contingency: the default 15% is an ASSUMPTION. HM Treasury Green Book optimism-bias guidance (programme_benchmarks.json, VERIFIED) puts Equipment/ICT-development capex uplift at 10% (lower bound, achievable at contract award with evidenced risk mitigation) to 200% (upper bound, the mandated starting
A30: ▪ FX: all USD-quoted sources convert at 0.74015 GBP/USD (ECB reference rate via Frankfurter API, 16 Jul 2026, VERIFIED in both people_rates.json and org_it_benchmarks.json). Converted lines are status INDICATIVE and show the arithmetic in notes - nothing converted silently.
A31: ▪ ServiceNow: no published list prices exist; the GBP 74.02/user/mo line is aggregator-sourced INDICATIVE, the adversarial verdict confirmed the source says per USER not per fulfiller, and ServiceNow moved to Foundation/Advanced/Prime packaging with a consumption meter in April 2026 - treat as an adju
A32: ▪ M365/Copilot baseline: SEGRO already licenses M365 and rolled Copilot out to all employees in 2025 (ARA25 p21). These lines are in the spec for completeness and marginal-cost modelling - treat core M365 + Copilot as existing baseline, not incremental POAP cost.
A33: ▪ Azure scope exclusions (will appear on a real bill but are not priced in the fact files): managed disks for node pools, bandwidth/egress, Azure Firewall, Private Link endpoints, backup storage. Defender for Cloud is carried explicitly as RATE_MISSING. Log Analytics ingestion is the most under-estima
A34: ▪ Training: no authoritative per-rollout per-employee figure exists (RATE_MISSING, GBP 0 adjustable). The Training Magazine USD 774/learner/yr (~GBP 573) enterprise average is INDICATIVE context for annual all-training spend only - not a rollout unit cost.
A35: ▪ Maker/verifier provenance: all four source fact files carry APPROVE verdicts in workbook_build/poap/verdicts/ (17 Jul 2026). Every VERIFIED value_gbp in this spec is copied unchanged from its fact file; DERIVED/INDICATIVE lines state their arithmetic; nothing is invented at spec time.

Sheet Rates
A1: Rates — every figure on this tab is an editable input
A2: Azure rates VERIFIED from the Azure Retail Prices API (GBP, uksouth); people rates VERIFIED from ITJobsWatch / G-Cloud 14 published rate cards; RATE_MISSING lines are £0 until a real rate is supplied. Sources cited per row.
A4: AZURE — COMPUTE & PLATFORM
A5: Rate | B5: Unit | C5: Value (£) | D5: Status | E5: Source | F5: Notes
A6: AKS cluster management - Standard tier (Uptime SLA) | B6: per cluster per hour | C6: 0.0758 | D6: VERIFIED | E6: azure_infra_rates.json: AKS cluster management - Standard tier (Uptime SLA), as-of 2026-07-16 | F6: ~GBP 55.3/cluster/month at 730 hrs. Production default tier. Azure Retail Prices API, uksouth, PAYG.
A7: AKS node - Standard_D4s_v5 (4 vCPU / 16 GiB) Linux | B7: per node per hour | C7: 0.1682 | D7: VERIFIED | E7: azure_infra_rates.json: VM Standard_D4s_v5 (4 vCPU / 16 GiB) Linux - AKS node pool, as-of 2026-07-16 | F7: ~GBP 122.8/month at 730 hrs. OS disk billed separately. Candidate NodeSize=S/M mapping.
A8: VM Standard_D4ds_v5 (4 vCPU / 16 GiB / local temp disk) Linux — ARO minimum worker family | B8: per node per hour | C8: 0.1985 | D8: VERIFIED | E8: facts/azure_infra_rates.json: 'VM Standard_D4ds_v5 (4 vCPU / 16 GiB / local temp disk) Linux', as_of 2026-07-1 | F8: Ddsv5 (with local disk) is the ARO minimum-spec worker family per the fact file. Used for the ARO branch worker lines; AKS branch uses D4s_v5.
A9: AKS node - Standard_D8s_v5 (8 vCPU / 32 GiB) Linux | B9: per node per hour | C9: 0.3364 | D9: VERIFIED | E9: azure_infra_rates.json: VM Standard_D8s_v5 (8 vCPU / 32 GiB) Linux - AKS node pool, as-of 2026-07-16 | F9: ~GBP 245.6/month at 730 hrs. Candidate NodeSize=L mapping.
A10: ARO OpenShift worker licence uplift (General Purpose) | B10: per vCPU per hour | C10: 0.0324 | D10: VERIFIED | E10: azure_infra_rates.json: Azure Red Hat OpenShift (ARO) - OpenShift worker licence uplift, General Purpose, as-o | F10: Charged on top of base Linux VM rate per worker node: 4 vCPU = 0.1296/hr, 8 vCPU = 0.2591/hr. ARO also needs 3 control-plane nodes billed as plain VMs. Drives t
A12: AZURE — DATA SERVICES
A13: Rate | B13: Unit | C13: Value (£) | D13: Status | E13: Source | F13: Notes
A14: PostgreSQL Flexible Server - GP D4ds_v5 (4 vCore) compute | B14: per hour | C14: 0.3121 | D14: VERIFIED | E14: azure_infra_rates.json: Azure Database for PostgreSQL Flexible Server - General Purpose D4ds_v5 (4 vCore) comp | F14: ~GBP 227.8/month at 730 hrs. Per-vCore rate 0.078/hr scales linearly. Storage extra (separate line).
A15: PostgreSQL Flexible Server - provisioned storage | B15: per GB per month | C15: 0.1008 | D15: VERIFIED | E15: azure_infra_rates.json: Azure Database for PostgreSQL Flexible Server - storage, as-of 2026-07-16 | F15: Backup storage up to 100% of provisioned is free; excess billed separately.
A16: Azure SQL Database - General Purpose Gen5, 4 vCore (provisioned) | B16: per hour | C16: 0.5766 | D16: VERIFIED | E16: azure_infra_rates.json: Azure SQL Database - General Purpose Gen5, 4 vCore (provisioned, single DB), as-of 202 | F16: ~GBP 421/month at 730 hrs. PAYG rate includes SQL licence; storage billed separately.
A17: Cosmos DB - serverless request units | B17: per 1 million RUs consumed | C17: 0.225 | D17: VERIFIED | E17: azure_infra_rates.json: Cosmos DB - serverless request units, as-of 2026-07-16 | F17: Best for spiky/low agent-state workloads; no minimum. Storage billed separately.
A18: Event Hubs - Standard tier, Throughput Unit | B18: per Throughput Unit per hour | C18: 0.0227 | D18: VERIFIED | E18: azure_infra_rates.json: Event Hubs - Standard tier, Throughput Unit, as-of 2026-07-16 | F18: ~GBP 16.6/TU/month; 1 TU = 1 MB/s ingress. Ingress events charged additionally at 0.0212 per 1M events (same source file).
A19: Azure Cache for Redis - Standard C1 (1 GB, replicated) | B19: per cache per hour | C19: 0.1311 | D19: VERIFIED | E19: azure_infra_rates.json: Azure Cache for Redis - Standard C1 (1 GB, replicated), as-of 2026-07-16 | F19: ~GBP 95.7/month.
A21: AZURE — NETWORKING
A22: Rate | B22: Unit | C22: Value (£) | D22: Status | E22: Source | F22: Notes
A23: Application Gateway WAF_v2 - fixed gateway cost | B23: per gateway per hour | C23: 0.3409 | D23: VERIFIED | E23: azure_infra_rates.json: Application Gateway WAF_v2 - fixed gateway cost, as-of 2026-07-16 | F23: ~GBP 248.9/month fixed, plus capacity units. WAF policies included in v2 SKU.
A24: Application Gateway WAF_v2 - capacity unit | B24: per capacity unit per hour | C24: 0.0109 | D24: VERIFIED | E24: azure_infra_rates.json: Application Gateway WAF_v2 - capacity unit, as-of 2026-07-16 | F24: Typical small prod ~10 CU avg adds ~GBP 79.6/month.
A25: API Management - Standard tier (classic) | B25: per unit per hour | C25: 0.7127 | D25: VERIFIED | E25: azure_infra_rates.json: API Management - Standard tier (classic), as-of 2026-07-16 | F25: ~GBP 520.3/unit/month. SEGRO already runs APIM (all integration via APIM per architecture principles) - existing estate APIM may absorb this; treat as marginal-
A26: VPN Gateway - VpnGw1 | B26: per gateway per hour | C26: 0.1439 | D26: VERIFIED | E26: azure_infra_rates.json: VPN Gateway - VpnGw1, as-of 2026-07-16 | F26: ~GBP 105/month. SEGRO single-tenant Azure estate likely already has connectivity - marginal cost may be nil.
A27: Azure Private DNS - hosted zone | B27: per zone per month (first 25 zones) | C27: 0.3788 | D27: VERIFIED | E27: azure_infra_rates.json: Azure Private DNS - hosted zone, as-of 2026-07-16 | F27: Zones 26+ at 0.0758/zone/month. Billed globally, not per region.
A29: AZURE — OBSERVABILITY
A30: Rate | B30: Unit | C30: Value (£) | D30: Status | E30: Source | F30: Notes
A31: Log Analytics - PAYG data ingestion (Analytics Logs) | B31: per GB ingested | C31: 2.1819 | D31: VERIFIED | E31: azure_infra_rates.json: Log Analytics - Pay-As-You-Go data ingestion (Analytics Logs), as-of 2026-07-16 | F31: First 5 GB/month free. Single biggest observability cost driver for agent platforms - budget by GB/day. Basic Logs alternative 0.4735/GB (same source file).
A32: Azure Monitor - metric alert rule | B32: per monitored metric timeseries per month | C32: 0.0758 | D32: VERIFIED | E32: azure_infra_rates.json: Azure Monitor - metric alert rule (per monitored metric timeseries), as-of 2026-07-16 | F32: First 10 metric timeseries free. Log alert at 5-min frequency 0.1136/rule/month.
A34: OBSERVABILITY — DATADOG (Observability=Datadog branch)
A35: Rate | B35: Unit | C35: Value (£) | D35: Status | E35: Source | F35: Notes
A36: Datadog LLM Observability (Agent Observability) - Pro tier, up to 100K LLM spans (annual/c | B36: per month, includes up to 100,000 LLM spans | C36: 118.42 | D36: INDICATIVE | E36: datadoghq.com/product/llm-observability - Pro tier USD 160/month, up to 100K LLM spans, 15-day retention (annu | F36: USD 160 x 0.74015 = 118.424, rounded 118.42. Billing unit = LLM span, defined by Datadog as 'a single call to an LLM provider' - tool/workflow/agent/embedding/r
A37: Datadog LLM Observability - on-demand, first 100K LLM spans | B37: per month, for first 100,000 LLM spans | C37: 177.64 | D37: INDICATIVE | E37: datadoghq.com/pricing/list - Agent Observability 'For first 100k LLM spans, per month' on-demand USD 240, fetc | F37: USD 240 x 0.74015 = 177.636, rounded 177.64. On-demand (uncommitted) list price for the same 100K-span base tier that costs USD 160 committed - i.e. the committ
A38: Datadog LLM Observability - overage per additional 10K LLM spans (on-demand) | B38: per 10,000 additional LLM spans per month | C38: 3.7 | D38: INDICATIVE | E38: datadoghq.com/pricing/list - Agent Observability 'Per 10K additional LLM spans, per month' on-demand USD 5, fe | F38: USD 5 x 0.74015 = 3.70075, rounded 3.70. Charged for LLM spans beyond the 100K included in the base tier. This is the true volume driver for an agent platform:
A39: Datadog APM (Application Performance Monitoring) - per host per month (annual, with Infras | B39: per APM host per month, billed annually | C39: 22.94 | D39: INDICATIVE | E39: datadoghq.com/pricing - APM 'Per host, per month' USD 31 billed annually (with Infrastructure Monitoring attac | F39: USD 31 x 0.74015 = 22.94465, rounded 22.94. This is the INFRA-ATTACHED APM rate. Per Datadog's pricing page, the attached rate REQUIRES a paired Pro/Enterprise
A40: Datadog APM (Application Performance Monitoring) - per host per month (annual, STANDALONE | B40: per APM host per month, billed annually | C40: 26.65 | D40: INDICATIVE | E40: datadoghq.com/pricing - APM standalone 'Per host, per month' USD 36 billed annually (rate quoted when Infrastr | F40: USD 36 x 0.74015 = 26.6454, rounded 26.65. The STANDALONE APM rate — used ONLY when Infrastructure Monitoring is NOT bought at all on the host. It is HIGHER tha
A41: Datadog Infrastructure Monitoring - Pro tier, per host per month (annual) | B41: per infra host per month, billed annually | C41: 11.1 | D41: INDICATIVE | E41: datadoghq.com/pricing - Infrastructure Monitoring Pro 'Per host, per month' USD 15 billed annually (or USD 18 | F41: USD 15 x 0.74015 = 11.10225, rounded 11.10. The foundational per-host SKU; APM is typically attached to it (the USD 31 APM line above assumes Infra attached). V
A42: Datadog enterprise committed-annual-spend discount tier (negotiated) | B42: GBP per year (committed spend / EA discount) | C42: 0 | D42: RATE_MISSING | E42: Not published - Datadog volume/multi-year discounts are quote-only ('Multi-Year/Volume discounts available', c | F42: £0 until a rate is supplied. Adjustable input defaulting to 0. Datadog's public list prices above are the pre-negotiation CEILING; enterprise agreements with co
A44: AZURE — SECURITY
A45: Rate | B45: Unit | C45: Value (£) | D45: Status | E45: Source | F45: Notes
A46: Key Vault - operations (secrets/software keys) | B46: per 10,000 operations | C46: 0.0227 | D46: VERIFIED | E46: azure_infra_rates.json: Key Vault - operations (Standard and Premium, secrets/software keys), as-of 2026-07-16 | F46: Negligible at platform scale (millions of ops = a few GBP).
A47: Microsoft Defender for Cloud (workload protection plans) | B47: per resource per month | C47: 0 | D47: RATE_MISSING | E47: azure_infra_rates.json narrative_notes: explicitly listed under 'Excluded (not in scope of the request, but wi | F47: £0 until a rate is supplied. Not priced in the fact files - adjustable input defaulting to 0. Defender plans are per-resource-type (servers, containers, databas
A49: FOUNDATION MODEL — SELF-HOSTED SERVING (ModelVendor=Llama)
A50: Rate | B50: Unit | C50: Value (£) | D50: Status | E50: Source | F50: Notes
A51: Azure GPU VM Standard_NC24ads_A100_v4 (1x NVIDIA A100 80GB / 24 vCPU / 220 GiB) Linux - si | B51: per node per hour | C51: 3.4782 | D51: VERIFIED | E51: Azure Retail Prices API, uksouth, Consumption (PAYG): armSkuName 'Standard_NC24ads_A100_v4', productName 'NCad | F51: LLAMA branch (self-hosted). Modest, defensible single-GPU serving SKU for a single-model inference pool (1x A100 80GB serves a quantised ~70B or smaller Llama c
A52: Azure GPU VM Standard_NC40ads_H100_v5 (1x NVIDIA H100 NVL 94GB / 40 vCPU) Linux - higher-t | B52: per node per hour | C52: 6.6101 | D52: VERIFIED | E52: Azure Retail Prices API, uksouth, Consumption (PAYG): armSkuName 'Standard_NC40ads_H100_v5', productName 'Virt | F52: LLAMA branch alternative. Newer H100-class single-GPU node for larger models or higher throughput than the A100 line above. ~GBP 4825.37/node/month at 730 hrs.
A53: Azure GPU capacity - quota request / reserved-capacity commitment (procurement act) | B53: per procurement (one-off / annual commitment) | C53: 0 | D53: RATE_MISSING | E53: No clean public unit price - Azure GPU (NC/ND-series) capacity requires a quota-increase request and, at scale | F53: £0 until a rate is supplied. LLAMA branch. Adjustable input cell defaulting to GBP 0 - never a verified figure. Same RATE_MISSING procurement FAMILY as the exis
A55: FOUNDATION MODEL — AZURE-SERVED TOKENS (ModelSKU ladder)
A56: Rate | B56: Unit | C56: Value (£) | D56: Status | E56: Source | F56: Notes
A57: Anthropic Claude Sonnet (current production tier) - input tokens, standard list | B57: GBP per 1M input tokens | C57: 2.22 | D57: INDICATIVE | E57: Anthropic pricing (platform.claude.com/docs pricing table, fetched 2026-07-18): Claude Sonnet 5 base input USD | F57: CLAUDE branch (hosted API) - token meters only, like the existing Azure OpenAI GPT-4o pattern (aoai_gpt4o_input_1m_tokens). NO GPU node and NO inference-ops FTE
A58: Anthropic Claude Sonnet (current production tier) - output tokens, standard list | B58: GBP per 1M output tokens | C58: 11.1 | D58: INDICATIVE | E58: Anthropic pricing (platform.claude.com/docs pricing table, fetched 2026-07-18): Claude Sonnet 5 output USD 15. | F58: CLAUDE branch. Standard list USD 15/MTok out. INTRODUCTORY USD 10/MTok out through 31 Aug 2026 (= GBP 7.40) then reverts to USD 15 - use the standard 11.10 as t
A59: Azure OpenAI GPT-4.1 — input tokens, Global, uksouth | B59: GBP per 1M input tokens | C59: 1.5 | D59: VERIFIED | E59: Azure Retail API uksouth meter 'gpt 4.1 Inp glbl Tokens' £0.0015/1K, retrieved 2026-07-19 | F59: Cheaper than GPT-4o; AzureOpenAI ladder.
A60: Azure OpenAI GPT-4.1 — output tokens, Global, uksouth | B60: GBP per 1M output tokens | C60: 6.1 | D60: VERIFIED | E60: Azure Retail API uksouth meter 'gpt 4.1 Outp glbl Tokens' £0.0061/1K, retrieved 2026-07-19
A61: Azure OpenAI / Foundry GPT-5.6 Terra — input (Azure-served list) | B61: GBP per 1M input tokens | C61: 1.8504 | D61: INDICATIVE | E61: OpenAI list USD 2.50/MTok × 0.74015; no Azure Retail meter yet 2026-07-19 | F61: Balance tier of GPT-5.6 family. INDICATIVE until uksouth meter publishes.
A62: Azure OpenAI / Foundry GPT-5.6 Terra — output (Azure-served list) | B62: GBP per 1M output tokens | C62: 11.1022 | D62: INDICATIVE | E62: OpenAI list USD 15.00/MTok × 0.74015
A63: Azure OpenAI / Foundry GPT-5.6 Sol — input (Azure-served list) | B63: GBP per 1M input tokens | C63: 3.7007 | D63: INDICATIVE | E63: OpenAI list USD 5.00/MTok × 0.74015; no Azure Retail meter yet 2026-07-19 | F63: Frontier tier. INDICATIVE until uksouth meter publishes.
A64: Azure OpenAI / Foundry GPT-5.6 Sol — output (Azure-served list) | B64: GBP per 1M output tokens | C64: 22.2045 | D64: INDICATIVE | E64: OpenAI list USD 30.00/MTok × 0.74015
A65: Claude Fable 5 on Azure — input tokens, standard list | B65: GBP per 1M input tokens | C65: 7.4015 | D65: INDICATIVE | E65: Anthropic Claude Fable 5 USD 10/MTok × 0.74015; Azure-served (Foundry/BYOK) | F65: ClaudeOnAzure top of ladder.
A66: Claude Fable 5 on Azure — output tokens, standard list | B66: GBP per 1M output tokens | C66: 37.0075 | D66: INDICATIVE | E66: Anthropic Claude Fable 5 USD 50/MTok × 0.74015
A67: Grok 4.3 on Azure AI Foundry — input (<200k) | B67: GBP per 1M input tokens | C67: 0.9252 | D67: INDICATIVE | E67: xAI/Foundry list USD 1.25/MTok × 0.74015 | F67: GrokOnAzure mid tier.
A68: Grok 4.3 on Azure AI Foundry — output (<200k) | B68: GBP per 1M output tokens | C68: 1.8504 | D68: INDICATIVE | E68: xAI/Foundry list USD 2.50/MTok × 0.74015
A69: Grok 4.5 on Azure AI Foundry — input (<200k) | B69: GBP per 1M input tokens | C69: 1.4803 | D69: INDICATIVE | E69: xAI docs grok-4.5 USD 2.00/MTok × 0.74015 | F69: GrokOnAzure top of ladder.
A70: Grok 4.5 on Azure AI Foundry — output (<200k) | B70: GBP per 1M output tokens | C70: 4.4409 | D70: INDICATIVE | E70: xAI docs grok-4.5 USD 6.00/MTok × 0.74015
A71: Azure OpenAI text-embedding-ada — tokens, Global uksouth | B71: GBP per 1M tokens | C71: 0.1 | D71: VERIFIED | E71: Azure Retail API uksouth meter 'embedding-ada-glbl Tokens' £0.0001/1K, retrieved 2026-07-19 | F71: RAG embedding meter.
A73: FOUNDATION MODEL — INFERENCE-OPS (ModelVendor=Llama)
A74: Rate | B74: Unit | C74: Value (£) | D74: Status | E74: Source | F74: Notes
A75: MLOps engineer contractor day rate (UK median) - basis for the inference-ops uplift | B75: GBP per day | C75: 575 | D75: VERIFIED | E75: ITJobsWatch - MLOps contracts UK, 6 months to 18 Jul 2026 (242 rate quotes): median GBP 575/day, 25th pct 500, | F75: LLAMA branch. The day rate itself is VERIFIED (ITJobsWatch median, 242 quotes). It is the RATE basis for the inference-ops FTE uplift line below - self-hosting
A76: Inference-ops run-team uplift for self-hosted model serving (FTE fraction of an MLOps engi | B76: FTE fraction (of mlops_engineer_contractor_day) - | C76: 0 | D76: ASSUMPTION | E76: No published per-platform headcount figure. Expressed as a basis: 0.2-0.5 FTE of an MLOps engineer at the VERI | F76: LLAMA branch ONLY. Value shipped as 0 (adjustable) so a total never silently bakes in an invented headcount; the intended live cell = FTE_fraction x 575 x worki
A78: AGENT STACK — MCP / RAG / MEMORY (AgentStack=Include)
A79: Rate | B79: Unit | C79: Value (£) | D79: Status | E79: Source | F79: Notes
A80: Azure Container Apps — active vCPU-second (MCP hosting) | B80: per vCPU-second | C80: 2e-05 | D80: INDICATIVE | E80: tco/facts/azure_rates.json aca_vcpu_second (Retail API £0 free-grant; USD list converted) | F80: Per MCP server scale via McpServerCount.
A81: Azure Container Apps — active GiB-second (MCP hosting) | B81: per GiB-second | C81: 2.5e-06 | D81: INDICATIVE | E81: tco/facts/azure_rates.json aca_gib_second
A82: APIM — marginal call unit (derived from Standard tier capacity ASSUMPTION) | B82: GBP per 1K calls | C82: 0.043 | D82: ASSUMPTION | E82: Derived: APIM Standard ~£520.27/mo (tco azure_rates VERIFIED-lineage INDICATIVE) / ~12M calls/mo capacity floo | F82: SEGRO principle: all MCP behind APIM. Not a published per-call meter — ASSUMPTION unit for estate scaling.
A83: Azure AI Search Basic — search unit hour | B83: per unit-hour | C83: 0.0842 | D83: VERIFIED | E83: Azure Retail API uksouth meter 'Basic CC Unit' product Azure AI Search £0.0842/hr, retrieved 2026-07-19 | F83: Active when RagMemoryShape=AISearch_Cosmos.
A84: Azure Cosmos DB autoscale — 100 RU/s hour (Mongo API memory/vector) | B84: per 100 RU/s per hour | C84: 0.0091 | D84: VERIFIED | E84: Azure Retail API uksouth Cosmos DB autoscale 100 RUs £0.0091/hr, retrieved 2026-07-19 | F84: Agent memory always; vectors when CosmosOnly.
A86: PEOPLE — SEGRO INTERNAL
A87: Rate | B87: Unit | C87: Value (£) | D87: Status | E87: Source | F87: Notes
A88: SEGRO internal fully-loaded FTE cost (platform engineer) | B88: GBP per FTE per year | C88: 95000 | D88: ASSUMPTION | E88: Not in fact files - ASSUMPTION per brief | F88: Rationale: UK fully-loaded platform engineer cost (salary + NI + pension + overheads), consistent with the existing TCO workbook input. Adjustable. Context only
A90: PEOPLE — UK CONTRACTOR MARKET (ITJobsWatch medians)
A91: Rate | B91: Unit | C91: Value (£) | D91: Status | E91: Source | F91: Notes
A92: Platform Engineer contractor day rate (UK median) | B92: GBP per day | C92: 525 | D92: VERIFIED | E92: people_rates.json: Platform Engineer contractor median day rate, UK (ITJobsWatch, 6 months to 16 Jul 2026), as | F92: Median of 362 rate quotes; 25th pct 481, 75th pct 624. London median 581.
A93: DevOps Engineer contractor day rate (UK median) | B93: GBP per day | C93: 525 | D93: VERIFIED | E93: people_rates.json: DevOps Engineer contractor median day rate, UK (ITJobsWatch, 6 months to 16 Jul 2026), as-o | F93: 25th pct 449, 75th pct 613.
A94: Kubernetes-skill contractor day rate (UK median) | B94: GBP per day | C94: 535 | D94: VERIFIED | E94: people_rates.json: Kubernetes (skill) contractor median day rate, UK (ITJobsWatch, 6 months to 16 Jul 2026), a | F94: Median of 1,819 rate quotes; 25th pct 459, 75th pct 624.
A95: Cloud Security contractor day rate (UK median) | B95: GBP per day | C95: 550 | D95: VERIFIED | E95: people_rates.json: Cloud Security (skill) contractor median day rate, UK (ITJobsWatch, 6 months to 16 Jul 2026 | F95: Median of 687 rate quotes; 25th pct 481, 75th pct 650.
A96: Solutions Architect contractor day rate (UK median) | B96: GBP per day | C96: 625 | D96: VERIFIED | E96: people_rates.json: Solutions Architect contractor median day rate, UK (ITJobsWatch, 6 months to 16 Jul 2026), | F96: Median of 1,120 rate quotes; 25th pct 525, 75th pct 725.
A97: Project Manager contractor day rate (UK median) | B97: GBP per day | C97: 535 | D97: VERIFIED | E97: people_rates.json: Project Manager contractor median day rate, UK (ITJobsWatch, 6 months to 16 Jul 2026), as-o | F97: 25th pct 450, 75th pct 625. Delivery Manager median 533 (same source file) if that role label is preferred.
A98: Test Engineer contractor day rate (UK median) | B98: GBP per day | C98: 431 | D98: VERIFIED | E98: people_rates.json: Test Engineer contractor median day rate, UK (ITJobsWatch, 6 months to 16 Jul 2026), as-of | F98: Median of 206 rate quotes; 25th pct 363, 75th pct 538. SDET median 453 (small sample, 49 quotes).
A99: Test Manager contractor day rate (UK median) | B99: GBP per day | C99: 515 | D99: VERIFIED | E99: people_rates.json: Test Manager contractor median day rate, UK (ITJobsWatch, 6 months to 16 Jul 2026), as-of 2 | F99: 25th pct 450, 75th pct 600.
A100: Data Engineer contractor day rate (UK median) | B100: GBP per day | C100: 500 | D100: VERIFIED | E100: people_rates.json: Data Engineer contractor median day rate, UK (ITJobsWatch, 6 months to 16 Jul 2026), as-of | F100: Median of 1,322 rate quotes; 25th pct 425, 75th pct 588.
A101: Business Analyst contractor day rate (UK median) | B101: GBP per day | C101: 500 | D101: VERIFIED | E101: people_rates.json: Business Analyst contractor median day rate, UK (ITJobsWatch, 6 months to 16 Jul 2026), as- | F101: Median of 1,430 rate quotes; 25th pct 413, 75th pct 588.
A102: Blended delivery day rate (adjustable placeholder) | B102: GBP per day | C102: =DayRate -> 850 | D102: ASSUMPTION | E102: people_rates.json: Tier-1 Indian SI blended onshore/offshore day rate = RATE_MISSING (no public analyst-publis | F102: RATE_MISSING in sources; ships as a visible, user-adjustable GBP 850 placeholder per project convention (same treatment as the TCO workbook). Sits between ITJob
A104: PEOPLE — HCL (G-Cloud 14 published rate card)
A105: Rate | B105: Unit | C105: Value (£) | D105: Status | E105: Source | F105: Notes
A106: HCL G-Cloud 14 SFIA rate - Solution development & implementation, Level 3 (Apply) | B106: GBP per day (8-hr day excl. travel/lunch) | C106: 950 | D106: VERIFIED | E106: people_rates.json: HCLTech G-Cloud 14 SFIA rate card - Solution development & implementation, Level 3 (Apply), | F106: HCL's own published UK public-sector ceiling rate (SFIA card, Oct 2024). Grid context: L1 750 / L2 850 / L3 950 / L4 1050 / L5 1150 / L6 1250 / L7 1850; Strateg
A107: HCL G-Cloud 14 published day-rate range - floor | B107: GBP per day | C107: 550 | D107: VERIFIED | E107: people_rates.json: HCLTech G-Cloud 14 Cloud Application Services day-rate range (published) 550-1650, as-of 20 | F107: Low end of HCL's published SFIA-graded band (UK Digital Marketplace service 613304395170242). Per HCL's pricing document the card includes offshore India delive
A108: HCL G-Cloud 14 published day-rate range - ceiling | B108: GBP per day | C108: 1650 | D108: VERIFIED | E108: people_rates.json: HCLTech G-Cloud 14 Cloud Application Services day-rate range (published) 550-1650, as-of 20 | F108: High end of HCL's published band. Note the SFIA card itself lists Strategy & architecture L7 at 2050 for that category (same source file); 1650 is the range pub
A110: LICENCES & SUBSCRIPTIONS
A111: Rate | B111: Unit | C111: Value (£) | D111: Status | E111: Source | F111: Notes
A112: Microsoft 365 E3 (with Teams) | B112: GBP per user per month (paid yearly, annual commit | C112: 33.5 | D112: VERIFIED | E112: org_it_benchmarks.json: Microsoft 365 E3 (with Teams), Microsoft UK pricing page fetched 16 Jul 2026 | F112: E3 without Teams: 27.00. Monthly-billed annual-term subs carry +5% premium (since 1 Apr 2025). SEGRO baseline - treat as existing cost, not incremental.
A113: Microsoft 365 E5 (with Teams) | B113: GBP per user per month (paid yearly, annual commit | C113: 51.6 | D113: VERIFIED | E113: org_it_benchmarks.json: Microsoft 365 E5 (with Teams), Microsoft UK pricing page fetched 16 Jul 2026 | F113: E5 without Teams: 45.00.
A114: Microsoft 365 Copilot add-on | B114: GBP per user per month (annual subscription, ex VA | C114: 23.1 | D114: VERIFIED | E114: org_it_benchmarks.json: Microsoft 365 Copilot add-on, Microsoft UK pricing page fetched 16 Jul 2026 | F114: SEGRO already rolled Copilot out to all employees in 2025 (ARA25 p21) - existing baseline, not incremental to POAP.
...

Sheet POAP Build Cost
A1: POAP Build Cost — phase by phase (aligned to POAP slide 3)
A2: ="Scenario: effort = "&EffortBasis&" · HCL = "&HCL_Toggle&" · platform = "&Platform&" · sku = "&ModelSKU&" · agents = "&AgentStack&" · obs = "&Observability&" · envs = "&EnvCount&" · clusters = "&ClusterCount&" · node size = "&NodeSize&" · day rate £"&TEXT(DayRate,"#,##0")&" · slip = "&SlipWeeks&" wk · overlap = "&OverlapWeeks&" wk" -> Scenario: effort = Likely · HCL = Include · platform = AKS · sku = GPT-4o · agents = Exclude · obs = Azure · envs = 4 · clusters = Single · node size = M · day rate £850 · slip = 0 wk · overlap = 0 wk
A4: P1 — DESIGN & PLAN (5 wk, from 2026-07-13, Slide 3: Design & Plan bar '5 weeks' x=1.98-4.52; workshop chain (Arch kick-off, Sizing, Cyber, IAM, Data Mgmt); KDD + procurement lane)
A5: Cost line | B5: Side | C5: Quantity model | D5: Qty Low | E5: Qty Likely | F5: Qty High | G5: Qty (live) | H5: Rate/unit £ | I5: Cost £ (live) | J5: Status | K5: Basis / source | L5: Schedule
A6: Solutions architect - workshop lead, HLD/LLD, target arch for EA, KDD papers (AKS v ARO, env count, cluster topology) | B6: SEGRO | C6: 1 FTE x 5 wk x 5 d = 25 days | D6: 20 | E6: 25 | F6: 30 | G6: =CHOOSE(MATCH(EffortBasis,{"Low","Likely","High"},0),D6,E6,F6) -> 25 | H6: =Rates!$C$96 -> 625 | I6: =G6*Rates!$C$96 -> 15625 | J6: ASSUMPTION | K6: Team size ASSUMPTION: slide 3 workshop chain + slide 5 doc list (HLD, LLD, TCO for options, KDDs) need a full-time architect for the 5-wk phase. Rate VERIFIED (ITJobsWatch median). | L6: TD
A7: Platform engineer - sizing workshop, physical infrastructure diagrams, physical sizing of infrastructure | B7: SEGRO | C7: 0.6 FTE x 5 wk x 5 d = 15 days | D7: 10 | E7: 15 | F7: 25 | G7: =CHOOSE(MATCH(EffortBasis,{"Low","Likely","High"},0),D7,E7,F7) -> 15 | H7: =Rates!$C$92 -> 525 | I7: =G7*Rates!$C$92 -> 7875 | J7: ASSUMPTION | K7: ASSUMPTION: slide 5 requires 'Physical sizing of infrastructure' + 'Physical Low Level Technical Arch Diagrams'. Rate VERIFIED. | L7: TD
A8: Cloud security - Cyber Sec Workshop, cyber security impact analysis + diagrams | B8: SEGRO | C8: 0.4 FTE x 5 wk x 5 d = 10 days | D8: 5 | E8: 10 | F8: 15 | G8: =CHOOSE(MATCH(EffortBasis,{"Low","Likely","High"},0),D8,E8,F8) -> 10 | H8: =Rates!$C$95 -> 550 | I8: =G8*Rates!$C$95 -> 5500 | J8: ASSUMPTION | K8: ASSUMPTION sized to slide 5 cyber deliverables (impact analysis, diagrams). Rate VERIFIED. | L8: TD
